Workbook
Name different: #REF!
Name mike: 'ARR Waterfall'!$A$8
Name unit: 'ARR Waterfall'!$A$1
Name unit: 'Billing Waterfall'!#REF!
Name unit: Capitalizations!#REF!
Name unit: Cohorts!$A$1
Name unit: Model!#REF!
Name unit: 'Model (Start)'!#REF!
Name unit: 'SaaS Metrics'!#REF!
Name unit: Transaction!#REF!
Name unit: #REF!

Sheet Resources
B4: GO, GO, GO!
B5: Practice really does make perfect!
B6: You got this! :-)
B10: This template is part of a comprehensive course for SaaS investing roles & interviews.
B11: For more video courses and tutorials:
B13: =HYPERLINK("https://GrowthEquityInterviewGuide.com", "GrowthEquityInterviewGuide.com") -> GrowthEquityInterviewGuide.com
B25: All rights reserved. Growth Equity Interview Guide.

Sheet Start ->

Sheet Model (Start)
B2: Income Statement | AH2: $ in thousands, except noted
C3: =YEAR(C4) -> 2020 | D3: =YEAR(D4) -> 2020 | E3: =YEAR(E4) -> 2020 | F3: =YEAR(F4) -> 2020 | G3: =YEAR(G4) -> 2021 | H3: =YEAR(H4) -> 2021 | I3: =YEAR(I4) -> 2021 | J3: =YEAR(J4) -> 2021 | ... AH3: =YEAR(AH4) -> 2027
C4: 43921 | D4: =EOMONTH(C4, 3) -> 44012 | E4: =EOMONTH(D4, 3) -> 44104 | F4: =EOMONTH(E4, 3) -> 44196 | G4: =EOMONTH(F4, 3) -> 44286 | H4: =EOMONTH(G4, 3) -> 44377 | I4: =EOMONTH(H4, 3) -> 44469 | J4: =EOMONTH(I4, 3) -> 44561 | K4: =EOMONTH(J4, 3) -> 44651 | ... AH4: =EOMONTH(AG4, 3) -> 46752
B5: Ending ARR | C5: =+'ARR Waterfall'!C11 -> 8563.9987 | D5: =+'ARR Waterfall'!D11 -> 10870.48 | E5: =+'ARR Waterfall'!E11 -> 12868.786 | F5: =+'ARR Waterfall'!F11 -> 17227.514 | G5: =+'ARR Waterfall'!G11 -> 20583.553 | H5: =+'ARR Waterfall'!H11 -> 24832.39 | I5: =+'ARR Waterfall'!I11 -> 30936.948 | J5: =+'ARR Waterfall'!J11 -> 37345.929 | ... N5: =+'ARR Waterfall'!N11 -> 71551.25
B6: % YoY Growth | G6: =G5/C5-1 -> 1.4034979 | H6: =H5/D5-1 -> 1.2843875 | I6: =I5/E5-1 -> 1.40403 | J6: =J5/F5-1 -> 1.1678072 | K6: =K5/G5-1 -> 1.1093313 | L6: =L5/H5-1 -> 1.0809316 | M6: =M5/I5-1 -> 0.91602693 | N6: =N5/J5-1 -> 0.91590496
B8: GAAP Revenue | C8: 2198.9787 | D8: 2784.2487 | E8: 3286.6844 | F8: 4387.6529 | G8: 5236.4888 | H8: 6301.1027 | I8: 7833.5468 | J8: 9427.8556 | K8: 10932.177 | L8: 12966.669 | M8: 14824.426 | N8: 17887.813
B9: % of ARR | C9: =+C8/C5 -> 0.25677009 | D9: =+D8/D5 -> 0.25612932 | E9: =+E8/E5 -> 0.25539972 | F9: =+F8/F5 -> 0.25468869 | G9: =+G8/G5 -> 0.2544016 | H9: =+H8/H5 -> 0.25374532 | I9: =+I8/I5 -> 0.25321007 | J9: =+J8/J5 -> 0.25244668 | ... N9: =+N8/N5 -> 0.25
B10: % YoY Growth | G10: =G8/C8-1 -> 1.3813276 | H10: =H8/D8-1 -> 1.2631249 | I10: =I8/E8-1 -> 1.3834193 | J10: =J8/F8-1 -> 1.1487241 | K10: =K8/G8-1 -> 1.0876922 | L10: =L8/H8-1 -> 1.0578413 | M10: =M8/I8-1 -> 0.89242832 | N10: =N8/J8-1 -> 0.89733629
B12: LTM GAAP Revenue | F12: =SUM(C8:F8) -> 12657.565 | G12: =SUM(D8:G8) -> 15695.075 | H12: =SUM(E8:H8) -> 19211.929 | I12: =SUM(F8:I8) -> 23758.791 | J12: =SUM(G8:J8) -> 28798.994 | K12: =SUM(H8:K8) -> 34494.682 | L12: =SUM(I8:L8) -> 41160.248 | M12: =SUM(J8:M8) -> 48151.127 | N12: =SUM(K8:N8) -> 56611.084
B14: Gross Profit
B15: COGS | C15: 722.2534 | D15: 918.37481 | E15: 1085.7528 | F15: 1453.3984 | G15: 1740.5519 | H15: 2108.5494 | I15: 2628.3375 | J15: 3172.8358 | K15: 3697.5797 | L15: 4401.0711 | M15: 5056.4593 | N15: 6099.5097
B16: Gross Profit | C16: =C8-C15 -> 1476.7253 | D16: =D8-D15 -> 1865.8739 | E16: =E8-E15 -> 2200.9315 | F16: =F8-F15 -> 2934.2545 | G16: =G8-G15 -> 3495.9369 | H16: =H8-H15 -> 4192.5532 | I16: =I8-I15 -> 5205.2092 | J16: =J8-J15 -> 6255.0198 | ... N16: =N8-N15 -> 11788.303
B17: Gross Margin % | C17: =C16/C8 -> 0.67155053 | D17: =D16/D8 -> 0.67015346 | E17: =E16/E8 -> 0.66965101 | F17: =F16/F8 -> 0.66875266 | G17: =G16/G8 -> 0.66761088 | H17: =H16/H8 -> 0.66536819 | I17: =I16/I8 -> 0.66447669 | J17: =J16/J8 -> 0.66346156 | ... N17: =N16/N8 -> 0.6590131
B19: Operating Expenses
B20: S&M | C20: 1200.0106 | D20: 1349.9439 | E20: 1491.0471 | F20: 1617.078 | G20: 1758.3879 | H20: 1902.2561 | I20: 2438.482 | J20: 2927.6113 | K20: 3411.8055 | L20: 4597.6605 | M20: 4968.3289 | N20: 6584.1337
B21: R&D | C21: 2384.2614 | D21: 2500.9067 | E21: 2551.3452 | F21: 2636.7793 | G21: 2660.6691 | H21: 2698.5614 | I21: 3369.0085 | J21: 4151.8057 | K21: 4502.3103 | L21: 5732.0898 | M21: 5605.4327 | N21: 7072.7661
B22: G&A | C22: 1361.0007 | D22: 1326.3992 | E22: 1478.9223 | F22: 1886.0624 | G22: 1697.4529 | H22: 2916.5136 | I22: 3509.8164 | J22: 3710.7398 | K22: 4047.0941 | L22: 4572.464 | M22: 4505.0889 | N22: 4913.5268
B23: Operating Expenses | C23: =SUM(C20:C22) -> 4945.2726 | D23: =SUM(D20:D22) -> 5177.2499 | E23: =SUM(E20:E22) -> 5521.3146 | F23: =SUM(F20:F22) -> 6139.9196 | G23: =SUM(G20:G22) -> 6116.5098 | H23: =SUM(H20:H22) -> 7517.3311 | I23: =SUM(I20:I22) -> 9317.3069 | J23: =SUM(J20:J22) -> 10790.157 | ... N23: =SUM(N20:N22) -> 18570.427
B24: =B20&" as % of Revenue" -> S&M as % of Revenue | C24: =+C20/C$8 -> 0.54571268 | D24: =+D20/D$8 -> 0.48485034 | E24: =+E20/E$8 -> 0.45366301 | F24: =+F20/F$8 -> 0.36855193 | G24: =+G20/G$8 -> 0.33579521 | H24: =+H20/H$8 -> 0.30189257 | I24: =+I20/I$8 -> 0.3112871 | J24: =+J20/J$8 -> 0.3105278 | ... N24: =+N20/N$8 -> 0.36807931
B25: =B21&" as % of Revenue" -> R&D as % of Revenue | C25: =+C21/C$8 -> 1.0842585 | D25: =+D21/D$8 -> 0.89823395 | E25: =+E21/E$8 -> 0.77626718 | F25: =+F21/F$8 -> 0.60095439 | G25: =+G21/G$8 -> 0.50810174 | H25: =+H21/H$8 -> 0.42826812 | I25: =+I21/I$8 -> 0.43007447 | J25: =+J21/J$8 -> 0.44037646 | ... N25: =+N21/N$8 -> 0.39539581
B26: =B22&" as % of Revenue" -> G&A as % of Revenue | C26: =+C22/C$8 -> 0.61892398 | D26: =+D22/D$8 -> 0.47639393 | E26: =+E22/E$8 -> 0.44997395 | F26: =+F22/F$8 -> 0.42985679 | G26: =+G22/G$8 -> 0.3241586 | H26: =+H22/H$8 -> 0.46285766 | I26: =+I22/I$8 -> 0.44804946 | J26: =+J22/J$8 -> 0.39359319 | ... N26: =+N22/N$8 -> 0.27468573
B27: =B23&" as % of Revenue" -> Operating Expenses as % of Revenue | C27: =+C23/C$8 -> 2.2488952 | D27: =+D23/D$8 -> 1.8594782 | E27: =+E23/E$8 -> 1.6799041 | F27: =+F23/F$8 -> 1.3993631 | G27: =+G23/G$8 -> 1.1680556 | H27: =+H23/H$8 -> 1.1930184 | I27: =+I23/I$8 -> 1.189411 | J27: =+J23/J$8 -> 1.1444975 | ... N27: =+N23/N$8 -> 1.0381608
B29: Operating Income | C29: =+C16-C23 -> -3468.5473 | D29: =+D16-D23 -> -3311.376 | E29: =+E16-E23 -> -3320.3831 | F29: =+F16-F23 -> -3205.6651 | G29: =+G16-G23 -> -2620.5729 | H29: =+H16-H23 -> -3324.7779 | I29: =+I16-I23 -> -4112.0977 | J29: =+J16-J23 -> -4535.1369 | ... N29: =+N16-N23 -> -6782.1238
B30: % Margin | C30: =+C29/C8 -> -1.5773446 | D30: =+D29/D8 -> -1.1893248 | E30: =+E29/E8 -> -1.0102531 | F30: =+F29/F8 -> -0.73061046 | G30: =+G29/G8 -> -0.50044468 | H30: =+H29/H8 -> -0.52765017 | I30: =+I29/I8 -> -0.52493434 | J30: =+J29/J8 -> -0.48103589 | ... N30: =+N29/N8 -> -0.37914774
B32: D&A | F32: 532.1409 | G32: 636.10833 | H32: 765.86278 | I32: 929.68827 | J32: 1124.4055 | K32: 1351.9878 | L32: 1608.1003 | M32: 1814.7037 | N32: 2119.6867
B33: EBITDA | F33: =+F29+F32 -> -2673.5242 | G33: =+G29+G32 -> -1984.4646 | H33: =+H29+H32 -> -2558.9151 | I33: =+I29+I32 -> -3182.4094 | J33: =+J29+J32 -> -3410.7314 | K33: =+K29+K32 -> -3374.6249 | L33: =+L29+L32 -> -4728.516 | M33: =+M29+M32 -> -3496.1804 | N33: =+N29+N32 -> -4662.4371
B34: % Margin | F34: =+F33/F8 -> -0.60932901 | G34: =+G33/G8 -> -0.37896856 | H34: =+H33/H8 -> -0.40610592 | I34: =+I33/I8 -> -0.40625396 | J34: =+J33/J8 -> -0.36177171 | K34: =+K33/K8 -> -0.30868737 | L34: =+L33/L8 -> -0.36466698 | M34: =+M33/M8 -> -0.23583918 | N34: =+N33/N8 -> -0.26064881
B36: Interest Expense | F36: 0 | G36: 0 | H36: 0 | I36: 0 | J36: 0 | K36: 0 | L36: 0 | M36: 0 | N36: 0
B37: Taxable Income | F37: =+F29-F36 -> -3205.6651 | G37: =+G29-G36 -> -2620.5729 | H37: =+H29-H36 -> -3324.7779 | I37: =+I29-I36 -> -4112.0977 | J37: =+J29-J36 -> -4535.1369 | K37: =+K29-K36 -> -4726.6127 | L37: =+L29-L36 -> -6336.6164 | M37: =+M29-M36 -> -5310.8841 | N37: =+N29-N36 -> -6782.1238
B39: Taxes | F39: 0 | G39: 0 | H39: 0 | I39: 0 | J39: 0 | K39: 0 | L39: 0 | M39: 0 | N39: 0
B40: Tax Rate | F40: 0.25 | G40: 0.25 | H40: 0.25 | I40: 0.25 | J40: 0.25 | K40: 0.25 | L40: 0.25 | M40: 0.25 | N40: 0.25
B42: Net Income | F42: =+F37-F39 -> -3205.6651 | G42: =+G37-G39 -> -2620.5729 | H42: =+H37-H39 -> -3324.7779 | I42: =+I37-I39 -> -4112.0977 | J42: =+J37-J39 -> -4535.1369 | K42: =+K37-K39 -> -4726.6127 | L42: =+L37-L39 -> -6336.6164 | M42: =+M37-M39 -> -5310.8841 | N42: =+N37-N39 -> -6782.1238
B43: % Margin | F43: =+F42/F8 -> -0.73061046 | G43: =+G42/G8 -> -0.50044468 | H43: =+H42/H8 -> -0.52765017 | I43: =+I42/I8 -> -0.52493434 | J43: =+J42/J8 -> -0.48103589 | K43: =+K42/K8 -> -0.43235787 | L43: =+L42/L8 -> -0.48868498 | M43: =+M42/M8 -> -0.35825227 | N43: =+N42/N8 -> -0.37914774
B45: Note:
B46: Prior Year Renewal ARR for Billing | K46: 5660.477 | L46: 6828.9072 | M46: 8507.6607 | N46: 10270.13
B49: Balance Sheet | AH49: $ in thousands, except noted
N50: =N4 -> 44926 | O50: =O4 -> 45016 | P50: =P4 -> 45107 | Q50: =Q4 -> 45199 | R50: =R4 -> 45291 | S50: =S4 -> 45382 | T50: =T4 -> 45473 | U50: =U4 -> 45565 | ... AH50: =AH4 -> 46752
B51: Cash | N51: 26476.734
B52: Accounts Receivable | N52: 15182.163
B53: Net PP&E | N53: 35699.125
B54: Prepaid Expenses | N54: 4374.0516
B55: Deferred Commissions | N55: 7406.8
B56: Capitalized Software Costs | N56: 2955.4587
B57: Total Assets | N57: =SUM(N51:N56) -> 92094.332
B59: Accounts Payable | N59: 2557.049
B60: Deferred Revenue | N60: 19792.961
B61: Debt | N61: 0
B62: Equity | N62: 69744.322
B63: Total Liabilities & Equity | N63: =SUM(N59:N62) -> 92094.332
B64: Check? | N64: =+N57-N63 -> 0

Sheet Primary Assumptions (Start)
B2: Assumption | C2: Unit | D2: 2023 | E2: 2024 | F2: 2025 | G2: 2026 | H2: 2027
B3: New logo ARR | C3: % of beginning quarterly ARR balance | D3: 0.12 | E3: 0.1 | F3: 0.08 | G3: 0.06 | H3: 0.06
B4: Upsell ARR | C4: " | D4: 0.08 | E4: 0.07 | F4: 0.05 | G4: 0.04 | H4: 0.04
B5: Downsell ARR | C5: " | D5: -0.02 | E5: -0.02 | F5: -0.02 | G5: -0.02 | H5: -0.02
B6: Churn ARR | C6: " | D6: -0.02 | E6: -0.02 | F6: -0.02 | G6: -0.02 | H6: -0.02
B8: COGS | C8: % of quarterly GAAP revenue | D8: 0.65 | E8: 0.65 | F8: 0.65 | G8: 0.65 | H8: 0.65
B9: =Model!B20 -> S&M | C9: " | D9: 0.4 | E9: 0.38 | F9: 0.36 | G9: 0.34 | H9: 0.32
B10: =Model!B21 -> R&D | C10: " | D10: 0.42 | E10: 0.4 | F10: 0.38 | G10: 0.36 | H10: 0.34
B11: =Model!B22 -> G&A | C11: " | D11: 0.3 | E11: 0.28 | F11: 0.26 | G11: 0.24 | H11: 0.22
B13: Note: See prompt for complete list of assumptions

Sheet End ->

Sheet Transaction
B2: Entry | G2: $ in thousands, except noted
B3: Entry Assumptions | E3: Sources
B4: Entry LTM Revenue | C4: =Model!N64 -> 56611.084 | E4: Sponsor Equity | G4: 300000
B5: Entry Multiple | C5: 30 | E5: Total Sources | G5: =SUM(G4) -> 300000
B6: Entry Enterprise Value | C6: =C5*C4 -> 1698332.5
B7: (-) Debt | C7: =Model!L58 -> 0 | E7: Uses
B8: (+) Cash | C8: =Model!L48 -> 26476.734 | E8: Cash to B/S | G8: =G4 -> 300000
B9: Entry Equity Value | C9: =+C6-C7+C8 -> 1724809.3 | E9: Total Uses | G9: =SUM(G8) -> 300000
B11: Pre-Money Shares Outstanding | C11: 525000
B12: Pre-Money Stock Price | C12: =+C9/C11*1000 -> 3285.351
B13: New Shares Issued | C13: =+G4/C12*1000 -> 91314.445
B14: Post-Money Shares Outstanding | C14: =+C13+C11 -> 616314.44
B17: Exit & Returns
B18: Exit Value | E18: Exit Ownership
B19: Exit LTM Revenue | C19: =SUM(Model!AE8:AH8) -> 436393.45 | E19: Initial Ownership | G19: =+C13/C14 -> 0.1481621
B20: Exit Multiple | C20: 16 | E20: Dilution from Stock-Based Compensation | G20: =+Model!AH136 -> 0.13433396
B21: Exit Enterprise Value | C21: =C20*C19 -> 6982295.2 | E21: Exit Ownership | G21: =+G19*(1-G20) -> 0.1282589
B22: (-) Debt | C22: =+Model!AH58 -> 0
B23: (+) Cash | C23: =+Model!AH48 -> 118164.88
B24: Exit Equity value | C24: =+C21+C23-C22 -> 7100460.1
B25: (x) Exit Ownership | C25: =+G21 -> 0.1282589
B26: Exit Sponsor Value | C26: =+C24*C25 -> 910697.21
B28: IRR | C28: =XIRR(C32:C33, C34:C35) -> 0.2485264
B29: M-o-M | C29: =+C33/(-C32) -> 3.0356574
B32: Entry Investment | C32: =+-G4 -> -300000
B33: Exit Proceeds | C33: =+C26 -> 910697.21
B34: Entry Date | C34: =+Model!N4 -> 44926
B35: Exit Date | C35: =+Model!AH4 -> 46752

Sheet Model
B2: Income Statement | AH2: $ in thousands, except noted
C3: =YEAR(C4) -> 2020 | D3: =YEAR(D4) -> 2020 | E3: =YEAR(E4) -> 2020 | F3: =YEAR(F4) -> 2020 | G3: =YEAR(G4) -> 2021 | H3: =YEAR(H4) -> 2021 | I3: =YEAR(I4) -> 2021 | J3: =YEAR(J4) -> 2021 | ... AH3: =YEAR(AH4) -> 2027
C4: 43921 | D4: =EOMONTH(C4, 3) -> 44012 | E4: =EOMONTH(D4, 3) -> 44104 | F4: =EOMONTH(E4, 3) -> 44196 | G4: =EOMONTH(F4, 3) -> 44286 | H4: =EOMONTH(G4, 3) -> 44377 | I4: =EOMONTH(H4, 3) -> 44469 | J4: =EOMONTH(I4, 3) -> 44561 | K4: =EOMONTH(J4, 3) -> 44651 | ... AH4: =EOMONTH(AG4, 3) -> 46752
B5: Ending ARR | C5: =+'ARR Waterfall'!C11 -> 8563.9987 | D5: =+'ARR Waterfall'!D11 -> 10870.48 | E5: =+'ARR Waterfall'!E11 -> 12868.786 | F5: =+'ARR Waterfall'!F11 -> 17227.514 | G5: =+'ARR Waterfall'!G11 -> 20583.553 | H5: =+'ARR Waterfall'!H11 -> 24832.39 | I5: =+'ARR Waterfall'!I11 -> 30936.948 | J5: =+'ARR Waterfall'!J11 -> 37345.929 | ... AH5: =+'ARR Waterfall'!AH11 -> 475243.16
B6: % YoY Growth | G6: =G5/C5-1 -> 1.4034979 | H6: =H5/D5-1 -> 1.2843875 | I6: =I5/E5-1 -> 1.40403 | J6: =J5/F5-1 -> 1.1678072 | K6: =K5/G5-1 -> 1.1093313 | L6: =L5/H5-1 -> 1.0809316 | M6: =M5/I5-1 -> 0.91602693 | N6: =N5/J5-1 -> 0.91590496 | ... AH6: =AH5/AD5-1 -> 0.26247696
B8: GAAP Revenue | C8: 2198.9787 | D8: 2784.2487 | E8: 3286.6844 | F8: 4387.6529 | G8: 5236.4888 | H8: 6301.1027 | I8: 7833.5468 | J8: 9427.8556 | K8: 10932.177 | L8: 12966.669 | M8: 14824.426 | N8: 17887.813 | O8: =O9*O5 -> 20749.863 | P8: =P9*P5 -> 24069.841 | Q8: =Q9*Q5 -> 27921.015 | R8: =R9*R5 -> 32388.377 | S8: =S9*S5 -> 36598.867 | T8: =T9*T5 -> 41356.719 | U8: =U9*U5 -> 46733.093 | V8: =V9*V5 -> 52808.395 | ... AH8: =AH9*AH5 -> 118810.79
B9: % of ARR | C9: =+C8/C5 -> 0.25677009 | D9: =+D8/D5 -> 0.25612932 | E9: =+E8/E5 -> 0.25539972 | F9: =+F8/F5 -> 0.25468869 | G9: =+G8/G5 -> 0.2544016 | H9: =+H8/H5 -> 0.25374532 | I9: =+I8/I5 -> 0.25321007 | J9: =+J8/J5 -> 0.25244668 | ... N9: =+N8/N5 -> 0.25 | O9: 0.25 | P9: 0.25 | Q9: 0.25 | R9: 0.25 | S9: 0.25 | T9: 0.25 | U9: 0.25 | V9: 0.25 | W9: 0.25 | X9: 0.25 | Y9: 0.25 | Z9: 0.25 | AA9: 0.25 | AB9: 0.25 | AC9: 0.25 | AD9: 0.25 | AE9: 0.25 | AF9: 0.25 | AG9: 0.25 | AH9: 0.25
B10: % YoY Growth | G10: =G8/C8-1 -> 1.3813276 | H10: =H8/D8-1 -> 1.2631249 | I10: =I8/E8-1 -> 1.3834193 | J10: =J8/F8-1 -> 1.1487241 | K10: =K8/G8-1 -> 1.0876922 | L10: =L8/H8-1 -> 1.0578413 | M10: =M8/I8-1 -> 0.89242832 | N10: =N8/J8-1 -> 0.89733629 | ... AH10: =AH8/AD8-1 -> 0.26247696
B12: LTM GAAP Revenue | F12: =SUM(C8:F8) -> 12657.565 | G12: =SUM(D8:G8) -> 15695.075 | H12: =SUM(E8:H8) -> 19211.929 | I12: =SUM(F8:I8) -> 23758.791 | J12: =SUM(G8:J8) -> 28798.994 | K12: =SUM(H8:K8) -> 34494.682 | L12: =SUM(I8:L8) -> 41160.248 | M12: =SUM(J8:M8) -> 48151.127 | ... AH12: =SUM(AE8:AH8) -> 436393.45
B14: Gross Profit
B15: COGS | C15: 722.2534 | D15: 918.37481 | E15: 1085.7528 | F15: 1453.3984 | G15: 1740.5519 | H15: 2108.5494 | I15: 2628.3375 | J15: 3172.8358 | K15: 3697.5797 | L15: 4401.0711 | M15: 5056.4593 | N15: 6099.5097 | O15: =(1-O17)*O8 -> 7262.4519 | P15: =(1-P17)*P8 -> 8424.4442 | Q15: =(1-Q17)*Q8 -> 9772.3553 | R15: =(1-R17)*R8 -> 11335.932 | S15: =(1-S17)*S8 -> 12809.603 | T15: =(1-T17)*T8 -> 14474.852 | U15: =(1-U17)*U8 -> 16356.582 | V15: =(1-V17)*V8 -> 18482.938 | ... AH15: =(1-AH17)*AH8 -> 41583.776
B16: Gross Profit | C16: =C8-C15 -> 1476.7253 | D16: =D8-D15 -> 1865.8739 | E16: =E8-E15 -> 2200.9315 | F16: =F8-F15 -> 2934.2545 | G16: =G8-G15 -> 3495.9369 | H16: =H8-H15 -> 4192.5532 | I16: =I8-I15 -> 5205.2092 | J16: =J8-J15 -> 6255.0198 | ... AH16: =AH8-AH15 -> 77227.013
B17: Gross Margin % | C17: =C16/C8 -> 0.67155053 | D17: =D16/D8 -> 0.67015346 | E17: =E16/E8 -> 0.66965101 | F17: =F16/F8 -> 0.66875266 | G17: =G16/G8 -> 0.66761088 | H17: =H16/H8 -> 0.66536819 | I17: =I16/I8 -> 0.66447669 | J17: =J16/J8 -> 0.66346156 | ... N17: =N16/N8 -> 0.6590131 | O17: 0.65 | P17: 0.65 | Q17: 0.65 | R17: 0.65 | S17: 0.65 | T17: 0.65 | U17: 0.65 | V17: 0.65 | W17: 0.65 | X17: 0.65 | Y17: 0.65 | Z17: 0.65 | AA17: 0.65 | AB17: 0.65 | AC17: 0.65 | AD17: 0.65 | AE17: 0.65 | AF17: 0.65 | AG17: 0.65 | AH17: 0.65
B19: Operating Expenses
B20: S&M | C20: 1200.0106 | D20: 1349.9439 | E20: 1491.0471 | F20: 1617.078 | G20: 1758.3879 | H20: 1902.2561 | I20: 2438.482 | J20: 2927.6113 | K20: 3411.8055 | L20: 4597.6605 | M20: 4968.3289 | N20: 6584.1337 | O20: =O$8*O24 -> 8299.945 | P20: =P$8*P24 -> 9627.9362 | Q20: =Q$8*Q24 -> 11168.406 | R20: =R$8*R24 -> 12955.351 | S20: =S$8*S24 -> 13907.569 | T20: =T$8*T24 -> 15715.553 | U20: =U$8*U24 -> 17758.575 | V20: =V$8*V24 -> 20067.19 | ... AH20: =AH$8*AH24 -> 38019.453
B21: R&D | C21: 2384.2614 | D21: 2500.9067 | E21: 2551.3452 | F21: 2636.7793 | G21: 2660.6691 | H21: 2698.5614 | I21: 3369.0085 | J21: 4151.8057 | K21: 4502.3103 | L21: 5732.0898 | M21: 5605.4327 | N21: 7072.7661 | O21: =O$8*O25 -> 8714.9423 | P21: =P$8*P25 -> 10109.333 | Q21: =Q$8*Q25 -> 11726.826 | R21: =R$8*R25 -> 13603.119 | S21: =S$8*S25 -> 14639.547 | T21: =T$8*T25 -> 16542.688 | U21: =U$8*U25 -> 18693.237 | V21: =V$8*V25 -> 21123.358 | ... AH21: =AH$8*AH25 -> 40395.668
B22: G&A | C22: 1361.0007 | D22: 1326.3992 | E22: 1478.9223 | F22: 1886.0624 | G22: 1697.4529 | H22: 2916.5136 | I22: 3509.8164 | J22: 3710.7398 | K22: 4047.0941 | L22: 4572.464 | M22: 4505.0889 | N22: 4913.5268 | O22: =O$8*O26 -> 6224.9588 | P22: =P$8*P26 -> 7220.9522 | Q22: =Q$8*Q26 -> 8376.3045 | R22: =R$8*R26 -> 9716.5132 | S22: =S$8*S26 -> 10247.683 | T22: =T$8*T26 -> 11579.881 | U22: =U$8*U26 -> 13085.266 | V22: =V$8*V26 -> 14786.351 | ... AH22: =AH$8*AH26 -> 26138.374
B23: Operating Expenses | C23: =SUM(C20:C22) -> 4945.2726 | D23: =SUM(D20:D22) -> 5177.2499 | E23: =SUM(E20:E22) -> 5521.3146 | F23: =SUM(F20:F22) -> 6139.9196 | G23: =SUM(G20:G22) -> 6116.5098 | H23: =SUM(H20:H22) -> 7517.3311 | I23: =SUM(I20:I22) -> 9317.3069 | J23: =SUM(J20:J22) -> 10790.157 | ... AH23: =SUM(AH20:AH22) -> 104553.49
B24: =B20&" as % of Revenue" -> S&M as % of Revenue | C24: =+C20/C$8 -> 0.54571268 | D24: =+D20/D$8 -> 0.48485034 | E24: =+E20/E$8 -> 0.45366301 | F24: =+F20/F$8 -> 0.36855193 | G24: =+G20/G$8 -> 0.33579521 | H24: =+H20/H$8 -> 0.30189257 | I24: =+I20/I$8 -> 0.3112871 | J24: =+J20/J$8 -> 0.3105278 | ... N24: =+N20/N$8 -> 0.36807931 | O24: 0.4 | P24: 0.4 | Q24: 0.4 | R24: 0.4 | S24: 0.38 | T24: 0.38 | U24: 0.38 | V24: 0.38 | W24: 0.36 | X24: 0.36 | Y24: 0.36 | Z24: 0.36 | AA24: 0.34 | AB24: 0.34 | AC24: 0.34 | AD24: 0.34 | AE24: 0.32 | AF24: 0.32 | AG24: 0.32 | AH24: 0.32
B25: =B21&" as % of Revenue" -> R&D as % of Revenue | C25: =+C21/C$8 -> 1.0842585 | D25: =+D21/D$8 -> 0.89823395 | E25: =+E21/E$8 -> 0.77626718 | F25: =+F21/F$8 -> 0.60095439 | G25: =+G21/G$8 -> 0.50810174 | H25: =+H21/H$8 -> 0.42826812 | I25: =+I21/I$8 -> 0.43007447 | J25: =+J21/J$8 -> 0.44037646 | ... N25: =+N21/N$8 -> 0.39539581 | O25: 0.42 | P25: 0.42 | Q25: 0.42 | R25: 0.42 | S25: 0.4 | T25: 0.4 | U25: 0.4 | V25: 0.4 | W25: 0.38 | X25: 0.38 | Y25: 0.38 | Z25: 0.38 | AA25: 0.36 | AB25: 0.36 | AC25: 0.36 | AD25: 0.36 | AE25: 0.34 | AF25: 0.34 | AG25: 0.34 | AH25: 0.34
B26: =B22&" as % of Revenue" -> G&A as % of Revenue | C26: =+C22/C$8 -> 0.61892398 | D26: =+D22/D$8 -> 0.47639393 | E26: =+E22/E$8 -> 0.44997395 | F26: =+F22/F$8 -> 0.42985679 | G26: =+G22/G$8 -> 0.3241586 | H26: =+H22/H$8 -> 0.46285766 | I26: =+I22/I$8 -> 0.44804946 | J26: =+J22/J$8 -> 0.39359319 | ... N26: =+N22/N$8 -> 0.27468573 | O26: 0.3 | P26: 0.3 | Q26: 0.3 | R26: 0.3 | S26: 0.28 | T26: 0.28 | U26: 0.28 | V26: 0.28 | W26: 0.26 | X26: 0.26 | Y26: 0.26 | Z26: 0.26 | AA26: 0.24 | AB26: 0.24 | AC26: 0.24 | AD26: 0.24 | AE26: 0.22 | AF26: 0.22 | AG26: 0.22 | AH26: 0.22
B27: =B23&" as % of Revenue" -> Operating Expenses as % of Revenue | C27: =+C23/C$8 -> 2.2488952 | D27: =+D23/D$8 -> 1.8594782 | E27: =+E23/E$8 -> 1.6799041 | F27: =+F23/F$8 -> 1.3993631 | G27: =+G23/G$8 -> 1.1680556 | H27: =+H23/H$8 -> 1.1930184 | I27: =+I23/I$8 -> 1.189411 | J27: =+J23/J$8 -> 1.1444975 | ... AH27: =+AH23/AH$8 -> 0.88
B29: Operating Income | C29: =+C16-C23 -> -3468.5473 | D29: =+D16-D23 -> -3311.376 | E29: =+E16-E23 -> -3320.3831 | F29: =+F16-F23 -> -3205.6651 | G29: =+G16-G23 -> -2620.5729 | H29: =+H16-H23 -> -3324.7779 | I29: =+I16-I23 -> -4112.0977 | J29: =+J16-J23 -> -4535.1369 | ... AH29: =+AH16-AH23 -> -27326.481
B30: % Margin | C30: =+C29/C8 -> -1.5773446 | D30: =+D29/D8 -> -1.1893248 | E30: =+E29/E8 -> -1.0102531 | F30: =+F29/F8 -> -0.73061046 | G30: =+G29/G8 -> -0.50044468 | H30: =+H29/H8 -> -0.52765017 | I30: =+I29/I8 -> -0.52493434 | J30: =+J29/J8 -> -0.48103589 | ... AH30: =+AH29/AH8 -> -0.23
B32: D&A | F32: 532.1409 | G32: 636.10833 | H32: 765.86278 | I32: 929.68827 | J32: 1124.4055 | K32: 1351.9878 | L32: 1608.1003 | M32: 1814.7037 | N32: 2119.6867 | O32: =+O106+O107 -> 2093.5817 | P32: =+P106+P107 -> 2484.4798 | Q32: =+Q106+Q107 -> 2942.2599 | R32: =+R106+R107 -> 3459.4552 | S32: =+S106+S107 -> 4039.9687 | T32: =+T106+T107 -> 4668.7375 | U32: =+U106+U107 -> 5364.8043 | V32: =+V106+V107 -> 6134.6073 | ... AH32: =+AH106+AH107 -> 16008.64
B33: EBITDA | F33: =+F29+F32 -> -2673.5242 | G33: =+G29+G32 -> -1984.4646 | H33: =+H29+H32 -> -2558.9151 | I33: =+I29+I32 -> -3182.4094 | J33: =+J29+J32 -> -3410.7314 | K33: =+K29+K32 -> -3374.6249 | L33: =+L29+L32 -> -4728.516 | M33: =+M29+M32 -> -3496.1804 | ... AH33: =+AH29+AH32 -> -11317.841
B34: % Margin | F34: =+F33/F8 -> -0.60932901 | G34: =+G33/G8 -> -0.37896856 | H34: =+H33/H8 -> -0.40610592 | I34: =+I33/I8 -> -0.40625396 | J34: =+J33/J8 -> -0.36177171 | K34: =+K33/K8 -> -0.30868737 | L34: =+L33/L8 -> -0.36466698 | M34: =+M33/M8 -> -0.23583918 | ... AH34: =+AH33/AH8 -> -0.095259372
B36: Interest Expense | F36: 0 | G36: 0 | H36: 0 | I36: 0 | J36: 0 | K36: 0 | L36: 0 | M36: 0 | N36: 0 | O36: 0 | P36: 0 | Q36: 0 | R36: 0 | S36: 0 | T36: 0 | U36: 0 | V36: 0 | W36: 0 | X36: 0 | Y36: 0 | Z36: 0 | AA36: 0 | AB36: 0 | AC36: 0 | AD36: 0 | AE36: 0 | AF36: 0 | AG36: 0 | AH36: 0
B37: Taxable Income | F37: =+F29-F36 -> -3205.6651 | G37: =+G29-G36 -> -2620.5729 | H37: =+H29-H36 -> -3324.7779 | I37: =+I29-I36 -> -4112.0977 | J37: =+J29-J36 -> -4535.1369 | K37: =+K29-K36 -> -4726.6127 | L37: =+L29-L36 -> -6336.6164 | M37: =+M29-M36 -> -5310.8841 | ... AH37: =+AH29-AH36 -> -27326.481
B39: Taxes | F39: 0 | G39: 0 | H39: 0 | I39: 0 | J39: 0 | K39: 0 | L39: 0 | M39: 0 | N39: 0 | O39: =IF(O37<0, 0, O37*O40) -> 0 | P39: =IF(P37<0, 0, P37*P40) -> 0 | Q39: =IF(Q37<0, 0, Q37*Q40) -> 0 | R39: =IF(R37<0, 0, R37*R40) -> 0 | S39: =IF(S37<0, 0, S37*S40) -> 0 | T39: =IF(T37<0, 0, T37*T40) -> 0 | U39: =IF(U37<0, 0, U37*U40) -> 0 | V39: =IF(V37<0, 0, V37*V40) -> 0 | ... AH39: =IF(AH37<0, 0, AH37*AH40) -> 0
B40: Tax Rate | F40: 0.25 | G40: 0.25 | H40: 0.25 | I40: 0.25 | J40: 0.25 | K40: 0.25 | L40: 0.25 | M40: 0.25 | N40: 0.25 | O40: 0.25 | P40: 0.25 | Q40: 0.25 | R40: 0.25 | S40: 0.25 | T40: 0.25 | U40: 0.25 | V40: 0.25 | W40: 0.25 | X40: 0.25 | Y40: 0.25 | Z40: 0.25 | AA40: 0.25 | AB40: 0.25 | AC40: 0.25 | AD40: 0.25 | AE40: 0.25 | AF40: 0.25 | AG40: 0.25 | AH40: 0.25
B42: Net Income | F42: =+F37-F39 -> -3205.6651 | G42: =+G37-G39 -> -2620.5729 | H42: =+H37-H39 -> -3324.7779 | I42: =+I37-I39 -> -4112.0977 | J42: =+J37-J39 -> -4535.1369 | K42: =+K37-K39 -> -4726.6127 | L42: =+L37-L39 -> -6336.6164 | M42: =+M37-M39 -> -5310.8841 | ... AH42: =+AH37-AH39 -> -27326.481
B43: % Margin | F43: =+F42/F8 -> -0.73061046 | G43: =+G42/G8 -> -0.50044468 | H43: =+H42/H8 -> -0.52765017 | I43: =+I42/I8 -> -0.52493434 | J43: =+J42/J8 -> -0.48103589 | K43: =+K42/K8 -> -0.43235787 | L43: =+L42/L8 -> -0.48868498 | M43: =+M42/M8 -> -0.35825227 | ... AH43: =+AH42/AH8 -> -0.23
B46: Balance Sheet | L46: Actual | N46: PF | AH46: $ in thousands, except noted
L47: =N4 -> 44926 | M47: Adj. | N47: =+L47 -> 44926 | O47: =O4 -> 45016 | P47: =P4 -> 45107 | Q47: =Q4 -> 45199 | R47: =R4 -> 45291 | S47: =S4 -> 45382 | T47: =T4 -> 45473 | U47: =U4 -> 45565 | V47: =V4 -> 45657 | ... AH47: =AH4 -> 46752
B48: Cash | L48: 26476.734 | M48: =Transaction!G8 -> 300000 | N48: =+M48+L48 -> 326476.73 | O48: =+O119 -> 318575.88 | P48: =+P119 -> 309646.37 | Q48: =+Q119 -> 299517.55 | R48: =+R119 -> 288309.15 | S48: =+S119 -> 278010.43 | T48: =+T119 -> 266296 | U48: =+U119 -> 253503.79 | V48: =+V119 -> 239769.99 | ... AH48: =+AH119 -> 118164.88
B49: Accounts Receivable | L49: 15182.163 | N49: =+M49+L49 -> 15182.163 | O49: =O92 -> 16390.475 | P49: =P92 -> 18237.018 | Q49: =Q92 -> 20092.296 | R49: =R92 -> 22769.334 | S49: =S92 -> 24414.272 | T49: =T92 -> 27054.91 | U49: =U92 -> 29767.677 | V49: =V92 -> 33367.461 | ... AH49: =AH92 -> 67051.233
B50: Net PP&E | L50: 35699.125 | N50: =+M50+L50 -> 35699.125 | O50: =+O82 -> 36031.269 | P50: =+P82 -> 36418.929 | Q50: =+Q82 -> 36872.071 | R50: =+R82 -> 37397.717 | S50: =+S82 -> 38002.607 | T50: =+T82 -> 38693.932 | U50: =+U82 -> 39479.317 | V50: =+V82 -> 40366.803 | ... AH50: =+AH82 -> 59307.169
B51: Prepaid Expenses | L51: 4374.0516 | N51: =+M51+L51 -> 4374.0516 | O51: =O73*O64 -> 5115.0153 | P51: =P73*P64 -> 5969.9595 | Q51: =Q73*Q64 -> 6978.3969 | R51: =R73*R64 -> 8094.9404 | S51: =S73*S64 -> 9315.3137 | T51: =T73*T64 -> 10646.403 | U51: =U73*U64 -> 12094.933 | V51: =V73*V64 -> 13667.275 | ... AH51: =AH73*AH64 -> 33602.295
B52: Deferred Commissions | L52: 7406.8 | N52: =+M52+L52 -> 7406.8 | O52: =Capitalizations!H9 -> 8449.5557 | P52: =Capitalizations!I9 -> 9619.5772 | Q52: =Capitalizations!J9 -> 10937.227 | R52: =Capitalizations!K9 -> 12426.126 | S52: =Capitalizations!L9 -> 13889.546 | T52: =Capitalizations!M9 -> 15482.77 | U52: =Capitalizations!N9 -> 17222.672 | V52: =Capitalizations!O9 -> 19128.321 | ... AH52: =Capitalizations!AA9 -> 41600.197
B53: Capitalized Software Costs | L53: 2955.4587 | N53: =+M53+L53 -> 2955.4587 | O53: =Capitalizations!H49 -> 3417.7317 | P53: =Capitalizations!I49 -> 3947.1098 | Q53: =Capitalizations!J49 -> 4554.3297 | R53: =Capitalizations!K49 -> 5251.8462 | S53: =Capitalizations!L49 -> 5974.3018 | T53: =Capitalizations!M49 -> 6778.7388 | U53: =Capitalizations!N49 -> 7675.8149 | V53: =Capitalizations!O49 -> 8677.5731 | ... AH53: =Capitalizations!AA49 -> 21773.547
B54: Total Assets | L54: =SUM(L48:L53) -> 92094.332 | N54: =SUM(N48:N53) -> 392094.33 | O54: =SUM(O48:O53) -> 387979.93 | P54: =SUM(P48:P53) -> 383838.96 | Q54: =SUM(Q48:Q53) -> 378951.87 | R54: =SUM(R48:R53) -> 374249.11 | S54: =SUM(S48:S53) -> 369606.47 | T54: =SUM(T48:T53) -> 364952.76 | U54: =SUM(U48:U53) -> 359744.21 | ... AH54: =SUM(AH48:AH53) -> 341499.33
B56: Accounts Payable | L56: 2557.049 | N56: =+M56+L56 -> 2557.049 | O56: =O72*O15/90 -> 2824.2869 | P56: =P72*P15/90 -> 3276.1727 | Q56: =Q72*Q15/90 -> 3800.3604 | R56: =R72*R15/90 -> 4408.418 | S56: =S72*S15/90 -> 4981.5124 | T56: =T72*T15/90 -> 5629.109 | U56: =U72*U15/90 -> 6360.8932 | V56: =V72*V15/90 -> 7187.8093 | ... AH56: =AH72*AH15/90 -> 16171.469
B57: Deferred Revenue | L57: 19792.961 | N57: =+M57+L57 -> 19792.961 | O57: =O98 -> 19063.294 | P57: =P98 -> 18706.734 | Q57: =Q98 -> 18209.556 | R57: =R98 -> 18599.091 | S57: =S98 -> 18068.014 | T57: =T98 -> 18060.36 | U57: =U98 -> 18101.866 | V57: =V98 -> 19267.639 | ... AH57: =AH98 -> 21943.616
B58: Debt | L58: 0 | N58: =+M58+L58 -> 0 | O58: =N58 -> 0 | P58: =O58 -> 0 | Q58: =P58 -> 0 | R58: =Q58 -> 0 | S58: =R58 -> 0 | T58: =S58 -> 0 | U58: =T58 -> 0 | V58: =U58 -> 0 | ... AH58: =AG58 -> 0
B59: Equity | L59: 69744.322 | M59: =Transaction!G4 -> 300000 | N59: =+M59+L59 -> 369744.32 | O59: =N59+O42+O109 -> 366092.35 | P59: =O59+P42+P109 -> 361856.05 | Q59: =P59+Q42+Q109 -> 356941.96 | R59: =Q59+R42+R109 -> 351241.6 | S59: =R59+S42+S109 -> 346556.95 | T59: =S59+T42+T109 -> 341263.29 | U59: =T59+U42+U109 -> 335281.45 | V59: =U59+V42+V109 -> 328521.98 | ... AH59: =AG59+AH42+AH109 -> 303384.24
B60: Total Liabilities & Equity | L60: =SUM(L56:L59) -> 92094.332 | N60: =SUM(N56:N59) -> 392094.33 | O60: =SUM(O56:O59) -> 387979.93 | P60: =SUM(P56:P59) -> 383838.96 | Q60: =SUM(Q56:Q59) -> 378951.87 | R60: =SUM(R56:R59) -> 374249.11 | S60: =SUM(S56:S59) -> 369606.47 | T60: =SUM(T56:T59) -> 364952.76 | U60: =SUM(U56:U59) -> 359744.21 | ... AH60: =SUM(AH56:AH59) -> 341499.33
B61: Check? | L61: =+L54-L60 -> 0 | N61: =+N54-N60 -> 0 | O61: =+O54-O60 -> 0 | P61: =+P54-P60 -> 0 | Q61: =+Q54-Q60 -> 0 | R61: =+R54-R60 -> 0 | S61: =+S54-S60 -> 0 | T61: =+T54-T60 -> 0 | U61: =+U54-U60 -> 0 | ... AH61: =+AH54-AH60 -> 0
B63: Memo
B64: LTM GAAP Revenue | L64: =+N64 -> 56611.084 | N64: =SUM(K8:N8) -> 56611.084 | O64: =SUM(L8:O8) -> 66428.77 | P64: =SUM(M8:P8) -> 77531.941 | Q64: =SUM(N8:Q8) -> 90628.531 | R64: =SUM(O8:R8) -> 105129.1 | S64: =SUM(P8:S8) -> 120978.1 | T64: =SUM(Q8:T8) -> 138264.98 | U64: =SUM(R8:U8) -> 157077.06 | ... AH64: =SUM(AE8:AH8) -> 436393.45
B65: LTM COGS | L65: =+N65 -> 19254.62 | N65: =N15+M15+L15+K15 -> 19254.62 | O65: =O15+N15+M15+L15 -> 22819.492 | P65: =P15+O15+N15+M15 -> 26842.865 | Q65: =Q15+P15+O15+N15 -> 31558.761 | R65: =R15+Q15+P15+O15 -> 36795.184 | S65: =S15+R15+Q15+P15 -> 42342.335 | T65: =T15+S15+R15+Q15 -> 48392.742 | U65: =U15+T15+S15+R15 -> 54976.97 | ... AH65: =AH15+AG15+AF15+AE15 -> 152737.71
B66: LTM S&M Expense | L66: =+N66 -> 19561.929 | N66: =SUM(K20:N20) -> 19561.929 | O66: =SUM(L20:O20) -> 24450.068 | P66: =SUM(M20:P20) -> 29480.344 | Q66: =SUM(N20:Q20) -> 35680.421 | R66: =SUM(O20:R20) -> 42051.638 | S66: =SUM(P20:S20) -> 47659.263 | T66: =SUM(Q20:T20) -> 53746.88 | U66: =SUM(R20:U20) -> 60337.049 | ... AH66: =SUM(AE20:AH20) -> 139645.9
B67: LTM R&D Expense | L67: =+N67 -> 22912.599 | N67: =SUM(K21:N21) -> 22912.599 | O67: =SUM(L21:O21) -> 27125.231 | P67: =SUM(M21:P21) -> 31502.474 | Q67: =SUM(N21:Q21) -> 37623.868 | R67: =SUM(O21:R21) -> 44154.22 | S67: =SUM(P21:S21) -> 50078.825 | T67: =SUM(Q21:T21) -> 56512.179 | U67: =SUM(R21:U21) -> 63478.59 | ... AH67: =SUM(AE21:AH21) -> 148373.77
B68: Net Working Capital | L68: =+L49+L51-L56-L57 -> -2793.796 | N68: =+N49+N51-N56-N57 -> -2793.796 | O68: =+O49+O51-O56-O57 -> -382.09044 | P68: =+P49+P51-P56-P57 -> 2224.0706 | Q68: =+Q49+Q51-Q56-Q57 -> 5060.7767 | R68: =+R49+R51-R56-R57 -> 7856.7652 | S68: =+S49+S51-S56-S57 -> 10680.06 | T68: =+T49+T51-T56-T57 -> 14011.844 | U68: =+U49+U51-U56-U57 -> 17399.851 | ... AH68: =+AH49+AH51-AH56-AH57 -> 62538.445
B70: Metrics & Drivers
B71: Receivable Days Outstanding | N71: =N49/N8*90 -> 76.386905 | O71: =O49/O8*90 -> 71.091689 | P71: =P49/P8*90 -> 68.19038 | Q71: =Q49/Q8*90 -> 64.765076 | R71: =R49/R8*90 -> 63.270846 | S71: =S49/S8*90 -> 60.036955 | T71: =T49/T8*90 -> 58.876573 | U71: =U49/U8*90 -> 57.32749 | ... AH71: =AH49/AH8*90 -> 50.791776
B72: Payable Days Outstanding | N72: =N56/N15*90 -> 37.729986 | O72: 35 | P72: =O72 -> 35 | Q72: =P72 -> 35 | R72: =Q72 -> 35 | S72: =R72 -> 35 | T72: =S72 -> 35 | U72: =T72 -> 35 | V72: =U72 -> 35 | W72: =V72 -> 35 | ... AH72: =AG72 -> 35
B73: Prepaid Expenses, % of LTM Rev | N73: =N51/N64 -> 0.077264932 | O73: 0.077 | P73: =O73 -> 0.077 | Q73: =P73 -> 0.077 | R73: =Q73 -> 0.077 | S73: =R73 -> 0.077 | T73: =S73 -> 0.077 | U73: =T73 -> 0.077 | V73: =U73 -> 0.077 | W73: =V73 -> 0.077 | ... AH73: =AG73 -> 0.077
B74: Deferred Commissions, % of LTM S&M Expense | N74: =+N52/N66 -> 0.37863342 | O74: =+O52/O66 -> 0.34558414 | P74: =+P52/P66 -> 0.32630478 | Q74: =+Q52/Q66 -> 0.30653301 | R74: =+R52/R66 -> 0.29549683 | S74: =+S52/S66 -> 0.29143434 | T74: =+T52/T66 -> 0.28806825 | U74: =+U52/U66 -> 0.28544107 | ... AH74: =+AH52/AH66 -> 0.29789773
B75: Capitalized Software Costs, % of LTM R&D Expense | N75: =N53/N67 -> 0.12898836 | O75: =O53/O67 -> 0.12599825 | P75: =P53/P67 -> 0.12529523 | Q75: =Q53/Q67 -> 0.12104895 | R75: =R53/R67 -> 0.11894325 | S75: =S53/S67 -> 0.11929796 | T75: =T53/T67 -> 0.11995182 | U75: =U53/U67 -> 0.12091974 | ... AH75: =AH53/AH67 -> 0.14674795
B76: Deferred Revenue, % of ARR | N76: =N57/N5 -> 0.27662635 | O76: =O57/O5 -> 0.22967976 | P76: =P57/P5 -> 0.1942964 | Q76: =Q57/Q5 -> 0.16304525 | R76: =R57/R5 -> 0.143563 | S76: =S57/S5 -> 0.12341922 | T76: =T57/T5 -> 0.10917428 | U76: =U57/U5 -> 0.096836441 | ... AH76: =AH57/AH5 -> 0.046173449
B78: Net PP&E
B79: Beginning Net PP&E | O79: =+N82 -> 35699.125 | P79: =+O82 -> 36031.269 | Q79: =+P82 -> 36418.929 | R79: =+Q82 -> 36872.071 | S79: =+R82 -> 37397.717 | T79: =+S82 -> 38002.607 | U79: =+T82 -> 38693.932 | V79: =+U82 -> 39479.317 | ... AH79: =+AG82 -> 57125.202
B80: Capex | O80: =O86*O64 -> 1660.7192 | P80: =P86*P64 -> 1938.2985 | Q80: =Q86*Q64 -> 2265.7133 | R80: =R86*R64 -> 2628.2274 | S80: =S86*S64 -> 3024.4525 | T80: =T86*T64 -> 3456.6245 | U80: =U86*U64 -> 3926.9264 | V80: =V86*V64 -> 4437.4268 | ... AH80: =AH86*AH64 -> 10909.836
B81: Depreciation | O81: =-O85*O64 -> -1328.5754 | P81: =-P85*P64 -> -1550.6388 | Q81: =-Q85*Q64 -> -1812.5706 | R81: =-R85*R64 -> -2102.5819 | S81: =-S85*S64 -> -2419.562 | T81: =-T85*T64 -> -2765.2996 | U81: =-U85*U64 -> -3141.5411 | V81: =-V85*V64 -> -3549.9415 | ... AH81: =-AH85*AH64 -> -8727.869
B82: Ending Net PP&E | N82: =+N50 -> 35699.125 | O82: =SUM(O79:O81) -> 36031.269 | P82: =SUM(P79:P81) -> 36418.929 | Q82: =SUM(Q79:Q81) -> 36872.071 | R82: =SUM(R79:R81) -> 37397.717 | S82: =SUM(S79:S81) -> 38002.607 | T82: =SUM(T79:T81) -> 38693.932 | U82: =SUM(U79:U81) -> 39479.317 | V82: =SUM(V79:V81) -> 40366.803 | ... AH82: =SUM(AH79:AH81) -> 59307.169
B84: Drivers:
B85: Depreciation as % of LTM Rev | O85: 0.02 | P85: =O85 -> 0.02 | Q85: =P85 -> 0.02 | R85: =Q85 -> 0.02 | S85: =R85 -> 0.02 | T85: =S85 -> 0.02 | U85: =T85 -> 0.02 | V85: =U85 -> 0.02 | W85: =V85 -> 0.02 | ... AH85: =AG85 -> 0.02
B86: Capex as % of LTM Rev | O86: 0.025 | P86: 0.025 | Q86: 0.025 | R86: 0.025 | S86: 0.025 | T86: 0.025 | U86: 0.025 | V86: 0.025 | W86: 0.025 | X86: 0.025 | Y86: 0.025 | Z86: 0.025 | AA86: 0.025 | AB86: 0.025 | AC86: 0.025 | AD86: 0.025 | AE86: 0.025 | AF86: 0.025 | AG86: 0.025 | AH86: 0.025
B88: Accounts Receivable
B89: Beginning Accounts Receivable | O89: =+N92 -> 15182.163 | P89: =+O92 -> 16390.475 | Q89: =+P92 -> 18237.018 | R89: =+Q92 -> 20092.296 | S89: =+R92 -> 22769.334 | T89: =+S92 -> 24414.272 | U89: =+T92 -> 27054.91 | V89: =+U92 -> 29767.677 | ... AH89: =+AG92 -> 62715.353
B90: New Billings | O90: =+'Billing Waterfall'!I69 -> 20020.195 | P90: =+'Billing Waterfall'!J69 -> 23713.28 | Q90: =+'Billing Waterfall'!K69 -> 27423.837 | R90: =+'Billing Waterfall'!L69 -> 32777.912 | S90: =+'Billing Waterfall'!M69 -> 36067.79 | T90: =+'Billing Waterfall'!N69 -> 41349.065 | U90: =+'Billing Waterfall'!O69 -> 46774.598 | V90: =+'Billing Waterfall'!P69 -> 53974.168 | ... AH90: =+'Billing Waterfall'!AB69 -> 121341.71
B91: Cash Collected | O91: =+-'Billing Waterfall'!I126 -> -18811.883 | P91: =+-'Billing Waterfall'!J126 -> -21866.738 | Q91: =+-'Billing Waterfall'!K126 -> -25568.559 | R91: =+-'Billing Waterfall'!L126 -> -30100.875 | S91: =+-'Billing Waterfall'!M126 -> -34422.851 | T91: =+-'Billing Waterfall'!N126 -> -38708.428 | U91: =+-'Billing Waterfall'!O126 -> -44061.832 | V91: =+-'Billing Waterfall'!P126 -> -50374.383 | ... AH91: =+-'Billing Waterfall'!AB126 -> -117005.83
B92: Ending Accounts Receivable | N92: =N49 -> 15182.163 | O92: =SUM(O89:O91) -> 16390.475 | P92: =SUM(P89:P91) -> 18237.018 | Q92: =SUM(Q89:Q91) -> 20092.296 | R92: =SUM(R89:R91) -> 22769.334 | S92: =SUM(S89:S91) -> 24414.272 | T92: =SUM(T89:T91) -> 27054.91 | U92: =SUM(U89:U91) -> 29767.677 | V92: =SUM(V89:V91) -> 33367.461 | ... AH92: =SUM(AH89:AH91) -> 67051.233
B94: Deferred Revenue
B95: Beginning Deferred Revenue | O95: =+N98 -> 19792.961 | P95: =+O98 -> 19063.294 | Q95: =+P98 -> 18706.734 | R95: =+Q98 -> 18209.556 | S95: =+R98 -> 18599.091 | T95: =+S98 -> 18068.014 | U95: =+T98 -> 18060.36 | V95: =+U98 -> 18101.866 | ... AH95: =+AG98 -> 19412.693
B96: New Billings | O96: =O90 -> 20020.195 | P96: =P90 -> 23713.28 | Q96: =Q90 -> 27423.837 | R96: =R90 -> 32777.912 | S96: =S90 -> 36067.79 | T96: =T90 -> 41349.065 | U96: =U90 -> 46774.598 | V96: =V90 -> 53974.168 | ... AH96: =AH90 -> 121341.71
B97: Recognized Revenue | O97: =-O8 -> -20749.863 | P97: =-P8 -> -24069.841 | Q97: =-Q8 -> -27921.015 | R97: =-R8 -> -32388.377 | S97: =-S8 -> -36598.867 | T97: =-T8 -> -41356.719 | U97: =-U8 -> -46733.093 | V97: =-V8 -> -52808.395 | ... AH97: =-AH8 -> -118810.79
B98: Ending Deferred Revenue | N98: =N57 -> 19792.961 | O98: =SUM(O95:O97) -> 19063.294 | P98: =SUM(P95:P97) -> 18706.734 | Q98: =SUM(Q95:Q97) -> 18209.556 | R98: =SUM(R95:R97) -> 18599.091 | S98: =SUM(S95:S97) -> 18068.014 | T98: =SUM(T95:T97) -> 18060.36 | U98: =SUM(U95:U97) -> 18101.866 | V98: =SUM(V95:V97) -> 19267.639 | ... AH98: =SUM(AH95:AH97) -> 21943.616
B101: Cash Flow Statement | E101: y | AH101: $ in thousands, except noted
C102: =YEAR(C103) -> 2020 | D102: =YEAR(D103) -> 2020 | E102: =YEAR(E103) -> 2020 | F102: =YEAR(F103) -> 2020 | G102: =YEAR(G103) -> 2021 | H102: =YEAR(H103) -> 2021 | I102: =YEAR(I103) -> 2021 | J102: =YEAR(J103) -> 2021 | ... AH102: =YEAR(AH103) -> 2027
C103: =C$4 -> 43921 | D103: =D$4 -> 44012 | E103: =E$4 -> 44104 | F103: =F$4 -> 44196 | G103: =G$4 -> 44286 | H103: =H$4 -> 44377 | I103: =I$4 -> 44469 | J103: =J$4 -> 44561 | ... AH103: =AH$4 -> 46752
B104: Free Cash Flow
B105: Net Income | O105: =+O42 -> -9752.4354 | P105: =+P42 -> -11312.825 | Q105: =+Q42 -> -13122.877 | R105: =+R42 -> -15222.537 | S105: =+S42 -> -15005.535 | T105: =+T42 -> -16956.255 | U105: =+U42 -> -19160.568 | V105: =+V42 -> -21651.442 | ... AH105: =+AH42 -> -27326.481
B106: Depreciation | O106: =+-O81 -> 1328.5754 | P106: =+-P81 -> 1550.6388 | Q106: =+-Q81 -> 1812.5706 | R106: =+-R81 -> 2102.5819 | S106: =+-S81 -> 2419.562 | T106: =+-T81 -> 2765.2996 | U106: =+-U81 -> 3141.5411 | V106: =+-V81 -> 3549.9415 | ... AH106: =+-AH81 -> 8727.869
B107: Amortization | O107: =+-(Capitalizations!H8+Capitalizations!H48) -> 765.00627 | P107: =+-(Capitalizations!I8+Capitalizations!I48) -> 933.84098 | Q107: =+-(Capitalizations!J8+Capitalizations!J48) -> 1129.6893 | R107: =+-(Capitalizations!K8+Capitalizations!K48) -> 1356.8732 | S107: =+-(Capitalizations!L8+Capitalizations!L48) -> 1620.4067 | T107: =+-(Capitalizations!M8+Capitalizations!M48) -> 1903.4379 | U107: =+-(Capitalizations!N8+Capitalizations!N48) -> 2223.2632 | V107: =+-(Capitalizations!O8+Capitalizations!O48) -> 2584.6658 | ... AH107: =+-(Capitalizations!AA8+Capitalizations!AA48) -> 7280.7714
B108: Net Change in WC | O108: =+N68-O68 -> -2411.7056 | P108: =+O68-P68 -> -2606.1611 | Q108: =+P68-Q68 -> -2836.7061 | R108: =+Q68-R68 -> -2795.9886 | S108: =+R68-S68 -> -2823.2945 | T108: =+S68-T68 -> -3331.7847 | U108: =+T68-U68 -> -3388.0068 | V108: =+U68-V68 -> -3179.437 | ... AH108: =+AG68-AH68 -> -2791.6081
B109: Stock-Based Compensation | O109: =Model!O126 -> 6100.4596 | P109: =Model!P126 -> 7076.5331 | Q109: =Model!Q126 -> 8208.7784 | R109: =Model!R126 -> 9522.183 | S109: =Model!S126 -> 10320.88 | T109: =Model!T126 -> 11662.595 | U109: =Model!U126 -> 13178.732 | V109: =Model!V126 -> 14891.967 | ... AH109: =Model!AH126 -> 29227.454
B110: Deferred Commissions Paid | O110: =-Capitalizations!H7 -> -1659.989 | P110: =-Capitalizations!I7 -> -1925.5872 | Q110: =-Capitalizations!J7 -> -2233.6812 | R110: =-Capitalizations!K7 -> -2591.0702 | S110: =-Capitalizations!L7 -> -2781.5139 | T110: =-Capitalizations!M7 -> -3143.1107 | U110: =-Capitalizations!N7 -> -3551.715 | V110: =-Capitalizations!O7 -> -4013.438 | ... AH110: =-Capitalizations!AA7 -> -7603.8905
B111: Capitalized Software Paid | O111: =-Capitalizations!H47 -> -610.04596 | P111: =-Capitalizations!I47 -> -707.65331 | Q111: =-Capitalizations!J47 -> -820.87784 | R111: =-Capitalizations!K47 -> -952.2183 | S111: =-Capitalizations!L47 -> -1024.7683 | T111: =-Capitalizations!M47 -> -1157.9881 | U111: =-Capitalizations!N47 -> -1308.5266 | V111: =-Capitalizations!O47 -> -1478.6351 | ... AH111: =-Capitalizations!AA47 -> -2827.6968
B112: Capex | O112: =-O80 -> -1660.7192 | P112: =-P80 -> -1938.2985 | Q112: =-Q80 -> -2265.7133 | R112: =-R80 -> -2628.2274 | S112: =-S80 -> -3024.4525 | T112: =-T80 -> -3456.6245 | U112: =-U80 -> -3926.9264 | V112: =-V80 -> -4437.4268 | ... AH112: =-AH80 -> -10909.836
B113: Free Cash Flow | O113: =SUM(O105:O112) -> -7900.854 | P113: =SUM(P105:P112) -> -8929.5123 | Q113: =SUM(Q105:Q112) -> -10128.817 | R113: =SUM(R105:R112) -> -11208.404 | S113: =SUM(S105:S112) -> -10298.715 | T113: =SUM(T105:T112) -> -11714.431 | U113: =SUM(U105:U112) -> -12792.206 | V113: =SUM(V105:V112) -> -13733.804 | ... AH113: =SUM(AH105:AH112) -> -6223.4186
B114: % Margin
B116: Cash Balance
B117: Beginning Cash Balance | O117: =+N119 -> 326476.73 | P117: =+O119 -> 318575.88 | Q117: =+P119 -> 309646.37 | R117: =+Q119 -> 299517.55 | S117: =+R119 -> 288309.15 | T117: =+S119 -> 278010.43 | U117: =+T119 -> 266296 | V117: =+U119 -> 253503.79 | ... AH117: =+AG119 -> 124388.3
B118: Change in Cash | O118: =+O113 -> -7900.854 | P118: =+P113 -> -8929.5123 | Q118: =+Q113 -> -10128.817 | R118: =+R113 -> -11208.404 | S118: =+S113 -> -10298.715 | T118: =+T113 -> -11714.431 | U118: =+U113 -> -12792.206 | V118: =+V113 -> -13733.804 | ... AH118: =+AH113 -> -6223.4186
B119: Ending Cash Balance | N119: =+N48 -> 326476.73 | O119: =SUM(O117:O118) -> 318575.88 | P119: =SUM(P117:P118) -> 309646.37 | Q119: =SUM(Q117:Q118) -> 299517.55 | R119: =SUM(R117:R118) -> 288309.15 | S119: =SUM(S117:S118) -> 278010.43 | T119: =SUM(T117:T118) -> 266296 | U119: =SUM(U117:U118) -> 253503.79 | V119: =SUM(V117:V118) -> 239769.99 | ... AH119: =SUM(AH117:AH118) -> 118164.88
B121: Stock-Based Compensation
B122: Total Opex + COGS | O122: =O20+O21+O22+O15 -> 30502.298 | P122: =P20+P21+P22+P15 -> 35382.666 | Q122: =Q20+Q21+Q22+Q15 -> 41043.892 | R122: =R20+R21+R22+R15 -> 47610.915 | S122: =S20+S21+S22+S15 -> 51604.402 | T122: =T20+T21+T22+T15 -> 58312.974 | U122: =U20+U21+U22+U15 -> 65893.661 | V122: =V20+V21+V22+V15 -> 74459.837 | ... AH122: =AH20+AH21+AH22+AH15 -> 146137.27
B123: Compensation as % of Total Opex + COGS | O123: 0.8 | P123: 0.8 | Q123: 0.8 | R123: 0.8 | S123: 0.8 | T123: 0.8 | U123: 0.8 | V123: 0.8 | W123: 0.8 | X123: 0.8 | Y123: 0.8 | Z123: 0.8 | AA123: 0.8 | AB123: 0.8 | AC123: 0.8 | AD123: 0.8 | AE123: 0.8 | AF123: 0.8 | AG123: 0.8 | AH123: 0.8
...

Sheet Billing Waterfall
AB2: $ in thousands, except noted
I3: =EOMONTH(#REF!, 3) -> #REF! | J3: =EOMONTH(I3, 3) -> #REF! | K3: =EOMONTH(J3, 3) -> #REF! | L3: =EOMONTH(K3, 3) -> #REF! | M3: =EOMONTH(L3, 3) -> #REF! | N3: =EOMONTH(M3, 3) -> #REF! | O3: =EOMONTH(N3, 3) -> #REF! | P3: =EOMONTH(O3, 3) -> #REF! | Q3: =EOMONTH(P3, 3) -> #REF! | ... AB3: =EOMONTH(AA3, 3) -> #REF!
I4: =EOMONTH(#REF!, 2)+1 -> #REF! | J4: =EOMONTH(I4, 2)+1 -> #REF! | K4: =EOMONTH(J4, 2)+1 -> #REF! | L4: =EOMONTH(K4, 2)+1 -> #REF! | M4: =EOMONTH(L4, 2)+1 -> #REF! | N4: =EOMONTH(M4, 2)+1 -> #REF! | O4: =EOMONTH(N4, 2)+1 -> #REF! | P4: =EOMONTH(O4, 2)+1 -> #REF! | Q4: =EOMONTH(P4, 2)+1 -> #REF! | ... AB4: =EOMONTH(AA4, 2)+1 -> #REF!
E5: =EOMONTH(F5, -3) -> 44651 | F5: =EOMONTH(G5, -3) -> 44742 | G5: =EOMONTH(H5, -3) -> 44834 | H5: =EOMONTH(I5, -3) -> 44926 | I5: =Model!O4 -> 45016 | J5: =EOMONTH(I5, 3) -> 45107 | K5: =EOMONTH(J5, 3) -> 45199 | L5: =EOMONTH(K5, 3) -> 45291 | M5: =EOMONTH(L5, 3) -> 45382 | N5: =EOMONTH(M5, 3) -> 45473 | O5: =EOMONTH(N5, 3) -> 45565 | P5: =EOMONTH(O5, 3) -> 45657 | Q5: =EOMONTH(P5, 3) -> 45747 | ... AB5: =EOMONTH(AA5, 3) -> 46752
B6: ARR Eligible for Billings
B7: Prior Year Renewal ARR | E7: 5660.477 | F7: 6828.9072 | G7: 8507.6607 | H7: 10270.13 | I7: =+E12 -> 11732.08 | J7: =+F12 -> 15085.88 | K7: =+G12 -> 16109.181 | L7: =+H12 -> 22545.355 | M7: =+I12 -> 23180.28 | N7: =+J12 -> 28365.792 | O7: =+K12 -> 31513.879 | P7: =+L12 -> 40414.805 | ... AB7: =+X12 -> 110643.6
B8: New Logo ARR | E8: ='ARR Waterfall'!K7 -> 2938.65 | F8: ='ARR Waterfall'!L7 -> 4775.55 | G8: ='ARR Waterfall'!M7 -> 4969.35 | H8: ='ARR Waterfall'!N7 -> 6157.89 | I8: ='ARR Waterfall'!O7 -> 8586.15 | J8: ='ARR Waterfall'!P7 -> 9959.934 | K8: ='ARR Waterfall'!Q7 -> 11553.523 | L8: ='ARR Waterfall'!R7 -> 13402.087 | ... AB8: ='ARR Waterfall'!AH7 -> 26900.556
B9: Upsell ARR | E9: ='ARR Waterfall'!K8 -> 4008.832 | F9: ='ARR Waterfall'!L8 -> 4671.897 | G9: ='ARR Waterfall'!M8 -> 4734.5702 | H9: ='ARR Waterfall'!N8 -> 7403.581 | I9: ='ARR Waterfall'!O8 -> 5724.1 | J9: ='ARR Waterfall'!P8 -> 6639.956 | K9: ='ARR Waterfall'!Q8 -> 7702.349 | L9: ='ARR Waterfall'!R8 -> 8934.7248 | ... AB9: ='ARR Waterfall'!AH8 -> 17933.704
B10: Downsell ARR | E10: ='ARR Waterfall'!K9 -> -379.4445 | F10: ='ARR Waterfall'!L9 -> -407.0975 | G10: ='ARR Waterfall'!M9 -> -880.041 | H10: ='ARR Waterfall'!N9 -> -556.12475 | I10: ='ARR Waterfall'!O9 -> -1431.025 | J10: ='ARR Waterfall'!P9 -> -1659.989 | K10: ='ARR Waterfall'!Q9 -> -1925.5872 | L10: ='ARR Waterfall'!R9 -> -2233.6812 | ... AB10: ='ARR Waterfall'!AH9 -> -8966.852
B11: Churn ARR | E11: ='ARR Waterfall'!K10 -> -496.4345 | F11: ='ARR Waterfall'!L10 -> -783.3765 | G11: ='ARR Waterfall'!M10 -> -1222.3585 | H11: ='ARR Waterfall'!N10 -> -730.1215 | I11: ='ARR Waterfall'!O10 -> -1431.025 | J11: ='ARR Waterfall'!P10 -> -1659.989 | K11: ='ARR Waterfall'!Q10 -> -1925.5872 | L11: ='ARR Waterfall'!R10 -> -2233.6812 | ... AB11: ='ARR Waterfall'!AH10 -> -8966.852
B12: ARR Eligible for Billing | E12: =SUM(E7:E11) -> 11732.08 | F12: =SUM(F7:F11) -> 15085.88 | G12: =SUM(G7:G11) -> 16109.181 | H12: =SUM(H7:H11) -> 22545.355 | I12: =SUM(I7:I11) -> 23180.28 | J12: =SUM(J7:J11) -> 28365.792 | K12: =SUM(K7:K11) -> 31513.879 | L12: =SUM(L7:L11) -> 40414.805 | ... AB12: =SUM(AB7:AB11) -> 137544.15
B14: Upfront (Annual) Billing
B15: Cohort | C15: $ Eligible | D15: Cohort %
B16: {=TRANSPOSE(E5:AB5)} -> 44651 | C16: {=TRANSPOSE(E12:AB12)} -> 11732.08 | D16: 0.2 | E16: =$C16*$D16 -> 2346.416
B17: 44742 | C17: 15085.88 | D17: =+D16 -> 0.2 | F17: =$C17*$D17 -> 3017.1761
B18: 44834 | C18: 16109.181 | D18: =+D17 -> 0.2 | G18: =$C18*$D18 -> 3221.8363
B19: 44926 | C19: 22545.355 | D19: =+D18 -> 0.2 | H19: =$C19*$D19 -> 4509.071
B20: 45016 | C20: 23180.28 | D20: =+D19 -> 0.2 | I20: =$C20*$D20 -> 4636.056
B21: 45107 | C21: 28365.792 | D21: =+D20 -> 0.2 | J21: =$C21*$D21 -> 5673.1585
B22: 45199 | C22: 31513.879 | D22: =+D21 -> 0.2 | K22: =$C22*$D22 -> 6302.7759
B23: 45291 | C23: 40414.805 | D23: =+D22 -> 0.2 | L23: =$C23*$D23 -> 8082.961
B24: 45382 | C24: 40022.236 | D24: =+D23 -> 0.2 | M24: =$C24*$D24 -> 8004.4473
B25: 45473 | C25: 47397.203 | D25: =+D24 -> 0.2 | N25: =$C25*$D25 -> 9479.4406
B26: 45565 | C26: 53019.373 | D26: =+D25 -> 0.2 | O26: =$C26*$D26 -> 10603.875
B27: 45657 | C27: 64716.013 | D27: =+D26 -> 0.2 | P27: =$C27*$D27 -> 12943.203
B28: 45747 | C28: 59033.258 | D28: =+D27 -> 0.2 | Q28: =$C28*$D28 -> 11806.652
B29: 45838 | C29: 68119.217 | D29: =+D28 -> 0.2 | R29: =$C29*$D29 -> 13623.843
B30: 45930 | C30: 75606.369 | D30: =+D29 -> 0.2 | S30: =$C30*$D30 -> 15121.274
B31: 46022 | C31: 89335.838 | D31: =+D30 -> 0.2 | T31: =$C31*$D31 -> 17867.168
B32: 46112 | C32: 76923.665 | D32: =+D31 -> 0.2 | U32: =$C32*$D32 -> 15384.733
B33: 46203 | C33: 87083.048 | D33: =+D32 -> 0.2 | V33: =$C33*$D33 -> 17416.61
B34: 46295 | C34: 95708.029 | D34: =+D33 -> 0.2 | W34: =$C34*$D34 -> 19141.606
B35: 46387 | C35: 110643.6 | D35: =+D34 -> 0.2 | X35: =$C35*$D35 -> 22128.72
B36: 46477 | C36: 99509.89 | D36: =+D35 -> 0.2 | Y36: =$C36*$D36 -> 19901.978
B37: 46568 | C37: 111024.45 | D37: =+D36 -> 0.2 | Z37: =$C37*$D37 -> 22204.889
B38: 46660 | C38: 121085.91 | D38: =+D37 -> 0.2 | AA38: =$C38*$D38 -> 24217.182
B39: 46752 | C39: 137544.15 | D39: =+D38 -> 0.2 | AB39: =$C39*$D39 -> 27508.831
B42: Quarterly Billing
B43: Cohort | C43: $ Eligible | D43: Cohort %
B44: =+B16 -> 44651 | C44: =+C16 -> 11732.08 | D44: =1-D16 -> 0.8 | E44: =$C44*$D44/4 -> 2346.416 | F44: =$C44*$D44/4 -> 2346.416 | G44: =$C44*$D44/4 -> 2346.416 | H44: =$C44*$D44/4 -> 2346.416
B45: =+B17 -> 44742 | C45: =+C17 -> 15085.88 | D45: =1-D17 -> 0.8 | F45: =$C45*$D45/4 -> 3017.1761 | G45: =$C45*$D45/4 -> 3017.1761 | H45: =$C45*$D45/4 -> 3017.1761 | I45: =$C45*$D45/4 -> 3017.1761
B46: =+B18 -> 44834 | C46: =+C18 -> 16109.181 | D46: =1-D18 -> 0.8 | G46: =$C46*$D46/4 -> 3221.8363 | H46: =$C46*$D46/4 -> 3221.8363 | I46: =$C46*$D46/4 -> 3221.8363 | J46: =$C46*$D46/4 -> 3221.8363
B47: =+B19 -> 44926 | C47: =+C19 -> 22545.355 | D47: =1-D19 -> 0.8 | H47: =$C47*$D47/4 -> 4509.071 | I47: =$C47*$D47/4 -> 4509.071 | J47: =$C47*$D47/4 -> 4509.071 | K47: =$C47*$D47/4 -> 4509.071
B48: =+B20 -> 45016 | C48: =+C20 -> 23180.28 | D48: =1-D20 -> 0.8 | I48: =$C48*$D48/4 -> 4636.056 | J48: =$C48*$D48/4 -> 4636.056 | K48: =$C48*$D48/4 -> 4636.056 | L48: =$C48*$D48/4 -> 4636.056
B49: =+B21 -> 45107 | C49: =+C21 -> 28365.792 | D49: =1-D21 -> 0.8 | J49: =$C49*$D49/4 -> 5673.1585 | K49: =$C49*$D49/4 -> 5673.1585 | L49: =$C49*$D49/4 -> 5673.1585 | M49: =$C49*$D49/4 -> 5673.1585
B50: =+B22 -> 45199 | C50: =+C22 -> 31513.879 | D50: =1-D22 -> 0.8 | K50: =$C50*$D50/4 -> 6302.7759 | L50: =$C50*$D50/4 -> 6302.7759 | M50: =$C50*$D50/4 -> 6302.7759 | N50: =$C50*$D50/4 -> 6302.7759
B51: =+B23 -> 45291 | C51: =+C23 -> 40414.805 | D51: =1-D23 -> 0.8 | L51: =$C51*$D51/4 -> 8082.961 | M51: =$C51*$D51/4 -> 8082.961 | N51: =$C51*$D51/4 -> 8082.961 | O51: =$C51*$D51/4 -> 8082.961
B52: =+B24 -> 45382 | C52: =+C24 -> 40022.236 | D52: =1-D24 -> 0.8 | M52: =$C52*$D52/4 -> 8004.4473 | N52: =$C52*$D52/4 -> 8004.4473 | O52: =$C52*$D52/4 -> 8004.4473 | P52: =$C52*$D52/4 -> 8004.4473
B53: =+B25 -> 45473 | C53: =+C25 -> 47397.203 | D53: =1-D25 -> 0.8 | N53: =$C53*$D53/4 -> 9479.4406 | O53: =$C53*$D53/4 -> 9479.4406 | P53: =$C53*$D53/4 -> 9479.4406 | Q53: =$C53*$D53/4 -> 9479.4406
B54: =+B26 -> 45565 | C54: =+C26 -> 53019.373 | D54: =1-D26 -> 0.8 | O54: =$C54*$D54/4 -> 10603.875 | P54: =$C54*$D54/4 -> 10603.875 | Q54: =$C54*$D54/4 -> 10603.875 | R54: =$C54*$D54/4 -> 10603.875
B55: =+B27 -> 45657 | C55: =+C27 -> 64716.013 | D55: =1-D27 -> 0.8 | P55: =$C55*$D55/4 -> 12943.203 | Q55: =$C55*$D55/4 -> 12943.203 | R55: =$C55*$D55/4 -> 12943.203 | S55: =$C55*$D55/4 -> 12943.203
B56: =+B28 -> 45747 | C56: =+C28 -> 59033.258 | D56: =1-D28 -> 0.8 | Q56: =$C56*$D56/4 -> 11806.652 | R56: =$C56*$D56/4 -> 11806.652 | S56: =$C56*$D56/4 -> 11806.652 | T56: =$C56*$D56/4 -> 11806.652
B57: =+B29 -> 45838 | C57: =+C29 -> 68119.217 | D57: =1-D29 -> 0.8 | R57: =$C57*$D57/4 -> 13623.843 | S57: =$C57*$D57/4 -> 13623.843 | T57: =$C57*$D57/4 -> 13623.843 | U57: =$C57*$D57/4 -> 13623.843
B58: =+B30 -> 45930 | C58: =+C30 -> 75606.369 | D58: =1-D30 -> 0.8 | S58: =$C58*$D58/4 -> 15121.274 | T58: =$C58*$D58/4 -> 15121.274 | U58: =$C58*$D58/4 -> 15121.274 | V58: =$C58*$D58/4 -> 15121.274
B59: =+B31 -> 46022 | C59: =+C31 -> 89335.838 | D59: =1-D31 -> 0.8 | T59: =$C59*$D59/4 -> 17867.168 | U59: =$C59*$D59/4 -> 17867.168 | V59: =$C59*$D59/4 -> 17867.168 | W59: =$C59*$D59/4 -> 17867.168
B60: =+B32 -> 46112 | C60: =+C32 -> 76923.665 | D60: =1-D32 -> 0.8 | U60: =$C60*$D60/4 -> 15384.733 | V60: =$C60*$D60/4 -> 15384.733 | W60: =$C60*$D60/4 -> 15384.733 | X60: =$C60*$D60/4 -> 15384.733
B61: =+B33 -> 46203 | C61: =+C33 -> 87083.048 | D61: =1-D33 -> 0.8 | V61: =$C61*$D61/4 -> 17416.61 | W61: =$C61*$D61/4 -> 17416.61 | X61: =$C61*$D61/4 -> 17416.61 | Y61: =$C61*$D61/4 -> 17416.61
B62: =+B34 -> 46295 | C62: =+C34 -> 95708.029 | D62: =1-D34 -> 0.8 | W62: =$C62*$D62/4 -> 19141.606 | X62: =$C62*$D62/4 -> 19141.606 | Y62: =$C62*$D62/4 -> 19141.606 | Z62: =$C62*$D62/4 -> 19141.606
B63: =+B35 -> 46387 | C63: =+C35 -> 110643.6 | D63: =1-D35 -> 0.8 | X63: =$C63*$D63/4 -> 22128.72 | Y63: =$C63*$D63/4 -> 22128.72 | Z63: =$C63*$D63/4 -> 22128.72 | AA63: =$C63*$D63/4 -> 22128.72
B64: =+B36 -> 46477 | C64: =+C36 -> 99509.89 | D64: =1-D36 -> 0.8 | Y64: =$C64*$D64/4 -> 19901.978 | Z64: =$C64*$D64/4 -> 19901.978 | AA64: =$C64*$D64/4 -> 19901.978 | AB64: =$C64*$D64/4 -> 19901.978
B65: =+B37 -> 46568 | C65: =+C37 -> 111024.45 | D65: =1-D37 -> 0.8 | Z65: =$C65*$D65/4 -> 22204.889 | AA65: =$C65*$D65/4 -> 22204.889 | AB65: =$C65*$D65/4 -> 22204.889
B66: =+B38 -> 46660 | C66: =+C38 -> 121085.91 | D66: =1-D38 -> 0.8 | AA66: =$C66*$D66/4 -> 24217.182 | AB66: =$C66*$D66/4 -> 24217.182
B67: =+B39 -> 46752 | C67: =+C39 -> 137544.15 | D67: =1-D39 -> 0.8 | AB67: =$C67*$D67/4 -> 27508.831
B69: Total Billed Amount | E69: =SUM(E16:E68) -> 4692.832 | F69: =SUM(F16:F68) -> 8380.7681 | G69: =SUM(G16:G68) -> 11807.265 | H69: =SUM(H16:H68) -> 17603.57 | I69: =SUM(I16:I68) -> 20020.195 | J69: =SUM(J16:J68) -> 23713.28 | K69: =SUM(K16:K68) -> 27423.837 | L69: =SUM(L16:L68) -> 32777.912 | ... AB69: =SUM(AB16:AB68) -> 121341.71
B72: Cash Collections in Same Quarter
B73: Cohort | C73: $ Billed | D73: Cohort %
B74: =+B44 -> 44651 | C74: {=TRANSPOSE(E69:AB69)} -> 4692.832 | D74: 0.5 | E74: =+$C74*$D74 -> 2346.416
B75: =+B45 -> 44742 | C75: 8380.7681 | D75: =+D74 -> 0.5 | F75: =+$C75*$D75 -> 4190.3841
B76: =+B46 -> 44834 | C76: 11807.265 | D76: =+D75 -> 0.5 | G76: =+$C76*$D76 -> 5903.6323
B77: =+B47 -> 44926 | C77: 17603.57 | D77: =+D76 -> 0.5 | H77: =+$C77*$D77 -> 8801.7852
B78: =+B48 -> 45016 | C78: 20020.195 | D78: =+D77 -> 0.5 | I78: =+$C78*$D78 -> 10010.098
B79: =+B49 -> 45107 | C79: 23713.28 | D79: =+D78 -> 0.5 | J79: =+$C79*$D79 -> 11856.64
B80: =+B50 -> 45199 | C80: 27423.837 | D80: =+D79 -> 0.5 | K80: =+$C80*$D80 -> 13711.919
B81: =+B51 -> 45291 | C81: 32777.912 | D81: =+D80 -> 0.5 | L81: =+$C81*$D81 -> 16388.956
B82: =+B52 -> 45382 | C82: 36067.79 | D82: =+D81 -> 0.5 | M82: =+$C82*$D82 -> 18033.895
B83: =+B53 -> 45473 | C83: 41349.065 | D83: =+D82 -> 0.5 | N83: =+$C83*$D83 -> 20674.533
B84: =+B54 -> 45565 | C84: 46774.598 | D84: =+D83 -> 0.5 | O84: =+$C84*$D84 -> 23387.299
B85: =+B55 -> 45657 | C85: 53974.168 | D85: =+D84 -> 0.5 | P85: =+$C85*$D85 -> 26987.084
B86: =+B56 -> 45747 | C86: 56639.821 | D86: =+D85 -> 0.5 | Q86: =+$C86*$D86 -> 28319.911
B87: =+B57 -> 45838 | C87: 62601.416 | D87: =+D86 -> 0.5 | R87: =+$C87*$D87 -> 31300.708
B88: =+B58 -> 45930 | C88: 68616.245 | D88: =+D87 -> 0.5 | S88: =+$C88*$D88 -> 34308.123
B89: =+B59 -> 46022 | C89: 76286.104 | D89: =+D88 -> 0.5 | T89: =+$C89*$D89 -> 38143.052
B90: =+B60 -> 46112 | C90: 77381.751 | D90: =+D89 -> 0.5 | U90: =+$C90*$D90 -> 38690.875
B91: =+B61 -> 46203 | C91: 83206.393 | D91: =+D90 -> 0.5 | V91: =+$C91*$D91 -> 41603.197
B92: =+B62 -> 46295 | C92: 88951.722 | D92: =+D91 -> 0.5 | W92: =+$C92*$D92 -> 44475.861
B93: =+B63 -> 46387 | C93: 96200.387 | D93: =+D92 -> 0.5 | X93: =+$C93*$D93 -> 48100.194
B94: =+B64 -> 46477 | C94: 98490.891 | D94: =+D93 -> 0.5 | Y94: =+$C94*$D94 -> 49245.445
B95: =+B65 -> 46568 | C95: 105582.08 | D95: =+D94 -> 0.5 | Z95: =+$C95*$D95 -> 52791.041
B96: =+B66 -> 46660 | C96: 112669.95 | D96: =+D95 -> 0.5 | AA96: =+$C96*$D96 -> 56334.976
B97: =+B67 -> 46752 | C97: 121341.71 | D97: =+D96 -> 0.5 | AB97: =+$C97*$D97 -> 60670.856
B99: Cash Collections in Next Quarter
B100: Cohort | C100: $ Billed | D100: Cohort %
B101: =B74 -> 44651 | C101: =+C74 -> 4692.832 | D101: =1-D74 -> 0.5 | F101: =+$C101*$D101 -> 2346.416
B102: =B75 -> 44742 | C102: =+C75 -> 8380.7681 | D102: =1-D75 -> 0.5 | G102: =+$C102*$D102 -> 4190.3841
B103: =B76 -> 44834 | C103: =+C76 -> 11807.265 | D103: =1-D76 -> 0.5 | H103: =+$C103*$D103 -> 5903.6323
B104: =B77 -> 44926 | C104: =+C77 -> 17603.57 | D104: =1-D77 -> 0.5 | I104: =+$C104*$D104 -> 8801.7852
B105: =B78 -> 45016 | C105: =+C78 -> 20020.195 | D105: =1-D78 -> 0.5 | J105: =+$C105*$D105 -> 10010.098
B106: =B79 -> 45107 | C106: =+C79 -> 23713.28 | D106: =1-D79 -> 0.5 | K106: =+$C106*$D106 -> 11856.64
B107: =B80 -> 45199 | C107: =+C80 -> 27423.837 | D107: =1-D80 -> 0.5 | L107: =+$C107*$D107 -> 13711.919
B108: =B81 -> 45291 | C108: =+C81 -> 32777.912 | D108: =1-D81 -> 0.5 | M108: =+$C108*$D108 -> 16388.956
...

Sheet Capitalizations
AA2: $ in thousands, except noted
G3: 44926 | H3: =EOMONTH(G3, 3) -> 45016 | I3: =EOMONTH(H3, 3) -> 45107 | J3: =EOMONTH(I3, 3) -> 45199 | K3: =EOMONTH(J3, 3) -> 45291 | L3: =EOMONTH(K3, 3) -> 45382 | M3: =EOMONTH(L3, 3) -> 45473 | N3: =EOMONTH(M3, 3) -> 45565 | O3: =EOMONTH(N3, 3) -> 45657 | ... AA3: =EOMONTH(Z3, 3) -> 46752
B4: Deferred Commissions
B5: Balance Sheet
B6: Beginning Deferred Commissions | H6: =+G9 -> 7406.8 | I6: =+H9 -> 8449.5557 | J6: =+I9 -> 9619.5772 | K6: =+J9 -> 10937.227 | L6: =+K9 -> 12426.126 | M6: =+L9 -> 13889.546 | N6: =+M9 -> 15482.77 | O6: =+N9 -> 17222.672 | ... AA6: =+Z9 -> 39562.707
B7: New Deferred Commissions | H7: =+H12*H13 -> 1659.989 | I7: =+I12*I13 -> 1925.5872 | J7: =+J12*J13 -> 2233.6812 | K7: =+K12*K13 -> 2591.0702 | L7: =+L12*L13 -> 2781.5139 | M7: =+M12*M13 -> 3143.1107 | N7: =+N12*N13 -> 3551.715 | O7: =+O12*O13 -> 4013.438 | ... AA7: =+AA12*AA13 -> 7603.8905
B8: Amortization of Deferred Commissions | H8: =+-H39 -> -617.23333 | I8: =+-I39 -> -755.56575 | J8: =+-J39 -> -916.03135 | K8: =+-K39 -> -1102.1715 | L8: =+-L39 -> -1318.094 | M8: =+-M39 -> -1549.8868 | N8: =+-N39 -> -1811.8127 | O8: =+-O39 -> -2107.7889 | ... AA8: =+-AA39 -> -5566.4002
B9: Ending Deferred Commissions | G9: =Model!N52 -> 7406.8 | H9: =SUM(H6:H8) -> 8449.5557 | I9: =SUM(I6:I8) -> 9619.5772 | J9: =SUM(J6:J8) -> 10937.227 | K9: =SUM(K6:K8) -> 12426.126 | L9: =SUM(L6:L8) -> 13889.546 | M9: =SUM(M6:M8) -> 15482.77 | N9: =SUM(N6:N8) -> 17222.672 | O9: =SUM(O6:O8) -> 19128.321 | ... AA9: =SUM(AA6:AA8) -> 41600.197
B11: Memo/Drivers:
B12: Total S&M Expense | H12: =Model!O20 -> 8299.945 | I12: =Model!P20 -> 9627.9362 | J12: =Model!Q20 -> 11168.406 | K12: =Model!R20 -> 12955.351 | L12: =Model!S20 -> 13907.569 | M12: =Model!T20 -> 15715.553 | N12: =Model!U20 -> 17758.575 | O12: =Model!V20 -> 20067.19 | ... AA12: =Model!AH20 -> 38019.453
B13: Deferred Comp as % of Total S&M Expense | H13: 0.2 | I13: 0.2 | J13: 0.2 | K13: 0.2 | L13: 0.2 | M13: 0.2 | N13: 0.2 | O13: 0.2 | P13: 0.2 | Q13: 0.2 | R13: 0.2 | S13: 0.2 | T13: 0.2 | U13: 0.2 | V13: 0.2 | W13: 0.2 | X13: 0.2 | Y13: 0.2 | Z13: 0.2 | AA13: 0.2
B15: Amortization Schedule
B16: Cohort | C16: $ Deferrals | D16: Years | E16: Quarters | F16: End
B17: {=TRANSPOSE(G3:AA3)} -> 44926 | C17: =G9 -> 7406.8 | D17: 3 | E17: =+D17*4 -> 12 | F17: =EOMONTH(B17, D17*12) -> 46022 | H17: =$C17/$E17 -> 617.23333 | I17: =$C17/$E17 -> 617.23333 | J17: =$C17/$E17 -> 617.23333 | K17: =$C17/$E17 -> 617.23333 | L17: =$C17/$E17 -> 617.23333 | M17: =$C17/$E17 -> 617.23333 | N17: =$C17/$E17 -> 617.23333 | O17: =$C17/$E17 -> 617.23333 | ... S17: =$C17/$E17 -> 617.23333
B18: 45016 | C18: {=TRANSPOSE(H7:AA7)} -> 1659.989 | D18: 3 | E18: =+D18*4 -> 12 | F18: =EOMONTH(B18, D18*12) -> 46112 | I18: =$C18/$E18 -> 138.33242 | J18: =$C18/$E18 -> 138.33242 | K18: =$C18/$E18 -> 138.33242 | L18: =$C18/$E18 -> 138.33242 | M18: =$C18/$E18 -> 138.33242 | N18: =$C18/$E18 -> 138.33242 | O18: =$C18/$E18 -> 138.33242 | P18: =$C18/$E18 -> 138.33242 | ... T18: =$C18/$E18 -> 138.33242
B19: 45107 | C19: 1925.5872 | D19: 3 | E19: =+D19*4 -> 12 | F19: =EOMONTH(B19, D19*12) -> 46203 | J19: =$C19/$E19 -> 160.4656 | K19: =$C19/$E19 -> 160.4656 | L19: =$C19/$E19 -> 160.4656 | M19: =$C19/$E19 -> 160.4656 | N19: =$C19/$E19 -> 160.4656 | O19: =$C19/$E19 -> 160.4656 | P19: =$C19/$E19 -> 160.4656 | Q19: =$C19/$E19 -> 160.4656 | ... U19: =$C19/$E19 -> 160.4656
B20: 45199 | C20: 2233.6812 | D20: 3 | E20: =+D20*4 -> 12 | F20: =EOMONTH(B20, D20*12) -> 46295 | K20: =$C20/$E20 -> 186.1401 | L20: =$C20/$E20 -> 186.1401 | M20: =$C20/$E20 -> 186.1401 | N20: =$C20/$E20 -> 186.1401 | O20: =$C20/$E20 -> 186.1401 | P20: =$C20/$E20 -> 186.1401 | Q20: =$C20/$E20 -> 186.1401 | R20: =$C20/$E20 -> 186.1401 | ... V20: =$C20/$E20 -> 186.1401
B21: 45291 | C21: 2591.0702 | D21: 3 | E21: =+D21*4 -> 12 | F21: =EOMONTH(B21, D21*12) -> 46387 | L21: =$C21/$E21 -> 215.92252 | M21: =$C21/$E21 -> 215.92252 | N21: =$C21/$E21 -> 215.92252 | O21: =$C21/$E21 -> 215.92252 | P21: =$C21/$E21 -> 215.92252 | Q21: =$C21/$E21 -> 215.92252 | R21: =$C21/$E21 -> 215.92252 | S21: =$C21/$E21 -> 215.92252 | ... W21: =$C21/$E21 -> 215.92252
B22: 45382 | C22: 2781.5139 | D22: 3 | E22: =+D22*4 -> 12 | F22: =EOMONTH(B22, D22*12) -> 46477 | M22: =$C22/$E22 -> 231.79282 | N22: =$C22/$E22 -> 231.79282 | O22: =$C22/$E22 -> 231.79282 | P22: =$C22/$E22 -> 231.79282 | Q22: =$C22/$E22 -> 231.79282 | R22: =$C22/$E22 -> 231.79282 | S22: =$C22/$E22 -> 231.79282 | T22: =$C22/$E22 -> 231.79282 | ... X22: =$C22/$E22 -> 231.79282
B23: 45473 | C23: 3143.1107 | D23: 3 | E23: =+D23*4 -> 12 | F23: =EOMONTH(B23, D23*12) -> 46568 | N23: =$C23/$E23 -> 261.92589 | O23: =$C23/$E23 -> 261.92589 | P23: =$C23/$E23 -> 261.92589 | Q23: =$C23/$E23 -> 261.92589 | R23: =$C23/$E23 -> 261.92589 | S23: =$C23/$E23 -> 261.92589 | T23: =$C23/$E23 -> 261.92589 | U23: =$C23/$E23 -> 261.92589 | ... Y23: =$C23/$E23 -> 261.92589
B24: 45565 | C24: 3551.715 | D24: 3 | E24: =+D24*4 -> 12 | F24: =EOMONTH(B24, D24*12) -> 46660 | O24: =$C24/$E24 -> 295.97625 | P24: =$C24/$E24 -> 295.97625 | Q24: =$C24/$E24 -> 295.97625 | R24: =$C24/$E24 -> 295.97625 | S24: =$C24/$E24 -> 295.97625 | T24: =$C24/$E24 -> 295.97625 | U24: =$C24/$E24 -> 295.97625 | V24: =$C24/$E24 -> 295.97625 | ... Z24: =$C24/$E24 -> 295.97625
B25: 45657 | C25: 4013.438 | D25: 3 | E25: =+D25*4 -> 12 | F25: =EOMONTH(B25, D25*12) -> 46752 | P25: =$C25/$E25 -> 334.45317 | Q25: =$C25/$E25 -> 334.45317 | R25: =$C25/$E25 -> 334.45317 | S25: =$C25/$E25 -> 334.45317 | T25: =$C25/$E25 -> 334.45317 | U25: =$C25/$E25 -> 334.45317 | V25: =$C25/$E25 -> 334.45317 | W25: =$C25/$E25 -> 334.45317 | ... AA25: =$C25/$E25 -> 334.45317
B26: 45747 | C26: 4144.4028 | D26: 3 | E26: =+D26*4 -> 12 | F26: =EOMONTH(B26, D26*12) -> 46843 | Q26: =$C26/$E26 -> 345.3669 | R26: =$C26/$E26 -> 345.3669 | S26: =$C26/$E26 -> 345.3669 | T26: =$C26/$E26 -> 345.3669 | U26: =$C26/$E26 -> 345.3669 | V26: =$C26/$E26 -> 345.3669 | W26: =$C26/$E26 -> 345.3669 | X26: =$C26/$E26 -> 345.3669 | ... AA26: =$C26/$E26 -> 345.3669
B27: 45838 | C27: 4517.3991 | D27: 3 | E27: =+D27*4 -> 12 | F27: =EOMONTH(B27, D27*12) -> 46934 | R27: =$C27/$E27 -> 376.44992 | S27: =$C27/$E27 -> 376.44992 | T27: =$C27/$E27 -> 376.44992 | U27: =$C27/$E27 -> 376.44992 | V27: =$C27/$E27 -> 376.44992 | W27: =$C27/$E27 -> 376.44992 | X27: =$C27/$E27 -> 376.44992 | Y27: =$C27/$E27 -> 376.44992 | ... AA27: =$C27/$E27 -> 376.44992
B28: 45930 | C28: 4923.965 | D28: 3 | E28: =+D28*4 -> 12 | F28: =EOMONTH(B28, D28*12) -> 47026 | S28: =$C28/$E28 -> 410.33042 | T28: =$C28/$E28 -> 410.33042 | U28: =$C28/$E28 -> 410.33042 | V28: =$C28/$E28 -> 410.33042 | W28: =$C28/$E28 -> 410.33042 | X28: =$C28/$E28 -> 410.33042 | Y28: =$C28/$E28 -> 410.33042 | Z28: =$C28/$E28 -> 410.33042 | AA28: =$C28/$E28 -> 410.33042
B29: 46022 | C29: 5367.1218 | D29: 3 | E29: =+D29*4 -> 12 | F29: =EOMONTH(B29, D29*12) -> 47118 | T29: =$C29/$E29 -> 447.26015 | U29: =$C29/$E29 -> 447.26015 | V29: =$C29/$E29 -> 447.26015 | W29: =$C29/$E29 -> 447.26015 | X29: =$C29/$E29 -> 447.26015 | Y29: =$C29/$E29 -> 447.26015 | Z29: =$C29/$E29 -> 447.26015 | AA29: =$C29/$E29 -> 447.26015
B30: 46112 | C30: 5373.0853 | D30: 3 | E30: =+D30*4 -> 12 | F30: =EOMONTH(B30, D30*12) -> 47208 | U30: =$C30/$E30 -> 447.75711 | V30: =$C30/$E30 -> 447.75711 | W30: =$C30/$E30 -> 447.75711 | X30: =$C30/$E30 -> 447.75711 | Y30: =$C30/$E30 -> 447.75711 | Z30: =$C30/$E30 -> 447.75711 | AA30: =$C30/$E30 -> 447.75711
B31: 46203 | C31: 5695.4704 | D31: 3 | E31: =+D31*4 -> 12 | F31: =EOMONTH(B31, D31*12) -> 47299 | V31: =$C31/$E31 -> 474.62254 | W31: =$C31/$E31 -> 474.62254 | X31: =$C31/$E31 -> 474.62254 | Y31: =$C31/$E31 -> 474.62254 | Z31: =$C31/$E31 -> 474.62254 | AA31: =$C31/$E31 -> 474.62254
B32: 46295 | C32: 6037.1987 | D32: 3 | E32: =+D32*4 -> 12 | F32: =EOMONTH(B32, D32*12) -> 47391 | W32: =$C32/$E32 -> 503.09989 | X32: =$C32/$E32 -> 503.09989 | Y32: =$C32/$E32 -> 503.09989 | Z32: =$C32/$E32 -> 503.09989 | AA32: =$C32/$E32 -> 503.09989
B33: 46387 | C33: 6399.4306 | D33: 3 | E33: =+D33*4 -> 12 | F33: =EOMONTH(B33, D33*12) -> 47483 | X33: =$C33/$E33 -> 533.28588 | Y33: =$C33/$E33 -> 533.28588 | Z33: =$C33/$E33 -> 533.28588 | AA33: =$C33/$E33 -> 533.28588
B34: 46477 | C34: 6384.3731 | D34: 3 | E34: =+D34*4 -> 12 | F34: =EOMONTH(B34, D34*12) -> 47573 | Y34: =$C34/$E34 -> 532.03109 | Z34: =$C34/$E34 -> 532.03109 | AA34: =$C34/$E34 -> 532.03109
B35: 46568 | C35: 6767.4355 | D35: 3 | E35: =+D35*4 -> 12 | F35: =EOMONTH(B35, D35*12) -> 47664 | Z35: =$C35/$E35 -> 563.95296 | AA35: =$C35/$E35 -> 563.95296
B36: 46660 | C36: 7173.4816 | D36: 3 | E36: =+D36*4 -> 12 | F36: =EOMONTH(B36, D36*12) -> 47756 | AA36: =$C36/$E36 -> 597.79013
B37: 46752 | C37: 7603.8905 | D37: 3 | E37: =+D37*4 -> 12 | F37: =EOMONTH(B37, D37*12) -> 47848
B39: Amortization of Deferred Compensation | H39: =SUM(H17:H38) -> 617.23333 | I39: =SUM(I17:I38) -> 755.56575 | J39: =SUM(J17:J38) -> 916.03135 | K39: =SUM(K17:K38) -> 1102.1715 | L39: =SUM(L17:L38) -> 1318.094 | M39: =SUM(M17:M38) -> 1549.8868 | N39: =SUM(N17:N38) -> 1811.8127 | O39: =SUM(O17:O38) -> 2107.7889 | ... AA39: =SUM(AA17:AA38) -> 5566.4002
B44: Capitalized Software Costs
B45: Balance Sheet
B46: Beginning Capitalized Software Costs | H46: =+G49 -> 2955.4587 | I46: =+H49 -> 3417.7317 | J46: =+I49 -> 3947.1098 | K46: =+J49 -> 4554.3297 | L46: =+K49 -> 5251.8462 | M46: =+L49 -> 5974.3018 | N46: =+M49 -> 6778.7388 | O46: =+N49 -> 7675.8149 | ... AA46: =+Z49 -> 20660.222
B47: New Capitalized Software Costs | H47: =H52*H53 -> 610.04596 | I47: =I52*I53 -> 707.65331 | J47: =J52*J53 -> 820.87784 | K47: =K52*K53 -> 952.2183 | L47: =L52*L53 -> 1024.7683 | M47: =M52*M53 -> 1157.9881 | N47: =N52*N53 -> 1308.5266 | O47: =O52*O53 -> 1478.6351 | ... AA47: =AA52*AA53 -> 2827.6968
B48: Amortization of Capitalized Software Costs | H48: =-H78 -> -147.77293 | I48: =-I78 -> -178.27523 | J48: =-J78 -> -213.6579 | K48: =-K78 -> -254.70179 | L48: =-L78 -> -302.3127 | M48: =-M78 -> -353.55112 | N48: =-N78 -> -411.45052 | O48: =-O78 -> -476.87685 | ... AA48: =-AA78 -> -1714.3712
B49: Ending Capitalized Software Costs | G49: =Model!N53 -> 2955.4587 | H49: =SUM(H46:H48) -> 3417.7317 | I49: =SUM(I46:I48) -> 3947.1098 | J49: =SUM(J46:J48) -> 4554.3297 | K49: =SUM(K46:K48) -> 5251.8462 | L49: =SUM(L46:L48) -> 5974.3018 | M49: =SUM(M46:M48) -> 6778.7388 | N49: =SUM(N46:N48) -> 7675.8149 | O49: =SUM(O46:O48) -> 8677.5731 | ... AA49: =SUM(AA46:AA48) -> 21773.547
B51: Memo/Drivers
B52: Total R&D Expense | H52: =Model!O21 -> 8714.9423 | I52: =Model!P21 -> 10109.333 | J52: =Model!Q21 -> 11726.826 | K52: =Model!R21 -> 13603.119 | L52: =Model!S21 -> 14639.547 | M52: =Model!T21 -> 16542.688 | N52: =Model!U21 -> 18693.237 | O52: =Model!V21 -> 21123.358 | ... AA52: =Model!AH21 -> 40395.668
B53: Capitalized Software Costs as % of R&D Expense | H53: 0.07 | I53: =H53 -> 0.07 | J53: =I53 -> 0.07 | K53: =J53 -> 0.07 | L53: =K53 -> 0.07 | M53: =L53 -> 0.07 | N53: =M53 -> 0.07 | O53: =N53 -> 0.07 | P53: =O53 -> 0.07 | ... AA53: =Z53 -> 0.07
B55: Amortization Schedule
B56: Cohort | C56: $ Costs | D56: Years | E56: Quarters | F56: End
B57: {=TRANSPOSE(G3:AA3)} -> 44926 | C57: =G49 -> 2955.4587 | D57: 5 | E57: =+D57*4 -> 20 | F57: =EOMONTH(B57, 12*D57) -> 46752 | H57: =$C57/$E57 -> 147.77293 | I57: =$C57/$E57 -> 147.77293 | J57: =$C57/$E57 -> 147.77293 | K57: =$C57/$E57 -> 147.77293 | L57: =$C57/$E57 -> 147.77293 | M57: =$C57/$E57 -> 147.77293 | N57: =$C57/$E57 -> 147.77293 | O57: =$C57/$E57 -> 147.77293 | ... AA57: =$C57/$E57 -> 147.77293
B58: 45016 | C58: {=TRANSPOSE(H47:AA47)} -> 610.04596 | D58: 5 | E58: =+D58*4 -> 20 | F58: =EOMONTH(B58, 12*D58) -> 46843 | I58: =$C58/$E58 -> 30.502298 | J58: =$C58/$E58 -> 30.502298 | K58: =$C58/$E58 -> 30.502298 | L58: =$C58/$E58 -> 30.502298 | M58: =$C58/$E58 -> 30.502298 | N58: =$C58/$E58 -> 30.502298 | O58: =$C58/$E58 -> 30.502298 | P58: =$C58/$E58 -> 30.502298 | ... AA58: =$C58/$E58 -> 30.502298
B59: 45107 | C59: 707.65331 | D59: 5 | E59: =+D59*4 -> 20 | F59: =EOMONTH(B59, 12*D59) -> 46934 | J59: =$C59/$E59 -> 35.382666 | K59: =$C59/$E59 -> 35.382666 | L59: =$C59/$E59 -> 35.382666 | M59: =$C59/$E59 -> 35.382666 | N59: =$C59/$E59 -> 35.382666 | O59: =$C59/$E59 -> 35.382666 | P59: =$C59/$E59 -> 35.382666 | Q59: =$C59/$E59 -> 35.382666 | ... AA59: =$C59/$E59 -> 35.382666
B60: 45199 | C60: 820.87784 | D60: 5 | E60: =+D60*4 -> 20 | F60: =EOMONTH(B60, 12*D60) -> 47026 | K60: =$C60/$E60 -> 41.043892 | L60: =$C60/$E60 -> 41.043892 | M60: =$C60/$E60 -> 41.043892 | N60: =$C60/$E60 -> 41.043892 | O60: =$C60/$E60 -> 41.043892 | P60: =$C60/$E60 -> 41.043892 | Q60: =$C60/$E60 -> 41.043892 | R60: =$C60/$E60 -> 41.043892 | ... AA60: =$C60/$E60 -> 41.043892
B61: 45291 | C61: 952.2183 | D61: 5 | E61: =+D61*4 -> 20 | F61: =EOMONTH(B61, 12*D61) -> 47118 | L61: =$C61/$E61 -> 47.610915 | M61: =$C61/$E61 -> 47.610915 | N61: =$C61/$E61 -> 47.610915 | O61: =$C61/$E61 -> 47.610915 | P61: =$C61/$E61 -> 47.610915 | Q61: =$C61/$E61 -> 47.610915 | R61: =$C61/$E61 -> 47.610915 | S61: =$C61/$E61 -> 47.610915 | ... AA61: =$C61/$E61 -> 47.610915
B62: 45382 | C62: 1024.7683 | D62: 5 | E62: =+D62*4 -> 20 | F62: =EOMONTH(B62, 12*D62) -> 47208 | M62: =$C62/$E62 -> 51.238413 | N62: =$C62/$E62 -> 51.238413 | O62: =$C62/$E62 -> 51.238413 | P62: =$C62/$E62 -> 51.238413 | Q62: =$C62/$E62 -> 51.238413 | R62: =$C62/$E62 -> 51.238413 | S62: =$C62/$E62 -> 51.238413 | T62: =$C62/$E62 -> 51.238413 | ... AA62: =$C62/$E62 -> 51.238413
B63: 45473 | C63: 1157.9881 | D63: 5 | E63: =+D63*4 -> 20 | F63: =EOMONTH(B63, 12*D63) -> 47299 | N63: =$C63/$E63 -> 57.899407 | O63: =$C63/$E63 -> 57.899407 | P63: =$C63/$E63 -> 57.899407 | Q63: =$C63/$E63 -> 57.899407 | R63: =$C63/$E63 -> 57.899407 | S63: =$C63/$E63 -> 57.899407 | T63: =$C63/$E63 -> 57.899407 | U63: =$C63/$E63 -> 57.899407 | ... AA63: =$C63/$E63 -> 57.899407
B64: 45565 | C64: 1308.5266 | D64: 5 | E64: =+D64*4 -> 20 | F64: =EOMONTH(B64, 12*D64) -> 47391 | O64: =$C64/$E64 -> 65.42633 | P64: =$C64/$E64 -> 65.42633 | Q64: =$C64/$E64 -> 65.42633 | R64: =$C64/$E64 -> 65.42633 | S64: =$C64/$E64 -> 65.42633 | T64: =$C64/$E64 -> 65.42633 | U64: =$C64/$E64 -> 65.42633 | V64: =$C64/$E64 -> 65.42633 | ... AA64: =$C64/$E64 -> 65.42633
B65: 45657 | C65: 1478.6351 | D65: 5 | E65: =+D65*4 -> 20 | F65: =EOMONTH(B65, 12*D65) -> 47483 | P65: =$C65/$E65 -> 73.931753 | Q65: =$C65/$E65 -> 73.931753 | R65: =$C65/$E65 -> 73.931753 | S65: =$C65/$E65 -> 73.931753 | T65: =$C65/$E65 -> 73.931753 | U65: =$C65/$E65 -> 73.931753 | V65: =$C65/$E65 -> 73.931753 | W65: =$C65/$E65 -> 73.931753 | ... AA65: =$C65/$E65 -> 73.931753
B66: 45747 | C66: 1531.1266 | D66: 5 | E66: =+D66*4 -> 20 | F66: =EOMONTH(B66, 12*D66) -> 47573 | Q66: =$C66/$E66 -> 76.55633 | R66: =$C66/$E66 -> 76.55633 | S66: =$C66/$E66 -> 76.55633 | T66: =$C66/$E66 -> 76.55633 | U66: =$C66/$E66 -> 76.55633 | V66: =$C66/$E66 -> 76.55633 | W66: =$C66/$E66 -> 76.55633 | X66: =$C66/$E66 -> 76.55633 | ... AA66: =$C66/$E66 -> 76.55633
B67: 45838 | C67: 1668.928 | D67: 5 | E67: =+D67*4 -> 20 | F67: =EOMONTH(B67, 12*D67) -> 47664 | R67: =$C67/$E67 -> 83.4464 | S67: =$C67/$E67 -> 83.4464 | T67: =$C67/$E67 -> 83.4464 | U67: =$C67/$E67 -> 83.4464 | V67: =$C67/$E67 -> 83.4464 | W67: =$C67/$E67 -> 83.4464 | X67: =$C67/$E67 -> 83.4464 | Y67: =$C67/$E67 -> 83.4464 | ... AA67: =$C67/$E67 -> 83.4464
B68: 45930 | C68: 1819.1315 | D68: 5 | E68: =+D68*4 -> 20 | F68: =EOMONTH(B68, 12*D68) -> 47756 | S68: =$C68/$E68 -> 90.956576 | T68: =$C68/$E68 -> 90.956576 | U68: =$C68/$E68 -> 90.956576 | V68: =$C68/$E68 -> 90.956576 | W68: =$C68/$E68 -> 90.956576 | X68: =$C68/$E68 -> 90.956576 | Y68: =$C68/$E68 -> 90.956576 | Z68: =$C68/$E68 -> 90.956576 | AA68: =$C68/$E68 -> 90.956576
B69: 46022 | C69: 1982.8533 | D69: 5 | E69: =+D69*4 -> 20 | F69: =EOMONTH(B69, 12*D69) -> 47848 | T69: =$C69/$E69 -> 99.142667 | U69: =$C69/$E69 -> 99.142667 | V69: =$C69/$E69 -> 99.142667 | W69: =$C69/$E69 -> 99.142667 | X69: =$C69/$E69 -> 99.142667 | Y69: =$C69/$E69 -> 99.142667 | Z69: =$C69/$E69 -> 99.142667 | AA69: =$C69/$E69 -> 99.142667
B70: 46112 | C70: 1991.2022 | D70: 5 | E70: =+D70*4 -> 20 | F70: =EOMONTH(B70, 12*D70) -> 47938 | U70: =$C70/$E70 -> 99.56011 | V70: =$C70/$E70 -> 99.56011 | W70: =$C70/$E70 -> 99.56011 | X70: =$C70/$E70 -> 99.56011 | Y70: =$C70/$E70 -> 99.56011 | Z70: =$C70/$E70 -> 99.56011 | AA70: =$C70/$E70 -> 99.56011
B71: 46203 | C71: 2110.6743 | D71: 5 | E71: =+D71*4 -> 20 | F71: =EOMONTH(B71, 12*D71) -> 48029 | V71: =$C71/$E71 -> 105.53372 | W71: =$C71/$E71 -> 105.53372 | X71: =$C71/$E71 -> 105.53372 | Y71: =$C71/$E71 -> 105.53372 | Z71: =$C71/$E71 -> 105.53372 | AA71: =$C71/$E71 -> 105.53372
B72: 46295 | C72: 2237.3148 | D72: 5 | E72: =+D72*4 -> 20 | F72: =EOMONTH(B72, 12*D72) -> 48121 | W72: =$C72/$E72 -> 111.86574 | X72: =$C72/$E72 -> 111.86574 | Y72: =$C72/$E72 -> 111.86574 | Z72: =$C72/$E72 -> 111.86574 | AA72: =$C72/$E72 -> 111.86574
B73: 46387 | C73: 2371.5537 | D73: 5 | E73: =+D73*4 -> 20 | F73: =EOMONTH(B73, 12*D73) -> 48213 | X73: =$C73/$E73 -> 118.57768 | Y73: =$C73/$E73 -> 118.57768 | Z73: =$C73/$E73 -> 118.57768 | AA73: =$C73/$E73 -> 118.57768
B74: 46477 | C74: 2374.1887 | D74: 5 | E74: =+D74*4 -> 20 | F74: =EOMONTH(B74, 12*D74) -> 48304 | Y74: =$C74/$E74 -> 118.70944 | Z74: =$C74/$E74 -> 118.70944 | AA74: =$C74/$E74 -> 118.70944
B75: 46568 | C75: 2516.6401 | D75: 5 | E75: =+D75*4 -> 20 | F75: =EOMONTH(B75, 12*D75) -> 48395 | Z75: =$C75/$E75 -> 125.832 | AA75: =$C75/$E75 -> 125.832
B76: 46660 | C76: 2667.6385 | D76: 5 | E76: =+D76*4 -> 20 | F76: =EOMONTH(B76, 12*D76) -> 48487 | AA76: =$C76/$E76 -> 133.38192
B77: 46752 | C77: 2827.6968 | D77: 5 | E77: =+D77*4 -> 20 | F77: =EOMONTH(B77, 12*D77) -> 48579
B78: Amortization of Capitalized Software Costs | H78: =SUM(H57:H77) -> 147.77293 | I78: =SUM(I57:I77) -> 178.27523 | J78: =SUM(J57:J77) -> 213.6579 | K78: =SUM(K57:K77) -> 254.70179 | L78: =SUM(L57:L77) -> 302.3127 | M78: =SUM(M57:M77) -> 353.55112 | N78: =SUM(N57:N77) -> 411.45052 | O78: =SUM(O57:O77) -> 476.87685 | ... AA78: =SUM(AA57:AA77) -> 1714.3712

Sheet SaaS Metrics
B2: Key Metrics | AH2: $ in thousands, except noted
C3: =YEAR(C4) -> 2020 | D3: =YEAR(D4) -> 2020 | E3: =YEAR(E4) -> 2020 | F3: =YEAR(F4) -> 2020 | G3: =YEAR(G4) -> 2021 | H3: =YEAR(H4) -> 2021 | I3: =YEAR(I4) -> 2021 | J3: =YEAR(J4) -> 2021 | ... AH3: =YEAR(AH4) -> 2027
C4: ='ARR Waterfall'!C4 -> 43921 | D4: =EOMONTH(C4, 3) -> 44012 | E4: =EOMONTH(D4, 3) -> 44104 | F4: =EOMONTH(E4, 3) -> 44196 | G4: =EOMONTH(F4, 3) -> 44286 | H4: =EOMONTH(G4, 3) -> 44377 | I4: =EOMONTH(H4, 3) -> 44469 | J4: =EOMONTH(I4, 3) -> 44561 | K4: =EOMONTH(J4, 3) -> 44651 | ... AH4: =EOMONTH(AG4, 3) -> 46752
B5: =+'ARR Waterfall'!B5 -> ARR Build
B6: =+'ARR Waterfall'!B6 -> Beginning ARR | C6: =+'ARR Waterfall'!C6 -> 6783.5742 | D6: =+'ARR Waterfall'!D6 -> 8563.9987 | E6: =+'ARR Waterfall'!E6 -> 10870.48 | F6: =+'ARR Waterfall'!F6 -> 12868.786 | G6: =+'ARR Waterfall'!G6 -> 17227.514 | H6: =+'ARR Waterfall'!H6 -> 20583.553 | I6: =+'ARR Waterfall'!I6 -> 24832.39 | ... AH6: =+'ARR Waterfall'!AH6 -> 448342.6
B7: =+'ARR Waterfall'!B7 -> New Logo ARR | C7: =+'ARR Waterfall'!C7 -> 1389.75 | D7: =+'ARR Waterfall'!D7 -> 1457.7 | E7: =+'ARR Waterfall'!E7 -> 1443.9 | F7: =+'ARR Waterfall'!F7 -> 2939.85 | G7: =+'ARR Waterfall'!G7 -> 1869.3 | H7: =+'ARR Waterfall'!H7 -> 2653.5 | I7: =+'ARR Waterfall'!I7 -> 3860.4 | ... AH7: =+'ARR Waterfall'!AH7 -> 26900.556
B8: =+'ARR Waterfall'!B8 -> Upsell ARR | C8: =+'ARR Waterfall'!C8 -> 575.678 | D8: =+'ARR Waterfall'!D8 -> 994.191 | E8: =+'ARR Waterfall'!E8 -> 955.39325 | F8: =+'ARR Waterfall'!F8 -> 1583.759 | G8: =+'ARR Waterfall'!G8 -> 1911.3585 | H8: =+'ARR Waterfall'!H8 -> 2160.428 | I8: =+'ARR Waterfall'!I8 -> 2432.2903 | ... AH8: =+'ARR Waterfall'!AH8 -> 17933.704
B9: =+'ARR Waterfall'!B9 -> Downsell ARR | C9: =+'ARR Waterfall'!C9 -> -116.0035 | D9: =+'ARR Waterfall'!D9 -> -145.40925 | E9: =+'ARR Waterfall'!E9 -> -189.91525 | F9: =+'ARR Waterfall'!F9 -> -164.88125 | G9: =+'ARR Waterfall'!G9 -> -208.328 | H9: =+'ARR Waterfall'!H9 -> -403.57425 | I9: =+'ARR Waterfall'!I9 -> -188.13225 | ... AH9: =+'ARR Waterfall'!AH9 -> -8966.852
B10: =+'ARR Waterfall'!B10 -> Churn ARR | C10: =+'ARR Waterfall'!C10 -> -69 | D10: =+'ARR Waterfall'!D10 -> 0 | E10: =+'ARR Waterfall'!E10 -> -211.0725 | F10: =+'ARR Waterfall'!F10 -> 0 | G10: =+'ARR Waterfall'!G10 -> -216.2915 | H10: =+'ARR Waterfall'!H10 -> -161.5165 | I10: =+'ARR Waterfall'!I10 -> 0 | ... AH10: =+'ARR Waterfall'!AH10 -> -8966.852
B11: =+'ARR Waterfall'!B11 -> Ending ARR | C11: =+'ARR Waterfall'!C11 -> 8563.9987 | D11: =+'ARR Waterfall'!D11 -> 10870.48 | E11: =+'ARR Waterfall'!E11 -> 12868.786 | F11: =+'ARR Waterfall'!F11 -> 17227.514 | G11: =+'ARR Waterfall'!G11 -> 20583.553 | H11: =+'ARR Waterfall'!H11 -> 24832.39 | I11: =+'ARR Waterfall'!I11 -> 30936.948 | ... AH11: =+'ARR Waterfall'!AH11 -> 475243.16
B13: =+'ARR Waterfall'!B20 -> Customer Bridge
B14: =+'ARR Waterfall'!B21 -> Beginning Customers | C14: =+'ARR Waterfall'!C21 -> 51 | D14: =+'ARR Waterfall'!D21 -> 63 | E14: =+'ARR Waterfall'!E21 -> 77 | F14: =+'ARR Waterfall'!F21 -> 89 | G14: =+'ARR Waterfall'!G21 -> 118 | H14: =+'ARR Waterfall'!H21 -> 135 | I14: =+'ARR Waterfall'!I21 -> 159 | ... AH14: =+'ARR Waterfall'!AH21 -> 3249.6923
B15: =+'ARR Waterfall'!B22 -> New Customers | C15: =+'ARR Waterfall'!C22 -> 13 | D15: =+'ARR Waterfall'!D22 -> 14 | E15: =+'ARR Waterfall'!E22 -> 13 | F15: =+'ARR Waterfall'!F22 -> 29 | G15: =+'ARR Waterfall'!G22 -> 18 | H15: =+'ARR Waterfall'!H22 -> 25 | I15: =+'ARR Waterfall'!I22 -> 37 | ... AH15: =+'ARR Waterfall'!AH22 -> 269.00556
B16: =+'ARR Waterfall'!B23 -> Churn Customers | C16: =+'ARR Waterfall'!C23 -> -1 | D16: =+'ARR Waterfall'!D23 -> 0 | E16: =+'ARR Waterfall'!E23 -> -1 | F16: =+'ARR Waterfall'!F23 -> 0 | G16: =+'ARR Waterfall'!G23 -> -1 | H16: =+'ARR Waterfall'!H23 -> -1 | I16: =+'ARR Waterfall'!I23 -> 0 | ... AH16: =+'ARR Waterfall'!AH23 -> -48.46947
B17: =+'ARR Waterfall'!B24 -> Ending Customers | C17: =+'ARR Waterfall'!C24 -> 63 | D17: =+'ARR Waterfall'!D24 -> 77 | E17: =+'ARR Waterfall'!E24 -> 89 | F17: =+'ARR Waterfall'!F24 -> 118 | G17: =+'ARR Waterfall'!G24 -> 135 | H17: =+'ARR Waterfall'!H24 -> 159 | I17: =+'ARR Waterfall'!I24 -> 196 | ... AH17: =+'ARR Waterfall'!AH24 -> 3470.2284
B20: Revenue & Retention
B21: YoY ARR Growth
B22: Ending ARR | C22: =+'ARR Waterfall'!C11 -> 8563.9987 | D22: =+'ARR Waterfall'!D11 -> 10870.48 | E22: =+'ARR Waterfall'!E11 -> 12868.786 | F22: =+'ARR Waterfall'!F11 -> 17227.514 | G22: =+'ARR Waterfall'!G11 -> 20583.553 | H22: =+'ARR Waterfall'!H11 -> 24832.39 | I22: =+'ARR Waterfall'!I11 -> 30936.948 | J22: =+'ARR Waterfall'!J11 -> 37345.929 | ... AH22: =+'ARR Waterfall'!AH11 -> 475243.16
B23: YoY ARR Growth | G23: =+G22/C22-1 -> 1.4034979 | H23: =+H22/D22-1 -> 1.2843875 | I23: =+I22/E22-1 -> 1.40403 | J23: =+J22/F22-1 -> 1.1678072 | K23: =+K22/G22-1 -> 1.1093313 | L23: =+L22/H22-1 -> 1.0809316 | M23: =+M22/I22-1 -> 0.91602693 | N23: =+N22/J22-1 -> 0.91590496 | ... AH23: =+AH22/AD22-1 -> 0.26247696
B25: Retention
B26: Annualized Net Dollar Retention | C26: {=1+((SUM(C8:C10/C6)*4))} -> 1.230365 | D26: {=1+((SUM(D8:D10/D6)*4))} -> 1.3964418 | E26: {=1+((SUM(E8:E10/E6)*4))} -> 1.204004 | F26: {=1+((SUM(F8:F10/F6)*4))} -> 1.4410292 | G26: {=1+((SUM(G8:G10/G6)*4))} -> 1.3452011 | H26: {=1+((SUM(H8:H10/H6)*4))} -> 1.3100217 | I26: {=1+((SUM(I8:I10/I6)*4))} -> 1.3614888 | J26: {=1+((SUM(J8:J10/J6)*4))} -> 1.2919817 | ... AH26: {=1+((SUM(AH8:AH10/AH6)*4))} -> 1
B27: Annualized Gross Dollar Retention | C27: =1+((SUM(C9:C10)/C6)*4) -> 0.8909109 | D27: =1+((SUM(D9:D10)/D6)*4) -> 0.93208348 | E27: =1+((SUM(E9:E10)/E6)*4) -> 0.85244893 | F27: =1+((SUM(F9:F10)/F6)*4) -> 0.94875002 | G27: =1+((SUM(G9:G10)/G6)*4) -> 0.90140899 | H27: =1+((SUM(H9:H10)/H6)*4) -> 0.89018596 | I27: =1+((SUM(I9:I10)/I6)*4) -> 0.96969567 | J27: =1+((SUM(J9:J10)/J6)*4) -> 0.92467234 | ... AH27: =1+((SUM(AH9:AH10)/AH6)*4) -> 0.84
B28: Annualized Logo Retention | C28: =1+((C16/C14)*4) -> 0.92156863 | D28: =1+((D16/D14)*4) -> 1 | E28: =1+((E16/E14)*4) -> 0.94805195 | F28: =1+((F16/F14)*4) -> 1 | G28: =1+((G16/G14)*4) -> 0.96610169 | H28: =1+((H16/H14)*4) -> 0.97037037 | I28: =1+((I16/I14)*4) -> 1 | J28: =1+((J16/J14)*4) -> 0.95918367 | ... AH28: =1+((AH16/AH14)*4) -> 0.94033962
B30: Quick Ratio
B31: New Logo ARR | C31: =+C7 -> 1389.75 | D31: =+D7 -> 1457.7 | E31: =+E7 -> 1443.9 | F31: =+F7 -> 2939.85 | G31: =+G7 -> 1869.3 | H31: =+H7 -> 2653.5 | I31: =+I7 -> 3860.4 | J31: =+J7 -> 4150.725 | ... AH31: =+AH7 -> 26900.556
B32: Upsell ARR | C32: =+C8 -> 575.678 | D32: =+D8 -> 994.191 | E32: =+E8 -> 955.39325 | F32: =+F8 -> 1583.759 | G32: =+G8 -> 1911.3585 | H32: =+H8 -> 2160.428 | I32: =+I8 -> 2432.2903 | J32: =+J8 -> 2840.8578 | ... AH32: =+AH8 -> 17933.704
B33: Downsell ARR | C33: =+C9 -> -116.0035 | D33: =+D9 -> -145.40925 | E33: =+E9 -> -189.91525 | F33: =+F9 -> -164.88125 | G33: =+G9 -> -208.328 | H33: =+H9 -> -403.57425 | I33: =+I9 -> -188.13225 | J33: =+J9 -> -271.31825 | ... AH33: =+AH9 -> -8966.852
B34: Churn ARR | C34: =+C10 -> -69 | D34: =+D10 -> 0 | E34: =+E10 -> -211.0725 | F34: =+F10 -> 0 | G34: =+G10 -> -216.2915 | H34: =+H10 -> -161.5165 | I34: =+I10 -> 0 | J34: =+J10 -> -311.28375 | ... AH34: =+AH10 -> -8966.852
B35: Quick Ratio | C35: =-SUM(C31:C32)/SUM(C33:C34) -> 10.623734 | D35: =-SUM(D31:D32)/SUM(D33:D34) -> 16.862002 | E35: =-SUM(E31:E32)/SUM(E33:E34) -> 5.9834577 | F35: =-SUM(F31:F32)/SUM(F33:F34) -> 27.435557 | G35: =-SUM(G31:G32)/SUM(G33:G34) -> 8.9036384 | H35: =-SUM(H31:H32)/SUM(H33:H34) -> 8.5188583 | I35: =-SUM(I31:I32)/SUM(I33:I34) -> 33.448227 | J35: =-SUM(J31:J32)/SUM(J33:J34) -> 12.000616 | ... AH35: =-SUM(AH31:AH32)/SUM(AH33:AH34) -> 2.5
B37: Efficiency
B38: Rule of 40
B39: LTM GAAP Revenue | C39: =SUM(Model!C8:C8) -> 2198.9787 | D39: =SUM(Model!C8:D8) -> 4983.2274 | E39: =SUM(Model!C8:E8) -> 8269.9118 | F39: =SUM(Model!C8:F8) -> 12657.565 | G39: =SUM(Model!D8:G8) -> 15695.075 | H39: =SUM(Model!E8:H8) -> 19211.929 | I39: =SUM(Model!F8:I8) -> 23758.791 | J39: =SUM(Model!G8:J8) -> 28798.994 | K39: =SUM(Model!H8:K8) -> 34494.682 | L39: =SUM(Model!I8:L8) -> 41160.248 | M39: =SUM(Model!J8:M8) -> 48151.127 | ... AH39: =SUM(Model!AE8:AH8) -> 436393.45
B40: LTM EBITDA | C40: =SUM(Model!C33:C33) -> 0 | D40: =SUM(Model!C33:D33) -> 0 | E40: =SUM(Model!C33:E33) -> 0 | F40: =SUM(Model!C33:F33) -> -2673.5242 | G40: =SUM(Model!D33:G33) -> -4657.9888 | H40: =SUM(Model!E33:H33) -> -7216.9039 | I40: =SUM(Model!F33:I33) -> -10399.313 | J40: =SUM(Model!G33:J33) -> -11136.521 | K40: =SUM(Model!H33:K33) -> -12526.681 | L40: =SUM(Model!I33:L33) -> -14696.282 | M40: =SUM(Model!J33:M33) -> -15010.053 | ... AH40: =SUM(Model!AE33:AH33) -> -41770.094
B41: YoY Growth | G41: =G39/C39-1 -> 6.1374382 | H41: =H39/D39-1 -> 2.8553185 | I41: =I39/E39-1 -> 1.8729195 | J41: =J39/F39-1 -> 1.2752397 | K41: =K39/G39-1 -> 1.197803 | L41: =L39/H39-1 -> 1.1424319 | M41: =M39/I39-1 -> 1.0266657 | N41: =N39/J39-1 -> 0.96573132 | ... AH41: =AH39/AD39-1 -> 0.26247696
B42: EBITDA Margin | G42: =G40/G39 -> -0.29678029 | H42: =H40/H39 -> -0.37564703 | I42: =I40/I39 -> -0.43770381 | J42: =J40/J39 -> -0.38669825 | K42: =K40/K39 -> -0.36314818 | L42: =L40/L39 -> -0.35705037 | M42: =M40/M39 -> -0.31172796 | N42: =N40/N39 -> -0.28725397 | ... AH42: =AH40/AH39 -> -0.095716593
B43: Rule of 40 | G43: =G41+G42 -> 5.840658 | H43: =H41+H42 -> 2.4796714 | I43: =I41+I42 -> 1.4352157 | J43: =J41+J42 -> 0.88854146 | K43: =K41+K42 -> 0.83465479 | L43: =L41+L42 -> 0.7853815 | M43: =M41+M42 -> 0.71493775 | N43: =N41+N42 -> 0.67847736 | ... AH43: =AH41+AH42 -> 0.16676037
B45: Magic Number
B46: New Logo ARR | D46: =+D7 -> 1457.7 | E46: =+E7 -> 1443.9 | F46: =+F7 -> 2939.85 | G46: =+G7 -> 1869.3 | H46: =+H7 -> 2653.5 | I46: =+I7 -> 3860.4 | J46: =+J7 -> 4150.725 | K46: =+K7 -> 2938.65 | ... AH46: =+AH7 -> 26900.556
B47: Upsell ARR | D47: =+D8 -> 994.191 | E47: =+E8 -> 955.39325 | F47: =+F8 -> 1583.759 | G47: =+G8 -> 1911.3585 | H47: =+H8 -> 2160.428 | I47: =+I8 -> 2432.2903 | J47: =+J8 -> 2840.8578 | K47: =+K8 -> 4008.832 | ... AH47: =+AH8 -> 17933.704
B48: Prior Period S&M | D48: =+Model!C20 -> 1200.0106 | E48: =+Model!D20 -> 1349.9439 | F48: =+Model!E20 -> 1491.0471 | G48: =+Model!F20 -> 1617.078 | H48: =+Model!G20 -> 1758.3879 | I48: =+Model!H20 -> 1902.2561 | J48: =+Model!I20 -> 2438.482 | K48: =+Model!J20 -> 2927.6113 | ... AH48: =+Model!AG20 -> 35867.408
B49: Magic Number | D49: =+D46/D48 -> 1.2147393 | E49: =+E46/E48 -> 1.0696 | F49: =+F46/F48 -> 1.9716681 | G49: =+G46/G48 -> 1.155974 | H49: =+H46/H48 -> 1.5090527 | I49: =+I46/I48 -> 2.0293798 | J49: =+J46/J48 -> 1.7021757 | K49: =+K46/K48 -> 1.0037706 | ... AH49: =+AH46/AH48 -> 0.75
B51: Burn Multiple
B52: Net Cash Burned | P52: =-Model!O113 -> 7900.854 | Q52: =-Model!P113 -> 8929.5123 | R52: =-Model!Q113 -> 10128.817 | S52: =-Model!R113 -> 11208.404 | T52: =-Model!S113 -> 10298.715 | U52: =-Model!T113 -> 11714.431 | V52: =-Model!U113 -> 12792.206 | W52: =-Model!V113 -> 13733.804 | ... AH52: =-Model!AG113 -> 7151.0693
B53: Net New ARR | P53: =P11-O11 -> 13279.912 | Q53: =Q11-P11 -> 15404.698 | R53: =R11-Q11 -> 17869.45 | S53: =S11-R11 -> 16841.956 | T53: =T11-S11 -> 19031.411 | U53: =U11-T11 -> 21505.494 | V53: =V11-U11 -> 24301.208 | W53: =W11-V11 -> 19011.022 | ... AH53: =AH11-AG11 -> 26900.556
B54: Burn Multiple | P54: =+P52/P53 -> 0.59494776 | Q54: =+Q52/Q53 -> 0.57966163 | R54: =+R52/R53 -> 0.56682312 | S54: =+S52/S53 -> 0.66550486 | T54: =+T52/T53 -> 0.54114304 | U54: =+U52/U53 -> 0.54471804 | V54: =+V52/V53 -> 0.52640207 | W54: =+W52/W53 -> 0.72241272 | ... AH54: =+AH52/AH53 -> 0.26583351
B57: Unit Economics
B58: Gross Margin
B59: Gross Profit - Total | C59: =Model!C16 -> 1476.7253 | D59: =Model!D16 -> 1865.8739 | E59: =Model!E16 -> 2200.9315 | F59: =Model!F16 -> 2934.2545 | G59: =Model!G16 -> 3495.9369 | H59: =Model!H16 -> 4192.5532 | I59: =Model!I16 -> 5205.2092 | J59: =Model!J16 -> 6255.0198 | ... AH59: =Model!AH16 -> 77227.013
B60: GAAP Revenue - Total | C60: =+Model!C8 -> 2198.9787 | D60: =+Model!D8 -> 2784.2487 | E60: =+Model!E8 -> 3286.6844 | F60: =+Model!F8 -> 4387.6529 | G60: =+Model!G8 -> 5236.4888 | H60: =+Model!H8 -> 6301.1027 | I60: =+Model!I8 -> 7833.5468 | J60: =+Model!J8 -> 9427.8556 | ... AH60: =+Model!AH8 -> 118810.79
B61: LTM Gross Margin % | C61: =SUM(C59:C59)/SUM(C60:C60) -> 0.67155053 | D61: =SUM(C59:D59)/SUM(C60:D60) -> 0.67076995 | E61: =SUM(C59:E59)/SUM(C60:E60) -> 0.67032526 | F61: =SUM(C59:F59)/SUM(C60:F60) -> 0.66978013 | G61: =SUM(D59:G59)/SUM(D60:G60) -> 0.66880834 | H61: =SUM(E59:H59)/SUM(E60:H60) -> 0.6674851 | I61: =SUM(F59:I59)/SUM(F60:I60) -> 0.66619357 | J61: =SUM(G59:J59)/SUM(G60:J60) -> 0.66490931 | K61: =SUM(H59:K59)/SUM(H60:K60) -> 0.66350458 | L61: =SUM(I59:L59)/SUM(I60:L60) -> 0.6622998 | M61: =SUM(J59:M59)/SUM(J60:M60) -> 0.66090211 | ... AH61: =SUM(AE59:AH59)/SUM(AE60:AH60) -> 0.65
B63: CAC
B64: New Customers | D64: =D15 -> 14 | E64: =E15 -> 13 | F64: =F15 -> 29 | G64: =G15 -> 18 | H64: =H15 -> 25 | I64: =I15 -> 37 | J64: =J15 -> 38 | K64: =K15 -> 29 | ... AH64: =AH15 -> 269.00556
B65: S&M Prior Period | D65: =+Model!C20 -> 1200.0106 | E65: =+Model!D20 -> 1349.9439 | F65: =+Model!E20 -> 1491.0471 | G65: =+Model!F20 -> 1617.078 | H65: =+Model!G20 -> 1758.3879 | I65: =+Model!H20 -> 1902.2561 | J65: =+Model!I20 -> 2438.482 | K65: =+Model!J20 -> 2927.6113 | ... AH65: =+Model!AG20 -> 35867.408
B66: Acquisition Cost Per Customer | D66: =+D65/D64 -> 85.715041 | E66: =+E65/E64 -> 103.84184 | F66: =+F65/F64 -> 51.415418 | G66: =+G65/G64 -> 89.837664 | H66: =+H65/H64 -> 70.335514 | I66: =+I65/I64 -> 51.412327 | J66: =+J65/J64 -> 64.17058 | K66: =+K65/K64 -> 100.95211 | ... AH66: =+AH65/AH64 -> 133.33333
B68: CAC Payback
B69: New Logo ARR | C69: =+C7 -> 1389.75 | D69: =+D7 -> 1457.7 | E69: =+E7 -> 1443.9 | F69: =+F7 -> 2939.85 | G69: =+G7 -> 1869.3 | H69: =+H7 -> 2653.5 | I69: =+I7 -> 3860.4 | J69: =+J7 -> 4150.725 | ... AH69: =+AH7 -> 26900.556
B70: Gross Margin Subscriptions | C70: =+Model!C17 -> 0.67155053 | D70: =+Model!D17 -> 0.67015346 | E70: =+Model!E17 -> 0.66965101 | F70: =+Model!F17 -> 0.66875266 | G70: =+Model!G17 -> 0.66761088 | H70: =+Model!H17 -> 0.66536819 | I70: =+Model!I17 -> 0.66447669 | J70: =+Model!J17 -> 0.66346156 | ... AH70: =+Model!AH17 -> 0.65
B71: New Logo Gross Profit | C71: =+C70*C69 -> 933.28735 | D71: =+D70*D69 -> 976.8827 | E71: =+E70*E69 -> 966.9091 | F71: =+F70*F69 -> 1966.0325 | G71: =+G70*G69 -> 1247.965 | H71: =+H70*H69 -> 1765.5545 | I71: =+I70*I69 -> 2565.1458 | J71: =+J70*J69 -> 2753.8465 | ... AH71: =+AH70*AH69 -> 17485.361
B72: S&M Prior Period | C72: =+C65 -> 0 | D72: =+D65 -> 1200.0106 | E72: =+E65 -> 1349.9439 | F72: =+F65 -> 1491.0471 | G72: =+G65 -> 1617.078 | H72: =+H65 -> 1758.3879 | I72: =+I65 -> 1902.2561 | J72: =+J65 -> 2438.482 | ... AH72: =+AH65 -> 35867.408
B73: GP Payback [Months] | C73: =(C72/C71)*12 -> 0 | D73: =(D72/D71)*12 -> 14.740897 | E73: =(E72/E71)*12 -> 16.753723 | F73: =(F72/F71)*12 -> 9.1008493 | G73: =(G72/G71)*12 -> 15.549262 | H73: =(H72/H71)*12 -> 11.95129 | I73: =(I72/I71)*12 -> 8.8989378 | J73: =(J72/J71)*12 -> 10.625786 | ... AH73: =(AH72/AH71)*12 -> 24.615385
B74: GP Payback w/ Upsell [Months] | C74: =(C72/(SUM(C7:C8)*C70))*12 -> 0 | D74: =(D72/(SUM(D7:D8)*D70))*12 -> 8.7637684 | E74: =(E72/(SUM(E7:E8)*E70))*12 -> 10.082428 | F74: =(F72/(SUM(F7:F8)*F70))*12 -> 5.9145545 | G74: =(G72/(SUM(G7:G8)*G70))*12 -> 7.6881412 | H74: =(H72/(SUM(H7:H8)*H70))*12 -> 6.5877074 | I74: =(I72/(SUM(I7:I8)*I70))*12 -> 5.4592643 | J74: =(J72/(SUM(J7:J8)*J70))*12 -> 6.3082593 | ... AH74: =(AH72/(SUM(AH7:AH8)*AH70))*12 -> 14.769231
B76: LTV / CAC
B77: Customer Lifetime (Years) | D77: =IFERROR(1/(1-D28),0) -> 0 | E77: =IFERROR(1/(1-E28),0) -> 19.25 | F77: =IFERROR(1/(1-F28),0) -> 0 | G77: =IFERROR(1/(1-G28),0) -> 29.5 | H77: =IFERROR(1/(1-H28),0) -> 33.75 | I77: =IFERROR(1/(1-I28),0) -> 0 | J77: =IFERROR(1/(1-J28),0) -> 24.5 | K77: =IFERROR(1/(1-K28),0) -> 19.333333 | ... AH77: =IFERROR(1/(1-AH28),0) -> 16.761542
B78: New Logo Gross Profit - Year 1 | D78: =D7*D70 -> 976.8827 | E78: =E7*E70 -> 966.9091 | F78: =F7*F70 -> 1966.0325 | G78: =G7*G70 -> 1247.965 | H78: =H7*H70 -> 1765.5545 | I78: =I7*I70 -> 2565.1458 | J78: =J7*J70 -> 2753.8465 | K78: =K7*K70 -> 1944.7132 | ... AH78: =AH7*AH70 -> 17485.361
B79: New Logo Gross Profit - Year 2 | D79: =+D78*D$26 -> 1364.1598 | E79: =+E78*E$26 -> 1164.1625 | F79: =+F78*F$26 -> 2833.1103 | G79: =+G78*G$26 -> 1678.7639 | H79: =+H78*H$26 -> 2312.9148 | I79: =+I78*I$26 -> 3492.4174 | J79: =+J78*J$26 -> 3557.9193 | K79: =+K78*K$26 -> 2597.2819 | ... AH79: =+AH78*AH$26 -> 17485.361
B80: New Logo Gross Profit - Year 3 | D80: =+D79*D$26 -> 1904.9698 | E80: =+E79*E$26 -> 1401.6563 | F80: =+F79*F$26 -> 4082.5949 | G80: =+G79*G$26 -> 2258.2749 | H80: =+H79*H$26 -> 3029.9686 | I80: =+I79*I$26 -> 4754.8874 | J80: =+J79*J$26 -> 4596.7667 | K80: =+K79*K$26 -> 3468.8266 | ... AH80: =+AH79*AH$26 -> 17485.361
B81: New Logo Gross Profit - Year 4 | D81: =+D80*D$26 -> 2660.1794 | E81: =+E80*E$26 -> 1687.5999 | F81: =+F80*F$26 -> 5883.1386 | G81: =+G80*G$26 -> 3037.8338 | H81: =+H80*H$26 -> 3969.3248 | I81: =+I80*I$26 -> 6473.7261 | J81: =+J80*J$26 -> 5938.9385 | K81: =+K80*K$26 -> 4632.8272 | ... AH81: =+AH80*AH$26 -> 17485.361
B82: New Logo Gross Profit - Year 5 | D82: =+D81*D$26 -> 3714.7857 | E82: =+E81*E$26 -> 2031.8771 | F82: =+F81*F$26 -> 8477.7748 | G82: =+G81*G$26 -> 4086.4973 | H82: =+H81*H$26 -> 5199.9018 | I82: =+I81*I$26 -> 8813.9059 | J82: =+J81*J$26 -> 7672.9999 | K82: =+K81*K$26 -> 6187.4202 | ... AH82: =+AH81*AH$26 -> 17485.361
B83: Overall LTV | D83: =+D77*D78 -> 0 | E83: =+E77*E78 -> 18613 | F83: =+F77*F78 -> 0 | G83: =+G77*G78 -> 36814.968 | H83: =+H77*H78 -> 59587.464 | I83: =+I77*I78 -> 0 | J83: =+J77*J78 -> 67469.239 | K83: =+K77*K78 -> 37597.789 | ... AH83: =+AH77*AH78 -> 293081.62
B84: 3 Year LTV | D84: =SUM(D78:D80) -> 4246.0123 | E84: =SUM(E78:E80) -> 3532.7279 | F84: =SUM(F78:F80) -> 8881.7377 | G84: =SUM(G78:G80) -> 5185.0038 | H84: =SUM(H78:H80) -> 7108.4379 | I84: =SUM(I78:I80) -> 10812.451 | J84: =SUM(J78:J80) -> 10908.532 | K84: =SUM(K78:K80) -> 8010.8217 | ... AH84: =SUM(AH78:AH80) -> 52456.084
B85: 5 Year LTV | D85: =SUM(D78:D82) -> 10620.977 | E85: =SUM(E78:E82) -> 7252.2048 | F85: =SUM(F78:F82) -> 23242.651 | G85: =SUM(G78:G82) -> 12309.335 | H85: =SUM(H78:H82) -> 16277.665 | I85: =SUM(I78:I82) -> 26100.083 | J85: =SUM(J78:J82) -> 24520.471 | K85: =SUM(K78:K82) -> 18831.069 | ... AH85: =SUM(AH78:AH82) -> 87426.807
B86: S&M Prior Period | D86: =D72 -> 1200.0106 | E86: =E72 -> 1349.9439 | F86: =F72 -> 1491.0471 | G86: =G72 -> 1617.078 | H86: =H72 -> 1758.3879 | I86: =I72 -> 1902.2561 | J86: =J72 -> 2438.482 | K86: =K72 -> 2927.6113 | ... AH86: =AH72 -> 35867.408
B87: Overall LTV / CAC | D87: =D83/D86 -> 0 | E87: =E83/E86 -> 13.78798 | F87: =F83/F86 -> 0 | G87: =G83/G86 -> 22.766353 | H87: =H83/H86 -> 33.887554 | I87: =I83/I86 -> 0 | J87: =J83/J86 -> 27.66854 | K87: =K83/K86 -> 12.84248 | ... AH87: =AH83/AH86 -> 8.1712518
B88: 3 Year LTV / CAC | D88: =+D84/D86 -> 3.5383124 | E88: =+E84/E86 -> 2.6169441 | F88: =+F84/F86 -> 5.9567116 | G88: =+G84/G86 -> 3.2064031 | H88: =+H84/H86 -> 4.0425881 | I88: =+I84/I86 -> 5.6840142 | J88: =+J84/J86 -> 4.473493 | K88: =+K84/K86 -> 2.7362997 | ... AH88: =+AH84/AH86 -> 1.4625
B89: 5 Year LTV / CAC | D89: =+D85/D86 -> 8.8507366 | E89: =+E85/E86 -> 5.3722266 | F89: =+F85/F86 -> 15.58814 | G89: =+G85/G86 -> 7.612085 | H89: =+H85/H86 -> 9.2571525 | I89: =+I85/I86 -> 13.720594 | J89: =+J85/J86 -> 10.055629 | K89: =+K85/K86 -> 6.43223 | ... AH89: =+AH85/AH86 -> 2.4375
B91: Other Margin Profile
B92: GAAP Revenue | C92: =Model!C8 -> 2198.9787 | D92: =Model!D8 -> 2784.2487 | E92: =Model!E8 -> 3286.6844 | F92: =Model!F8 -> 4387.6529 | G92: =Model!G8 -> 5236.4888 | H92: =Model!H8 -> 6301.1027 | I92: =Model!I8 -> 7833.5468 | J92: =Model!J8 -> 9427.8556 | ... AH92: =Model!AH8 -> 118810.79
B93: S&M | C93: =Model!C20 -> 1200.0106 | D93: =Model!D20 -> 1349.9439 | E93: =Model!E20 -> 1491.0471 | F93: =Model!F20 -> 1617.078 | G93: =Model!G20 -> 1758.3879 | H93: =Model!H20 -> 1902.2561 | I93: =Model!I20 -> 2438.482 | J93: =Model!J20 -> 2927.6113 | ... AH93: =Model!AH20 -> 38019.453
B94: R&D | C94: =Model!C21 -> 2384.2614 | D94: =Model!D21 -> 2500.9067 | E94: =Model!E21 -> 2551.3452 | F94: =Model!F21 -> 2636.7793 | G94: =Model!G21 -> 2660.6691 | H94: =Model!H21 -> 2698.5614 | I94: =Model!I21 -> 3369.0085 | J94: =Model!J21 -> 4151.8057 | ... AH94: =Model!AH21 -> 40395.668
B95: G&A | C95: =Model!C22 -> 1361.0007 | D95: =Model!D22 -> 1326.3992 | E95: =Model!E22 -> 1478.9223 | F95: =Model!F22 -> 1886.0624 | G95: =Model!G22 -> 1697.4529 | H95: =Model!H22 -> 2916.5136 | I95: =Model!I22 -> 3509.8164 | J95: =Model!J22 -> 3710.7398 | ... AH95: =Model!AH22 -> 26138.374
B96: Free Cash Flow - (Negative) / Positive | O96: =Model!O113 -> -7900.854 | P96: =Model!P113 -> -8929.5123 | Q96: =Model!Q113 -> -10128.817 | R96: =Model!R113 -> -11208.404 | S96: =Model!S113 -> -10298.715 | T96: =Model!T113 -> -11714.431 | U96: =Model!U113 -> -12792.206 | V96: =Model!V113 -> -13733.804 | ... AH96: =Model!AH113 -> -6223.4186
B97: LTM S&M, % of Revenue | C97: =+SUM(C93:C93)/SUM(C$92:C$92) -> 0.54571268 | D97: =+SUM(C93:D93)/SUM(C$92:D$92) -> 0.51170743 | E97: =+SUM(C93:E93)/SUM(C$92:E$92) -> 0.48863903 | F97: =+SUM(C93:F93)/SUM(C$92:F$92) -> 0.44701171 | G97: =+SUM(D93:G93)/SUM(D$92:G$92) -> 0.39607692 | H97: =+SUM(E93:H93)/SUM(E$92:H$92) -> 0.35232116 | I97: =+SUM(F93:I93)/SUM(F$92:I$92) -> 0.32477258 | J97: =+SUM(G93:J93)/SUM(G$92:J$92) -> 0.31343933 | K97: =+SUM(H93:K93)/SUM(H$92:K$92) -> 0.30961743 | L97: =+SUM(I93:L93)/SUM(I$92:L$92) -> 0.32496304 | M97: =+SUM(J93:M93)/SUM(J$92:M$92) -> 0.33032261 | ... AH97: =+SUM(AE93:AH93)/SUM(AE$92:AH$92) -> 0.32
B98: LTM R&D, % of Revenue | C98: =+SUM(C94:C94)/SUM(C$92:C$92) -> 1.0842585 | D98: =+SUM(C94:D94)/SUM(C$92:D$92) -> 0.98032212 | E98: =+SUM(C94:E94)/SUM(C$92:E$92) -> 0.89922522 | F98: =+SUM(C94:F94)/SUM(C$92:F$92) -> 0.7958318 | G98: =+SUM(D94:G94)/SUM(D$92:G$92) -> 0.65942345 | H98: =+SUM(E94:H94)/SUM(E$92:H$92) -> 0.54900032 | I98: =+SUM(F94:I94)/SUM(F$92:I$92) -> 0.47835002 | J98: =+SUM(G94:J94)/SUM(G$92:J$92) -> 0.4472394 | K98: =+SUM(H94:K94)/SUM(H$92:K$92) -> 0.42678132 | L98: =+SUM(I94:L94)/SUM(I$92:L$92) -> 0.43136801 | M98: =+SUM(J94:M94)/SUM(J$92:M$92) -> 0.41518527 | ... AH98: =+SUM(AE94:AH94)/SUM(AE$92:AH$92) -> 0.34
B99: LTM G&A, % of Revenue | C99: =+SUM(C95:C95)/SUM(C$92:C$92) -> 0.61892398 | D99: =+SUM(C95:D95)/SUM(C$92:D$92) -> 0.53928902 | E99: =+SUM(C95:E95)/SUM(C$92:E$92) -> 0.50379282 | F99: =+SUM(C95:F95)/SUM(C$92:F$92) -> 0.47816343 | G99: =+SUM(D95:G95)/SUM(D$92:G$92) -> 0.40705998 | H99: =+SUM(E95:H95)/SUM(E$92:H$92) -> 0.41531235 | I99: =+SUM(F95:I95)/SUM(F$92:I$92) -> 0.42131122 | J99: =+SUM(G95:J95)/SUM(G$92:J$92) -> 0.41093528 | K99: =+SUM(H95:K95)/SUM(H$92:K$92) -> 0.41119857 | L99: =+SUM(I95:L95)/SUM(I$92:L$92) -> 0.3848401 | M99: =+SUM(J95:M95)/SUM(J$92:M$92) -> 0.3496364 | ... AH99: =+SUM(AE95:AH95)/SUM(AE$92:AH$92) -> 0.22
B100: LTM FCF, % Margin | R100: =+SUM(O96:R96)/SUM(O$92:R$92) -> -0.36305446 | S100: =+SUM(P96:S96)/SUM(P$92:S$92) -> -0.33531233 | T100: =+SUM(Q96:T96)/SUM(Q$92:T$92) -> -0.31353107 | U100: =+SUM(R96:U96)/SUM(R$92:U$92) -> -0.29293747 | V100: =+SUM(S96:V96)/SUM(S$92:V$92) -> -0.27346455 | W100: =+SUM(T96:W96)/SUM(T$92:W$92) -> -0.25063801 | X100: =+SUM(U96:X96)/SUM(U$92:X$92) -> -0.23188905 | Y100: =+SUM(V96:Y96)/SUM(V$92:Y$92) -> -0.21288864 | ... AH100: =+SUM(AE96:AH96)/SUM(AE$92:AH$92) -> -0.062576701

Sheet Cohorts
A1: 1000
B2: Cohorts | O2: $ in thousands, except noted
D3: =EOMONTH(#REF!, 3) -> #REF! | E3: =EOMONTH(D3, 3) -> #REF! | F3: =EOMONTH(E3, 3) -> #REF! | G3: =EOMONTH(F3, 3) -> #REF! | H3: =EOMONTH(G3, 3) -> #REF! | I3: =EOMONTH(H3, 3) -> #REF! | J3: =EOMONTH(I3, 3) -> #REF! | K3: =EOMONTH(J3, 3) -> #REF! | L3: =EOMONTH(K3, 3) -> #REF! | ... O3: =EOMONTH(N3, 3) -> #REF!
D4: =EOMONTH(#REF!, 2)+1 -> #REF! | E4: =EOMONTH(D4, 2)+1 -> #REF! | F4: =EOMONTH(E4, 2)+1 -> #REF! | G4: =EOMONTH(F4, 2)+1 -> #REF! | H4: =EOMONTH(G4, 2)+1 -> #REF! | I4: =EOMONTH(H4, 2)+1 -> #REF! | J4: =EOMONTH(I4, 2)+1 -> #REF! | K4: =EOMONTH(J4, 2)+1 -> #REF! | L4: =EOMONTH(K4, 2)+1 -> #REF! | ... O4: =EOMONTH(N4, 2)+1 -> #REF!
D5: ='Raw Customer ARR'!D1 -> 43921 | E5: =EOMONTH(D5, 3) -> 44012 | F5: =EOMONTH(E5, 3) -> 44104 | G5: =EOMONTH(F5, 3) -> 44196 | H5: =EOMONTH(G5, 3) -> 44286 | I5: =EOMONTH(H5, 3) -> 44377 | J5: =EOMONTH(I5, 3) -> 44469 | K5: =EOMONTH(J5, 3) -> 44561 | L5: =EOMONTH(K5, 3) -> 44651 | ... O5: =EOMONTH(N5, 3) -> 44926
B6: ARR by Cohort
B7: {=TRANSPOSE(D5:O5)} -> 43921 | D7: =SUMIFS('Raw Customer ARR'!D$2:D$422, 'Raw Customer ARR'!$B$2:$B$422, Cohorts!$B7)/unit -> 8563.9988 | E7: =SUMIFS('Raw Customer ARR'!E$2:E$422, 'Raw Customer ARR'!$B$2:$B$422, Cohorts!$B7)/unit -> 9412.7805 | F7: =SUMIFS('Raw Customer ARR'!F$2:F$422, 'Raw Customer ARR'!$B$2:$B$422, Cohorts!$B7)/unit -> 9869.6385 | G7: =SUMIFS('Raw Customer ARR'!G$2:G$422, 'Raw Customer ARR'!$B$2:$B$422, Cohorts!$B7)/unit -> 10954.97 | H7: =SUMIFS('Raw Customer ARR'!H$2:H$422, 'Raw Customer ARR'!$B$2:$B$422, Cohorts!$B7)/unit -> 11939.255 | I7: =SUMIFS('Raw Customer ARR'!I$2:I$422, 'Raw Customer ARR'!$B$2:$B$422, Cohorts!$B7)/unit -> 12477.348 | J7: =SUMIFS('Raw Customer ARR'!J$2:J$422, 'Raw Customer ARR'!$B$2:$B$422, Cohorts!$B7)/unit -> 13802.687 | K7: =SUMIFS('Raw Customer ARR'!K$2:K$422, 'Raw Customer ARR'!$B$2:$B$422, Cohorts!$B7)/unit -> 14898.418 | ... O7: =SUMIFS('Raw Customer ARR'!O$2:O$422, 'Raw Customer ARR'!$B$2:$B$422, Cohorts!$B7)/unit -> 21666.762
B8: 44012 | D8: =SUMIFS('Raw Customer ARR'!D$2:D$422, 'Raw Customer ARR'!$B$2:$B$422, Cohorts!$B8)/unit -> 0 | E8: =SUMIFS('Raw Customer ARR'!E$2:E$422, 'Raw Customer ARR'!$B$2:$B$422, Cohorts!$B8)/unit -> 1457.7 | F8: =SUMIFS('Raw Customer ARR'!F$2:F$422, 'Raw Customer ARR'!$B$2:$B$422, Cohorts!$B8)/unit -> 1555.2475 | G8: =SUMIFS('Raw Customer ARR'!G$2:G$422, 'Raw Customer ARR'!$B$2:$B$422, Cohorts!$B8)/unit -> 1640.4162 | H8: =SUMIFS('Raw Customer ARR'!H$2:H$422, 'Raw Customer ARR'!$B$2:$B$422, Cohorts!$B8)/unit -> 1767.1488 | I8: =SUMIFS('Raw Customer ARR'!I$2:I$422, 'Raw Customer ARR'!$B$2:$B$422, Cohorts!$B8)/unit -> 1929.651 | J8: =SUMIFS('Raw Customer ARR'!J$2:J$422, 'Raw Customer ARR'!$B$2:$B$422, Cohorts!$B8)/unit -> 2118.0377 | K8: =SUMIFS('Raw Customer ARR'!K$2:K$422, 'Raw Customer ARR'!$B$2:$B$422, Cohorts!$B8)/unit -> 2317.1225 | ... O8: =SUMIFS('Raw Customer ARR'!O$2:O$422, 'Raw Customer ARR'!$B$2:$B$422, Cohorts!$B8)/unit -> 2707.4702
B9: 44104 | D9: =SUMIFS('Raw Customer ARR'!D$2:D$422, 'Raw Customer ARR'!$B$2:$B$422, Cohorts!$B9)/unit -> 0 | E9: =SUMIFS('Raw Customer ARR'!E$2:E$422, 'Raw Customer ARR'!$B$2:$B$422, Cohorts!$B9)/unit -> 0 | F9: =SUMIFS('Raw Customer ARR'!F$2:F$422, 'Raw Customer ARR'!$B$2:$B$422, Cohorts!$B9)/unit -> 1443.9 | G9: =SUMIFS('Raw Customer ARR'!G$2:G$422, 'Raw Customer ARR'!$B$2:$B$422, Cohorts!$B9)/unit -> 1692.2775 | H9: =SUMIFS('Raw Customer ARR'!H$2:H$422, 'Raw Customer ARR'!$B$2:$B$422, Cohorts!$B9)/unit -> 1800.8265 | I9: =SUMIFS('Raw Customer ARR'!I$2:I$422, 'Raw Customer ARR'!$B$2:$B$422, Cohorts!$B9)/unit -> 2044.897 | J9: =SUMIFS('Raw Customer ARR'!J$2:J$422, 'Raw Customer ARR'!$B$2:$B$422, Cohorts!$B9)/unit -> 2255.5147 | K9: =SUMIFS('Raw Customer ARR'!K$2:K$422, 'Raw Customer ARR'!$B$2:$B$422, Cohorts!$B9)/unit -> 2328.4815 | ... O9: =SUMIFS('Raw Customer ARR'!O$2:O$422, 'Raw Customer ARR'!$B$2:$B$422, Cohorts!$B9)/unit -> 2422.1962
B10: 44196 | D10: =SUMIFS('Raw Customer ARR'!D$2:D$422, 'Raw Customer ARR'!$B$2:$B$422, Cohorts!$B10)/unit -> 0 | E10: =SUMIFS('Raw Customer ARR'!E$2:E$422, 'Raw Customer ARR'!$B$2:$B$422, Cohorts!$B10)/unit -> 0 | F10: =SUMIFS('Raw Customer ARR'!F$2:F$422, 'Raw Customer ARR'!$B$2:$B$422, Cohorts!$B10)/unit -> 0 | G10: =SUMIFS('Raw Customer ARR'!G$2:G$422, 'Raw Customer ARR'!$B$2:$B$422, Cohorts!$B10)/unit -> 2939.85 | H10: =SUMIFS('Raw Customer ARR'!H$2:H$422, 'Raw Customer ARR'!$B$2:$B$422, Cohorts!$B10)/unit -> 3207.0222 | I10: =SUMIFS('Raw Customer ARR'!I$2:I$422, 'Raw Customer ARR'!$B$2:$B$422, Cohorts!$B10)/unit -> 3558.4857 | J10: =SUMIFS('Raw Customer ARR'!J$2:J$422, 'Raw Customer ARR'!$B$2:$B$422, Cohorts!$B10)/unit -> 3760.8792 | K10: =SUMIFS('Raw Customer ARR'!K$2:K$422, 'Raw Customer ARR'!$B$2:$B$422, Cohorts!$B10)/unit -> 3986.4198 | ... O10: =SUMIFS('Raw Customer ARR'!O$2:O$422, 'Raw Customer ARR'!$B$2:$B$422, Cohorts!$B10)/unit -> 5812.52
B11: 44286 | D11: =SUMIFS('Raw Customer ARR'!D$2:D$422, 'Raw Customer ARR'!$B$2:$B$422, Cohorts!$B11)/unit -> 0 | E11: =SUMIFS('Raw Customer ARR'!E$2:E$422, 'Raw Customer ARR'!$B$2:$B$422, Cohorts!$B11)/unit -> 0 | F11: =SUMIFS('Raw Customer ARR'!F$2:F$422, 'Raw Customer ARR'!$B$2:$B$422, Cohorts!$B11)/unit -> 0 | G11: =SUMIFS('Raw Customer ARR'!G$2:G$422, 'Raw Customer ARR'!$B$2:$B$422, Cohorts!$B11)/unit -> 0 | H11: =SUMIFS('Raw Customer ARR'!H$2:H$422, 'Raw Customer ARR'!$B$2:$B$422, Cohorts!$B11)/unit -> 1869.3 | I11: =SUMIFS('Raw Customer ARR'!I$2:I$422, 'Raw Customer ARR'!$B$2:$B$422, Cohorts!$B11)/unit -> 2168.5085 | J11: =SUMIFS('Raw Customer ARR'!J$2:J$422, 'Raw Customer ARR'!$B$2:$B$422, Cohorts!$B11)/unit -> 2347.2458 | K11: =SUMIFS('Raw Customer ARR'!K$2:K$422, 'Raw Customer ARR'!$B$2:$B$422, Cohorts!$B11)/unit -> 2586.914 | ... O11: =SUMIFS('Raw Customer ARR'!O$2:O$422, 'Raw Customer ARR'!$B$2:$B$422, Cohorts!$B11)/unit -> 3609.1748
B12: 44377 | D12: =SUMIFS('Raw Customer ARR'!D$2:D$422, 'Raw Customer ARR'!$B$2:$B$422, Cohorts!$B12)/unit -> 0 | E12: =SUMIFS('Raw Customer ARR'!E$2:E$422, 'Raw Customer ARR'!$B$2:$B$422, Cohorts!$B12)/unit -> 0 | F12: =SUMIFS('Raw Customer ARR'!F$2:F$422, 'Raw Customer ARR'!$B$2:$B$422, Cohorts!$B12)/unit -> 0 | G12: =SUMIFS('Raw Customer ARR'!G$2:G$422, 'Raw Customer ARR'!$B$2:$B$422, Cohorts!$B12)/unit -> 0 | H12: =SUMIFS('Raw Customer ARR'!H$2:H$422, 'Raw Customer ARR'!$B$2:$B$422, Cohorts!$B12)/unit -> 0 | I12: =SUMIFS('Raw Customer ARR'!I$2:I$422, 'Raw Customer ARR'!$B$2:$B$422, Cohorts!$B12)/unit -> 2653.5 | J12: =SUMIFS('Raw Customer ARR'!J$2:J$422, 'Raw Customer ARR'!$B$2:$B$422, Cohorts!$B12)/unit -> 2792.1833 | K12: =SUMIFS('Raw Customer ARR'!K$2:K$422, 'Raw Customer ARR'!$B$2:$B$422, Cohorts!$B12)/unit -> 2901.4828 | ... O12: =SUMIFS('Raw Customer ARR'!O$2:O$422, 'Raw Customer ARR'!$B$2:$B$422, Cohorts!$B12)/unit -> 3158.4428
B13: 44469 | D13: =SUMIFS('Raw Customer ARR'!D$2:D$422, 'Raw Customer ARR'!$B$2:$B$422, Cohorts!$B13)/unit -> 0 | E13: =SUMIFS('Raw Customer ARR'!E$2:E$422, 'Raw Customer ARR'!$B$2:$B$422, Cohorts!$B13)/unit -> 0 | F13: =SUMIFS('Raw Customer ARR'!F$2:F$422, 'Raw Customer ARR'!$B$2:$B$422, Cohorts!$B13)/unit -> 0 | G13: =SUMIFS('Raw Customer ARR'!G$2:G$422, 'Raw Customer ARR'!$B$2:$B$422, Cohorts!$B13)/unit -> 0 | H13: =SUMIFS('Raw Customer ARR'!H$2:H$422, 'Raw Customer ARR'!$B$2:$B$422, Cohorts!$B13)/unit -> 0 | I13: =SUMIFS('Raw Customer ARR'!I$2:I$422, 'Raw Customer ARR'!$B$2:$B$422, Cohorts!$B13)/unit -> 0 | J13: =SUMIFS('Raw Customer ARR'!J$2:J$422, 'Raw Customer ARR'!$B$2:$B$422, Cohorts!$B13)/unit -> 3860.4 | K13: =SUMIFS('Raw Customer ARR'!K$2:K$422, 'Raw Customer ARR'!$B$2:$B$422, Cohorts!$B13)/unit -> 4176.3655 | ... O13: =SUMIFS('Raw Customer ARR'!O$2:O$422, 'Raw Customer ARR'!$B$2:$B$422, Cohorts!$B13)/unit -> 5568.6332
B14: 44561 | D14: =SUMIFS('Raw Customer ARR'!D$2:D$422, 'Raw Customer ARR'!$B$2:$B$422, Cohorts!$B14)/unit -> 0 | E14: =SUMIFS('Raw Customer ARR'!E$2:E$422, 'Raw Customer ARR'!$B$2:$B$422, Cohorts!$B14)/unit -> 0 | F14: =SUMIFS('Raw Customer ARR'!F$2:F$422, 'Raw Customer ARR'!$B$2:$B$422, Cohorts!$B14)/unit -> 0 | G14: =SUMIFS('Raw Customer ARR'!G$2:G$422, 'Raw Customer ARR'!$B$2:$B$422, Cohorts!$B14)/unit -> 0 | H14: =SUMIFS('Raw Customer ARR'!H$2:H$422, 'Raw Customer ARR'!$B$2:$B$422, Cohorts!$B14)/unit -> 0 | I14: =SUMIFS('Raw Customer ARR'!I$2:I$422, 'Raw Customer ARR'!$B$2:$B$422, Cohorts!$B14)/unit -> 0 | J14: =SUMIFS('Raw Customer ARR'!J$2:J$422, 'Raw Customer ARR'!$B$2:$B$422, Cohorts!$B14)/unit -> 0 | K14: =SUMIFS('Raw Customer ARR'!K$2:K$422, 'Raw Customer ARR'!$B$2:$B$422, Cohorts!$B14)/unit -> 4150.725 | ... O14: =SUMIFS('Raw Customer ARR'!O$2:O$422, 'Raw Customer ARR'!$B$2:$B$422, Cohorts!$B14)/unit -> 5484.887
B15: 44651 | D15: =SUMIFS('Raw Customer ARR'!D$2:D$422, 'Raw Customer ARR'!$B$2:$B$422, Cohorts!$B15)/unit -> 0 | E15: =SUMIFS('Raw Customer ARR'!E$2:E$422, 'Raw Customer ARR'!$B$2:$B$422, Cohorts!$B15)/unit -> 0 | F15: =SUMIFS('Raw Customer ARR'!F$2:F$422, 'Raw Customer ARR'!$B$2:$B$422, Cohorts!$B15)/unit -> 0 | G15: =SUMIFS('Raw Customer ARR'!G$2:G$422, 'Raw Customer ARR'!$B$2:$B$422, Cohorts!$B15)/unit -> 0 | H15: =SUMIFS('Raw Customer ARR'!H$2:H$422, 'Raw Customer ARR'!$B$2:$B$422, Cohorts!$B15)/unit -> 0 | I15: =SUMIFS('Raw Customer ARR'!I$2:I$422, 'Raw Customer ARR'!$B$2:$B$422, Cohorts!$B15)/unit -> 0 | J15: =SUMIFS('Raw Customer ARR'!J$2:J$422, 'Raw Customer ARR'!$B$2:$B$422, Cohorts!$B15)/unit -> 0 | K15: =SUMIFS('Raw Customer ARR'!K$2:K$422, 'Raw Customer ARR'!$B$2:$B$422, Cohorts!$B15)/unit -> 0 | ... O15: =SUMIFS('Raw Customer ARR'!O$2:O$422, 'Raw Customer ARR'!$B$2:$B$422, Cohorts!$B15)/unit -> 3832.8553
B16: 44742 | D16: =SUMIFS('Raw Customer ARR'!D$2:D$422, 'Raw Customer ARR'!$B$2:$B$422, Cohorts!$B16)/unit -> 0 | E16: =SUMIFS('Raw Customer ARR'!E$2:E$422, 'Raw Customer ARR'!$B$2:$B$422, Cohorts!$B16)/unit -> 0 | F16: =SUMIFS('Raw Customer ARR'!F$2:F$422, 'Raw Customer ARR'!$B$2:$B$422, Cohorts!$B16)/unit -> 0 | G16: =SUMIFS('Raw Customer ARR'!G$2:G$422, 'Raw Customer ARR'!$B$2:$B$422, Cohorts!$B16)/unit -> 0 | H16: =SUMIFS('Raw Customer ARR'!H$2:H$422, 'Raw Customer ARR'!$B$2:$B$422, Cohorts!$B16)/unit -> 0 | I16: =SUMIFS('Raw Customer ARR'!I$2:I$422, 'Raw Customer ARR'!$B$2:$B$422, Cohorts!$B16)/unit -> 0 | J16: =SUMIFS('Raw Customer ARR'!J$2:J$422, 'Raw Customer ARR'!$B$2:$B$422, Cohorts!$B16)/unit -> 0 | K16: =SUMIFS('Raw Customer ARR'!K$2:K$422, 'Raw Customer ARR'!$B$2:$B$422, Cohorts!$B16)/unit -> 0 | ... O16: =SUMIFS('Raw Customer ARR'!O$2:O$422, 'Raw Customer ARR'!$B$2:$B$422, Cohorts!$B16)/unit -> 5655.766
B17: 44834 | D17: =SUMIFS('Raw Customer ARR'!D$2:D$422, 'Raw Customer ARR'!$B$2:$B$422, Cohorts!$B17)/unit -> 0 | E17: =SUMIFS('Raw Customer ARR'!E$2:E$422, 'Raw Customer ARR'!$B$2:$B$422, Cohorts!$B17)/unit -> 0 | F17: =SUMIFS('Raw Customer ARR'!F$2:F$422, 'Raw Customer ARR'!$B$2:$B$422, Cohorts!$B17)/unit -> 0 | G17: =SUMIFS('Raw Customer ARR'!G$2:G$422, 'Raw Customer ARR'!$B$2:$B$422, Cohorts!$B17)/unit -> 0 | H17: =SUMIFS('Raw Customer ARR'!H$2:H$422, 'Raw Customer ARR'!$B$2:$B$422, Cohorts!$B17)/unit -> 0 | I17: =SUMIFS('Raw Customer ARR'!I$2:I$422, 'Raw Customer ARR'!$B$2:$B$422, Cohorts!$B17)/unit -> 0 | J17: =SUMIFS('Raw Customer ARR'!J$2:J$422, 'Raw Customer ARR'!$B$2:$B$422, Cohorts!$B17)/unit -> 0 | K17: =SUMIFS('Raw Customer ARR'!K$2:K$422, 'Raw Customer ARR'!$B$2:$B$422, Cohorts!$B17)/unit -> 0 | ... O17: =SUMIFS('Raw Customer ARR'!O$2:O$422, 'Raw Customer ARR'!$B$2:$B$422, Cohorts!$B17)/unit -> 5474.6525
B18: 44926 | D18: =SUMIFS('Raw Customer ARR'!D$2:D$422, 'Raw Customer ARR'!$B$2:$B$422, Cohorts!$B18)/unit -> 0 | E18: =SUMIFS('Raw Customer ARR'!E$2:E$422, 'Raw Customer ARR'!$B$2:$B$422, Cohorts!$B18)/unit -> 0 | F18: =SUMIFS('Raw Customer ARR'!F$2:F$422, 'Raw Customer ARR'!$B$2:$B$422, Cohorts!$B18)/unit -> 0 | G18: =SUMIFS('Raw Customer ARR'!G$2:G$422, 'Raw Customer ARR'!$B$2:$B$422, Cohorts!$B18)/unit -> 0 | H18: =SUMIFS('Raw Customer ARR'!H$2:H$422, 'Raw Customer ARR'!$B$2:$B$422, Cohorts!$B18)/unit -> 0 | I18: =SUMIFS('Raw Customer ARR'!I$2:I$422, 'Raw Customer ARR'!$B$2:$B$422, Cohorts!$B18)/unit -> 0 | J18: =SUMIFS('Raw Customer ARR'!J$2:J$422, 'Raw Customer ARR'!$B$2:$B$422, Cohorts!$B18)/unit -> 0 | K18: =SUMIFS('Raw Customer ARR'!K$2:K$422, 'Raw Customer ARR'!$B$2:$B$422, Cohorts!$B18)/unit -> 0 | ... O18: =SUMIFS('Raw Customer ARR'!O$2:O$422, 'Raw Customer ARR'!$B$2:$B$422, Cohorts!$B18)/unit -> 6157.89
B19: Ending ARR | D19: =SUM(D7:D18) -> 8563.9988 | E19: =SUM(E7:E18) -> 10870.481 | F19: =SUM(F7:F18) -> 12868.786 | G19: =SUM(G7:G18) -> 17227.514 | H19: =SUM(H7:H18) -> 20583.553 | I19: =SUM(I7:I18) -> 24832.39 | J19: =SUM(J7:J18) -> 30936.948 | K19: =SUM(K7:K18) -> 37345.929 | ... O19: =SUM(O7:O18) -> 71551.25
B20: Check? | D20: ='ARR Waterfall'!C11-D19 -> 0 | E20: ='ARR Waterfall'!D11-E19 -> 0 | F20: ='ARR Waterfall'!E11-F19 -> 0 | G20: ='ARR Waterfall'!F11-G19 -> 0 | H20: ='ARR Waterfall'!G11-H19 -> 0 | I20: ='ARR Waterfall'!H11-I19 -> 0 | J20: ='ARR Waterfall'!I11-J19 -> 0 | K20: ='ARR Waterfall'!J11-K19 -> 0 | ... O20: ='ARR Waterfall'!N11-O19 -> 0
D23: 1 | E23: =+D23+1 -> 2 | F23: =+E23+1 -> 3 | G23: =+F23+1 -> 4 | H23: =+G23+1 -> 5 | I23: =+H23+1 -> 6 | J23: =+I23+1 -> 7 | K23: =+J23+1 -> 8 | L23: =+K23+1 -> 9 | ... O23: =+N23+1 -> 12
B24: ARR by Cohort (Reordered)
B25: =+B7 -> 43921 | D25: =D7 -> 8563.9988 | E25: =E7 -> 9412.7805 | F25: =F7 -> 9869.6385 | G25: =G7 -> 10954.97 | H25: =H7 -> 11939.255 | I25: =I7 -> 12477.348 | J25: =J7 -> 13802.687 | K25: =K7 -> 14898.418 | ... O25: =O7 -> 21666.762
B26: =+B8 -> 44012 | D26: =+E8 -> 1457.7 | E26: =+F8 -> 1555.2475 | F26: =+G8 -> 1640.4162 | G26: =+H8 -> 1767.1488 | H26: =+I8 -> 1929.651 | I26: =+J8 -> 2118.0377 | J26: =+K8 -> 2317.1225 | K26: =+L8 -> 2445.3535 | ... O26: =+P8 -> 0
B27: =+B9 -> 44104 | D27: =+F9 -> 1443.9 | E27: =+G9 -> 1692.2775 | F27: =+H9 -> 1800.8265 | G27: =+I9 -> 2044.897 | H27: =+J9 -> 2255.5147 | I27: =+K9 -> 2328.4815 | J27: =+L9 -> 2238.0595 | K27: =+M9 -> 2295.121 | ... O27: =+Q9 -> 0
B28: =+B10 -> 44196 | D28: =+G10 -> 2939.85 | E28: =+H10 -> 3207.0222 | F28: =+I10 -> 3558.4857 | G28: =+J10 -> 3760.8792 | H28: =+K10 -> 3986.4198 | I28: =+L10 -> 4503.409 | J28: =+M10 -> 4772.5935 | K28: =+N10 -> 5402.7635 | ... O28: =+R10 -> 0
B29: =+B11 -> 44286 | D29: =+H11 -> 1869.3 | E29: =+I11 -> 2168.5085 | F29: =+J11 -> 2347.2458 | G29: =+K11 -> 2586.914 | H29: =+L11 -> 2766.7773 | I29: =+M11 -> 2802.0143 | J29: =+N11 -> 3202.3917 | K29: =+O11 -> 3609.1748 | ... O29: =+S11 -> 0
B30: =+B12 -> 44377 | D30: =+I12 -> 2653.5 | E30: =+J12 -> 2792.1833 | F30: =+K12 -> 2901.4828 | G30: =+L12 -> 3107.7297 | H30: =+M12 -> 2964.2288 | I30: =+N12 -> 2890.0478 | J30: =+O12 -> 3158.4428 | K30: =+P12 -> 0 | ... O30: =+T12 -> 0
B31: =+B13 -> 44469 | D31: =+J13 -> 3860.4 | E31: =+K13 -> 4176.3655 | F31: =+L13 -> 4445.3358 | G31: =+M13 -> 4817.5403 | H31: =+N13 -> 4934.465 | I31: =+O13 -> 5568.6332 | J31: =+P13 -> 0 | K31: =+Q13 -> 0 | ... O31: =+U13 -> 0
B32: =+B14 -> 44561 | D32: =+K14 -> 4150.725 | E32: =+L14 -> 4422.8895 | F32: =+M14 -> 4912.5617 | G32: =+N14 -> 5119.4478 | H32: =+O14 -> 5484.887 | I32: =+P14 -> 0 | J32: =+Q14 -> 0 | K32: =+R14 -> 0 | ... O32: =+V14 -> 0
B33: =+B15 -> 44651 | D33: =+L15 -> 2938.65 | E33: =+M15 -> 3202.0935 | F33: =+N15 -> 3468.2595 | G33: =+O15 -> 3832.8553 | H33: =+P15 -> 0 | I33: =+Q15 -> 0 | J33: =+R15 -> 0 | K33: =+S15 -> 0 | ... O33: =+W15 -> 0
B34: =+B16 -> 44742 | D34: =+M16 -> 4775.55 | E34: =+N16 -> 5166.911 | F34: =+O16 -> 5655.766 | G34: =+P16 -> 0 | H34: =+Q16 -> 0 | I34: =+R16 -> 0 | J34: =+S16 -> 0 | K34: =+T16 -> 0 | ... O34: =+X16 -> 0
B35: =+B17 -> 44834 | D35: =+N17 -> 4969.35 | E35: =+O17 -> 5474.6525 | F35: =+P17 -> 0 | G35: =+Q17 -> 0 | H35: =+R17 -> 0 | I35: =+S17 -> 0 | J35: =+T17 -> 0 | K35: =+U17 -> 0 | ... O35: =+Y17 -> 0
B36: =+B18 -> 44926 | D36: =+O18 -> 6157.89 | E36: =+P18 -> 0 | F36: =+Q18 -> 0 | G36: =+R18 -> 0 | H36: =+S18 -> 0 | I36: =+T18 -> 0 | J36: =+U18 -> 0 | K36: =+V18 -> 0 | ... O36: =+Z18 -> 0
D39: =+D$23 -> 1 | E39: =+E$23 -> 2 | F39: =+F$23 -> 3 | G39: =+G$23 -> 4 | H39: =+H$23 -> 5 | I39: =+I$23 -> 6 | J39: =+J$23 -> 7 | K39: =+K$23 -> 8 | ... O39: =+O$23 -> 12
B40: Net Revenue Retention by Cohort
B41: =+B25 -> 43921 | D41: =D25/$D25 -> 1 | E41: =E25/$D25 -> 1.0991104 | F41: =F25/$D25 -> 1.1524568 | G41: =G25/$D25 -> 1.2791887 | H41: =H25/$D25 -> 1.3941216 | I41: =I25/$D25 -> 1.4569535 | J41: =J25/$D25 -> 1.6117106 | K41: =K25/$D25 -> 1.7396567 | ... O41: =O25/$D25 -> 2.5299819
B42: =+B26 -> 44012 | D42: =D26/$D26 -> 1 | E42: =E26/$D26 -> 1.0669188 | F42: =F26/$D26 -> 1.1253456 | G42: =G26/$D26 -> 1.2122856 | H42: =H26/$D26 -> 1.3237641 | I42: =I26/$D26 -> 1.4529998 | J42: =J26/$D26 -> 1.5895743 | K42: =K26/$D26 -> 1.6775424 | ... O42: =O26/$D26 -> 0
B43: =+B27 -> 44104 | D43: =D27/$D27 -> 1 | E43: =E27/$D27 -> 1.1720185 | F43: =F27/$D27 -> 1.2471961 | G43: =G27/$D27 -> 1.4162317 | H43: =H27/$D27 -> 1.562099 | I43: =I27/$D27 -> 1.6126335 | J43: =J27/$D27 -> 1.55001 | K43: =K27/$D27 -> 1.5895291 | ... O43: =O27/$D27 -> 0
B44: =+B28 -> 44196 | D44: =D28/$D28 -> 1 | E44: =E28/$D28 -> 1.0908796 | F44: =F28/$D28 -> 1.2104311 | G44: =G28/$D28 -> 1.2792759 | H44: =H28/$D28 -> 1.3559943 | I44: =I28/$D28 -> 1.5318499 | J44: =J28/$D28 -> 1.6234139 | K44: =K28/$D28 -> 1.8377684 | ... O44: =O28/$D28 -> 0
B45: =+B29 -> 44286 | D45: =D29/$D29 -> 1 | E45: =E29/$D29 -> 1.1600645 | F45: =F29/$D29 -> 1.2556817 | G45: =G29/$D29 -> 1.3838945 | H45: =H29/$D29 -> 1.4801141 | I45: =I29/$D29 -> 1.4989645 | J45: =J29/$D29 -> 1.7131502 | K45: =K29/$D29 -> 1.9307627 | ... O45: =O29/$D29 -> 0
B46: =+B30 -> 44377 | D46: =D30/$D30 -> 1 | E46: =E30/$D30 -> 1.0522643 | F46: =F30/$D30 -> 1.093455 | G46: =G30/$D30 -> 1.1711814 | H46: =H30/$D30 -> 1.1171015 | I46: =I30/$D30 -> 1.0891456 | J46: =J30/$D30 -> 1.1902931 | K46: =K30/$D30 -> 0 | ... O46: =O30/$D30 -> 0
B47: =+B31 -> 44469 | D47: =D31/$D31 -> 1 | E47: =E31/$D31 -> 1.0818479 | F47: =F31/$D31 -> 1.1515221 | G47: =G31/$D31 -> 1.2479381 | H47: =H31/$D31 -> 1.2782263 | I47: =I31/$D31 -> 1.4425016 | J47: =J31/$D31 -> 0 | K47: =K31/$D31 -> 0 | ... O47: =O31/$D31 -> 0
B48: =+B32 -> 44561 | D48: =D32/$D32 -> 1 | E48: =E32/$D32 -> 1.0655704 | F48: =F32/$D32 -> 1.1835431 | G48: =G32/$D32 -> 1.2333864 | H48: =H32/$D32 -> 1.3214287 | I48: =I32/$D32 -> 0 | J48: =J32/$D32 -> 0 | K48: =K32/$D32 -> 0 | ... O48: =O32/$D32 -> 0
B49: =+B33 -> 44651 | D49: =D33/$D33 -> 1 | E49: =E33/$D33 -> 1.0896478 | F49: =F33/$D33 -> 1.180222 | G49: =G33/$D33 -> 1.3042912 | H49: =H33/$D33 -> 0 | I49: =I33/$D33 -> 0 | J49: =J33/$D33 -> 0 | K49: =K33/$D33 -> 0 | ... O49: =O33/$D33 -> 0
B50: =+B34 -> 44742 | D50: =D34/$D34 -> 1 | E50: =E34/$D34 -> 1.081951 | F50: =F34/$D34 -> 1.1843172 | G50: =G34/$D34 -> 0 | H50: =H34/$D34 -> 0 | I50: =I34/$D34 -> 0 | J50: =J34/$D34 -> 0 | K50: =K34/$D34 -> 0 | ... O50: =O34/$D34 -> 0
B51: =+B35 -> 44834 | D51: =D35/$D35 -> 1 | E51: =E35/$D35 -> 1.1016838 | F51: =F35/$D35 -> 0 | G51: =G35/$D35 -> 0 | H51: =H35/$D35 -> 0 | I51: =I35/$D35 -> 0 | J51: =J35/$D35 -> 0 | K51: =K35/$D35 -> 0 | ... O51: =O35/$D35 -> 0
B52: =+B36 -> 44926 | D52: =D36/$D36 -> 1 | E52: =E36/$D36 -> 0 | F52: =F36/$D36 -> 0 | G52: =G36/$D36 -> 0 | H52: =H36/$D36 -> 0 | I52: =I36/$D36 -> 0 | J52: =J36/$D36 -> 0 | K52: =K36/$D36 -> 0 | ... O52: =O36/$D36 -> 0
C55: S&M | D55: =+D$23 -> 1 | E55: =+E$23 -> 2 | F55: =+F$23 -> 3 | G55: =+G$23 -> 4 | H55: =+H$23 -> 5 | I55: =+I$23 -> 6 | J55: =+J$23 -> 7 | K55: =+K$23 -> 8 | ... O55: =+O$23 -> 12 | P55: GM%
B56: CAC Payback by Cohort
B57: =+B41 -> 43921 | C57: {=-TRANSPOSE(Model!C20:N20)} -> -1200.0106 | D57: =C57+(D25*$P57/4) -> 237.7789 | E57: =D57+(E25*$P57/4) -> 1818.0683 | F57: =E57+(F25*$P57/4) -> 3475.0586 | G57: =F57+(G25*$P57/4) -> 5314.2625 | H57: =G57+(H25*$P57/4) -> 7318.7158 | I57: =H57+(I25*$P57/4) -> 9413.5082 | J57: =I57+(J25*$P57/4) -> 11730.809 | K57: =J57+(K25*$P57/4) -> 14232.069 | ... O57: =N57+(O25*$P57/4) -> 26984.273 | P57: {=+TRANSPOSE(Model!C17:N17)} -> 0.67155053
B58: =+B42 -> 44012 | C58: -1349.9439 | D58: =C58+(D26*$P58/4) -> -1105.7233 | E58: =D58+(E26*$P58/4) -> -845.15965 | F58: =E58+(F26*$P58/4) -> -570.327 | G58: =F58+(G26*$P58/4) -> -274.26178 | H58: =G58+(H26*$P58/4) -> 49.028789 | I58: =H58+(I26*$P58/4) -> 403.88137 | J58: =I58+(J26*$P58/4) -> 792.08829 | K58: =J58+(K26*$P58/4) -> 1201.7788 | ... N58: =M58+(N26*$P58/4) -> 2532.0608 | P58: 0.67015346
B59: =+B43 -> 44104 | C59: -1491.0471 | D59: =C59+(D27*$P59/4) -> -1249.3199 | E59: =D59+(E27*$P59/4) -> -966.01102 | F59: =E59+(F27*$P59/4) -> -664.52969 | G59: =F59+(G27*$P59/4) -> -322.18786 | H59: =G59+(H27*$P59/4) -> 55.414077 | I59: =H59+(I27*$P59/4) -> 445.23158 | J59: =I59+(J27*$P59/4) -> 819.91128 | K59: =J59+(K27*$P59/4) -> 1204.1438 | ... M59: =L59+(M27*$P59/4) -> 1991.6542 | P59: 0.66965101
B60: =+B44 -> 44196 | C60: -1617.078 | D60: =C60+(D28*$P60/4) -> -1125.5698 | E60: =D60+(E28*$P60/4) -> -589.39367 | F60: =E60+(F28*$P60/4) -> 5.5430322 | G60: =F60+(G28*$P60/4) -> 634.31753 | H60: =G60+(H28*$P60/4) -> 1300.7997 | I60: =H60+(I28*$P60/4) -> 2053.7164 | J60: =I60+(J28*$P60/4) -> 2851.6376 | K60: =J60+(K28*$P60/4) -> 3754.9157 | L60: =K60+(L28*$P60/4) -> 4726.7002 | P60: 0.66875266
B61: =+B45 -> 44286 | C61: -1758.3879 | D61: =C61+(D29*$P61/4) -> -1446.3966 | E61: =D61+(E29*$P61/4) -> -1084.4666 | F61: =E61+(F29*$P61/4) -> -692.70494 | G61: =F61+(G29*$P61/4) -> -260.94196 | H61: =G61+(H29*$P61/4) -> 200.84069 | I61: =H61+(I29*$P61/4) -> 668.50449 | J61: =I61+(J29*$P61/4) -> 1202.9924 | K61: =J61+(K29*$P61/4) -> 1805.3735 | P61: 0.66761088
B62: =+B46 -> 44377 | C62: -1902.2561 | D62: =C62+(D30*$P62/4) -> -1460.8675 | E62: =D62+(E30*$P62/4) -> -996.40999 | F62: =E62+(F30*$P62/4) -> -513.77141 | G62: =F62+(G30*$P62/4) -> 3.1747159 | H62: =G62+(H30*$P62/4) -> 496.25059 | I62: =H62+(I30*$P62/4) -> 976.98705 | J62: =I62+(J30*$P62/4) -> 1502.3689 | P62: 0.66536819
B63: =+B47 -> 44469 | C63: -2438.482 | D63: =C63+(D31*$P63/4) -> -1797.1956 | E63: =D63+(E31*$P63/4) -> -1103.4212 | F63: =E63+(F31*$P63/4) -> -364.96571 | G63: =F63+(G31*$P63/4) -> 435.32009 | H63: =G63+(H31*$P63/4) -> 1255.0293 | I63: =H63+(I31*$P63/4) -> 2180.0861 | P63: 0.66447669
B64: =+B48 -> 44561 | C64: -2927.6113 | D64: =C64+(D32*$P64/4) -> -2239.1496 | E64: =D64+(E32*$P64/4) -> -1505.5453 | F64: =E64+(F32*$P64/4) -> -690.72137 | G64: =F64+(G32*$P64/4) -> 158.41783 | H64: =G64+(H32*$P64/4) -> 1068.1708 | P64: 0.66346156
B65: =+B49 -> 44651 | C65: -3411.8055 | D65: =C65+(D33*$P65/4) -> -2925.6272 | E65: =D65+(E33*$P65/4) -> -2395.8641 | F65: =E65+(F33*$P65/4) -> -1822.0658 | G65: =F65+(G33*$P65/4) -> -1187.9477 | P65: 0.66177096
B66: =+B50 -> 44742 | C66: -4597.6605 | D66: =C66+(D34*$P66/4) -> -3808.9953 | E66: =D66+(E34*$P66/4) -> -2955.6983 | F66: =E66+(F34*$P66/4) -> -2021.6685 | P66: 0.66058584
B67: =+B51 -> 44834 | C67: -4968.3289 | D67: =C67+(D35*$P67/4) -> -4149.7399 | E67: =D67+(E35*$P67/4) -> -3247.9137 | P67: 0.65891027
B68: =+B52 -> 44926 | C68: -6584.1337 | D68: =C68+(D36*$P68/4) -> -5569.6012 | P68: 0.6590131
D71: =+D$23 -> 1 | E71: =+E$23 -> 2 | F71: =+F$23 -> 3 | G71: =+G$23 -> 4 | H71: =+H$23 -> 5 | I71: =+I$23 -> 6 | J71: =+J$23 -> 7 | K71: =+K$23 -> 8 | ... O71: =+O$23 -> 12 | P71: GM%
B72: Cumulative Realized LTV
B73: =+B57 -> 43921 | D73: =(SUM($D25:D25)/4)*$P73 -> 1437.7895 | E73: =(SUM($D25:E25)/4)*$P73 -> 3018.0789 | F73: =(SUM($D25:F25)/4)*$P73 -> 4675.0691 | G73: =(SUM($D25:G25)/4)*$P73 -> 6514.2731 | H73: =(SUM($D25:H25)/4)*$P73 -> 8518.7264 | I73: =(SUM($D25:I25)/4)*$P73 -> 10613.519 | J73: =(SUM($D25:J25)/4)*$P73 -> 12930.819 | K73: =(SUM($D25:K25)/4)*$P73 -> 15432.079 | ... O73: =(SUM($D25:O25)/4)*$P73 -> 28184.283 | P73: =P57 -> 0.67155053
B74: =+B58 -> 44012 | D74: =(SUM($D26:D26)/4)*$P74 -> 244.22067 | E74: =(SUM($D26:E26)/4)*$P74 -> 504.7843 | F74: =(SUM($D26:F26)/4)*$P74 -> 779.61695 | G74: =(SUM($D26:G26)/4)*$P74 -> 1075.6822 | H74: =(SUM($D26:H26)/4)*$P74 -> 1398.9727 | I74: =(SUM($D26:I26)/4)*$P74 -> 1753.8253 | J74: =(SUM($D26:J26)/4)*$P74 -> 2142.0322 | K74: =(SUM($D26:K26)/4)*$P74 -> 2551.7228 | ... N74: =(SUM($D26:N26)/4)*$P74 -> 3882.0048 | P74: =P58 -> 0.67015346
B75: =+B59 -> 44104 | D75: =(SUM($D27:D27)/4)*$P75 -> 241.72727 | E75: =(SUM($D27:E27)/4)*$P75 -> 525.03611 | F75: =(SUM($D27:F27)/4)*$P75 -> 826.51743 | G75: =(SUM($D27:G27)/4)*$P75 -> 1168.8593 | H75: =(SUM($D27:H27)/4)*$P75 -> 1546.4612 | I75: =(SUM($D27:I27)/4)*$P75 -> 1936.2787 | J75: =(SUM($D27:J27)/4)*$P75 -> 2310.9584 | K75: =(SUM($D27:K27)/4)*$P75 -> 2695.1909 | ... M75: =(SUM($D27:M27)/4)*$P75 -> 3482.7013 | P75: =P59 -> 0.66965101
B76: =+B60 -> 44196 | D76: =(SUM($D28:D28)/4)*$P76 -> 491.50813 | E76: =(SUM($D28:E28)/4)*$P76 -> 1027.6843 | F76: =(SUM($D28:F28)/4)*$P76 -> 1622.621 | G76: =(SUM($D28:G28)/4)*$P76 -> 2251.3955 | H76: =(SUM($D28:H28)/4)*$P76 -> 2917.8777 | I76: =(SUM($D28:I28)/4)*$P76 -> 3670.7944 | J76: =(SUM($D28:J28)/4)*$P76 -> 4468.7155 | K76: =(SUM($D28:K28)/4)*$P76 -> 5371.9936 | L76: =(SUM($D28:L28)/4)*$P76 -> 6343.7782 | P76: =P60 -> 0.66875266
B77: =+B61 -> 44286 | D77: =(SUM($D29:D29)/4)*$P77 -> 311.99125 | E77: =(SUM($D29:E29)/4)*$P77 -> 673.92122 | F77: =(SUM($D29:F29)/4)*$P77 -> 1065.6829 | G77: =(SUM($D29:G29)/4)*$P77 -> 1497.4459 | H77: =(SUM($D29:H29)/4)*$P77 -> 1959.2286 | I77: =(SUM($D29:I29)/4)*$P77 -> 2426.8923 | J77: =(SUM($D29:J29)/4)*$P77 -> 2961.3802 | K77: =(SUM($D29:K29)/4)*$P77 -> 3563.7613 | P77: =P61 -> 0.66761088
B78: =+B62 -> 44377 | D78: =(SUM($D30:D30)/4)*$P78 -> 441.38862 | E78: =(SUM($D30:E30)/4)*$P78 -> 905.8461 | F78: =(SUM($D30:F30)/4)*$P78 -> 1388.4847 | G78: =(SUM($D30:G30)/4)*$P78 -> 1905.4308 | H78: =(SUM($D30:H30)/4)*$P78 -> 2398.5067 | I78: =(SUM($D30:I30)/4)*$P78 -> 2879.2431 | J78: =(SUM($D30:J30)/4)*$P78 -> 3404.625 | P78: =P62 -> 0.66536819
B79: =+B63 -> 44469 | D79: =(SUM($D31:D31)/4)*$P79 -> 641.28645 | E79: =(SUM($D31:E31)/4)*$P79 -> 1335.0608 | F79: =(SUM($D31:F31)/4)*$P79 -> 2073.5163 | G79: =(SUM($D31:G31)/4)*$P79 -> 2873.8021 | H79: =(SUM($D31:H31)/4)*$P79 -> 3693.5114 | I79: =(SUM($D31:I31)/4)*$P79 -> 4618.5681 | P79: =P63 -> 0.66447669
B80: =+B64 -> 44561 | D80: =(SUM($D32:D32)/4)*$P80 -> 688.46162 | E80: =(SUM($D32:E32)/4)*$P80 -> 1422.0659 | F80: =(SUM($D32:F32)/4)*$P80 -> 2236.8899 | G80: =(SUM($D32:G32)/4)*$P80 -> 3086.0291 | H80: =(SUM($D32:H32)/4)*$P80 -> 3995.782 | P80: =P64 -> 0.66346156
B81: =+B65 -> 44651 | D81: =(SUM($D33:D33)/4)*$P81 -> 486.17831 | E81: =(SUM($D33:E33)/4)*$P81 -> 1015.9414 | F81: =(SUM($D33:F33)/4)*$P81 -> 1589.7398 | G81: =(SUM($D33:G33)/4)*$P81 -> 2223.8579 | P81: =P65 -> 0.66177096
B82: =+B66 -> 44742 | D82: =(SUM($D34:D34)/4)*$P82 -> 788.66517 | E82: =(SUM($D34:E34)/4)*$P82 -> 1641.9622 | F82: =(SUM($D34:F34)/4)*$P82 -> 2575.992 | P82: =P66 -> 0.66058584
B83: =+B67 -> 44834 | D83: =(SUM($D35:D35)/4)*$P83 -> 818.58894 | E83: =(SUM($D35:E35)/4)*$P83 -> 1720.4151 | P83: =P67 -> 0.65891027
B84: =+B68 -> 44926 | D84: =(SUM($D36:D36)/4)*$P84 -> 1014.5326 | P84: =P68 -> 0.6590131
C87: S&M | D87: =+D$23 -> 1 | E87: =+E$23 -> 2 | F87: =+F$23 -> 3 | G87: =+G$23 -> 4 | H87: =+H$23 -> 5 | I87: =+I$23 -> 6 | J87: =+J$23 -> 7 | K87: =+K$23 -> 8 | ... O87: =+O$23 -> 12 | P87: Max
B88: LTV / CAC
B89: =+B73 -> 43921 | C89: =+C57 -> -1200.0106 | D89: =D73/-$C89 -> 1.1981473 | E89: =E73/-$C89 -> 2.5150436 | F89: =F73/-$C89 -> 3.8958566 | G89: =G73/-$C89 -> 5.4285131 | H89: =H73/-$C89 -> 7.0988761 | I89: =I73/-$C89 -> 8.8445211 | J89: =J73/-$C89 -> 10.775588 | K89: =K73/-$C89 -> 12.859953 | ... O89: =O73/-$C89 -> 23.486696 | P89: =MAX(D89:O89) -> 23.486696
B90: =+B74 -> 44012 | C90: =+C58 -> -1349.9439 | D90: =D74/-$C90 -> 0.18091171 | E90: =E74/-$C90 -> 0.37392982 | F90: =F74/-$C90 -> 0.57751802 | G90: =G74/-$C90 -> 0.79683469 | H90: =H74/-$C90 -> 1.0363191 | I90: =I74/-$C90 -> 1.2991838 | J90: =J74/-$C90 -> 1.5867564 | K90: =K74/-$C90 -> 1.8902435 | ... O90: =O74/-$C90 -> 0 | P90: =MAX(D90:O90) -> 2.8756785
B91: =+B75 -> 44104 | C91: =+C59 -> -1491.0471 | D91: =D75/-$C91 -> 0.16211914 | E91: =E75/-$C91 -> 0.35212576 | F91: =F75/-$C91 -> 0.55432013 | G91: =G75/-$C91 -> 0.78391839 | H91: =H75/-$C91 -> 1.0371645 | I91: =I75/-$C91 -> 1.2986033 | J91: =J75/-$C91 -> 1.5498896 | K91: =K75/-$C91 -> 1.8075827 | ... O91: =O75/-$C91 -> 0 | P91: =MAX(D91:O91) -> 2.3357419
B92: =+B76 -> 44196 | C92: =+C60 -> -1617.078 | D92: =D76/-$C92 -> 0.30394832 | E92: =E76/-$C92 -> 0.63551932 | F92: =F76/-$C92 -> 1.0034278 | G92: =G76/-$C92 -> 1.3922616 | H92: =H76/-$C92 -> 1.8044137 | I92: =I76/-$C92 -> 2.270017 | J92: =J76/-$C92 -> 2.7634509 | K92: =K76/-$C92 -> 3.3220375 | ... O92: =O76/-$C92 -> 0 | P92: =MAX(D92:O92) -> 3.9229885
B93: =+B77 -> 44286 | C93: =+C61 -> -1758.3879 | D93: =D77/-$C93 -> 0.17743028 | E93: =E77/-$C93 -> 0.38326085 | F93: =F77/-$C93 -> 0.6060568 | G93: =G77/-$C93 -> 0.85160159 | H93: =H77/-$C93 -> 1.1142187 | I93: =I77/-$C93 -> 1.3801803 | J93: =J77/-$C93 -> 1.6841451 | K93: =K77/-$C93 -> 2.0267208 | ... O93: =O77/-$C93 -> 0 | P93: =MAX(D93:O93) -> 2.0267208
B94: =+B78 -> 44377 | C94: =+C62 -> -1902.2561 | D94: =D78/-$C94 -> 0.23203428 | E94: =E78/-$C94 -> 0.47619566 | F94: =F78/-$C94 -> 0.7299147 | G94: =G78/-$C94 -> 1.0016689 | H94: =H78/-$C94 -> 1.2608748 | I94: =I78/-$C94 -> 1.5135939 | J94: =J78/-$C94 -> 1.7897827 | K94: =K78/-$C94 -> 0 | ... O94: =O78/-$C94 -> 0 | P94: =MAX(D94:O94) -> 1.7897827
B95: =+B79 -> 44469 | C95: =+C63 -> -2438.482 | D95: =D79/-$C95 -> 0.26298592 | E95: =E79/-$C95 -> 0.54749669 | F95: =F79/-$C95 -> 0.85033078 | G95: =G79/-$C95 -> 1.1785209 | H95: =H79/-$C95 -> 1.5146765 | I95: =I79/-$C95 -> 1.8940341 | J95: =J79/-$C95 -> 0 | K95: =K79/-$C95 -> 0 | ... O95: =O79/-$C95 -> 0 | P95: =MAX(D95:O95) -> 1.8940341
B96: =+B80 -> 44561 | C96: =+C64 -> -2927.6113 | D96: =D80/-$C96 -> 0.23516156 | E96: =E80/-$C96 -> 0.48574274 | F96: =F80/-$C96 -> 0.76406657 | G96: =G80/-$C96 -> 1.0541116 | H96: =H80/-$C96 -> 1.3648609 | I96: =I80/-$C96 -> 0 | J96: =J80/-$C96 -> 0 | K96: =K80/-$C96 -> 0 | ... O96: =O80/-$C96 -> 0 | P96: =MAX(D96:O96) -> 1.3648609
B97: =+B81 -> 44651 | C97: =+C65 -> -3411.8055 | D97: =D81/-$C97 -> 0.14249883 | E97: =E81/-$C97 -> 0.29777237 | F97: =F81/-$C97 -> 0.46595264 | G97: =G81/-$C97 -> 0.65181261 | H97: =H81/-$C97 -> 0 | I97: =I81/-$C97 -> 0 | J97: =J81/-$C97 -> 0 | K97: =K81/-$C97 -> 0 | ... O97: =O81/-$C97 -> 0 | P97: =MAX(D97:O97) -> 0.65181261
B98: =+B82 -> 44742 | C98: =+C66 -> -4597.6605 | D98: =D82/-$C98 -> 0.17153619 | E98: =E82/-$C98 -> 0.35712994 | F98: =F82/-$C98 -> 0.56028321 | G98: =G82/-$C98 -> 0 | H98: =H82/-$C98 -> 0 | I98: =I82/-$C98 -> 0 | J98: =J82/-$C98 -> 0 | K98: =K82/-$C98 -> 0 | ... O98: =O82/-$C98 -> 0 | P98: =MAX(D98:O98) -> 0.56028321
B99: =+B83 -> 44834 | C99: =+C67 -> -4968.3289 | D99: =D83/-$C99 -> 0.16476142 | E99: =E83/-$C99 -> 0.34627642 | F99: =F83/-$C99 -> 0 | G99: =G83/-$C99 -> 0 | H99: =H83/-$C99 -> 0 | I99: =I83/-$C99 -> 0 | J99: =J83/-$C99 -> 0 | K99: =K83/-$C99 -> 0 | ... O99: =O83/-$C99 -> 0 | P99: =MAX(D99:O99) -> 0.34627642
B100: =+B84 -> 44926 | C100: =+C68 -> -6584.1337 | D100: =D84/-$C100 -> 0.15408748 | E100: =E84/-$C100 -> 0 | F100: =F84/-$C100 -> 0 | G100: =G84/-$C100 -> 0 | H100: =H84/-$C100 -> 0 | I100: =I84/-$C100 -> 0 | J100: =J84/-$C100 -> 0 | K100: =K84/-$C100 -> 0 | ... O100: =O84/-$C100 -> 0 | P100: =MAX(D100:O100) -> 0.15408748
B101: Average | D101: =AVERAGEIFS(D89:D100, D89:D100, "<>"&0) -> 0.28213521 | E101: =AVERAGEIFS(E89:E100, E89:E100, "<>"&0) -> 0.61549938 | F101: =AVERAGEIFS(F89:F100, F89:F100, "<>"&0) -> 1.0007727 | G101: =AVERAGEIFS(G89:G100, G89:G100, "<>"&0) -> 1.4599159 | H101: =AVERAGEIFS(H89:H100, H89:H100, "<>"&0) -> 2.0289255 | I101: =AVERAGEIFS(I89:I100, I89:I100, "<>"&0) -> 2.6428762 | J101: =AVERAGEIFS(J89:J100, J89:J100, "<>"&0) -> 3.3582687 | K101: =AVERAGEIFS(K89:K100, K89:K100, "<>"&0) -> 4.3813075 | ... O101: =AVERAGEIFS(O89:O100, O89:O100, "<>"&0) -> 23.486696

Sheet ARR Waterfall
A1: 1000
B2: ARR Waterfall | AH2: $ in thousands, except noted
O3: =YEAR(O4) -> 2023 | P3: =YEAR(P4) -> 2023 | Q3: =YEAR(Q4) -> 2023 | R3: =YEAR(R4) -> 2023 | S3: =YEAR(S4) -> 2024 | T3: =YEAR(T4) -> 2024 | U3: =YEAR(U4) -> 2024 | V3: =YEAR(V4) -> 2024 | ... AH3: =YEAR(AH4) -> 2027
C4: 43921 | D4: =EOMONTH(C4, 3) -> 44012 | E4: =EOMONTH(D4, 3) -> 44104 | F4: =EOMONTH(E4, 3) -> 44196 | G4: =EOMONTH(F4, 3) -> 44286 | H4: =EOMONTH(G4, 3) -> 44377 | I4: =EOMONTH(H4, 3) -> 44469 | J4: =EOMONTH(I4, 3) -> 44561 | K4: =EOMONTH(J4, 3) -> 44651 | ... AH4: =EOMONTH(AG4, 3) -> 46752
B5: ARR Build
B6: Beginning ARR | C6: =SUM('Raw Customer ARR'!C2:C422)/1000 -> 6783.5742 | D6: =+C11 -> 8563.9987 | E6: =+D11 -> 10870.48 | F6: =+E11 -> 12868.786 | G6: =+F11 -> 17227.514 | H6: =+G11 -> 20583.553 | I6: =+H11 -> 24832.39 | J6: =+I11 -> 30936.948 | K6: =+J11 -> 37345.929 | ... AH6: =+AG11 -> 448342.6
B7: New Logo ARR | C7: {=SUMPRODUCT('Raw Customer ARR'!D$2:D$422 - 'Raw Customer ARR'!C$2:C$422, --('Raw Customer ARR'!C$2:C$422 = 0), --('Raw Customer ARR'!D$2:D$422 > 0))/unit} -> 1389.75 | D7: {=SUMPRODUCT('Raw Customer ARR'!E$2:E$422 - 'Raw Customer ARR'!D$2:D$422, --('Raw Customer ARR'!D$2:D$422 = 0), --('Raw Customer ARR'!E$2:E$422 > 0))/unit} -> 1457.7 | E7: {=SUMPRODUCT('Raw Customer ARR'!F$2:F$422 - 'Raw Customer ARR'!E$2:E$422, --('Raw Customer ARR'!E$2:E$422 = 0), --('Raw Customer ARR'!F$2:F$422 > 0))/unit} -> 1443.9 | F7: {=SUMPRODUCT('Raw Customer ARR'!G$2:G$422 - 'Raw Customer ARR'!F$2:F$422, --('Raw Customer ARR'!F$2:F$422 = 0), --('Raw Customer ARR'!G$2:G$422 > 0))/unit} -> 2939.85 | G7: {=SUMPRODUCT('Raw Customer ARR'!H$2:H$422 - 'Raw Customer ARR'!G$2:G$422, --('Raw Customer ARR'!G$2:G$422 = 0), --('Raw Customer ARR'!H$2:H$422 > 0))/unit} -> 1869.3 | H7: {=SUMPRODUCT('Raw Customer ARR'!I$2:I$422 - 'Raw Customer ARR'!H$2:H$422, --('Raw Customer ARR'!H$2:H$422 = 0), --('Raw Customer ARR'!I$2:I$422 > 0))/unit} -> 2653.5 | I7: {=SUMPRODUCT('Raw Customer ARR'!J$2:J$422 - 'Raw Customer ARR'!I$2:I$422, --('Raw Customer ARR'!I$2:I$422 = 0), --('Raw Customer ARR'!J$2:J$422 > 0))/unit} -> 3860.4 | J7: {=SUMPRODUCT('Raw Customer ARR'!K$2:K$422 - 'Raw Customer ARR'!J$2:J$422, --('Raw Customer ARR'!J$2:J$422 = 0), --('Raw Customer ARR'!K$2:K$422 > 0))/unit} -> 4150.725 | ... N7: {=SUMPRODUCT('Raw Customer ARR'!O$2:O$422 - 'Raw Customer ARR'!N$2:N$422, --('Raw Customer ARR'!N$2:N$422 = 0), --('Raw Customer ARR'!O$2:O$422 > 0))/unit} -> 6157.89 | O7: =O15*O$6 -> 8586.15 | P7: =P15*P$6 -> 9959.934 | Q7: =Q15*Q$6 -> 11553.523 | R7: =R15*R$6 -> 13402.087 | S7: =S15*S$6 -> 12955.351 | T7: =T15*T$6 -> 14639.547 | U7: =U15*U$6 -> 16542.688 | V7: =V15*V$6 -> 18693.237 | ... AH7: =AH15*AH$6 -> 26900.556
B8: Upsell ARR | C8: {=SUMPRODUCT('Raw Customer ARR'!D$2:D$422 - 'Raw Customer ARR'!C$2:C$422, --('Raw Customer ARR'!C$2:C$422 > 0), --('Raw Customer ARR'!D$2:D$422 > 'Raw Customer ARR'!C$2:C$422))/unit} -> 575.678 | D8: {=SUMPRODUCT('Raw Customer ARR'!E$2:E$422 - 'Raw Customer ARR'!D$2:D$422, --('Raw Customer ARR'!D$2:D$422 > 0), --('Raw Customer ARR'!E$2:E$422 > 'Raw Customer ARR'!D$2:D$422))/unit} -> 994.191 | E8: {=SUMPRODUCT('Raw Customer ARR'!F$2:F$422 - 'Raw Customer ARR'!E$2:E$422, --('Raw Customer ARR'!E$2:E$422 > 0), --('Raw Customer ARR'!F$2:F$422 > 'Raw Customer ARR'!E$2:E$422))/unit} -> 955.39325 | F8: {=SUMPRODUCT('Raw Customer ARR'!G$2:G$422 - 'Raw Customer ARR'!F$2:F$422, --('Raw Customer ARR'!F$2:F$422 > 0), --('Raw Customer ARR'!G$2:G$422 > 'Raw Customer ARR'!F$2:F$422))/unit} -> 1583.759 | G8: {=SUMPRODUCT('Raw Customer ARR'!H$2:H$422 - 'Raw Customer ARR'!G$2:G$422, --('Raw Customer ARR'!G$2:G$422 > 0), --('Raw Customer ARR'!H$2:H$422 > 'Raw Customer ARR'!G$2:G$422))/unit} -> 1911.3585 | H8: {=SUMPRODUCT('Raw Customer ARR'!I$2:I$422 - 'Raw Customer ARR'!H$2:H$422, --('Raw Customer ARR'!H$2:H$422 > 0), --('Raw Customer ARR'!I$2:I$422 > 'Raw Customer ARR'!H$2:H$422))/unit} -> 2160.428 | I8: {=SUMPRODUCT('Raw Customer ARR'!J$2:J$422 - 'Raw Customer ARR'!I$2:I$422, --('Raw Customer ARR'!I$2:I$422 > 0), --('Raw Customer ARR'!J$2:J$422 > 'Raw Customer ARR'!I$2:I$422))/unit} -> 2432.2903 | J8: {=SUMPRODUCT('Raw Customer ARR'!K$2:K$422 - 'Raw Customer ARR'!J$2:J$422, --('Raw Customer ARR'!J$2:J$422 > 0), --('Raw Customer ARR'!K$2:K$422 > 'Raw Customer ARR'!J$2:J$422))/unit} -> 2840.8578 | ... N8: {=SUMPRODUCT('Raw Customer ARR'!O$2:O$422 - 'Raw Customer ARR'!N$2:N$422, --('Raw Customer ARR'!N$2:N$422 > 0), --('Raw Customer ARR'!O$2:O$422 > 'Raw Customer ARR'!N$2:N$422))/unit} -> 7403.581 | O8: =O16*O$6 -> 5724.1 | P8: =P16*P$6 -> 6639.956 | Q8: =Q16*Q$6 -> 7702.349 | R8: =R16*R$6 -> 8934.7248 | S8: =S16*S$6 -> 9068.7457 | T8: =T16*T$6 -> 10247.683 | U8: =U16*U$6 -> 11579.881 | V8: =V16*V$6 -> 13085.266 | ... AH8: =AH16*AH$6 -> 17933.704
B9: Downsell ARR | C9: {=SUMPRODUCT('Raw Customer ARR'!D$2:D$422 - 'Raw Customer ARR'!C$2:C$422, --('Raw Customer ARR'!C$2:C$422 > 0), --('Raw Customer ARR'!D$2:D$422 < 'Raw Customer ARR'!C$2:C$422), --('Raw Customer ARR'!D$2:D$422 > 0))/unit} -> -116.0035 | D9: {=SUMPRODUCT('Raw Customer ARR'!E$2:E$422 - 'Raw Customer ARR'!D$2:D$422, --('Raw Customer ARR'!D$2:D$422 > 0), --('Raw Customer ARR'!E$2:E$422 < 'Raw Customer ARR'!D$2:D$422), --('Raw Customer ARR'!E$2:E$422 > 0))/unit} -> -145.40925 | E9: {=SUMPRODUCT('Raw Customer ARR'!F$2:F$422 - 'Raw Customer ARR'!E$2:E$422, --('Raw Customer ARR'!E$2:E$422 > 0), --('Raw Customer ARR'!F$2:F$422 < 'Raw Customer ARR'!E$2:E$422), --('Raw Customer ARR'!F$2:F$422 > 0))/unit} -> -189.91525 | F9: {=SUMPRODUCT('Raw Customer ARR'!G$2:G$422 - 'Raw Customer ARR'!F$2:F$422, --('Raw Customer ARR'!F$2:F$422 > 0), --('Raw Customer ARR'!G$2:G$422 < 'Raw Customer ARR'!F$2:F$422), --('Raw Customer ARR'!G$2:G$422 > 0))/unit} -> -164.88125 | G9: {=SUMPRODUCT('Raw Customer ARR'!H$2:H$422 - 'Raw Customer ARR'!G$2:G$422, --('Raw Customer ARR'!G$2:G$422 > 0), --('Raw Customer ARR'!H$2:H$422 < 'Raw Customer ARR'!G$2:G$422), --('Raw Customer ARR'!H$2:H$422 > 0))/unit} -> -208.328 | H9: {=SUMPRODUCT('Raw Customer ARR'!I$2:I$422 - 'Raw Customer ARR'!H$2:H$422, --('Raw Customer ARR'!H$2:H$422 > 0), --('Raw Customer ARR'!I$2:I$422 < 'Raw Customer ARR'!H$2:H$422), --('Raw Customer ARR'!I$2:I$422 > 0))/unit} -> -403.57425 | I9: {=SUMPRODUCT('Raw Customer ARR'!J$2:J$422 - 'Raw Customer ARR'!I$2:I$422, --('Raw Customer ARR'!I$2:I$422 > 0), --('Raw Customer ARR'!J$2:J$422 < 'Raw Customer ARR'!I$2:I$422), --('Raw Customer ARR'!J$2:J$422 > 0))/unit} -> -188.13225 | J9: {=SUMPRODUCT('Raw Customer ARR'!K$2:K$422 - 'Raw Customer ARR'!J$2:J$422, --('Raw Customer ARR'!J$2:J$422 > 0), --('Raw Customer ARR'!K$2:K$422 < 'Raw Customer ARR'!J$2:J$422), --('Raw Customer ARR'!K$2:K$422 > 0))/unit} -> -271.31825 | ... N9: {=SUMPRODUCT('Raw Customer ARR'!O$2:O$422 - 'Raw Customer ARR'!N$2:N$422, --('Raw Customer ARR'!N$2:N$422 > 0), --('Raw Customer ARR'!O$2:O$422 < 'Raw Customer ARR'!N$2:N$422), --('Raw Customer ARR'!O$2:O$422 > 0))/unit} -> -556.12475 | O9: =O17*O$6 -> -1431.025 | P9: =P17*P$6 -> -1659.989 | Q9: =Q17*Q$6 -> -1925.5872 | R9: =R17*R$6 -> -2233.6812 | S9: =S17*S$6 -> -2591.0702 | T9: =T17*T$6 -> -2927.9093 | U9: =U17*U$6 -> -3308.5375 | V9: =V17*V$6 -> -3738.6474 | ... AH9: =AH17*AH$6 -> -8966.852
B10: Churn ARR | C10: {=SUMPRODUCT('Raw Customer ARR'!D$2:D$422 - 'Raw Customer ARR'!C$2:C$422, --('Raw Customer ARR'!C$2:C$422 > 0), --('Raw Customer ARR'!D$2:D$422 = 0))/unit} -> -69 | D10: {=SUMPRODUCT('Raw Customer ARR'!E$2:E$422 - 'Raw Customer ARR'!D$2:D$422, --('Raw Customer ARR'!D$2:D$422 > 0), --('Raw Customer ARR'!E$2:E$422 = 0))/unit} -> 0 | E10: {=SUMPRODUCT('Raw Customer ARR'!F$2:F$422 - 'Raw Customer ARR'!E$2:E$422, --('Raw Customer ARR'!E$2:E$422 > 0), --('Raw Customer ARR'!F$2:F$422 = 0))/unit} -> -211.0725 | F10: {=SUMPRODUCT('Raw Customer ARR'!G$2:G$422 - 'Raw Customer ARR'!F$2:F$422, --('Raw Customer ARR'!F$2:F$422 > 0), --('Raw Customer ARR'!G$2:G$422 = 0))/unit} -> 0 | G10: {=SUMPRODUCT('Raw Customer ARR'!H$2:H$422 - 'Raw Customer ARR'!G$2:G$422, --('Raw Customer ARR'!G$2:G$422 > 0), --('Raw Customer ARR'!H$2:H$422 = 0))/unit} -> -216.2915 | H10: {=SUMPRODUCT('Raw Customer ARR'!I$2:I$422 - 'Raw Customer ARR'!H$2:H$422, --('Raw Customer ARR'!H$2:H$422 > 0), --('Raw Customer ARR'!I$2:I$422 = 0))/unit} -> -161.5165 | I10: {=SUMPRODUCT('Raw Customer ARR'!J$2:J$422 - 'Raw Customer ARR'!I$2:I$422, --('Raw Customer ARR'!I$2:I$422 > 0), --('Raw Customer ARR'!J$2:J$422 = 0))/unit} -> 0 | J10: {=SUMPRODUCT('Raw Customer ARR'!K$2:K$422 - 'Raw Customer ARR'!J$2:J$422, --('Raw Customer ARR'!J$2:J$422 > 0), --('Raw Customer ARR'!K$2:K$422 = 0))/unit} -> -311.28375 | ... N10: {=SUMPRODUCT('Raw Customer ARR'!O$2:O$422 - 'Raw Customer ARR'!N$2:N$422, --('Raw Customer ARR'!N$2:N$422 > 0), --('Raw Customer ARR'!O$2:O$422 = 0))/unit} -> -730.1215 | O10: =O18*O$6 -> -1431.025 | P10: =P18*P$6 -> -1659.989 | Q10: =Q18*Q$6 -> -1925.5872 | R10: =R18*R$6 -> -2233.6812 | S10: =S18*S$6 -> -2591.0702 | T10: =T18*T$6 -> -2927.9093 | U10: =U18*U$6 -> -3308.5375 | V10: =V18*V$6 -> -3738.6474 | ... AH10: =AH18*AH$6 -> -8966.852
B11: Ending ARR | C11: =SUM(C6:C10) -> 8563.9987 | D11: =SUM(D6:D10) -> 10870.48 | E11: =SUM(E6:E10) -> 12868.786 | F11: =SUM(F6:F10) -> 17227.514 | G11: =SUM(G6:G10) -> 20583.553 | H11: =SUM(H6:H10) -> 24832.39 | I11: =SUM(I6:I10) -> 30936.948 | J11: =SUM(J6:J10) -> 37345.929 | ... AH11: =SUM(AH6:AH10) -> 475243.16
B12: Check? | C12: =(SUM('Raw Customer ARR'!D2:D422)/unit)-C11 -> 0 | D12: =(SUM('Raw Customer ARR'!E2:E422)/unit)-D11 -> 0 | E12: =(SUM('Raw Customer ARR'!F2:F422)/unit)-E11 -> 0 | F12: =(SUM('Raw Customer ARR'!G2:G422)/unit)-F11 -> 0 | G12: =(SUM('Raw Customer ARR'!H2:H422)/unit)-G11 -> 0 | H12: =(SUM('Raw Customer ARR'!I2:I422)/unit)-H11 -> 0 | I12: =(SUM('Raw Customer ARR'!J2:J422)/unit)-I11 -> 0 | J12: =(SUM('Raw Customer ARR'!K2:K422)/unit)-J11 -> 0 | ... N12: =(SUM('Raw Customer ARR'!O2:O422)/unit)-N11 -> 0
B14: NRR | C14: =SUM(C6,C8,C9,C10)/C6 -> 1.0575912 | D14: =SUM(D6,D8,D9,D10)/D6 -> 1.0991104 | E14: =SUM(E6,E8,E9,E10)/E6 -> 1.051001 | F14: =SUM(F6,F8,F9,F10)/F6 -> 1.1102573 | G14: =SUM(G6,G8,G9,G10)/G6 -> 1.0863003 | H14: =SUM(H6,H8,H9,H10)/H6 -> 1.0775054 | I14: =SUM(I6,I8,I9,I10)/I6 -> 1.0903722 | J14: =SUM(J6,J8,J9,J10)/J6 -> 1.0729954 | ... AH14: =SUM(AH6,AH8,AH9,AH10)/AH6 -> 1
B15: New Logo as % of Beginning | C15: =+C7/C$6 -> 0.20486987 | D15: =+D7/D$6 -> 0.17021254 | E15: =+E7/E$6 -> 0.13282762 | F15: =+F7/F$6 -> 0.22844812 | G15: =+G7/G$6 -> 0.10850666 | H15: =+H7/H$6 -> 0.12891361 | I15: =+I7/I$6 -> 0.15545825 | J15: =+J7/J$6 -> 0.13416724 | ... N15: =+N7/N$6 -> 0.103885 | O15: 0.12 | P15: 0.12 | Q15: 0.12 | R15: 0.12 | S15: 0.1 | T15: 0.1 | U15: 0.1 | V15: 0.1 | W15: 0.08 | X15: 0.08 | Y15: 0.08 | Z15: 0.08 | AA15: 0.06 | AB15: 0.06 | AC15: 0.06 | AD15: 0.06 | AE15: 0.06 | AF15: 0.06 | AG15: 0.06 | AH15: 0.06
B16: Upsell as % of Beginning | C16: =+C8/C$6 -> 0.084863522 | D16: =+D8/D$6 -> 0.11608958 | E16: =+E8/E$6 -> 0.087888778 | F16: =+F8/F$6 -> 0.12306981 | G16: =+G8/G$6 -> 0.11094802 | H16: =+H8/H$6 -> 0.10495895 | I16: =+I8/I$6 -> 0.097948295 | J16: =+J8/J$6 -> 0.091827343 | ... N16: =+N8/N$6 -> 0.12490009 | O16: 0.08 | P16: 0.08 | Q16: 0.08 | R16: 0.08 | S16: 0.07 | T16: 0.07 | U16: 0.07 | V16: 0.07 | W16: 0.05 | X16: 0.05 | Y16: 0.05 | Z16: 0.05 | AA16: 0.04 | AB16: 0.04 | AC16: 0.04 | AD16: 0.04 | AE16: 0.04 | AF16: 0.04 | AG16: 0.04 | AH16: 0.04
B17: Downsell as % of Beginning | C17: =+C9/C$6 -> -0.017100646 | D17: =+D9/D$6 -> -0.01697913 | E17: =+E9/E$6 -> -0.017470732 | F17: =+F9/F$6 -> -0.012812495 | G17: =+G9/G$6 -> -0.012092749 | H17: =+H9/H$6 -> -0.019606637 | I17: =+I9/I$6 -> -0.0075760831 | J17: =+J9/J$6 -> -0.0087700393 | ... N17: =+N9/N$6 -> -0.0093819507 | O17: -0.02 | P17: =+O17 -> -0.02 | Q17: =+P17 -> -0.02 | R17: =+Q17 -> -0.02 | S17: =+R17 -> -0.02 | T17: =+S17 -> -0.02 | U17: =+T17 -> -0.02 | V17: =+U17 -> -0.02 | W17: =+V17 -> -0.02 | ... AH17: =+AG17 -> -0.02
B18: Churn as % of Beginning | C18: =+C10/C$6 -> -0.010171629 | D18: =+D10/D$6 -> 0 | E18: =+E10/E$6 -> -0.019417035 | F18: =+F10/F$6 -> 0 | G18: =+G10/G$6 -> -0.012555004 | H18: =+H10/H$6 -> -0.0078468718 | I18: =+I10/I$6 -> 0 | J18: =+J10/J$6 -> -0.010061876 | ... N18: =+N10/N$6 -> -0.012317315 | O18: -0.02 | P18: =+O18 -> -0.02 | Q18: =+P18 -> -0.02 | R18: =+Q18 -> -0.02 | S18: =+R18 -> -0.02 | T18: =+S18 -> -0.02 | U18: =+T18 -> -0.02 | V18: =+U18 -> -0.02 | W18: =+V18 -> -0.02 | ... AH18: =+AG18 -> -0.02
B20: Customer Bridge
B21: Beginning Customers | C21: =COUNTIFS('Raw Customer ARR'!C$2:C$422, ">"&0 ) -> 51 | D21: =C24 -> 63 | E21: =D24 -> 77 | F21: =E24 -> 89 | G21: =F24 -> 118 | H21: =G24 -> 135 | I21: =H24 -> 159 | J21: =I24 -> 196 | K21: =J24 -> 232 | ... AH21: =AG24 -> 3249.6923
B22: New Customers | C22: =COUNTIFS('Raw Customer ARR'!C$2:C$422, "="&0, 'Raw Customer ARR'!D$2:D$422, ">"&0 ) -> 13 | D22: =COUNTIFS('Raw Customer ARR'!D$2:D$422, "="&0, 'Raw Customer ARR'!E$2:E$422, ">"&0 ) -> 14 | E22: =COUNTIFS('Raw Customer ARR'!E$2:E$422, "="&0, 'Raw Customer ARR'!F$2:F$422, ">"&0 ) -> 13 | F22: =COUNTIFS('Raw Customer ARR'!F$2:F$422, "="&0, 'Raw Customer ARR'!G$2:G$422, ">"&0 ) -> 29 | G22: =COUNTIFS('Raw Customer ARR'!G$2:G$422, "="&0, 'Raw Customer ARR'!H$2:H$422, ">"&0 ) -> 18 | H22: =COUNTIFS('Raw Customer ARR'!H$2:H$422, "="&0, 'Raw Customer ARR'!I$2:I$422, ">"&0 ) -> 25 | I22: =COUNTIFS('Raw Customer ARR'!I$2:I$422, "="&0, 'Raw Customer ARR'!J$2:J$422, ">"&0 ) -> 37 | J22: =COUNTIFS('Raw Customer ARR'!J$2:J$422, "="&0, 'Raw Customer ARR'!K$2:K$422, ">"&0 ) -> 38 | ... N22: =COUNTIFS('Raw Customer ARR'!N$2:N$422, "="&0, 'Raw Customer ARR'!O$2:O$422, ">"&0 ) -> 59 | O22: =+O7/O27 -> 85.8615 | P22: =+P7/P27 -> 99.59934 | Q22: =+Q7/Q27 -> 115.53523 | R22: =+R7/R27 -> 134.02087 | S22: =+S7/S27 -> 129.55351 | T22: =+T7/T27 -> 146.39547 | U22: =+U7/U27 -> 165.42688 | V22: =+V7/V27 -> 186.93237 | ... AH22: =+AH7/AH27 -> 269.00556
B23: Churn Customers | C23: =-COUNTIFS('Raw Customer ARR'!C$2:C$422, ">"&0, 'Raw Customer ARR'!D$2:D$422, "="&0 ) -> -1 | D23: =-COUNTIFS('Raw Customer ARR'!D$2:D$422, ">"&0, 'Raw Customer ARR'!E$2:E$422, "="&0 ) -> 0 | E23: =-COUNTIFS('Raw Customer ARR'!E$2:E$422, ">"&0, 'Raw Customer ARR'!F$2:F$422, "="&0 ) -> -1 | F23: =-COUNTIFS('Raw Customer ARR'!F$2:F$422, ">"&0, 'Raw Customer ARR'!G$2:G$422, "="&0 ) -> 0 | G23: =-COUNTIFS('Raw Customer ARR'!G$2:G$422, ">"&0, 'Raw Customer ARR'!H$2:H$422, "="&0 ) -> -1 | H23: =-COUNTIFS('Raw Customer ARR'!H$2:H$422, ">"&0, 'Raw Customer ARR'!I$2:I$422, "="&0 ) -> -1 | I23: =-COUNTIFS('Raw Customer ARR'!I$2:I$422, ">"&0, 'Raw Customer ARR'!J$2:J$422, "="&0 ) -> 0 | J23: =-COUNTIFS('Raw Customer ARR'!J$2:J$422, ">"&0, 'Raw Customer ARR'!K$2:K$422, "="&0 ) -> -2 | ... N23: =-COUNTIFS('Raw Customer ARR'!N$2:N$422, ">"&0, 'Raw Customer ARR'!O$2:O$422, "="&0 ) -> -3 | O23: =+O10/O28 -> -7.7352703 | P23: =+P10/P28 -> -8.9729135 | Q23: =+Q10/Q28 -> -10.40858 | R23: =+R10/R28 -> -12.073952 | S23: =+S10/S28 -> -14.005785 | T23: =+T10/T28 -> -15.826537 | U23: =+U10/U28 -> -17.883987 | V23: =+V10/V28 -> -20.208905 | ... AH23: =+AH10/AH28 -> -48.46947
B24: Ending Customers | C24: =SUM(C21:C23) -> 63 | D24: =SUM(D21:D23) -> 77 | E24: =SUM(E21:E23) -> 89 | F24: =SUM(F21:F23) -> 118 | G24: =SUM(G21:G23) -> 135 | H24: =SUM(H21:H23) -> 159 | I24: =SUM(I21:I23) -> 196 | J24: =SUM(J21:J23) -> 232 | ... AH24: =SUM(AH21:AH23) -> 3470.2284
B25: Check? | C25: =COUNTIFS('Raw Customer ARR'!D$2:D$422, ">"&0)-C24 -> 0 | D25: =COUNTIFS('Raw Customer ARR'!E$2:E$422, ">"&0)-D24 -> 0 | E25: =COUNTIFS('Raw Customer ARR'!F$2:F$422, ">"&0)-E24 -> 0 | F25: =COUNTIFS('Raw Customer ARR'!G$2:G$422, ">"&0)-F24 -> 0 | G25: =COUNTIFS('Raw Customer ARR'!H$2:H$422, ">"&0)-G24 -> 0 | H25: =COUNTIFS('Raw Customer ARR'!I$2:I$422, ">"&0)-H24 -> 0 | I25: =COUNTIFS('Raw Customer ARR'!J$2:J$422, ">"&0)-I24 -> 0 | J25: =COUNTIFS('Raw Customer ARR'!K$2:K$422, ">"&0)-J24 -> 0 | ... N25: =COUNTIFS('Raw Customer ARR'!O$2:O$422, ">"&0)-N24 -> 0
B27: ARR per New Customer | C27: =IFERROR(C7/C22, 0) -> 106.90385 | D27: =IFERROR(D7/D22, 0) -> 104.12143 | E27: =IFERROR(E7/E22, 0) -> 111.06923 | F27: =IFERROR(F7/F22, 0) -> 101.37414 | G27: =IFERROR(G7/G22, 0) -> 103.85 | H27: =IFERROR(H7/H22, 0) -> 106.14 | I27: =IFERROR(I7/I22, 0) -> 104.33514 | J27: =IFERROR(J7/J22, 0) -> 109.22961 | ... N27: =IFERROR(N7/N22, 0) -> 104.37102 | O27: 100 | P27: =+O27 -> 100 | Q27: =+P27 -> 100 | R27: =+Q27 -> 100 | S27: =+R27 -> 100 | T27: =+S27 -> 100 | U27: =+T27 -> 100 | V27: =+U27 -> 100 | W27: =+V27 -> 100 | ... AH27: =+AG27 -> 100
B28: ARR per Churned Customer | C28: =IFERROR(C10/C23,0) -> 69 | D28: =IFERROR(D10/D23,0) -> 0 | E28: =IFERROR(E10/E23,0) -> 211.0725 | F28: =IFERROR(F10/F23,0) -> 0 | G28: =IFERROR(G10/G23,0) -> 216.2915 | H28: =IFERROR(H10/H23,0) -> 161.5165 | I28: =IFERROR(I10/I23,0) -> 0 | J28: =IFERROR(J10/J23,0) -> 155.64187 | ... N28: =IFERROR(N10/N23,0) -> 243.37383 | O28: 185 | P28: =+O28 -> 185 | Q28: =+P28 -> 185 | R28: =+Q28 -> 185 | S28: =+R28 -> 185 | T28: =+S28 -> 185 | U28: =+T28 -> 185 | V28: =+U28 -> 185 | W28: =+V28 -> 185 | ... AH28: =+AG28 -> 185
B29: ARR per Ending Customer | C29: =IFERROR(C11/C24, 0) -> 135.93649 | D29: =IFERROR(D11/D24, 0) -> 141.17507 | E29: =IFERROR(E11/E24, 0) -> 144.5931 | F29: =IFERROR(F11/F24, 0) -> 145.99588 | G29: =IFERROR(G11/G24, 0) -> 152.47076 | H29: =IFERROR(H11/H24, 0) -> 156.17855 | I29: =IFERROR(I11/I24, 0) -> 157.84157 | J29: =IFERROR(J11/J24, 0) -> 160.97383 | ... N29: =IFERROR(N11/N24, 0) -> 181.60216 | O29: =O11/O24 -> 175.79928 | P29: =P11/P24 -> 171.08646 | Q29: =Q11/Q24 -> 167.22192 | R29: =R11/R24 -> 164.02786 | S29: =S11/S24 -> 161.69613 | T29: =T11/T24 -> 159.68726 | U29: =U11/U24 -> 157.95067 | V29: =V11/V24 -> 156.44507 | ... AH29: =AH11/AH24 -> 136.94867

Sheet Raw Customer ARR
A1: Customer | B1: Cohort | C1: =EOMONTH(D1, -3) -> 43830 | D1: 43921 | E1: =EOMONTH(D1,3) -> 44012 | F1: =EOMONTH(E1,3) -> 44104 | G1: =EOMONTH(F1,3) -> 44196 | H1: =EOMONTH(G1,3) -> 44286 | I1: =EOMONTH(H1,3) -> 44377 | J1: =EOMONTH(I1,3) -> 44469 | K1: =EOMONTH(J1,3) -> 44561 | L1: =EOMONTH(K1,3) -> 44651 | ... O1: =EOMONTH(N1,3) -> 44926
A2: 1 | B2: {=INDEX(D$1:O$1, MATCH(TRUE, INDEX(($D2:$O2 <> 0), 0),0))} -> 44834 | C2: 0 | D2: 0 | E2: 0 | F2: 0 | G2: 0 | H2: 0 | I2: 0 | J2: 0 | K2: 0 | L2: 0 | M2: 0 | N2: 120000 | O2: 138000
A3: =+A2+1 -> 2 | B3: {=INDEX(D$1:O$1, MATCH(TRUE, INDEX(($D3:$O3 <> 0), 0),0))} -> 44742 | C3: 0 | D3: 0 | E3: 0 | F3: 0 | G3: 0 | H3: 0 | I3: 0 | J3: 0 | K3: 0 | L3: 0 | M3: 60000 | N3: 69000 | O3: 69000
A4: =+A3+1 -> 3 | B4: {=INDEX(D$1:O$1, MATCH(TRUE, INDEX(($D4:$O4 <> 0), 0),0))} -> 44926 | C4: 0 | D4: 0 | E4: 0 | F4: 0 | G4: 0 | H4: 0 | I4: 0 | J4: 0 | K4: 0 | L4: 0 | M4: 0 | N4: 0 | O4: 92400
A5: =+A4+1 -> 4 | B5: {=INDEX(D$1:O$1, MATCH(TRUE, INDEX(($D5:$O5 <> 0), 0),0))} -> 44742 | C5: 0 | D5: 0 | E5: 0 | F5: 0 | G5: 0 | H5: 0 | I5: 0 | J5: 0 | K5: 0 | L5: 0 | M5: 120000 | N5: 120000 | O5: 138000
A6: =+A5+1 -> 5 | B6: {=INDEX(D$1:O$1, MATCH(TRUE, INDEX(($D6:$O6 <> 0), 0),0))} -> 44286 | C6: 0 | D6: 0 | E6: 0 | F6: 0 | G6: 0 | H6: 120000 | I6: 158700 | J6: 182505 | K6: 182505 | L6: 182505 | M6: 0 | N6: 0 | O6: 0
A7: =+A6+1 -> 6 | B7: {=INDEX(D$1:O$1, MATCH(TRUE, INDEX(($D7:$O7 <> 0), 0),0))} -> 44651 | C7: 0 | D7: 0 | E7: 0 | F7: 0 | G7: 0 | H7: 0 | I7: 0 | J7: 0 | K7: 0 | L7: 60000 | M7: 69000 | N7: 79350 | O7: 69828
A8: =+A7+1 -> 7 | B8: {=INDEX(D$1:O$1, MATCH(TRUE, INDEX(($D8:$O8 <> 0), 0),0))} -> 44834 | C8: 0 | D8: 0 | E8: 0 | F8: 0 | G8: 0 | H8: 0 | I8: 0 | J8: 0 | K8: 0 | L8: 0 | M8: 0 | N8: 120000 | O8: 120000
A9: =+A8+1 -> 8 | B9: {=INDEX(D$1:O$1, MATCH(TRUE, INDEX(($D9:$O9 <> 0), 0),0))} -> 44834 | C9: 0 | D9: 0 | E9: 0 | F9: 0 | G9: 0 | H9: 0 | I9: 0 | J9: 0 | K9: 0 | L9: 0 | M9: 0 | N9: 120750 | O9: 120750
A10: =+A9+1 -> 9 | B10: {=INDEX(D$1:O$1, MATCH(TRUE, INDEX(($D10:$O10 <> 0), 0),0))} -> 44834 | C10: 0 | D10: 0 | E10: 0 | F10: 0 | G10: 0 | H10: 0 | I10: 0 | J10: 0 | K10: 0 | L10: 0 | M10: 0 | N10: 105000 | O10: 120750
A11: =+A10+1 -> 10 | B11: {=INDEX(D$1:O$1, MATCH(TRUE, INDEX(($D11:$O11 <> 0), 0),0))} -> 44469 | C11: 0 | D11: 0 | E11: 0 | F11: 0 | G11: 0 | H11: 0 | I11: 0 | J11: 60000 | K11: 69000 | L11: 69828 | M11: 69828 | N11: 92347.5 | O11: 81265.75
A12: =+A11+1 -> 11 | B12: {=INDEX(D$1:O$1, MATCH(TRUE, INDEX(($D12:$O12 <> 0), 0),0))} -> 44742 | C12: 0 | D12: 0 | E12: 0 | F12: 0 | G12: 0 | H12: 0 | I12: 0 | J12: 0 | K12: 0 | L12: 0 | M12: 60000 | N12: 60000 | O12: 69000
A13: =+A12+1 -> 12 | B13: {=INDEX(D$1:O$1, MATCH(TRUE, INDEX(($D13:$O13 <> 0), 0),0))} -> 44834 | C13: 0 | D13: 0 | E13: 0 | F13: 0 | G13: 0 | H13: 0 | I13: 0 | J13: 0 | K13: 0 | L13: 0 | M13: 0 | N13: 138000 | O13: 182505
A14: =+A13+1 -> 13 | B14: {=INDEX(D$1:O$1, MATCH(TRUE, INDEX(($D14:$O14 <> 0), 0),0))} -> 44012 | C14: 0 | D14: 0 | E14: 69000 | F14: 69828 | G14: 69828 | H14: 69828 | I14: 69828 | J14: 80302.25 | K14: 92347.5 | L14: 106199.75 | M14: 106199.75 | N14: 106199.75 | O14: 106199.75
... A422: =+A421+1 -> 421 | B422: {=INDEX(D$1:O$1, MATCH(TRUE, INDEX(($D422:$O422 <> 0), 0),0))} -> 43921 | C422: 143921.75 | D422: 126651.25 | E422: 111453 | F422: 111453 | G422: 128171 | H422: 128171 | I422: 128171 | J422: 147396.75 | K422: 169506 | L422: 194932 | M422: 226862 | N422: 226862 | O422: 226862
