Workbook

Sheet Start ->

Sheet Model - Start
B2: Historical financials | J2: $ millions
B3: Income statement | C3: =+D3-1 -> -2 | D3: =+E3-1 -> -1 | E3: 0 | F3: 1 | G3: =F3+1 -> 2 | H3: =G3+1 -> 3 | I3: =H3+1 -> 4 | J3: =I3+1 -> 5
B4: Gross revenue | C4: 27.24 | D4: 13.08 | E4: 33.2
B6: Discounts | C6: 1.6344 | D6: 1.635 | E6: 2.7224
B7: Returns | C7: 2.1792 | D7: 1.59576 | E7: 2.6228
B8: Net revenue | C8: =C4-C6-C7 -> 23.4264 | D8: =D4-D6-D7 -> 9.84924 | E8: =E4-E6-E7 -> 27.8548
B10: Product cost | C10: 8.9254584 | D10: 3.9593945 | E10: 13.426014
B11: Freight, duties, & taxes | C11: 0.5622336 | D11: 0.3447234 | E11: 1.0584824
B12: COGS | C12: =C10+C11 -> 9.487692 | D12: =D10+D11 -> 4.3041179 | E12: =E10+E11 -> 14.484496
B14: Gross profit | C14: =C8-C12 -> 13.938708 | D14: =D8-D12 -> 5.5451221 | E14: =E8-E12 -> 13.370304
B16: Picking & packing | C16: 0.4919544 | D16: 0.20683404 | E16: 0.5849508
B17: Packaging material | C17: 0.117132 | D17: 0.03939696 | E17: 0.139274
B18: Shipping to customers | C18: 1.6164216 | D18: 0.738693 | E18: 2.0055456
B19: Merchant fees | C19: 0.7496448 | D19: 0.31517568 | E19: 0.8913536
B20: Fulfillment costs | C20: =SUM(C16:C19) -> 2.9751528 | D20: =SUM(D16:D19) -> 1.3000997 | E20: =SUM(E16:E19) -> 3.621124
B22: Contribution Profit | C22: =C14-C20 -> 10.963555 | D22: =D14-D20 -> 4.2450224 | E22: =E14-E20 -> 9.74918
B24: Ad spend | C24: 4.7087064 | D24: 1.477386 | E24: 6.26733
B25: Other marketing spend | C25: 0.351396 | D25: 0.0492462 | E25: 0.557096
B26: Marketing expenses | C26: =SUM(C24:C25) -> 5.0601024 | D26: =SUM(D24:D25) -> 1.5266322 | E26: =SUM(E24:E25) -> 6.824426
B28: Headcount | C28: 2 | D28: 1.2 | E28: 3.254902
B29: Research & development | C29: 0.234264 | D29: 0.0492462 | E29: 0.1671288
B30: General & administrative | C30: 1.17132 | D30: 0.7879392 | E30: 1.1699016
B31: Operating expenses | C31: =SUM(C28:C30) -> 3.405584 | D31: =SUM(D28:D30) -> 2.0371854 | E31: =SUM(E28:E30) -> 4.5919324
B33: EBITDA | C33: =+C22-C26-C31 -> 2.4978688 | D33: =+D22-D26-D31 -> 0.68120484 | E33: =+E22-E26-E31 -> -1.6671784
B36: Balance sheet | E36: 0 | F36: 1 | G36: =F36+1 -> 2 | H36: =G36+1 -> 3 | I36: =H36+1 -> 4 | J36: =I36+1 -> 5
B37: Cash | E37: 2.2
B38: Accounts receivable | E38: 0.12836384
B39: Inventory | E39: 2.5993677
B40: Prepaid expenses | E40: 0.468528
B41: Capitalized financing fees | E41: 0
B42: Goodwill | E42: 0
B43: Net PP&E | E43: 2.5
B44: Total assets | E44: =SUM(E37:E43) -> 7.8962595
B46: Accounts payable | E46: 1.2996838
B47: Accrued expenses | E47: 0.4743846
B48: Existing debt | E48: 0
B49: New debt | E49: 0
B50: Shareholder equity | E50: 6.1221911
B51: Total liabilities & equity | E51: =SUM(E46:E50) -> 7.8962595

Sheet End ->

Sheet Model - End
B2: Assumptions | J2: $ millions
B3: Entry assumptions | G3: Other assumptions
C4: Pre-Money | D4: Post-Money | E4: Assumptions | G4: Management option pool | J4: 0.05
B5: LTM revenue | C5: =E51 -> 27.8548 | G5: Founders - % shares sold | J5: 0.25
B6: Entry multiple | C6: 3 | G6: Investor 1 - % shares sold | J6: 0
B7: Enterprise value | C7: =C5*C6 -> 83.5644 | D7: =C7 -> 83.5644 | G7: Investor 2 - % shares sold | J7: 1
B8: (-) Existing debt | C8: =C135 -> 0 | D8: =D135 -> 0
B9: (-) New debt | C9: =+C136 -> 0 | D9: 0
B10: (+) Cash | C10: =C124 -> 2.2 | D10: 35
B11: Equity value | C11: =C7-C8+C10-C9 -> 85.7644 | D11: =D7-D8+D10-D9 -> 118.5644
B12: (+) Transaction fees | D12: =+E12*D7 -> 0 | E12: 0
B13: (+) Financing fees | D13: =+E13*D9 -> 0 | E13: 0
B14: Equity value (incl. fees) | D14: =+D11+D12+D13 -> 118.5644
B17: Sources & uses | J17: $ millions
B18: Sources | G18: Uses
B19: New debt | D19: =+D9 -> 0 | G19: Proceeds to selling shareholders | J19: =+SUM(D35:D37)-SUM(H35:H37) -> 18.760963
B20: Rollover equity | D20: =+J20 -> 67.003438 | G20: Rollover equity | J20: =SUM(H35:H37) -> 67.003438
B21: Sponsor equity | D21: =+J25-D20-D19 -> 51.560963 | G21: Cash added to B/S | J21: =+D10-C10 -> 32.8
G22: Transaction fees | J22: =+D12 -> 0
G23: Financing fees | J23: =+D13 -> 0
B25: Total sources | D25: =SUM(D19:D24) -> 118.5644 | G25: Total uses | J25: =SUM(J19:J24) -> 118.5644
B26: Check 1? | D26: =+D25-J25 -> 0
B27: Check 2? | D27: =+D21-H34 -> 0
B29: Capitalization table
D30: Pre-Money | H30: Post-Money
D31: $ Amount | E31: Shares | F31: FD own % | H31: $ Amount | I31: Shares | J31: FD own %
B32: Primary (incl. fees) | D32: =+E32*D$41/1000000 -> 0 | E32: 0 | F32: =+E32/E$39 -> 0 | H32: =+J21+J22+J23 -> 32.8 | I32: =+H32*1000000/H$41 -> 152977.23 | J32: =+I32/I$39 -> 0.26281076
B33: Secondary | D33: =+E33*D$41/1000000 -> 0 | E33: 0 | F33: =+E33/E$39 -> 0 | H33: =D35-H35+D36-H36+D37-H37 -> 18.760962 | I33: =+H33*1000000/H$41 -> 87500 | J33: =+I33/I$39 -> 0.15032265
B34: Total new sponsor | D34: =SUM(D32:D33) -> 0 | E34: =SUM(E32:E33) -> 0 | F34: =+E34/E$39 -> 0 | H34: =+SUM(H32:H33) -> 51.560962 | I34: =+H34*1000000/H$41 -> 240477.23 | J34: =+I34/I$39 -> 0.41313341
B35: Founders | D35: =+E35*D$41/1000000 -> 32.16165 | E35: 150000 | F35: =+E35/E$39 -> 0.375 | H35: =+I35*H$41/1000000 -> 24.121238 | I35: =+E35*(1-J5) -> 112500 | J35: =+I35/I$39 -> 0.19327197
B36: Investor 1 | D36: =+E36*D$41/1000000 -> 42.8822 | E36: 200000 | F36: =+E36/E$39 -> 0.5 | H36: =+I36*H$41/1000000 -> 42.8822 | I36: =+E36*(1-J6) -> 200000 | J36: =+I36/I$39 -> 0.34359462
B37: Investor 2 | D37: =+E37*D$41/1000000 -> 10.72055 | E37: 50000 | F37: =+E37/E$39 -> 0.125 | H37: =+I37*H$41/1000000 -> 0 | I37: =+E37*(1-J7) -> 0 | J37: =+I37/I$39 -> 0
B38: New management option pool | D38: =+E38*D$41/1000000 -> 0 | E38: 0 | F38: =+E38/E$39 -> 0 | H38: 0 | I38: =SUM(I34:I37)/(1-J4)*J4 -> 29104.065 | J38: =+I38/I$39 -> 0.05
B39: Total company | D39: =SUM(D34:D38) -> 85.7644 | E39: =SUM(E34:E38) -> 400000 | F39: =+E39/E$39 -> 1 | H39: =SUM(H34:H38) -> 118.5644 | I39: =SUM(I34:I38) -> 582081.29 | J39: =+I39/I$39 -> 1
B41: Share price | D41: =+C11*1000000/E39 -> 214.411 | H41: =+D41 -> 214.411
B44: Model | J44: $ millions
B45: Income statement | C45: =+D45-1 -> -2 | D45: =+E45-1 -> -1 | E45: 0 | F45: 1 | G45: =F45+1 -> 2 | H45: =G45+1 -> 3 | I45: =H45+1 -> 4 | J45: =I45+1 -> 5
B46: Gross revenue | C46: =+'Revenue Build - End'!C10 -> 27.24 | D46: =+'Revenue Build - End'!D10 -> 13.08 | E46: =+'Revenue Build - End'!E10 -> 33.2 | F46: =+'Revenue Build - End'!F10 -> 58.1 | G46: =+'Revenue Build - End'!G10 -> 96.59125 | H46: =+'Revenue Build - End'!H10 -> 152.13122 | I46: =+'Revenue Build - End'!I10 -> 226.29519 | J46: =+'Revenue Build - End'!J10 -> 316.81326
B47: % Growth | D47: =D46/C46-1 -> -0.51982379 | E47: =E46/D46-1 -> 1.5382263 | F47: =F46/E46-1 -> 0.75 | G47: =G46/F46-1 -> 0.6625 | H47: =H46/G46-1 -> 0.575 | I47: =I46/H46-1 -> 0.4875 | J47: =J46/I46-1 -> 0.4
B49: Discounts | C49: =C55*C$46 -> 1.6344 | D49: =D55*D$46 -> 1.635 | E49: =E55*E$46 -> 2.7224 | F49: =F55*F$46 -> 4.648 | G49: =G55*G$46 -> 7.7273 | H49: =H55*H$46 -> 12.170497 | I49: =I55*I$46 -> 18.103615 | J49: =J55*J$46 -> 25.345061
B50: Returns | C50: =C56*C$46 -> 2.1792 | D50: =D56*D$46 -> 1.59576 | E50: =E56*E$46 -> 2.6228 | F50: =F56*F$46 -> 4.648 | G50: =G56*G$46 -> 7.7273 | H50: =H56*H$46 -> 12.170497 | I50: =I56*I$46 -> 18.103615 | J50: =J56*J$46 -> 25.345061
B51: Net revenue | C51: =C46-C49-C50 -> 23.4264 | D51: =D46-D49-D50 -> 9.84924 | E51: =E46-E49-E50 -> 27.8548 | F51: =F46-F49-F50 -> 48.804 | G51: =G46-G49-G50 -> 81.13665 | H51: =H46-H49-H50 -> 127.79022 | I51: =I46-I49-I50 -> 190.08796 | J51: =J46-J49-J50 -> 266.12314
B52: % Growth | D52: =D51/C51-1 -> -0.57956664 | E52: =E51/D51-1 -> 1.8281167 | F52: =F51/E51-1 -> 0.75208582 | G52: =G51/F51-1 -> 0.6625 | H52: =H51/G51-1 -> 0.575 | I52: =I51/H51-1 -> 0.4875 | J52: =J51/I51-1 -> 0.4
B54: % of gross revenue
B55: Discounts | C55: 0.06 | D55: 0.125 | E55: 0.082 | F55: 0.08 | G55: 0.08 | H55: 0.08 | I55: 0.08 | J55: 0.08
B56: Returns | C56: 0.08 | D56: 0.122 | E56: 0.079 | F56: 0.08 | G56: 0.08 | H56: 0.08 | I56: 0.08 | J56: 0.08
B57: Net revenue | C57: =C51/C$46 -> 0.86 | D57: =D51/D$46 -> 0.753 | E57: =E51/E$46 -> 0.839 | F57: =F51/F$46 -> 0.84 | G57: =G51/G$46 -> 0.84 | H57: =H51/H$46 -> 0.84 | I57: =I51/I$46 -> 0.84 | J57: =J51/J$46 -> 0.84
B59: Product cost | C59: =C64*C$51 -> 8.9254584 | D59: =D64*D$51 -> 3.9593945 | E59: =E64*E$51 -> 13.426014 | F59: =F64*F$51 -> 22.44984 | G59: =G64*G$51 -> 35.700126 | H59: =H64*H$51 -> 53.671894 | I59: =I64*I$51 -> 76.035183 | J59: =J64*J$51 -> 101.12679
B60: Freight, duties, & taxes | C60: =C65*C$51 -> 0.5622336 | D60: =D65*D$51 -> 0.3447234 | E60: =E65*E$51 -> 1.0584824 | F60: =F65*F$51 -> 1.70814 | G60: =G65*G$51 -> 2.8397828 | H60: =H65*H$51 -> 4.4726578 | I60: =I65*I$51 -> 6.6530785 | J60: =J65*J$51 -> 9.3143099
B61: COGS | C61: =C59+C60 -> 9.487692 | D61: =D59+D60 -> 4.3041179 | E61: =E59+E60 -> 14.484496 | F61: =F59+F60 -> 24.15798 | G61: =G59+G60 -> 38.539909 | H61: =H59+H60 -> 58.144552 | I61: =I59+I60 -> 82.688262 | J61: =J59+J60 -> 110.4411
B63: % of net revenue
B64: Product cost | C64: 0.381 | D64: 0.402 | E64: 0.482 | F64: 0.46 | G64: =+F64-2% -> 0.44 | H64: =+G64-2% -> 0.42 | I64: =+H64-2% -> 0.4 | J64: =+I64-2% -> 0.38
B65: Freight, duties, & taxes | C65: 0.024 | D65: 0.035 | E65: 0.038 | F65: 0.035 | G65: 0.035 | H65: 0.035 | I65: 0.035 | J65: 0.035
B66: COGS | C66: =C61/C51 -> 0.405 | D66: =D61/D51 -> 0.437 | E66: =E61/E51 -> 0.52 | F66: =F61/F51 -> 0.495 | G66: =G61/G51 -> 0.475 | H66: =H61/H51 -> 0.455 | I66: =I61/I51 -> 0.435 | J66: =J61/J51 -> 0.415
B68: Gross profit | C68: =C51-C61 -> 13.938708 | D68: =D51-D61 -> 5.5451221 | E68: =E51-E61 -> 13.370304 | F68: =F51-F61 -> 24.64602 | G68: =G51-G61 -> 42.596741 | H68: =H51-H61 -> 69.645672 | I68: =I51-I61 -> 107.3997 | J68: =J51-J61 -> 155.68204
B69: % of net revenue | C69: =+C68/C$51 -> 0.595 | D69: =+D68/D$51 -> 0.563 | E69: =+E68/E$51 -> 0.48 | F69: =+F68/F$51 -> 0.505 | G69: =+G68/G$51 -> 0.525 | H69: =+H68/H$51 -> 0.545 | I69: =+I68/I$51 -> 0.565 | J69: =+J68/J$51 -> 0.585
B71: Picking & packing | C71: =C78*C$51 -> 0.4919544 | D71: =D78*D$51 -> 0.20683404 | E71: =E78*E$51 -> 0.5849508 | F71: =F78*F$51 -> 0.97608 | G71: =G78*G$51 -> 1.622733 | H71: =H78*H$51 -> 2.5558045 | I71: =I78*I$51 -> 3.8017592 | J71: =J78*J$51 -> 5.3224628
B72: Packaging material | C72: =C79*C$51 -> 0.117132 | D72: =D79*D$51 -> 0.03939696 | E72: =E79*E$51 -> 0.139274 | F72: =F79*F$51 -> 0.24402 | G72: =G79*G$51 -> 0.40568325 | H72: =H79*H$51 -> 0.63895112 | I72: =I79*I$51 -> 0.95043979 | J72: =J79*J$51 -> 1.3306157
B73: Shipping to customers | C73: =C80*C$51 -> 1.6164216 | D73: =D80*D$51 -> 0.738693 | E73: =E80*E$51 -> 2.0055456 | F73: =F80*F$51 -> 3.41628 | G73: =G80*G$51 -> 5.6795655 | H73: =H80*H$51 -> 8.3063645 | I73: =I80*I$51 -> 11.405277 | J73: =J80*J$51 -> 14.636773
B74: Merchant fees | C74: =C81*C$51 -> 0.7496448 | D74: =D81*D$51 -> 0.31517568 | E74: =E81*E$51 -> 0.8913536 | F74: =F81*F$51 -> 1.46412 | G74: =G81*G$51 -> 2.4340995 | H74: =H81*H$51 -> 3.8337067 | I74: =I81*I$51 -> 5.7026387 | J74: =J81*J$51 -> 7.9836942
B75: Fulfillment costs | C75: =SUM(C71:C74) -> 2.9751528 | D75: =SUM(D71:D74) -> 1.3000997 | E75: =SUM(E71:E74) -> 3.621124 | F75: =SUM(F71:F74) -> 6.1005 | G75: =SUM(G71:G74) -> 10.142081 | H75: =SUM(H71:H74) -> 15.334827 | I75: =SUM(I71:I74) -> 21.860115 | J75: =SUM(J71:J74) -> 29.273546
B77: % of net revenue
B78: Picking & packing | C78: 0.021 | D78: 0.021 | E78: 0.021 | F78: 0.02 | G78: 0.02 | H78: 0.02 | I78: 0.02 | J78: 0.02
B79: Packaging material | C79: 0.005 | D79: 0.004 | E79: 0.005 | F79: 0.005 | G79: 0.005 | H79: 0.005 | I79: 0.005 | J79: 0.005
B80: Shipping to customers | C80: 0.069 | D80: 0.075 | E80: 0.072 | F80: 0.07 | G80: 0.07 | H80: 0.065 | I80: 0.06 | J80: 0.055
B81: Merchant fees | C81: 0.032 | D81: 0.032 | E81: 0.032 | F81: 0.03 | G81: 0.03 | H81: 0.03 | I81: 0.03 | J81: 0.03
B82: Fulfillment costs | C82: =C75/C51 -> 0.127 | D82: =D75/D51 -> 0.132 | E82: =E75/E51 -> 0.13 | F82: =F75/F51 -> 0.125 | G82: =G75/G51 -> 0.125 | H82: =H75/H51 -> 0.12 | I82: =I75/I51 -> 0.115 | J82: =J75/J51 -> 0.11
B84: Contribution Profit | C84: =C68-C75 -> 10.963555 | D84: =D68-D75 -> 4.2450224 | E84: =E68-E75 -> 9.74918 | F84: =F68-F75 -> 18.54552 | G84: =G68-G75 -> 32.45466 | H84: =H68-H75 -> 54.310845 | I84: =I68-I75 -> 85.539581 | J84: =J68-J75 -> 126.40849
B85: % of net revenue | C85: =C84/C51 -> 0.468 | D85: =D84/D51 -> 0.431 | E85: =E84/E51 -> 0.35 | F85: =F84/F51 -> 0.38 | G85: =G84/G51 -> 0.4 | H85: =H84/H51 -> 0.425 | I85: =I84/I51 -> 0.45 | J85: =J84/J51 -> 0.475
B87: Ad spend | C87: =+'Revenue Build - End'!C5 -> 4.7087064 | D87: =+'Revenue Build - End'!D5 -> 1.477386 | E87: =+'Revenue Build - End'!E5 -> 6.26733 | F87: =+'Revenue Build - End'!F5 -> 11.62 | G87: =+'Revenue Build - End'!G5 -> 20.335 | H87: =+'Revenue Build - End'!H5 -> 33.806937 | I87: =+'Revenue Build - End'!I5 -> 53.245927 | J87: =+'Revenue Build - End'!J5 -> 79.203316
B88: Other marketing spend | C88: =C93*C$51 -> 0.351396 | D88: =D93*D$51 -> 0.0492462 | E88: =E93*E$51 -> 0.557096 | F88: =F93*F$51 -> 0.97608 | G88: =G93*G$51 -> 1.622733 | H88: =H93*H$51 -> 2.5558045 | I88: =I93*I$51 -> 3.8017592 | J88: =J93*J$51 -> 5.3224628
B89: Marketing expenses | C89: =SUM(C87:C88) -> 5.0601024 | D89: =SUM(D87:D88) -> 1.5266322 | E89: =SUM(E87:E88) -> 6.824426 | F89: =SUM(F87:F88) -> 12.59608 | G89: =SUM(G87:G88) -> 21.957733 | H89: =SUM(H87:H88) -> 36.362742 | I89: =SUM(I87:I88) -> 57.047686 | J89: =SUM(J87:J88) -> 84.525779
B91: % of net revenue
B92: Ad spend | C92: =+C87/C51 -> 0.201 | D92: =+D87/D51 -> 0.15 | E92: =+E87/E51 -> 0.225 | F92: =+F87/F51 -> 0.23809524 | G92: =+G87/G51 -> 0.25062657 | H92: =+H87/H51 -> 0.26455026 | I92: =+I87/I51 -> 0.28011204 | J92: =+J87/J51 -> 0.29761905
B93: Other marketing spend | C93: 0.015 | D93: 0.005 | E93: 0.02 | F93: 0.02 | G93: 0.02 | H93: 0.02 | I93: 0.02 | J93: 0.02
B94: Marketing expenses | C94: =+C89/C51 -> 0.216 | D94: =+D89/D51 -> 0.155 | E94: =+E89/E51 -> 0.245 | F94: =+F89/F51 -> 0.25809524 | G94: =+G89/G51 -> 0.27062657 | H94: =+H89/H51 -> 0.28455026 | I94: =+I89/I51 -> 0.30011204 | J94: =+J89/J51 -> 0.31761905
B96: Headcount | C96: =C102*C$51 -> 2 | D96: =D102*D$51 -> 1.2 | E96: =E102*E$51 -> 3.254902 | F96: =F102*F$51 -> 5.36844 | G96: =G102*G$51 -> 8.113665 | H96: =H102*H$51 -> 11.50112 | I96: =I102*I$51 -> 15.207037 | J96: =J102*J$51 -> 18.62862
B97: Research & development | C97: =+C103*C$51 -> 0.234264 | D97: =+D103*D$51 -> 0.0492462 | E97: =+E103*E$51 -> 0.1671288 | F97: =+F103*F$51 -> 0.24402 | G97: =+G103*G$51 -> 0.40568325 | H97: =+H103*H$51 -> 0.63895112 | I97: =+I103*I$51 -> 0.95043979 | J97: =+J103*J$51 -> 1.3306157
B98: General & administrative | C98: =+C104*C$51 -> 1.17132 | D98: =+D104*D$51 -> 0.7879392 | E98: =+E104*E$51 -> 1.1699016 | F98: =+F104*F$51 -> 2.4402 | G98: =+G104*G$51 -> 4.0568325 | H98: =+H104*H$51 -> 6.3895112 | I98: =+I104*I$51 -> 9.5043979 | J98: =+J104*J$51 -> 13.306157
B99: Operating expenses | C99: =SUM(C96:C98) -> 3.405584 | D99: =SUM(D96:D98) -> 2.0371854 | E99: =SUM(E96:E98) -> 4.5919324 | F99: =SUM(F96:F98) -> 8.05266 | G99: =SUM(G96:G98) -> 12.576181 | H99: =SUM(H96:H98) -> 18.529582 | I99: =SUM(I96:I98) -> 25.661874 | J99: =SUM(J96:J98) -> 33.265393
B101: % of net revenue
B102: Headcount | C102: 0.085373766 | D102: 0.12183681 | E102: 0.11685246 | F102: 0.11 | G102: 0.1 | H102: 0.09 | I102: 0.08 | J102: 0.07
B103: Research & development | C103: 0.01 | D103: 0.005 | E103: 0.006 | F103: 0.005 | G103: 0.005 | H103: 0.005 | I103: 0.005 | J103: 0.005
B104: General & administrative | C104: 0.05 | D104: 0.08 | E104: 0.042 | F104: 0.05 | G104: 0.05 | H104: 0.05 | I104: 0.05 | J104: 0.05
B105: Operating expenses | C105: =+C99/C$51 -> 0.14537377 | D105: =+D99/D$51 -> 0.20683681 | E105: =+E99/E$51 -> 0.16485246 | F105: =+F99/F$51 -> 0.165 | G105: =+G99/G$51 -> 0.155 | H105: =+H99/H$51 -> 0.145 | I105: =+I99/I$51 -> 0.135 | J105: =+J99/J$51 -> 0.125
B107: EBITDA | C107: =+C84-C89-C99 -> 2.4978688 | D107: =+D84-D89-D99 -> 0.68120484 | E107: =+E84-E89-E99 -> -1.6671784 | F107: =+F84-F89-F99 -> -2.10322 | G107: =+G84-G89-G99 -> -2.0792537 | H107: =+H84-H89-H99 -> -0.58147933 | I107: =+I84-I89-I99 -> 2.830021 | J107: =+J84-J89-J99 -> 8.6173208
B108: % of net revenue | C108: =+C107/C$51 -> 0.10662623 | D108: =+D107/D$51 -> 0.069163188 | E108: =+E107/E$51 -> -0.059852462 | F108: =+F107/F$51 -> -0.043095238 | G108: =+G107/G$51 -> -0.025626566 | H108: =+H107/H$51 -> -0.0045502646 | I108: =+I107/I$51 -> 0.014887955 | J108: =+J107/J$51 -> 0.032380952
B110: D&A | F110: =F160*F$51 -> 1.46412 | G110: =G160*G$51 -> 2.4340995 | H110: =H160*H$51 -> 3.8337067 | I110: =I160*I$51 -> 5.7026387 | J110: =J160*J$51 -> 7.9836942
B111: Interest expense | F111: =F170+F176 -> 0 | G111: =G170+G176 -> 0 | H111: =H170+H176 -> 0.94541166 | I111: =I170+I176 -> 3.2062406 | J111: =J170+J176 -> 6.0087241
B112: Fee amortization expense | F112: =F163 -> 0 | G112: =G163 -> 0 | H112: =H163 -> 0 | I112: =I163 -> 0 | J112: =J163 -> 0
B113: Earnings before taxes | F113: =F107-F110-F111-F112 -> -3.56734 | G113: =G107-G110-G111-G112 -> -4.5133532 | H113: =H107-H110-H111-H112 -> -5.3605977 | I113: =I107-I110-I111-I112 -> -6.0788584 | J113: =J107-J110-J111-J112 -> -5.3750975
B114: % of net revenue | F114: =+F113/F$51 -> -0.073095238 | G114: =+G113/G$51 -> -0.055626566 | H114: =+H113/H$51 -> -0.041948418 | I114: =+I113/I$51 -> -0.031979187 | J114: =+J113/J$51 -> -0.020197783
B116: Tax provision | F116: =+IF(F113<0, 0, F113*F117) -> 0 | G116: =+IF(G113<0, 0, G113*G117) -> 0 | H116: =+IF(H113<0, 0, H113*H117) -> 0 | I116: =+IF(I113<0, 0, I113*I117) -> 0 | J116: =+IF(J113<0, 0, J113*J117) -> 0
B117: % tax rate | F117: 0.25 | G117: 0.25 | H117: 0.25 | I117: 0.25 | J117: 0.25
B119: Net income | F119: =F113-F116 -> -3.56734 | G119: =G113-G116 -> -4.5133532 | H119: =H113-H116 -> -5.3605977 | I119: =I113-I116 -> -6.0788584 | J119: =J113-J116 -> -5.3750975
B120: % of net revenue | F120: =+F119/F$51 -> -0.073095238 | G120: =+G119/G$51 -> -0.055626566 | H120: =+H119/H$51 -> -0.041948418 | I120: =+I119/I$51 -> -0.031979187 | J120: =+J119/J$51 -> -0.020197783
B123: Balance sheet | C123: 0 | D123: Adjust. | E123: Pro forma | F123: 1 | G123: =F123+1 -> 2 | H123: =G123+1 -> 3 | I123: =H123+1 -> 4 | J123: =I123+1 -> 5
B124: Cash | C124: 2.2 | D124: =E124-C124 -> 32.8 | E124: =+D10 -> 35 | F124: =F192+E124 -> 20.974059 | G124: =G192+F124 -> 13.57449 | H124: =H192+G124 -> 19.168534 | I124: =I192+H124 -> 28.513194 | J124: =J192+I124 -> 39.918471
B125: Accounts receivable | C125: 0.12836384 | E125: =+D125+C125 -> 0.12836384 | F125: =F146/365*F51 -> 0.26741918 | G125: =G146/365*G51 -> 0.44458438 | H125: =H146/365*H51 -> 0.7002204 | I125: =I146/365*I51 -> 1.0415779 | J125: =J146/365*J51 -> 1.458209
B126: Inventory | C126: 2.5993677 | E126: =+D126+C126 -> 2.5993677 | F126: =+F147*F61/365 -> 6.6186247 | G126: =+G147*G61/365 -> 10.558879 | H126: =+H147*H61/365 -> 15.930014 | I126: =+I147*I61/365 -> 22.654318 | J126: =+J147*J61/365 -> 30.257837
...

Sheet Revenue Build - End
B3: Revenue Build | J3: $ millions
B4: Paid Traffic | C4: =+D4-1 -> -2 | D4: =+E4-1 -> -1 | E4: 0 | F4: 1 | G4: =F4+1 -> 2 | H4: =G4+1 -> 3 | I4: =H4+1 -> 4 | J4: =I4+1 -> 5
B5: Total ad budget | C5: 4.7087064 | D5: 1.477386 | E5: 6.26733 | F5: =+F6*E10 -> 11.62 | G5: =+G6*F10 -> 20.335 | H5: =+H6*G10 -> 33.806937 | I5: =+I6*H10 -> 53.245927 | J5: =+J6*I10 -> 79.203316
B6: % of previous gross revenue | D6: =+D5/C10 -> 0.054235903 | E6: =+E5/D10 -> 0.47915367 | F6: 0.35 | G6: 0.35 | H6: 0.35 | I6: 0.35 | J6: 0.35
B8: Revenue per ad dollar spent | C8: =+C13/C18 -> 5.7850283 | D8: =+D13/D18 -> 8.853475 | E8: =+E13/E18 -> 5.2973116 | F8: 5 | G8: 4.75 | H8: 4.5 | I8: 4.25 | J8: 4
B10: Gross revenue | C10: 27.24 | D10: 13.08 | E10: 33.2 | F10: =+F5*F8 -> 58.1 | G10: =+G5*G8 -> 96.59125 | H10: =+H5*H8 -> 152.13122 | I10: =+I5*I8 -> 226.29519 | J10: =+J5*J8 -> 316.81326
B11: % Growth | D11: =D10/C10-1 -> -0.51982379 | E11: =E10/D10-1 -> 1.5382263 | F11: =F10/E10-1 -> 0.75 | G11: =G10/F10-1 -> 0.6625 | H11: =H10/G10-1 -> 0.575 | I11: =I10/H10-1 -> 0.4875 | J11: =J10/I10-1 -> 0.4
B13: Price per unit | C13: 4150 | D13: 4150 | E13: 4150 | F13: 4150 | G13: 4150 | H13: 4150 | I13: 4150 | J13: 4150
B15: Units sold | C15: =+C10*1000000/C13 -> 6563.8554 | D15: =+D10*1000000/D13 -> 3151.8072 | E15: =+E10*1000000/E13 -> 8000 | F15: =+F10*1000000/F13 -> 14000 | G15: =+G10*1000000/G13 -> 23275 | H15: =+H10*1000000/H13 -> 36658.125 | I15: =+I10*1000000/I13 -> 54528.961 | J15: =+J10*1000000/J13 -> 76340.545
B16: % Growth | D16: =+D15/C15-1 -> -0.51982379 | E16: =+E15/D15-1 -> 1.5382263 | F16: =+F15/E15-1 -> 0.75 | G16: =+G15/F15-1 -> 0.6625 | H16: =+H15/G15-1 -> 0.575 | I16: =+I15/H15-1 -> 0.4875 | J16: =+J15/I15-1 -> 0.4
B18: Ad spend per unit sold | C18: =+C5*1000000/C15 -> 717.369 | D18: =+D5*1000000/D15 -> 468.7425 | E18: =+E5*1000000/E15 -> 783.41625 | F18: =+F5*1000000/F15 -> 830 | G18: =+G5*1000000/G15 -> 873.68421 | H18: =+H5*1000000/H15 -> 922.22222 | I18: =+I5*1000000/I15 -> 976.47059 | J18: =+J5*1000000/J15 -> 1037.5
B19: % Growth | D19: =+D18/C18-1 -> -0.34658105 | E19: =+E18/D18-1 -> 0.67131474 | F19: =+F18/E18-1 -> 0.059462323 | G19: =+G18/F18-1 -> 0.052631579 | H19: =+H18/G18-1 -> 0.055555556 | I19: =+I18/H18-1 -> 0.058823529 | J19: =+J18/I18-1 -> 0.0625
B20: aka CAC
