Workbook

Sheet Resources
B4: GO, GO, GO!
B5: Practice really does make perfect!
B6: You got this! :-)
B10: This template is part of a comprehensive course for growth stage investing interviews & roles.
B11: For more video courses and tutorials:
B13: =HYPERLINK("https://GrowthEquityInterviewGuide.com", "GrowthEquityInterviewGuide.com") -> GrowthEquityInterviewGuide.com
B25: All rights reserved. Growth Equity Interview Guide.

Sheet Start ->

Sheet Model (Start - Video)
B2: Assumptions | J2: $ millions
B3: Entry assumptions | E3: Transaction assumptions
B4: LTM revenue | C4: =+E42 -> 50.83 | E4: Transaction fees | G4: 0.01
B5: Entry multiple | C5: 18 | E5: Financing fees | G5: 0.02
B6: Enterprise value | C6: =+C5*C4 -> 914.94
B7: (-) Debt | C7: =+C33 -> 0
B8: (+) Cash | C8: =+C25 -> 5
B9: Equity value | C9: =+C6-C7+C8 -> 919.94
B12: Sources & uses | J12: $ millions
B13: Sources | G13: Uses
B14: New debt | D14: 0 | G14: Purchase TEV | J14: =+C6 -> 914.94
B15: Sponsor equity | D15: =+J19-D14 -> 934.0894 | G15: Ending cash balance | J15: 10
G16: Transaction fees | J16: =+G4*C6 -> 9.1494
G17: Financing fees | J17: =+G5*D14 -> 0
B19: Total sources | D19: =SUM(D14:D18) -> 934.0894 | G19: Total uses | J19: =SUM(J14:J18) -> 934.0894
B23: Model | J23: $ millions
B24: Balance sheet | C24: 0 | D24: Adjust. | E24: Pro forma | F24: 1 | G24: =F24+1 -> 2 | H24: =G24+1 -> 3 | I24: =H24+1 -> 4 | J24: =I24+1 -> 5
B25: Cash | C25: 5 | D25: =+E25-C25 -> 5 | E25: =+J15 -> 10 | F25: =+F122+E25 -> 5 | G25: =+G122+F25 -> 5 | H25: =+H122+G25 -> 5 | I25: =+I122+H25 -> 5 | J25: =+J122+I25 -> 5
B26: Net working capital | C26: 100 | E26: =+D26+C26 -> 100 | F26: =+F80 -> 105 | G26: =+G80 -> 110 | H26: =+H80 -> 115 | I26: =+I80 -> 120 | J26: =+J80 -> 125
B27: Capitalized financing fees | C27: 0 | D27: =+J17 -> 0 | E27: =+D27+C27 -> 0 | F27: =+F91 -> 0 | G27: =+G91 -> 0 | H27: =+H91 -> 0 | I27: =+I91 -> 0 | J27: =+J91 -> 0
B28: Goodwill | C28: 0 | D28: =+C9-C36 -> 774.94 | E28: =+D28+C28 -> 774.94 | F28: =+E28 -> 774.94 | G28: =+F28 -> 774.94 | H28: =+G28 -> 774.94 | I28: =+H28 -> 774.94 | J28: =+I28 -> 774.94
B29: Deferred tax asset | C29: 20 | E29: =+D29+C29 -> 20 | F29: =+E29 -> 20 | G29: =+F29 -> 20 | H29: =+G29 -> 20 | I29: =+H29 -> 20 | J29: =+I29 -> 20
B30: Net PP&E | C30: 20 | E30: =+D30+C30 -> 20 | F30: =+F85 -> 21.42324 | G30: =+G85 -> 23.415776 | H30: =+H85 -> 26.205326 | I30: =+I85 -> 30.110697 | J30: =+J85 -> 35.578216
B31: Total assets | C31: =SUM(C25:C30) -> 145 | E31: =SUM(E25:E30) -> 924.94 | F31: =SUM(F25:F30) -> 926.36324 | G31: =SUM(G25:G30) -> 933.35578 | H31: =SUM(H25:H30) -> 941.14533 | I31: =SUM(I25:I30) -> 950.0507 | J31: =SUM(J25:J30) -> 960.51822
B33: Existing debt | C33: 0 | E33: =+D33+C33 -> 0 | F33: =+F96 -> 0 | G33: =+G96 -> 0 | H33: =+H96 -> 0 | I33: =+I96 -> 0 | J33: =+J96 -> 0
B34: New debt | C34: 0 | E34: =+D34+C34 -> 0 | F34: =+F102 -> 13.342875 | G34: =+G102 -> 31.078685 | H34: =+H102 -> 51.952927 | I34: =+I102 -> 65.558765 | J34: =+J102 -> 65.035369
B35: Shareholder equity | C35: 145 | D35: =+-C35+D15-J16 -> 779.94 | E35: =+D35+C35 -> 924.94 | F35: =+E35+F73 -> 913.02037 | G35: =+F35+G73 -> 902.27709 | H35: =+G35+H73 -> 889.1924 | I35: =+H35+I73 -> 884.49193 | J35: =+I35+J73 -> 895.48285
B36: Total liabilities & equity | C36: =SUM(C33:C35) -> 145 | E36: =SUM(E33:E35) -> 924.94 | F36: =SUM(F33:F35) -> 926.36324 | G36: =SUM(G33:G35) -> 933.35578 | H36: =SUM(H33:H35) -> 941.14533 | I36: =SUM(I33:I35) -> 950.0507 | J36: =SUM(J33:J35) -> 960.51822
B37: Check | C37: =C31-C36 -> 0 | E37: =E31-E36 -> 0 | F37: =F31-F36 -> 0 | G37: =G31-G36 -> 0 | H37: =H31-H36 -> 0 | I37: =I31-I36 -> 0 | J37: =J31-J36 -> 0
B41: Income statement | C41: =+D41-1 -> -2 | D41: =+E41-1 -> -1 | E41: 0 | F41: 1 | G41: =F41+1 -> 2 | H41: =G41+1 -> 3 | I41: =H41+1 -> 4 | J41: =I41+1 -> 5
B42: Revenue | C42: 19.21 | D42: 32.98 | E42: 50.83 | F42: =+E42*(1+F43) -> 71.162 | G42: =+F42*(1+G43) -> 99.6268 | H42: =+G42*(1+H43) -> 139.47752 | I42: =+H42*(1+I43) -> 195.26853 | J42: =+I42*(1+J43) -> 273.37594
B43: % growth | D43: =D42/C42-1 -> 0.71681416 | E43: =E42/D42-1 -> 0.54123711 | F43: 0.4 | G43: 0.4 | H43: 0.4 | I43: 0.4 | J43: 0.4
B44: ^ Assumptions to be replaced by your bottom's up revenue & sales forecast ("Cohorts" tab)
B46: Gross profit | C46: 13 | D46: 23 | E46: 35.8 | F46: =+F47*F$42 -> 49.8134 | G46: =+G47*G$42 -> 69.73876 | H46: =+H47*H$42 -> 97.634264 | I46: =+I47*I$42 -> 136.68797 | J46: =+J47*J$42 -> 191.36316
B47: % of revenue | C47: =+C46/C$42 -> 0.67673087 | D47: =+D46/D$42 -> 0.69739236 | E47: =+E46/E$42 -> 0.70430848 | F47: 0.7 | G47: 0.7 | H47: 0.7 | I47: 0.7 | J47: 0.7
B49: Selling and marketing expenses | C49: 9.56 | D49: 15.55 | E49: 20.75 | F49: =+F50*F$42 -> 28.4648 | G49: =+G50*G$42 -> 37.858184 | H49: =+H50*H$42 -> 50.211907 | I49: =+I50*I$42 -> 66.3913 | J49: =+J50*J$42 -> 87.480301
B50: % of revenue | C50: =+C49/C42 -> 0.49765747 | D50: =+D49/D42 -> 0.47149788 | E50: =+E49/E42 -> 0.40822349 | F50: 0.4 | G50: 0.38 | H50: 0.36 | I50: 0.34 | J50: 0.32
B51: ^ Assumptions to be replaced by your bottom's up revenue & sales forecast ("Cohorts" tab)
B53: Overhead expenses | C53: 10 | D53: 15.2 | E53: 22.2 | F53: =+F54*F$42 -> 28.4648 | G53: =+G54*G$42 -> 34.86938 | H53: =+H54*H$42 -> 48.817132 | I53: =+I54*I$42 -> 58.580558 | J53: =+J54*J$42 -> 68.343985
B54: % of revenue | C54: =+C53/C$42 -> 0.52056221 | D54: =+D53/D$42 -> 0.46088539 | E54: =+E53/E$42 -> 0.43674995 | F54: 0.4 | G54: 0.35 | H54: 0.35 | I54: 0.3 | J54: 0.25
B56: EBITDA | C56: =+C46-C49-C53 -> -6.56 | D56: =+D46-D49-D53 -> -7.75 | E56: =+E46-E49-E53 -> -7.15 | F56: =+F46-F49-F53 -> -7.1162 | G56: =+G46-G49-G53 -> -2.988804 | H56: =+H46-H49-H53 -> -1.3947752 | I56: =+I46-I49-I53 -> 11.716112 | J56: =+J46-J49-J53 -> 35.538872
B57: % of revenue | C57: =+C56/C42 -> -0.34148881 | D57: =+D56/D42 -> -0.2349909 | E57: =+E56/E42 -> -0.14066496 | F57: =+F56/F42 -> -0.1 | G57: =+G56/G42 -> -0.03 | H57: =+H56/H42 -> -0.01 | I57: =+I56/I42 -> 0.06 | J57: =+J56/J42 -> 0.13
B59: D&A | F59: =+F60*F$42 -> 4.26972 | G59: =+G60*G$42 -> 5.977608 | H59: =+H60*H$42 -> 8.3686512 | I59: =+I60*I$42 -> 11.716112 | J59: =+J60*J$42 -> 16.402556
B60: % of revenue | F60: 0.06 | G60: 0.06 | H60: 0.06 | I60: 0.06 | J60: 0.06
B62: Interest expense | F62: =+F104+F98 -> 0.533715 | G62: =+G104+G98 -> 1.7768624 | H62: =+H104+H98 -> 3.3212645 | I62: =+I104+I98 -> 4.7004677 | J62: =+J104+J98 -> 5.2237654
B64: Fee amortization expense | F64: =+F90 -> 0 | G64: =+G90 -> 0 | H64: =+H90 -> 0 | I64: =+I90 -> 0 | J64: =+J90 -> 0
B65: % of revenue | F65: =+F64/F42 -> 0 | G65: =+G64/G42 -> 0 | H65: =+H64/H42 -> 0 | I65: =+I64/I42 -> 0 | J65: =+J64/J42 -> 0
B67: Earnings before taxes | F67: =+F56-F59-F62-F64 -> -11.919635 | G67: =+G56-G59-G62-G64 -> -10.743274 | H67: =+H56-H59-H62-H64 -> -13.084691 | I67: =+I56-I59-I62-I64 -> -4.7004677 | J67: =+J56-J59-J62-J64 -> 13.91255
B68: % of revenue | F68: =+F67/F42 -> -0.1675 | G68: =+G67/G42 -> -0.10783519 | H68: =+H67/H42 -> -0.093812185 | I68: =+I67/I42 -> -0.024071814 | J68: =+J67/J42 -> 0.050891642
B70: Taxes | F70: =IF(F67<0, 0, F67*F71) -> 0 | G70: =IF(G67<0, 0, G67*G71) -> 0 | H70: =IF(H67<0, 0, H67*H71) -> 0 | I70: =IF(I67<0, 0, I67*I71) -> 0 | J70: =IF(J67<0, 0, J67*J71) -> 2.9216356
B71: % tax rate | F71: 0.21 | G71: 0.21 | H71: 0.21 | I71: 0.21 | J71: 0.21
B73: Net income | F73: =+F67-F70 -> -11.919635 | G73: =+G67-G70 -> -10.743274 | H73: =+H67-H70 -> -13.084691 | I73: =+I67-I70 -> -4.7004677 | J73: =+J67-J70 -> 10.990915
B74: % of revenue | F74: =+F73/F42 -> -0.1675 | G74: =+G73/G42 -> -0.10783519 | H74: =+H73/H42 -> -0.093812185 | I74: =+I73/I42 -> -0.024071814 | J74: =+J73/J42 -> 0.040204397
B77: Supporting schedules | E77: 0 | F77: 1 | G77: =F77+1 -> 2 | H77: =G77+1 -> 3 | I77: =H77+1 -> 4 | J77: =I77+1 -> 5
B78: Net working capital, beginning | F78: =+E80 -> 100 | G78: =+F80 -> 105 | H78: =+G80 -> 110 | I78: =+H80 -> 115 | J78: =+I80 -> 120
B79: (+) Increase / (decrease) | F79: 5 | G79: 5 | H79: 5 | I79: 5 | J79: 5
B80: Net working capital, ending | E80: =+E26 -> 100 | F80: =+F79+F78 -> 105 | G80: =+G79+G78 -> 110 | H80: =+H79+H78 -> 115 | I80: =+I79+I78 -> 120 | J80: =+J79+J78 -> 125
B82: PP&E, beginning | F82: =+E85 -> 20 | G82: =+F85 -> 21.42324 | H82: =+G85 -> 23.415776 | I82: =+H85 -> 26.205326 | J82: =+I85 -> 30.110697
B83: (+) Capex | F83: =+F86*F42 -> 5.69296 | G83: =+G86*G42 -> 7.970144 | H83: =+H86*H42 -> 11.158202 | I83: =+I86*I42 -> 15.621482 | J83: =+J86*J42 -> 21.870075
B84: (-) D&A | F84: =+F59 -> 4.26972 | G84: =+G59 -> 5.977608 | H84: =+H59 -> 8.3686512 | I84: =+I59 -> 11.716112 | J84: =+J59 -> 16.402556
B85: PP&E, ending | E85: =+E30 -> 20 | F85: =+F82+F83-F84 -> 21.42324 | G85: =+G82+G83-G84 -> 23.415776 | H85: =+H82+H83-H84 -> 26.205326 | I85: =+I82+I83-I84 -> 30.110697 | J85: =+J82+J83-J84 -> 35.578216
B86: Capex - % of revenue | F86: 0.08 | G86: 0.08 | H86: 0.08 | I86: 0.08 | J86: 0.08
B87: D&A - % of revenue | F87: =F60 -> 0.06 | G87: =G60 -> 0.06 | H87: =H60 -> 0.06 | I87: =I60 -> 0.06 | J87: =J60 -> 0.06
B89: Capitalized financing fees, beginning | D89: Amort. years? | E89: Expense? | F89: =+E91 -> 0 | G89: =+F91 -> 0 | H89: =+G91 -> 0 | I89: =+H91 -> 0 | J89: =+I91 -> 0
B90: (-) Fee amortization expense | D90: 5 | E90: =+E91/D90 -> 0 | F90: =+$E90 -> 0 | G90: =+$E90 -> 0 | H90: =+$E90 -> 0 | I90: =+$E90 -> 0 | J90: =+$E90 -> 0
B91: Capitalized financing fees, ending | E91: =+J17 -> 0 | F91: =+F89-F90 -> 0 | G91: =+G89-G90 -> 0 | H91: =+H89-H90 -> 0 | I91: =+I89-I90 -> 0 | J91: =+J89-J90 -> 0
B94: Existing debt, beginning | F94: =+E96 -> 0 | G94: =+F96 -> 0 | H94: =+G96 -> 0 | I94: =+H96 -> 0 | J94: =+I96 -> 0
B95: (-) Net issuance / (paydown) | F95: 0 | G95: 0 | H95: 0 | I95: 0 | J95: 0
B96: Existing debt, ending | E96: =+E33 -> 0 | F96: =+F94+F95 -> 0 | G96: =+G94+G95 -> 0 | H96: =+H94+H95 -> 0 | I96: =+I94+I95 -> 0 | J96: =+J94+J95 -> 0
B97: % Interest rate | F97: 0.05 | G97: 0.05 | H97: 0.05 | I97: 0.05 | J97: 0.05
B98: Interest expense | F98: =+AVERAGE(E96:F96)*F97 -> 0 | G98: =+AVERAGE(F96:G96)*G97 -> 0 | H98: =+AVERAGE(G96:H96)*H97 -> 0 | I98: =+AVERAGE(H96:I96)*I97 -> 0 | J98: =+AVERAGE(I96:J96)*J97 -> 0
B100: New debt, beginning | F100: =+E102 -> 0 | G100: =+F102 -> 13.342875 | H100: =+G102 -> 31.078685 | I100: =+H102 -> 51.952927 | J100: =+I102 -> 65.558765
B101: (-) Net issuance / (paydown) | F101: =-MIN(F100, F117+F108) -> 13.342875 | G101: =-MIN(G100, G117+G108) -> 17.73581 | H101: =-MIN(H100, H117+H108) -> 20.874241 | I101: =-MIN(I100, I117+I108) -> 13.605838 | J101: =-MIN(J100, J117+J108) -> -0.52339602
B102: New debt, ending | E102: =+E34 -> 0 | F102: =SUM(F100:F101) -> 13.342875 | G102: =SUM(G100:G101) -> 31.078685 | H102: =SUM(H100:H101) -> 51.952927 | I102: =SUM(I100:I101) -> 65.558765 | J102: =SUM(J100:J101) -> 65.035369
B103: % Interest rate | F103: 0.08 | G103: 0.08 | H103: 0.08 | I103: 0.08 | J103: 0.08
B104: Interest expense | F104: =+AVERAGE(E102:F102)*F103 -> 0.533715 | G104: =+AVERAGE(F102:G102)*G103 -> 1.7768624 | H104: =+AVERAGE(G102:H102)*H103 -> 3.3212645 | I104: =+AVERAGE(H102:I102)*I103 -> 4.7004677 | J104: =+AVERAGE(I102:J102)*J103 -> 5.2237654
B106: Cash balance before paydown | F106: =+E25 -> 10 | G106: =+F25 -> 5 | H106: =+G25 -> 5 | I106: =+H25 -> 5 | J106: =+I25 -> 5
B107: (-) Minimum cash balance | F107: 5 | G107: 5 | H107: 5 | I107: 5 | J107: 5
B108: Excess cash available for debt paydown | F108: =+F106-F107 -> 5 | G108: =+G106-G107 -> 0 | H108: =+H106-H107 -> 0 | I108: =+I106-I107 -> 0 | J108: =+J106-J107 -> 0
B111: Cash flow statement | F111: 1 | G111: =F111+1 -> 2 | H111: =G111+1 -> 3 | I111: =H111+1 -> 4 | J111: =I111+1 -> 5
B112: Net income | F112: =+F73 -> -11.919635 | G112: =+G73 -> -10.743274 | H112: =+H73 -> -13.084691 | I112: =+I73 -> -4.7004677 | J112: =+J73 -> 10.990915
B113: (+) D&A | F113: =+F84 -> 4.26972 | G113: =+G84 -> 5.977608 | H113: =+H84 -> 8.3686512 | I113: =+I84 -> 11.716112 | J113: =+J84 -> 16.402556
B114: (+) Fee amortization expense | F114: =+F90 -> 0 | G114: =+G90 -> 0 | H114: =+H90 -> 0 | I114: =+I90 -> 0 | J114: =+J90 -> 0
B115: (-) Capex | F115: =+F83 -> 5.69296 | G115: =+G83 -> 7.970144 | H115: =+H83 -> 11.158202 | I115: =+I83 -> 15.621482 | J115: =+J83 -> 21.870075
B116: (-) Change in WC | F116: =+F79 -> 5 | G116: =+G79 -> 5 | H116: =+H79 -> 5 | I116: =+I79 -> 5 | J116: =+J79 -> 5
B117: Cash from operations & investing | F117: =+F112+F113+F114-F115-F116 -> -18.342875 | G117: =+G112+G113+G114-G115-G116 -> -17.73581 | H117: =+H112+H113+H114-H115-H116 -> -20.874241 | I117: =+I112+I113+I114-I115-I116 -> -13.605838 | J117: =+J112+J113+J114-J115-J116 -> 0.52339602
B119: (+) Debt issuance / (paydown) | F119: =+F101 -> 13.342875 | G119: =+G101 -> 17.73581 | H119: =+H101 -> 20.874241 | I119: =+I101 -> 13.605838 | J119: =+J101 -> -0.52339602
B120: Cash from financing | F120: =+F119 -> 13.342875 | G120: =+G119 -> 17.73581 | H120: =+H119 -> 20.874241 | I120: =+I119 -> 13.605838 | J120: =+J119 -> -0.52339602
B122: Net change in cash | F122: =+F120+F117 -> -5 | G122: =+G120+G117 -> 0 | H122: =+H120+H117 -> 0 | I122: =+I120+I117 -> 0 | J122: =+J120+J117 -> 0
B126: Returns analysis | J126: $ millions
B128: Returns scenarios
B129: Multiple of money | D129: =J144/-E144 -> 5.2037113
B130: IRR | D130: =+L144 -> 0.39079346
B131: Net gain | D131: =J144+E144 -> 3926.6421
B134: Exit proceeds | E134: 0 | F134: 1 | G134: =F134+1 -> 2 | H134: =G134+1 -> 3 | I134: =H134+1 -> 4 | J134: =I134+1 -> 5
B135: Exit LTM Revenue | J135: =+J42 -> 273.37594
B136: Exit multiple | J136: 18
B137: Exit enterprise value | J137: =+J136*J135 -> 4920.7669
B138: (+) Cash | J138: =+J25 -> 5
B139: (-) Debt | J139: =+J34+J33 -> 65.035369
...

Sheet Model (Start - Blank)
B2: Assumptions | J2: $ millions
B3: Entry assumptions | E3: Transaction assumptions
B4: LTM revenue | E4: Transaction fees | G4: 0.01
B5: Entry multiple | C5: 18 | E5: Financing fees | G5: 0.02
B6: Enterprise value
B7: (-) Debt
B8: (+) Cash
B9: Equity value
B12: Sources & uses | J12: $ millions
B13: Sources | G13: Uses
B19: Total sources | G19: Total uses
B23: Model | J23: $ millions
B24: Balance sheet | C24: 0 | D24: Adjust. | E24: Pro forma | F24: 1 | G24: =F24+1 -> 2 | H24: =G24+1 -> 3 | I24: =H24+1 -> 4 | J24: =I24+1 -> 5
B25: Cash | C25: 5
B26: Net working capital | C26: 100
B27: Capitalized financing fees | C27: 0
B28: Goodwill | C28: 0
B29: Deferred tax asset | C29: 20
B30: Net PP&E | C30: 20
B31: Total assets | C31: =SUM(C25:C30) -> 145
B33: Existing debt | C33: 0
B34: New debt | C34: 0
B35: Shareholder equity | C35: 145
B36: Total liabilities & equity | C36: =SUM(C33:C35) -> 145
B37: Check | C37: =C31-C36 -> 0
B41: Income statement | C41: =+D41-1 -> -2 | D41: =+E41-1 -> -1 | E41: 0 | F41: 1 | G41: =F41+1 -> 2 | H41: =G41+1 -> 3 | I41: =H41+1 -> 4 | J41: =I41+1 -> 5
B42: Revenue | C42: 19.21 | D42: 32.98 | E42: 50.83
B43: % growth | D43: =D42/C42-1 -> 0.71681416 | E43: =E42/D42-1 -> 0.54123711 | F43: 0.4 | G43: 0.4 | H43: 0.4 | I43: 0.4 | J43: 0.4
B44: ^ Assumptions to be replaced by your bottom's up revenue & sales forecast ("Cohort" tab)
B46: Gross profit | C46: 13 | D46: 23 | E46: 35.8
B47: % of revenue | C47: =+C46/C$42 -> 0.67673087 | D47: =+D46/D$42 -> 0.69739236 | E47: =+E46/E$42 -> 0.70430848 | F47: 0.7 | G47: 0.7 | H47: 0.7 | I47: 0.7 | J47: 0.7
B49: Selling and marketing expenses | C49: 9.56 | D49: 15.55 | E49: 20.75
B50: % of revenue | C50: =+C49/C42 -> 0.49765747 | D50: =+D49/D42 -> 0.47149788 | E50: =+E49/E42 -> 0.40822349 | F50: 0.4 | G50: 0.38 | H50: 0.36 | I50: 0.34 | J50: 0.32
B51: ^ Assumptions to be replaced by your bottom's up revenue & sales forecast ("Cohort" tab)
B53: Overhead expenses | C53: 10 | D53: 15.2 | E53: 22.2
B54: % of revenue | C54: =+C53/C$42 -> 0.52056221 | D54: =+D53/D$42 -> 0.46088539 | E54: =+E53/E$42 -> 0.43674995 | F54: 0.4 | G54: 0.35 | H54: 0.35 | I54: 0.3 | J54: 0.25
B56: EBITDA | C56: =+C46-C49-C53 -> -6.56 | D56: =+D46-D49-D53 -> -7.75 | E56: =+E46-E49-E53 -> -7.15
B57: % of revenue | C57: =+C56/C42 -> -0.34148881 | D57: =+D56/D42 -> -0.2349909 | E57: =+E56/E42 -> -0.14066496
B59: D&A
B60: % of revenue | F60: 0.06 | G60: 0.06 | H60: 0.06 | I60: 0.06 | J60: 0.06
B62: Interest expense
B64: Fee amortization expense
B65: % of revenue
B67: Earnings before taxes
B68: % of revenue
B70: Taxes
B71: % tax rate | F71: 0.21 | G71: 0.21 | H71: 0.21 | I71: 0.21 | J71: 0.21
B73: Net income
B74: % of revenue
B77: Supporting schedules | E77: 0 | F77: 1 | G77: =F77+1 -> 2 | H77: =G77+1 -> 3 | I77: =H77+1 -> 4 | J77: =I77+1 -> 5
B78: Net working capital, beginning
B79: (+) Increase / (decrease) | F79: 5 | G79: 5 | H79: 5 | I79: 5 | J79: 5
B80: Net working capital, ending
B82: PP&E, beginning
B83: (+) Capex
B84: (-) D&A
B85: PP&E, ending
B86: Capex - % of revenue | F86: 0.08 | G86: 0.08 | H86: 0.08 | I86: 0.08 | J86: 0.08
B87: D&A - % of revenue | F87: =F60 -> 0.06 | G87: =G60 -> 0.06 | H87: =H60 -> 0.06 | I87: =I60 -> 0.06 | J87: =J60 -> 0.06
B89: Capitalized financing fees, beginning | D89: Amort. years?
B90: (-) Fee amortization expense | D90: 5
B91: Capitalized financing fees, ending
B94: Existing debt, beginning
B95: (-) Net issuance / (paydown)
B96: Existing debt, ending
B97: % Interest rate | F97: 0.05 | G97: 0.05 | H97: 0.05 | I97: 0.05 | J97: 0.05
B98: Interest expense
B100: New debt, beginning
B101: (-) Net issuance / (paydown)
B102: New debt, ending
B103: % Interest rate | F103: 0.08 | G103: 0.08 | H103: 0.08 | I103: 0.08 | J103: 0.08
B104: Interest expense
B106: Minimum cash balance | F106: 5 | G106: 5 | H106: 5 | I106: 5 | J106: 5
B109: Cash flow statement | F109: 1 | G109: =F109+1 -> 2 | H109: =G109+1 -> 3 | I109: =H109+1 -> 4 | J109: =I109+1 -> 5
B110: Net income
B111: (+) D&A
B112: (+) Fee amortization expense
B113: (-) Capex
B114: (-) Change in WC
B115: Cash from operations & investing
B117: (+) Debt issuance / (paydown)
B118: Cash from financing
B120: Net change in cash
B124: Returns analysis | J124: $ millions
B126: Returns scenarios
B127: Multiple of money
B128: IRR
B129: Net gain
B132: Exit proceeds | E132: 0 | F132: 1 | G132: =F132+1 -> 2 | H132: =G132+1 -> 3 | I132: =H132+1 -> 4 | J132: =I132+1 -> 5
B133: Exit LTM Revenue
B134: Exit multiple
B135: Exit enterprise value
B136: (+) Cash
B137: (-) Debt
B138: Exit equity value
B141: IRR cash flows | E141: 0 | F141: 1 | G141: =F141+1 -> 2 | H141: =G141+1 -> 3 | I141: =H141+1 -> 4 | J141: =I141+1 -> 5 | L141: IRR
B142: Sponsor cash flows

Sheet Cohorts (Start)
B2: ARR Waterfall Summary | M2: $ millions
B3: Annual recurring revenue | F3: -2 | G3: -1 | H3: 0 | I3: 1 | J3: =I3+1 -> 2 | K3: =J3+1 -> 3 | L3: =K3+1 -> 4 | M3: =L3+1 -> 5
B4: ARR, beginning | F4: 12
B5: (+) New bookings
B6: (-) Logo churn
B7: (+) Net upsell/(downsell)
B8: ARR, ending | F8: =SUM(F4:F7) -> 12 | G8: =SUM(G4:G7) -> 0 | H8: =SUM(H4:H7) -> 0
B10: % GAAP recognition | F10: 0.85 | G10: 0.85 | H10: 0.85 | I10: 0.85 | J10: 0.85 | K10: 0.85 | L10: 0.85 | M10: 0.85
B11: Recognized revenue | F11: =+F10*F8 -> 10.2 | G11: =+G10*G8 -> 0 | H11: =+H10*H8 -> 0
B12: % growth | G12: =+IFERROR(G11/F11-1, "n/a") -> -1 | H12: =+IFERROR(H11/G11-1, "n/a") -> n/a
B15: ARR Build | M15: $ millions
B16: Customers by cohort | F16: =+F$3 -> -2 | G16: =+G$3 -> -1 | H16: =+H$3 -> 0 | I16: =+I$3 -> 1 | J16: =+J$3 -> 2 | K16: =+K$3 -> 3 | L16: =+L$3 -> 4 | M16: =+M$3 -> 5
C17: New logos
B18: Before Year -2 | C18: n/a | F18: 53 | G18: 48 | H18: 45
B19: -2 | C19: =+F120 -> 60 | F19: =+$C19 -> 60 | G19: 56 | H19: 54
B20: -1 | C20: =+G120 -> 90 | G20: =+$C20 -> 90 | H20: 80
B21: 0 | C21: =+H120 -> 120 | H21: =+$C21 -> 120
B22: 1 | C22: =+I120 -> 0
B23: 2 | C23: =+J120 -> 0
B24: 3 | C24: =+K120 -> 0
B25: 4 | C25: =+L120 -> 0
B26: 5 | C26: =+M120 -> 0
B27: Total | F27: =SUM(F18:F26) -> 113 | G27: =SUM(G18:G26) -> 194 | H27: =SUM(H18:H26) -> 299
B30: Use this retention curve unless given otherwise --> | E30: Year 0 | F30: +1 Year | G30: +2 Years | H30: +3 Years | I30: Beyond
B31: Customer retention % | E31: 0.85 | F31: 0.92 | G31: 0.94 | H31: 0.96 | I31: 0.96
B33: Retention % | F33: =+F$3 -> -2 | G33: =+G$3 -> -1 | H33: =+H$3 -> 0 | I33: =+I$3 -> 1 | J33: =+J$3 -> 2 | K33: =+K$3 -> 3 | L33: =+L$3 -> 4 | M33: =+M$3 -> 5
B34: =+B18 -> Before Year -2
B35: =+B19 -> -2
B36: =+B20 -> -1
B37: =+B21 -> 0
B38: =+B22 -> 1
B39: =+B23 -> 2
B40: =+B24 -> 3
B41: =+B25 -> 4
B42: =+B26 -> 5
B43: Total
B46: Churned customers | F46: =+F$3 -> -2 | G46: =+G$3 -> -1 | H46: =+H$3 -> 0 | I46: =+I$3 -> 1 | J46: =+J$3 -> 2 | K46: =+K$3 -> 3 | L46: =+L$3 -> 4 | M46: =+M$3 -> 5
B47: =+B34 -> Before Year -2 | F47: 7 | G47: =+F18-G18 -> 5 | H47: =+G18-H18 -> 3
B48: =+B35 -> -2 | G48: =+F19-G19 -> 4 | H48: =+G19-H19 -> 2
B49: =+B36 -> -1 | H49: =+G20-H20 -> 10
B50: =+B37 -> 0
B51: =+B38 -> 1
B52: =+B39 -> 2
B53: =+B40 -> 3
B54: =+B41 -> 4
B55: =+B42 -> 5
B56: Total | F56: =SUM(F47:F55) -> 7 | G56: =SUM(G47:G55) -> 9 | H56: =SUM(H47:H55) -> 15
B59: Use this pricing curve unless given otherwise --> | E59: Year 0 | F59: +1 Year | G59: +2 Years | H59: +3 Years | I59: Beyond
B60: Pricing | E60: 0.2 | F60: 0.2 | G60: 0.2 | H60: 0.2 | I60: 0.2
B62: Average revenue per customer ("ARPU") | E62: -3 | F62: =+F$3 -> -2 | G62: =+G$3 -> -1 | H62: =+H$3 -> 0 | I62: =+I$3 -> 1 | J62: =+J$3 -> 2 | K62: =+K$3 -> 3 | L62: =+L$3 -> 4 | M62: =+M$3 -> 5
B63: =+B47 -> Before Year -2 | E63: 0.2 | F63: 0.2 | G63: 0.2 | H63: 0.2
B64: =+B48 -> -2 | F64: 0.2 | G64: 0.2 | H64: 0.2
B65: =+B49 -> -1 | G65: 0.2 | H65: 0.2
B66: =+B50 -> 0 | H66: 0.2
B67: =+B51 -> 1
B68: =+B52 -> 2
B69: =+B53 -> 3
B70: =+B54 -> 4
B71: =+B55 -> 5
B72: Average total | F72: =+IFERROR(F111/F27, "n/a") -> 0 | G72: =+IFERROR(G111/G27, "n/a") -> 0 | H72: =+IFERROR(H111/H27, "n/a") -> 0
B75: Churn by cohort - $ | F75: =+F$3 -> -2 | G75: =+G$3 -> -1 | H75: =+H$3 -> 0 | I75: =+I$3 -> 1 | J75: =+J$3 -> 2 | K75: =+K$3 -> 3 | L75: =+L$3 -> 4 | M75: =+M$3 -> 5
B76: =+B47 -> Before Year -2
B77: =+B48 -> -2
B78: =+B49 -> -1
B79: =+B50 -> 0
B80: =+B51 -> 1
B81: =+B52 -> 2
B82: =+B53 -> 3
B83: =+B54 -> 4
B84: =+B55 -> 5
B85: Total
B88: Net upsell/(downsell) - $ | F88: =+F$3 -> -2 | G88: =+G$3 -> -1 | H88: =+H$3 -> 0 | I88: =+I$3 -> 1 | J88: =+J$3 -> 2 | K88: =+K$3 -> 3 | L88: =+L$3 -> 4 | M88: =+M$3 -> 5
B89: =+B34 -> Before Year -2 | F89: =+F18*(F63-E63) -> 0 | G89: =+G18*(G63-F63) -> 0 | H89: =+H18*(H63-G63) -> 0 | I89: =+I18*(I63-H63) -> 0 | J89: =+J18*(J63-I63) -> 0 | K89: =+K18*(K63-J63) -> 0 | L89: =+L18*(L63-K63) -> 0 | M89: =+M18*(M63-L63) -> 0
B90: =+B35 -> -2 | G90: =+G19*(G64-F64) -> 0 | H90: =+H19*(H64-G64) -> 0 | I90: =+I19*(I64-H64) -> 0 | J90: =+J19*(J64-I64) -> 0 | K90: =+K19*(K64-J64) -> 0 | L90: =+L19*(L64-K64) -> 0 | M90: =+M19*(M64-L64) -> 0
B91: =+B36 -> -1 | H91: =+H20*(H65-G65) -> 0 | I91: =+I20*(I65-H65) -> 0 | J91: =+J20*(J65-I65) -> 0 | K91: =+K20*(K65-J65) -> 0 | L91: =+L20*(L65-K65) -> 0 | M91: =+M20*(M65-L65) -> 0
B92: =+B37 -> 0 | I92: =+I21*(I66-H66) -> 0 | J92: =+J21*(J66-I66) -> 0 | K92: =+K21*(K66-J66) -> 0 | L92: =+L21*(L66-K66) -> 0 | M92: =+M21*(M66-L66) -> 0
B93: =+B38 -> 1 | J93: =+J22*(J67-I67) -> 0 | K93: =+K22*(K67-J67) -> 0 | L93: =+L22*(L67-K67) -> 0 | M93: =+M22*(M67-L67) -> 0
B94: =+B39 -> 2 | K94: =+K23*(K68-J68) -> 0 | L94: =+L23*(L68-K68) -> 0 | M94: =+M23*(M68-L68) -> 0
B95: =+B40 -> 3 | L95: =+L24*(L69-K69) -> 0 | M95: =+M24*(M69-L69) -> 0
B96: =+B41 -> 4 | M96: =+M25*(M70-L70) -> 0
B97: =+B42 -> 5
B98: Total | F98: =SUM(F89:F97) -> 0 | G98: =SUM(G89:G97) -> 0 | H98: =SUM(H89:H97) -> 0 | I98: =SUM(I89:I97) -> 0 | J98: =SUM(J89:J97) -> 0 | K98: =SUM(K89:K97) -> 0 | L98: =SUM(L89:L97) -> 0 | M98: =SUM(M89:M97) -> 0
B101: Total ARR by cohort | F101: =+F$3 -> -2 | G101: =+G$3 -> -1 | H101: =+H$3 -> 0 | I101: =+I$3 -> 1 | J101: =+J$3 -> 2 | K101: =+K$3 -> 3 | L101: =+L$3 -> 4 | M101: =+M$3 -> 5
B102: =+B63 -> Before Year -2
B103: =+B64 -> -2
B104: =+B65 -> -1
B105: =+B66 -> 0
B106: =+B67 -> 1
B107: =+B68 -> 2
B108: =+B69 -> 3
B109: =+B70 -> 4
B110: =+B71 -> 5
B111: Total ARR
B112: ARR from new customers
B115: Drivers & assumptions | M115: $ millions
B116: Sales employees | F116: 16 | G116: 24 | H116: 32 | I116: 40 | J116: 48 | K116: 56 | L116: 68 | M116: 80
B117: Marketing employees | F117: 4 | G117: 5 | H117: 5 | I117: 6 | J117: 8 | K117: 10 | L117: 12 | M117: 14
B118: Implementation employees | F118: 8 | G118: 20 | H118: 30 | I118: 40 | J118: 60 | K118: 65 | L118: 70 | M118: 75
B119: New sales wins per sales employee | F119: 3.75 | G119: 3.75 | H119: 3.75 | I119: 3.75 | J119: 3.5 | K119: 3.5 | L119: 3.25 | M119: 3.25
B120: New customer wins | F120: =+F119*F116 -> 60 | G120: =+G119*G116 -> 90 | H120: =+H119*H116 -> 120
...

Sheet Sensitivities (Start)
B2: Sensitivities | J2: $ millions
E3: 0 | F3: 1 | G3: =F3+1 -> 2 | H3: =G3+1 -> 3 | I3: =H3+1 -> 4 | J3: =I3+1 -> 5
B4: Revenue
B5: =+'Model (End)'!$G$9 -> Management case
B6: =+'Model (End)'!$G$10 -> Base case
B8: YoY growth | D8: CAGR
B9: =+'Model (End)'!$G$9 -> Management case
B10: =+'Model (End)'!$G$10 -> Base case
B13: Selling & marketing expenses
B14: =+'Model (End)'!$G$9 -> Management case
B15: =+'Model (End)'!$G$10 -> Base case
B17: % of revenue | D17: CAGR
B18: =+'Model (End)'!$G$9 -> Management case
B19: =+'Model (End)'!$G$10 -> Base case

Sheet Valuation (Start)
B2: Public trading comparables
E3: Valuation metrics | M3: Operating metrics
C4: Enterprise | E4: EV/Revenue | I4: EV/EBITDA | M4: Revenue | Q4: Revenue Growth | U4: EBITDA | Y4: EBITDA margin
C5: Value | E5: LTM | F5: NTM | G5: NTM+1 | I5: LTM | J5: NTM | K5: NTM+1 | M5: LTM | N5: NTM | O5: NTM+1 | Q5: LTM | R5: NTM | S5: NTM+1 | U5: LTM | V5: NTM | W5: NTM+1 | Y5: LTM | Z5: NTM | AA5: NTM+1
B7: Company 1 | C7: 9536 | E7: =+$C7/M7 -> 18.16381 | F7: =+$C7/N7 -> 10.684594 | G7: =+$C7/O7 -> 6.6778711 | I7: =+$C7/U7 -> -181.6381 | J7: =+$C7/V7 -> -213.69188 | K7: =+$C7/W7 -> 333.89356 | M7: 525 | N7: =+M7*(1+R7) -> 892.5 | O7: =+N7*(1+S7) -> 1428 | Q7: 0.87 | R7: 0.7 | S7: 0.6 | U7: =+Y7*M7 -> -52.5 | V7: =+Z7*N7 -> -44.625 | W7: =+AA7*O7 -> 28.56 | Y7: -0.1 | Z7: -0.05 | AA7: 0.02
B8: Company 2 | C8: 5551 | E8: =+$C8/M8 -> 4.6258333 | F8: =+$C8/N8 -> 4.1302083 | G8: =+$C8/O8 -> 3.789182 | I8: =+$C8/U8 -> 14.017677 | J8: =+$C8/V8 -> 11.800595 | K8: =+$C8/W8 -> 10.826234 | M8: 1200 | N8: =+M8*(1+R8) -> 1344 | O8: =+N8*(1+S8) -> 1464.96 | Q8: 0.08 | R8: 0.12 | S8: 0.09 | U8: =+Y8*M8 -> 396 | V8: =+Z8*N8 -> 470.4 | W8: =+AA8*O8 -> 512.736 | Y8: 0.33 | Z8: 0.35 | AA8: 0.35
B9: Company 3 | C9: 5078 | E9: =+$C9/M9 -> 15.295181 | F9: =+$C9/N9 -> 8.4973226 | G9: =+$C9/O9 -> 4.9984251 | I9: =+$C9/U9 -> -38.237952 | J9: =+$C9/V9 -> -28.324409 | K9: =+$C9/W9 -> -24.992125 | M9: 332 | N9: =+M9*(1+R9) -> 597.6 | O9: =+N9*(1+S9) -> 1015.92 | Q9: 0.92 | R9: 0.8 | S9: 0.7 | U9: =+Y9*M9 -> -132.8 | V9: =+Z9*N9 -> -179.28 | W9: =+AA9*O9 -> -203.184 | Y9: -0.4 | Z9: -0.3 | AA9: -0.2
B10: Company 4 | C10: 896 | E10: =+$C10/M10 -> 11.487179 | F10: =+$C10/N10 -> 7.6074036 | G10: =+$C10/O10 -> 5.3953217 | I10: =+$C10/U10 -> -45.948718 | J10: =+$C10/V10 -> -36.225732 | K10: =+$C10/W10 -> -28.39643 | M10: 78 | N10: =+M10*(1+R10) -> 117.78 | O10: =+N10*(1+S10) -> 166.0698 | Q10: 0.66 | R10: 0.51 | S10: 0.41 | U10: =+Y10*M10 -> -19.5 | V10: =+Z10*N10 -> -24.7338 | W10: =+AA10*O10 -> -31.553262 | Y10: -0.25 | Z10: -0.21 | AA10: -0.19
B11: Company 5 | C11: 7412 | E11: =+$C11/M11 -> 12.332779 | F11: =+$C11/N11 -> 10.108835 | G11: =+$C11/O11 -> 8.087068 | I11: =+$C11/U11 -> -246.65557 | J11: =+$C11/V11 -> 336.96117 | K11: =+$C11/W11 -> 80.87068 | M11: 601 | N11: =+M11*(1+R11) -> 733.22 | O11: =+N11*(1+S11) -> 916.525 | Q11: 0.27 | R11: 0.22 | S11: 0.25 | U11: =+Y11*M11 -> -30.05 | V11: =+Z11*N11 -> 21.9966 | W11: =+AA11*O11 -> 91.6525 | Y11: -0.05 | Z11: 0.03 | AA11: 0.1
B12: Company 6 | C12: 4301 | E12: =+$C12/M12 -> 14.336667 | F12: =+$C12/N12 -> 10.779449 | G12: =+$C12/O12 -> 8.6235589 | I12: =+$C12/U12 -> 119.47222 | J12: =+$C12/V12 -> 71.862991 | K12: =+$C12/W12 -> 53.897243 | M12: 300 | N12: =+M12*(1+R12) -> 399 | O12: =+N12*(1+S12) -> 498.75 | Q12: 0.35 | R12: 0.33 | S12: 0.25 | U12: =+Y12*M12 -> 36 | V12: =+Z12*N12 -> 59.85 | W12: =+AA12*O12 -> 79.8 | Y12: 0.12 | Z12: 0.15 | AA12: 0.16
B13: Company 7 | C13: 5523 | E13: =+$C13/M13 -> 24.99095 | F13: =+$C13/N13 -> 12.190707 | G13: =+$C13/O13 -> 6.5895716 | I13: =+$C13/U13 -> -131.53132 | J13: =+$C13/V13 -> -67.726152 | K13: =+$C13/W13 -> -38.762186 | M13: 221 | N13: =+M13*(1+R13) -> 453.05 | O13: =+N13*(1+S13) -> 838.1425 | Q13: 1.08 | R13: 1.05 | S13: 0.85 | U13: =+Y13*M13 -> -41.99 | V13: =+Z13*N13 -> -81.549 | W13: =+AA13*O13 -> -142.48423 | Y13: -0.19 | Z13: -0.18 | AA13: -0.17
B14: Company 8 | C14: 2217 | E14: =+$C14/M14 -> 5.5012407 | F14: =+$C14/N14 -> 5.0470098 | G14: =+$C14/O14 -> 4.7168316 | I14: =+$C14/U14 -> 15.717831 | J14: =+$C14/V14 -> 14.844147 | K14: =+$C14/W14 -> 13.873034 | M14: 403 | N14: =+M14*(1+R14) -> 439.27 | O14: =+N14*(1+S14) -> 470.0189 | Q14: 0.1 | R14: 0.09 | S14: 0.07 | U14: =+Y14*M14 -> 141.05 | V14: =+Z14*N14 -> 149.3518 | W14: =+AA14*O14 -> 159.80643 | Y14: 0.35 | Z14: 0.34 | AA14: 0.34
B16: Entire comp set
B17: Average | E17: =AVERAGE(E7:E14) -> 13.341705 | F17: =AVERAGE(F7:F14) -> 8.6306912 | G17: =AVERAGE(G7:G14) -> 6.1097287 | I17: =AVERAGE(I7:I14) -> -61.850491 | J17: =AVERAGE(J7:J14) -> 11.187591 | K17: =AVERAGE(K7:K14) -> 50.151251
B18: Median | E18: =MEDIAN(E7:E14) -> 13.334723 | F18: =MEDIAN(F7:F14) -> 9.3030788 | G18: =MEDIAN(G7:G14) -> 5.9924467 | I18: =MEDIAN(I7:I14) -> -42.093335 | J18: =MEDIAN(J7:J14) -> -8.2619068 | K18: =MEDIAN(K7:K14) -> 12.349634
B20: Selected comps
B21: Average | E21: =AVERAGE(E11:E12) -> 13.334723 | F21: =AVERAGE(F11:F12) -> 10.444142 | G21: =AVERAGE(G11:G12) -> 8.3553134 | I21: =AVERAGE(I11:I12) -> -63.591676 | J21: =AVERAGE(J11:J12) -> 204.41208 | K21: =AVERAGE(K11:K12) -> 67.383962
B24: Precedent transaction comparables
C25: Acquisition | E25: Valuation metrics | M25: Operating metrics
C26: Enterprise | E26: EV/Revenue | I26: EV/EBITDA | M26: Revenue | Q26: Revenue Growth | U26: EBITDA | Y26: EBITDA margin
C27: Value | E27: LTM | F27: NTM | G27: NTM+1 | I27: LTM | J27: NTM | K27: NTM+1 | M27: LTM | N27: NTM | O27: NTM+1 | Q27: LTM | R27: NTM | S27: NTM+1 | U27: LTM | V27: NTM | W27: NTM+1 | Y27: LTM | Z27: NTM | AA27: NTM+1
B29: Company A | C29: 3000 | E29: =+$C29/M29 -> 24 | F29: =+$C29/N29 -> 13.333333 | G29: =+$C29/O29 -> 8.2304527 | I29: =+$C29/U29 -> -240 | J29: =+$C29/V29 -> -266.66667 | K29: =+$C29/W29 -> 411.52263 | M29: 125 | N29: =+M29*(1+R29) -> 225 | O29: =+N29*(1+S29) -> 364.5 | Q29: 0.78 | R29: 0.8 | S29: 0.62 | U29: =+Y29*M29 -> -12.5 | V29: =+Z29*N29 -> -11.25 | W29: =+AA29*O29 -> 7.29 | Y29: -0.1 | Z29: -0.05 | AA29: 0.02
B30: Company B | C30: 8800 | E30: =+$C30/M30 -> 9.8104794 | F30: =+$C30/N30 -> 8.0413765 | G30: =+$C30/O30 -> 6.8147259 | I30: =+$C30/U30 -> 54.502663 | J30: =+$C30/V30 -> 47.302215 | K30: =+$C30/W30 -> 37.859588 | M30: 897 | N30: =+M30*(1+R30) -> 1094.34 | O30: =+N30*(1+S30) -> 1291.3212 | Q30: 0.32 | R30: 0.22 | S30: 0.18 | U30: =+Y30*M30 -> 161.46 | V30: =+Z30*N30 -> 186.0378 | W30: =+AA30*O30 -> 232.43782 | Y30: 0.18 | Z30: 0.17 | AA30: 0.18
B31: Company C | C31: 2500 | E31: =+$C31/M31 -> 11.261261 | F31: =+$C31/N31 -> 10.23751 | G31: =+$C31/O31 -> 9.4791761 | I31: =+$C31/U31 -> 28.153153 | J31: =+$C31/V31 -> 24.375024 | K31: =+$C31/W31 -> 22.569467 | M31: 222 | N31: =+M31*(1+R31) -> 244.2 | O31: =+N31*(1+S31) -> 263.736 | Q31: 0.12 | R31: 0.1 | S31: 0.08 | U31: =+Y31*M31 -> 88.8 | V31: =+Z31*N31 -> 102.564 | W31: =+AA31*O31 -> 110.76912 | Y31: 0.4 | Z31: 0.42 | AA31: 0.42
B32: Company D | C32: 1250 | E32: =+$C32/M32 -> 23.584906 | F32: =+$C32/N32 -> 11.792453 | G32: =+$C32/O32 -> 6.0474117 | I32: =+$C32/U32 -> -63.742988 | J32: =+$C32/V32 -> -39.308176 | K32: =+$C32/W32 -> -30.237059 | M32: 53 | N32: =+M32*(1+R32) -> 106 | O32: =+N32*(1+S32) -> 206.7 | Q32: 1.22 | R32: 1 | S32: 0.95 | U32: =+Y32*M32 -> -19.61 | V32: =+Z32*N32 -> -31.8 | W32: =+AA32*O32 -> -41.34 | Y32: -0.37 | Z32: -0.3 | AA32: -0.2
B33: Company E | C33: 500 | E33: =+$C33/M33 -> 11.904762 | F33: =+$C33/N33 -> 9.1575092 | G33: =+$C33/O33 -> 7.2106371 | I33: =+$C33/U33 -> -99.206349 | J33: =+$C33/V33 -> -183.15018 | K33: =+$C33/W33 -> 144.21274 | M33: 42 | N33: =+M33*(1+R33) -> 54.6 | O33: =+N33*(1+S33) -> 69.342 | Q33: 0.38 | R33: 0.3 | S33: 0.27 | U33: =+Y33*M33 -> -5.04 | V33: =+Z33*N33 -> -2.73 | W33: =+AA33*O33 -> 3.4671 | Y33: -0.12 | Z33: -0.05 | AA33: 0.05
B35: Entire comp set
B36: Average | E36: =AVERAGE(E29:E33) -> 16.112282 | F36: =AVERAGE(F29:F33) -> 10.512436 | G36: =AVERAGE(G29:G33) -> 7.5564807 | I36: =AVERAGE(I29:I33) -> -64.058704 | J36: =AVERAGE(J29:J33) -> -83.489557 | K36: =AVERAGE(K29:K33) -> 117.18547
B37: Median | E37: =MEDIAN(E29:E33) -> 11.904762 | F37: =MEDIAN(F29:F33) -> 10.23751 | G37: =MEDIAN(G29:G33) -> 7.2106371 | I37: =MEDIAN(I29:I33) -> -63.742988 | J37: =MEDIAN(J29:J33) -> -39.308176 | K37: =MEDIAN(K29:K33) -> 37.859588
B39: Selected comps
B40: Average | E40: =AVERAGE(E33,E30) -> 10.857621 | F40: =AVERAGE(F33,F30) -> 8.5994428 | G40: =AVERAGE(G33,G30) -> 7.0126815 | I40: =AVERAGE(I33,I30) -> -22.351843 | J40: =AVERAGE(J33,J30) -> -67.923984 | K40: =AVERAGE(K33,K30) -> 91.036165
B43: Historical trading comparables - Software index
C45: Median
C46: EV/LTM Rev
B47: 20 quarters ago | C47: 5.2
B48: 19 quarters ago | C48: 5.9
B49: 18 quarters ago | C49: 6.2
B50: 17 quarters ago | C50: 6.5
B51: 16 quarters ago | C51: 7.2
B52: 15 quarters ago | C52: 6.9
B53: 14 quarters ago | C53: 6.7
B54: 13 quarters ago | C54: 6.4
B55: 12 quarters ago | C55: 7.4
B56: 11 quarters ago | C56: 7.7
B57: 10 quarters ago | C57: 8.4
B58: 9 quarters ago | C58: 8.6
... B67: Current quarter | C67: 13.3
B70: Average | C70: =AVERAGE(C47:C67) -> 9.147619
B71: Ratio | C71: =+C70/C67 -> 0.68779091
B74: Proposed valuation | C74: 12
B75: Adjusted valuation | C75: =+C74*70% -> 8.4

Sheet End ->

Sheet Model (End)
B2: Assumptions | J2: $ millions
B3: Entry assumptions | G3: Other assumptions
C4: Pre-Money | D4: Post-Money | E4: Assumptions | G4: Rollover equity | J4: 800
B5: LTM revenue | C5: =E61 -> 50.83 | G5: Management option pool | J5: 0.1
B6: Entry multiple | C6: 18
B7: Enterprise value | C7: =C5*C6 -> 914.94 | D7: =C7 -> 914.94
B8: (-) Existing debt | C8: =C52 -> 0 | D8: =D52 -> 0 | G8: ="Active: "&CHOOSE(J8,G9,G10,G11) -> Active: Base case | J8: 2
B9: (-) New debt | C9: =+C53 -> 0 | D9: 0 | G9: Management case | J9: 1
B10: (+) Cash | C10: =C44 -> 5 | D10: 105 | G10: Base case | J10: 2
B11: Equity value | C11: =C7-C8+C10-C9 -> 919.94 | D11: =D7-D8+D10-D9 -> 1019.94
B12: (+) Transaction fees | D12: =+E12*D7 -> 9.1494 | E12: 0.01
B13: (+) Financing fees | D13: =+E13*D9 -> 0 | E13: 0.02
B14: Equity value (incl. fees) | D14: =+D11+D12+D13 -> 1029.0894
B17: Sources & uses | J17: $ millions
B18: Sources | G18: Uses
B19: New debt | D19: =+D9 -> 0 | G19: Proceeds to selling shareholders | J19: =+C11-J20 -> 119.94
B20: Rollover equity | D20: =+J20 -> 800 | G20: Rollover equity | J20: =+J4 -> 800
B21: Sponsor equity | D21: =+J25-D20-D19 -> 229.0894 | G21: Cash added to B/S | J21: =+D10-C10 -> 100
G22: Transaction fees | J22: =+D12 -> 9.1494
G23: Financing fees | J23: =+D13 -> 0
B25: Total sources | D25: =SUM(D19:D24) -> 1029.0894 | G25: Total uses | J25: =SUM(J19:J24) -> 1029.0894
B29: Capitalization table
D30: Pre-Money | H30: Post-Money
D31: $ Amount | E31: Shares | F31: FD Own % | H31: $ Amount | I31: Shares | J31: FD Own %
B32: Primary (incl. fees) | D32: =+E32*D$39/1000000 -> 0 | E32: 0 | F32: =+E32/E$37 -> 0 | H32: =+J21+J22+J23 -> 109.1494 | I32: =+H32*1000000/H$39 -> 118648.39 | J32: =+I32/I$37 -> 0.095457654
B33: Secondary | D33: =+E33*D$39/1000000 -> 0 | E33: 0 | F33: =+E33/E$37 -> 0 | H33: =+D21-H32 -> 119.94 | I33: =+H33*1000000/H$39 -> 130378.07 | J33: =+I33/I$37 -> 0.10489468
B34: Total new sponsor | D34: =SUM(D32:D33) -> 0 | E34: =SUM(E32:E33) -> 0 | F34: =+E34/E$37 -> 0 | H34: =+SUM(H32:H33) -> 229.0894 | I34: =+H34*1000000/H$39 -> 249026.46 | J34: =+I34/I$37 -> 0.20035233
B35: Existing owners | D35: =+C11 -> 919.94 | E35: 1000000 | F35: =+E35/E$37 -> 1 | H35: =J20 -> 800 | I35: =+H35*1000000/H$39 -> 869621.93 | J35: =+I35/I$37 -> 0.69964767
B36: Management options | D36: =+E36*D$39/1000000 -> 0 | E36: 0 | F36: =+E36/E$37 -> 0 | H36: 0 | I36: =SUM(I34:I35)/(1-J5)*J5 -> 124294.27 | J36: =+I36/I$37 -> 0.1
B37: Total company | D37: =SUM(D34:D36) -> 919.94 | E37: =SUM(E34:E36) -> 1000000 | F37: =+E37/E$37 -> 1 | H37: =SUM(H34:H36) -> 1029.0894 | I37: =SUM(I34:I36) -> 1242942.7 | J37: =+I37/I$37 -> 1
B39: Share price | D39: =+D37*1000000/E37 -> 919.94 | H39: =+D39 -> 919.94
B42: Model | J42: $ millions
B43: Balance sheet | C43: 0 | D43: Adjust. | E43: Pro forma | F43: 1 | G43: =F43+1 -> 2 | H43: =G43+1 -> 3 | I43: =H43+1 -> 4 | J43: =I43+1 -> 5
B44: Cash | C44: 5 | D44: =E44-C44 -> 100 | E44: =+D10 -> 105 | F44: =F152+E44 -> 89.351544 | G44: =G152+F44 -> 75.218049 | H44: =H152+G44 -> 62.925027 | I44: =I152+H44 -> 58.710296 | J44: =J152+I44 -> 66.741612
B45: Net working capital | C45: 100 | E45: =D45+C45 -> 100 | F45: =F97 -> 105 | G45: =G97 -> 110 | H45: =H97 -> 115 | I45: =I97 -> 120 | J45: =J97 -> 125
B46: Capitalized financing fees | C46: 0 | D46: =+D13 -> 0 | E46: =D46+C46 -> 0 | F46: =F108 -> 0 | G46: =G108 -> 0 | H46: =H108 -> 0 | I46: =I108 -> 0 | J46: =J108 -> 0
B47: Goodwill | C47: 0 | E47: =D47+C47 -> 0 | F47: =E47 -> 0 | G47: =F47 -> 0 | H47: =G47 -> 0 | I47: =H47 -> 0 | J47: =I47 -> 0
B48: Deferred tax asset | C48: 20 | E48: =D48+C48 -> 20 | F48: =E48-F136 -> 21.93661 | G48: =F48-G136 -> 23.462854 | H48: =G48-H136 -> 24.496502 | I48: =H48-I136 -> 23.845543 | J48: =I48-J136 -> 20.932592
B49: Net PP&E | C49: 20 | E49: =D49+C49 -> 20 | F49: =F102 -> 21.426504 | G49: =G102 -> 23.292171 | H49: =H102 -> 25.663058 | I49: =I102 -> 28.589809 | J49: =J102 -> 32.169244
B50: Total assets | C50: =SUM(C44:C49) -> 145 | E50: =SUM(E44:E49) -> 245 | F50: =SUM(F44:F49) -> 237.71466 | G50: =SUM(G44:G49) -> 231.97307 | H50: =SUM(H44:H49) -> 228.08459 | I50: =SUM(I44:I49) -> 231.14565 | J50: =SUM(J44:J49) -> 244.84345
B52: Existing debt | C52: 0 | E52: =D52+C52 -> 0 | F52: =F112 -> 0 | G52: =G112 -> 0 | H52: =H112 -> 0 | I52: =I112 -> 0 | J52: =J112 -> 0
B53: New debt | C53: 0 | D53: =+D9 -> 0 | E53: =D53+C53 -> 0 | F53: =F118 -> 0 | G53: =G118 -> 0 | H53: =H118 -> 0 | I53: =I118 -> 0 | J53: =J118 -> 0
B54: Shareholder equity | C54: 145 | D54: =+H32-J22 -> 100 | E54: =D54+C54 -> 245 | F54: =E54+F90 -> 237.71466 | G54: =F54+G90 -> 231.97307 | H54: =G54+H90 -> 228.08459 | I54: =H54+I90 -> 231.14565 | J54: =I54+J90 -> 244.84345
B55: Total liabilities & equity | C55: =SUM(C52:C54) -> 145 | E55: =SUM(E52:E54) -> 245 | F55: =SUM(F52:F54) -> 237.71466 | G55: =SUM(G52:G54) -> 231.97307 | H55: =SUM(H52:H54) -> 228.08459 | I55: =SUM(I52:I54) -> 231.14565 | J55: =SUM(J52:J54) -> 244.84345
B56: Check | C56: =C50-C55 -> 0 | E56: =E50-E55 -> 0 | F56: =F50-F55 -> 0 | G56: =G50-G55 -> 0 | H56: =H50-H55 -> 0 | I56: =I50-I55 -> 0 | J56: =J50-J55 -> 0
B60: Income statement | C60: =+D60-1 -> -2 | D60: =+E60-1 -> -1 | E60: 0 | F60: 1 | G60: =F60+1 -> 2 | H60: =G60+1 -> 3 | I60: =H60+1 -> 4 | J60: =I60+1 -> 5
B61: Revenue | C61: 19.21 | D61: 32.98 | E61: 50.83 | F61: ='Sensitivities (End)'!F4 -> 71.3252 | G61: ='Sensitivities (End)'!G4 -> 93.283352 | H61: ='Sensitivities (End)'!H4 -> 118.54436 | I61: ='Sensitivities (End)'!I4 -> 146.33753 | J61: ='Sensitivities (End)'!J4 -> 178.97177
B62: % growth | D62: =D61/C61-1 -> 0.71681416 | E62: =E61/D61-1 -> 0.54123711 | F62: =F61/E61-1 -> 0.4032107 | G62: =G61/F61-1 -> 0.30785966 | H62: =H61/G61-1 -> 0.27079869 | I62: =I61/H61-1 -> 0.23445371 | J62: =J61/I61-1 -> 0.22300664
B64: Gross profit | C64: 13 | D64: 23 | E64: 35.8 | F64: =F65*F$61 -> 49.92764 | G64: =G65*G$61 -> 65.298346 | H64: =H65*H$61 -> 82.981053 | I64: =I65*I$61 -> 102.43627 | J64: =J65*J$61 -> 125.28024
B65: % of revenue | C65: =+C64/C$61 -> 0.67673087 | D65: =+D64/D$61 -> 0.69739236 | E65: =+E64/E$61 -> 0.70430848 | F65: 0.7 | G65: 0.7 | H65: 0.7 | I65: 0.7 | J65: 0.7
B67: Selling and marketing expenses | C67: 9.56 | D67: 15.55 | E67: 20.75 | F67: ='Sensitivities (End)'!F13 -> 26.34 | G67: ='Sensitivities (End)'!G13 -> 34.32 | H67: ='Sensitivities (End)'!H13 -> 39.3 | I67: ='Sensitivities (End)'!I13 -> 45.88 | J67: ='Sensitivities (End)'!J13 -> 52.46
B68: % of revenue | C68: =+C67/C61 -> 0.49765747 | D68: =+D67/D61 -> 0.47149788 | E68: =+E67/E61 -> 0.40822349 | F68: =+F67/F61 -> 0.36929444 | G68: =+G67/G61 -> 0.36791131 | H68: =+H67/H61 -> 0.33152146 | I68: =+I67/I61 -> 0.31352177 | J68: =+J67/J61 -> 0.29311886
B70: Overhead expenses | C70: 10 | D70: 15.2 | E70: 22.2 | F70: =F71*F$61 -> 28.53008 | G70: =G71*G$61 -> 32.649173 | H70: =H71*H$61 -> 41.490527 | I70: =I71*I$61 -> 43.901258 | J70: =J71*J$61 -> 44.742942
B71: % of revenue | C71: =+C70/C$61 -> 0.52056221 | D71: =+D70/D$61 -> 0.46088539 | E71: =+E70/E$61 -> 0.43674995 | F71: 0.4 | G71: 0.35 | H71: 0.35 | I71: 0.3 | J71: 0.25
B73: EBITDA | C73: =+C64-C67-C70 -> -6.56 | D73: =+D64-D67-D70 -> -7.75 | E73: =+E64-E67-E70 -> -7.15 | F73: =+F64-F67-F70 -> -4.94244 | G73: =+G64-G67-G70 -> -1.6708268 | H73: =+H64-H67-H70 -> 2.1905267 | I73: =+I64-I67-I70 -> 12.655011 | J73: =+J64-J67-J70 -> 28.077296
B74: % of revenue | C74: =+C73/C$61 -> -0.34148881 | D74: =+D73/D$61 -> -0.2349909 | E74: =+E73/E$61 -> -0.14066496 | F74: =+F73/F$61 -> -0.069294443 | G74: =+G73/G$61 -> -0.017911307 | H74: =+H73/H$61 -> 0.018478539 | I74: =+I73/I$61 -> 0.086478234 | J74: =+J73/J$61 -> 0.15688114
B76: D&A | F76: =F77*F$61 -> 4.279512 | G76: =G77*G$61 -> 5.5970011 | H76: =H77*H$61 -> 7.1126617 | I76: =I77*I$61 -> 8.7802516 | J76: =J77*J$61 -> 10.738306
B77: % of revenue | F77: 0.06 | G77: 0.06 | H77: 0.06 | I77: 0.06 | J77: 0.06
B79: Interest expense | F79: =F114+F120 -> 0 | G79: =G114+G120 -> 0 | H79: =H114+H120 -> 0 | I79: =I114+I120 -> 0 | J79: =J114+J120 -> 0
B81: Fee amortization expense | F81: =F107 -> 0 | G81: =G107 -> 0 | H81: =H107 -> 0 | I81: =I107 -> 0 | J81: =J107 -> 0
B82: % of revenue | F82: =+F81/F$61 -> 0 | G82: =+G81/G$61 -> 0 | H82: =+H81/H$61 -> 0 | I82: =+I81/I$61 -> 0 | J82: =+J81/J$61 -> 0
B84: Earnings before taxes | F84: =F73-F76-F79-F81 -> -9.221952 | G84: =G73-G76-G79-G81 -> -7.2678279 | H84: =H73-H76-H79-H81 -> -4.922135 | I84: =I73-I76-I79-I81 -> 3.8747593 | J84: =J73-J76-J79-J81 -> 17.338989
B85: % of revenue | F85: =+F84/F$61 -> -0.12929444 | G85: =+G84/G$61 -> -0.077911307 | H85: =+H84/H$61 -> -0.041521461 | I85: =+I84/I$61 -> 0.026478234 | J85: =+J84/J$61 -> 0.096881143
B87: Tax provision | F87: =+F135 -> -1.9366099 | G87: =+G135 -> -1.5262439 | H87: =+H135 -> -1.0336484 | I87: =+I135 -> 0.81369946 | J87: =+J135 -> 3.6411878
B88: % tax rate | F88: =+F137 -> 0.21 | G88: =+G137 -> 0.21 | H88: =+H137 -> 0.21 | I88: =+I137 -> 0.21 | J88: =+J137 -> 0.21
B90: Net income | F90: =F84-F87 -> -7.2853421 | G90: =G84-G87 -> -5.7415841 | H90: =H84-H87 -> -3.8884867 | I90: =I84-I87 -> 3.0610599 | J90: =J84-J87 -> 13.697802
B91: % of revenue | F91: =+F90/F$61 -> -0.10214261 | G91: =+G90/G$61 -> -0.061549933 | H91: =+H90/H$61 -> -0.032801954 | I91: =+I90/I$61 -> 0.020917805 | J91: =+J90/J$61 -> 0.076536103
B94: Supporting schedules | E94: 0 | F94: 1 | G94: =F94+1 -> 2 | H94: =G94+1 -> 3 | I94: =H94+1 -> 4 | J94: =I94+1 -> 5
B95: Net working capital, beginning | F95: =E97 -> 100 | G95: =F97 -> 105 | H95: =G97 -> 110 | I95: =H97 -> 115 | J95: =I97 -> 120
B96: (+) Increase / (decrease) | F96: 5 | G96: 5 | H96: 5 | I96: 5 | J96: 5
B97: Net working capital, ending | E97: =E45 -> 100 | F97: =SUM(F95:F96) -> 105 | G97: =SUM(G95:G96) -> 110 | H97: =SUM(H95:H96) -> 115 | I97: =SUM(I95:I96) -> 120 | J97: =SUM(J95:J96) -> 125
B99: PP&E, beginning | F99: =E102 -> 20 | G99: =F102 -> 21.426504 | H99: =G102 -> 23.292171 | I99: =H102 -> 25.663058 | J99: =I102 -> 28.589809
B100: (+) Capex | F100: =F103*F61 -> 5.706016 | G100: =G103*G61 -> 7.4626682 | H100: =H103*H61 -> 9.483549 | I100: =I103*I61 -> 11.707002 | J100: =J103*J61 -> 14.317741
B101: (-) D&A | F101: =F76 -> 4.279512 | G101: =G76 -> 5.5970011 | H101: =H76 -> 7.1126617 | I101: =I76 -> 8.7802516 | J101: =J76 -> 10.738306
B102: PP&E, ending | E102: =E49 -> 20 | F102: =F99+F100-F101 -> 21.426504 | G102: =G99+G100-G101 -> 23.292171 | H102: =H99+H100-H101 -> 25.663058 | I102: =I99+I100-I101 -> 28.589809 | J102: =J99+J100-J101 -> 32.169244
B103: Capex - % of revenue | F103: 0.08 | G103: 0.08 | H103: 0.08 | I103: 0.08 | J103: 0.08
B104: D&A - % of revenue | F104: =F77 -> 0.06 | G104: =G77 -> 0.06 | H104: =H77 -> 0.06 | I104: =I77 -> 0.06 | J104: =J77 -> 0.06
B106: Capitalized financing fees, beginning | D106: Amort. years? | E106: Yearly exp. | F106: =E108 -> 0 | G106: =F108 -> 0 | H106: =G108 -> 0 | I106: =H108 -> 0 | J106: =I108 -> 0
B107: (-) Fee amortization expense | D107: 5 | E107: =E108/D107 -> 0 | F107: =$E$107 -> 0 | G107: =$E$107 -> 0 | H107: =$E$107 -> 0 | I107: =$E$107 -> 0 | J107: =$E$107 -> 0
B108: Capitalized financing fees, ending | E108: =E46 -> 0 | F108: =F106-F107 -> 0 | G108: =G106-G107 -> 0 | H108: =H106-H107 -> 0 | I108: =I106-I107 -> 0 | J108: =J106-J107 -> 0
B110: Existing debt, beginning | F110: =E112 -> 0 | G110: =F112 -> 0 | H110: =G112 -> 0 | I110: =H112 -> 0 | J110: =I112 -> 0
B111: (-) Net issuance / (paydown) | F111: 0 | G111: 0 | H111: 0 | I111: 0 | J111: 0
B112: Existing debt, ending | E112: =E52 -> 0 | F112: =F111+F110 -> 0 | G112: =G111+G110 -> 0 | H112: =H111+H110 -> 0 | I112: =I111+I110 -> 0 | J112: =J111+J110 -> 0
B113: % Interest rate | F113: 0.05 | G113: 0.05 | H113: 0.05 | I113: 0.05 | J113: 0.05
B114: Interest expense | F114: =AVERAGE(E112:F112)*F113 -> 0 | G114: =AVERAGE(F112:G112)*G113 -> 0 | H114: =AVERAGE(G112:H112)*H113 -> 0 | I114: =AVERAGE(H112:I112)*I113 -> 0 | J114: =AVERAGE(I112:J112)*J113 -> 0
B116: New debt, beginning | F116: =E118 -> 0 | G116: =F118 -> 0 | H116: =G118 -> 0 | I116: =H118 -> 0 | J116: =I118 -> 0
B117: (-) Net issuance / (paydown) | F117: =-MIN(F116, F147+E44-F122) -> 0 | G117: =-MIN(G116, G147+F44-G122) -> 0 | H117: =-MIN(H116, H147+G44-H122) -> 0 | I117: =-MIN(I116, I147+H44-I122) -> 0 | J117: =-MIN(J116, J147+I44-J122) -> 0
B118: New debt, ending | E118: =E53 -> 0 | F118: =SUM(F116:F117) -> 0 | G118: =SUM(G116:G117) -> 0 | H118: =SUM(H116:H117) -> 0 | I118: =SUM(I116:I117) -> 0 | J118: =SUM(J116:J117) -> 0
B119: % Interest rate | F119: 0.08 | G119: 0.08 | H119: 0.08 | I119: 0.08 | J119: 0.08
B120: Interest expense | F120: =AVERAGE(E118:F118)*F119 -> 0 | G120: =AVERAGE(F118:G118)*G119 -> 0 | H120: =AVERAGE(G118:H118)*H119 -> 0 | I120: =AVERAGE(H118:I118)*I119 -> 0 | J120: =AVERAGE(I118:J118)*J119 -> 0
B122: Minimum cash balance | F122: 5 | G122: 5 | H122: 5 | I122: 5 | J122: 5
B125: Earnings before taxes | F125: =+F84 -> -9.221952 | G125: =+G84 -> -7.2678279 | H125: =+H84 -> -4.922135 | I125: =+I84 -> 3.8747593 | J125: =+J84 -> 17.338989
B126: (-) NOLs used | F126: =+F132 -> 0 | G126: =+G132 -> 0 | H126: =+H132 -> 0 | I126: =+I132 -> -3.0998075 | J126: =+J132 -> -13.871192
B127: Adjusted taxable income | F127: =SUM(F125:F126) -> -9.221952 | G127: =SUM(G125:G126) -> -7.2678279 | H127: =SUM(H125:H126) -> -4.922135 | I127: =SUM(I125:I126) -> 0.77495187 | J127: =SUM(J125:J126) -> 3.4677979
B128: Memo: Maximum allowable NOL used | F128: =+F125*80% -> -7.3775616 | G128: =+G125*80% -> -5.8142623 | H128: =+H125*80% -> -3.937708 | I128: =+I125*80% -> 3.0998075 | J128: =+J125*80% -> 13.871192
B130: Net operating losses, beginning | F130: =+E133 -> 50 | G130: =+F133 -> 59.221952 | H130: =+G133 -> 66.48978 | I130: =+H133 -> 71.411915 | J130: =+I133 -> 68.312107
B131: (+) Net operating losses, created | F131: =IF(F125>0, 0, -F125) -> 9.221952 | G131: =IF(G125>0, 0, -G125) -> 7.2678279 | H131: =IF(H125>0, 0, -H125) -> 4.922135 | I131: =IF(I125>0, 0, -I125) -> 0 | J131: =IF(J125>0, 0, -J125) -> 0
B132: (-) Net operating losses, used | F132: =IF(F125<0, 0, -MIN(F128, SUM(F130:F131))) -> 0 | G132: =IF(G125<0, 0, -MIN(G128, SUM(G130:G131))) -> 0 | H132: =IF(H125<0, 0, -MIN(H128, SUM(H130:H131))) -> 0 | I132: =IF(I125<0, 0, -MIN(I128, SUM(I130:I131))) -> -3.0998075 | J132: =IF(J125<0, 0, -MIN(J128, SUM(J130:J131))) -> -13.871192
B133: Net operating losses, ending | E133: 50 | F133: =SUM(F130:F132) -> 59.221952 | G133: =SUM(G130:G132) -> 66.48978 | H133: =SUM(H130:H132) -> 71.411915 | I133: =SUM(I130:I132) -> 68.312107 | J133: =SUM(J130:J132) -> 54.440916
B135: Tax provision | F135: =+F125*F137 -> -1.9366099 | G135: =+G125*G137 -> -1.5262439 | H135: =+H125*H137 -> -1.0336484 | I135: =+I125*I137 -> 0.81369946 | J135: =+J125*J137 -> 3.6411878
...

Sheet Model (Pre-Money Options)
B2: Assumptions | J2: $ millions
B3: Entry assumptions | G3: Other assumptions
C4: Pre-Money | D4: Post-Money | E4: Assumptions | G4: Rollover equity | J4: 731
B5: LTM revenue | C5: =E61 -> 50.83 | G5: Management option pool | J5: 0.1
B6: Entry multiple | C6: 18
B7: Enterprise value | C7: =C5*C6 -> 914.94 | D7: =C7 -> 914.94
B8: (-) Existing debt | C8: =C52 -> 0 | D8: =D52 -> 0 | G8: ="Active: "&CHOOSE(J8,G9,G10,G11) -> Active: Base case | J8: 2
B9: (-) New debt | C9: =+C53 -> 0 | D9: 0 | G9: Management case | J9: 1
B10: (+) Cash | C10: =C44 -> 5 | D10: 105 | G10: Base case | J10: 2
B11: Equity value | C11: =C7-C8+C10-C9 -> 919.94 | D11: =D7-D8+D10-D9 -> 1019.94
B12: (+) Transaction fees | D12: =+E12*D7 -> 9.1494 | E12: 0.01
B13: (+) Financing fees | D13: =+E13*D9 -> 0 | E13: 0.02
B14: Equity value (incl. fees) | D14: =+D11+D12+D13 -> 1029.0894
B17: Sources & uses | J17: $ millions
B18: Sources | G18: Uses
B19: New debt | D19: =+D9 -> 0 | G19: Proceeds to selling shareholders | J19: =+D35-J20 -> 96.946
B20: Rollover equity | D20: =+J20 -> 731 | G20: Rollover equity | J20: =+J4 -> 731
B21: Sponsor equity | D21: =+J25-D20-D19 -> 206.0954 | G21: Cash added to B/S | J21: =+D10-C10 -> 100
G22: Transaction fees | J22: =+D12 -> 9.1494
G23: Financing fees | J23: =+D13 -> 0
B25: Total sources | D25: =SUM(D19:D24) -> 937.0954 | G25: Total uses | J25: =SUM(J19:J24) -> 937.0954
B29: Capitalization table (options issued pre-money)
D30: Pre-Money (Post-options) | H30: Post-Money
D31: $ Amount | E31: FD Shares | F31: FD Own % | H31: $ Amount | I31: FD Shares | J31: FD Own %
B32: Primary (incl. fees) | D32: 0 | E32: 0 | F32: =+E32/E$37 -> 0 | H32: =+J21+J22+J23 -> 109.1494 | I32: =+H32*1000000/H$39 -> 131831.54 | J32: =+I32/I$37 -> 0.10606406
B33: Secondary | D33: 0 | E33: 0 | F33: =+E33/E$37 -> 0 | H33: =I33*H39/1000000 -> 96.946 | I33: =E35-I35 -> 117092.18 | J33: =+I33/I$37 -> 0.094205615
B34: Total new sponsor | D34: =SUM(D32:D33) -> 0 | E34: =SUM(E32:E33) -> 0 | F34: =+E34/E$37 -> 0 | H34: =+SUM(H32:H33) -> 206.0954 | I34: =+H34*1000000/H$39 -> 248923.72 | J34: =+I34/I$37 -> 0.20026968
B35: Existing owners | D35: =E35*D39/1000000 -> 827.946 | E35: 1000000 | F35: =+E35/E$37 -> 0.9 | H35: =J20 -> 731 | I35: =+H35*1000000/H$39 -> 882907.82 | J35: =+I35/I$37 -> 0.71033673
B36: Management options | D36: 0 | E36: =SUM(E34:E35)/(1-J5)*J5 -> 111111.11 | F36: =+E36/E$37 -> 0.1 | H36: 0 | I36: =+E36 -> 111111.11 | J36: =+I36/I$37 -> 0.089393594
B37: Total company | D37: =SUM(D34:D36) -> 827.946 | E37: =SUM(E34:E36) -> 1111111.1 | F37: =+E37/E$37 -> 1 | H37: =SUM(H34:H36) -> 937.0954 | I37: =SUM(I34:I36) -> 1242942.7 | J37: =+I37/I$37 -> 1
B39: Share price | D39: =+C11*1000000/E37 -> 827.946 | H39: =+D39 -> 827.946
B42: Model | J42: $ millions
B43: Balance sheet | C43: 0 | D43: Adjust. | E43: Pro forma | F43: 1 | G43: =F43+1 -> 2 | H43: =G43+1 -> 3 | I43: =H43+1 -> 4 | J43: =I43+1 -> 5
B44: Cash | C44: 5 | D44: =E44-C44 -> 100 | E44: =+D10 -> 105 | F44: =F152+E44 -> 89.351544 | G44: =G152+F44 -> 75.218049 | H44: =H152+G44 -> 62.925027 | I44: =I152+H44 -> 58.710296 | J44: =J152+I44 -> 66.741612
B45: Net working capital | C45: 100 | E45: =D45+C45 -> 100 | F45: =F97 -> 105 | G45: =G97 -> 110 | H45: =H97 -> 115 | I45: =I97 -> 120 | J45: =J97 -> 125
B46: Capitalized financing fees | C46: 0 | D46: =+D13 -> 0 | E46: =D46+C46 -> 0 | F46: =F108 -> 0 | G46: =G108 -> 0 | H46: =H108 -> 0 | I46: =I108 -> 0 | J46: =J108 -> 0
B47: Goodwill | C47: 0 | E47: =D47+C47 -> 0 | F47: =E47 -> 0 | G47: =F47 -> 0 | H47: =G47 -> 0 | I47: =H47 -> 0 | J47: =I47 -> 0
B48: Deferred tax asset | C48: 20 | E48: =D48+C48 -> 20 | F48: =E48-F136 -> 21.93661 | G48: =F48-G136 -> 23.462854 | H48: =G48-H136 -> 24.496502 | I48: =H48-I136 -> 23.845543 | J48: =I48-J136 -> 20.932592
B49: Net PP&E | C49: 20 | E49: =D49+C49 -> 20 | F49: =F102 -> 21.426504 | G49: =G102 -> 23.292171 | H49: =H102 -> 25.663058 | I49: =I102 -> 28.589809 | J49: =J102 -> 32.169244
B50: Total assets | C50: =SUM(C44:C49) -> 145 | E50: =SUM(E44:E49) -> 245 | F50: =SUM(F44:F49) -> 237.71466 | G50: =SUM(G44:G49) -> 231.97307 | H50: =SUM(H44:H49) -> 228.08459 | I50: =SUM(I44:I49) -> 231.14565 | J50: =SUM(J44:J49) -> 244.84345
B52: Existing debt | C52: 0 | E52: =D52+C52 -> 0 | F52: =F112 -> 0 | G52: =G112 -> 0 | H52: =H112 -> 0 | I52: =I112 -> 0 | J52: =J112 -> 0
B53: New debt | C53: 0 | D53: =+D9 -> 0 | E53: =D53+C53 -> 0 | F53: =F118 -> 0 | G53: =G118 -> 0 | H53: =H118 -> 0 | I53: =I118 -> 0 | J53: =J118 -> 0
B54: Shareholder equity | C54: 145 | D54: =+H32-J22 -> 100 | E54: =D54+C54 -> 245 | F54: =E54+F90 -> 237.71466 | G54: =F54+G90 -> 231.97307 | H54: =G54+H90 -> 228.08459 | I54: =H54+I90 -> 231.14565 | J54: =I54+J90 -> 244.84345
B55: Total liabilities & equity | C55: =SUM(C52:C54) -> 145 | E55: =SUM(E52:E54) -> 245 | F55: =SUM(F52:F54) -> 237.71466 | G55: =SUM(G52:G54) -> 231.97307 | H55: =SUM(H52:H54) -> 228.08459 | I55: =SUM(I52:I54) -> 231.14565 | J55: =SUM(J52:J54) -> 244.84345
B56: Check | C56: =C50-C55 -> 0 | E56: =E50-E55 -> 0 | F56: =F50-F55 -> 0 | G56: =G50-G55 -> 0 | H56: =H50-H55 -> 0 | I56: =I50-I55 -> 0 | J56: =J50-J55 -> 0
B60: Income statement | C60: =+D60-1 -> -2 | D60: =+E60-1 -> -1 | E60: 0 | F60: 1 | G60: =F60+1 -> 2 | H60: =G60+1 -> 3 | I60: =H60+1 -> 4 | J60: =I60+1 -> 5
B61: Revenue | C61: 19.21 | D61: 32.98 | E61: 50.83 | F61: ='Sensitivities (End)'!F4 -> 71.3252 | G61: ='Sensitivities (End)'!G4 -> 93.283352 | H61: ='Sensitivities (End)'!H4 -> 118.54436 | I61: ='Sensitivities (End)'!I4 -> 146.33753 | J61: ='Sensitivities (End)'!J4 -> 178.97177
B62: % growth | D62: =D61/C61-1 -> 0.71681416 | E62: =E61/D61-1 -> 0.54123711 | F62: =F61/E61-1 -> 0.4032107 | G62: =G61/F61-1 -> 0.30785966 | H62: =H61/G61-1 -> 0.27079869 | I62: =I61/H61-1 -> 0.23445371 | J62: =J61/I61-1 -> 0.22300664
B64: Gross profit | C64: 13 | D64: 23 | E64: 35.8 | F64: =F65*F$61 -> 49.92764 | G64: =G65*G$61 -> 65.298346 | H64: =H65*H$61 -> 82.981053 | I64: =I65*I$61 -> 102.43627 | J64: =J65*J$61 -> 125.28024
B65: % of revenue | C65: =+C64/C$61 -> 0.67673087 | D65: =+D64/D$61 -> 0.69739236 | E65: =+E64/E$61 -> 0.70430848 | F65: 0.7 | G65: 0.7 | H65: 0.7 | I65: 0.7 | J65: 0.7
B67: Selling and marketing expenses | C67: 9.56 | D67: 15.55 | E67: 20.75 | F67: ='Sensitivities (End)'!F13 -> 26.34 | G67: ='Sensitivities (End)'!G13 -> 34.32 | H67: ='Sensitivities (End)'!H13 -> 39.3 | I67: ='Sensitivities (End)'!I13 -> 45.88 | J67: ='Sensitivities (End)'!J13 -> 52.46
B68: % of revenue | C68: =+C67/C61 -> 0.49765747 | D68: =+D67/D61 -> 0.47149788 | E68: =+E67/E61 -> 0.40822349 | F68: =+F67/F61 -> 0.36929444 | G68: =+G67/G61 -> 0.36791131 | H68: =+H67/H61 -> 0.33152146 | I68: =+I67/I61 -> 0.31352177 | J68: =+J67/J61 -> 0.29311886
B70: Overhead expenses | C70: 10 | D70: 15.2 | E70: 22.2 | F70: =F71*F$61 -> 28.53008 | G70: =G71*G$61 -> 32.649173 | H70: =H71*H$61 -> 41.490527 | I70: =I71*I$61 -> 43.901258 | J70: =J71*J$61 -> 44.742942
B71: % of revenue | C71: =+C70/C$61 -> 0.52056221 | D71: =+D70/D$61 -> 0.46088539 | E71: =+E70/E$61 -> 0.43674995 | F71: 0.4 | G71: 0.35 | H71: 0.35 | I71: 0.3 | J71: 0.25
B73: EBITDA | C73: =+C64-C67-C70 -> -6.56 | D73: =+D64-D67-D70 -> -7.75 | E73: =+E64-E67-E70 -> -7.15 | F73: =+F64-F67-F70 -> -4.94244 | G73: =+G64-G67-G70 -> -1.6708268 | H73: =+H64-H67-H70 -> 2.1905267 | I73: =+I64-I67-I70 -> 12.655011 | J73: =+J64-J67-J70 -> 28.077296
B74: % of revenue | C74: =+C73/C$61 -> -0.34148881 | D74: =+D73/D$61 -> -0.2349909 | E74: =+E73/E$61 -> -0.14066496 | F74: =+F73/F$61 -> -0.069294443 | G74: =+G73/G$61 -> -0.017911307 | H74: =+H73/H$61 -> 0.018478539 | I74: =+I73/I$61 -> 0.086478234 | J74: =+J73/J$61 -> 0.15688114
B76: D&A | F76: =F77*F$61 -> 4.279512 | G76: =G77*G$61 -> 5.5970011 | H76: =H77*H$61 -> 7.1126617 | I76: =I77*I$61 -> 8.7802516 | J76: =J77*J$61 -> 10.738306
B77: % of revenue | F77: 0.06 | G77: 0.06 | H77: 0.06 | I77: 0.06 | J77: 0.06
B79: Interest expense | F79: =F114+F120 -> 0 | G79: =G114+G120 -> 0 | H79: =H114+H120 -> 0 | I79: =I114+I120 -> 0 | J79: =J114+J120 -> 0
B81: Fee amortization expense | F81: =F107 -> 0 | G81: =G107 -> 0 | H81: =H107 -> 0 | I81: =I107 -> 0 | J81: =J107 -> 0
B82: % of revenue | F82: =+F81/F$61 -> 0 | G82: =+G81/G$61 -> 0 | H82: =+H81/H$61 -> 0 | I82: =+I81/I$61 -> 0 | J82: =+J81/J$61 -> 0
B84: Earnings before taxes | F84: =F73-F76-F79-F81 -> -9.221952 | G84: =G73-G76-G79-G81 -> -7.2678279 | H84: =H73-H76-H79-H81 -> -4.922135 | I84: =I73-I76-I79-I81 -> 3.8747593 | J84: =J73-J76-J79-J81 -> 17.338989
B85: % of revenue | F85: =+F84/F$61 -> -0.12929444 | G85: =+G84/G$61 -> -0.077911307 | H85: =+H84/H$61 -> -0.041521461 | I85: =+I84/I$61 -> 0.026478234 | J85: =+J84/J$61 -> 0.096881143
B87: Tax provision | F87: =+F135 -> -1.9366099 | G87: =+G135 -> -1.5262439 | H87: =+H135 -> -1.0336484 | I87: =+I135 -> 0.81369946 | J87: =+J135 -> 3.6411878
B88: % tax rate | F88: =+F137 -> 0.21 | G88: =+G137 -> 0.21 | H88: =+H137 -> 0.21 | I88: =+I137 -> 0.21 | J88: =+J137 -> 0.21
B90: Net income | F90: =F84-F87 -> -7.2853421 | G90: =G84-G87 -> -5.7415841 | H90: =H84-H87 -> -3.8884867 | I90: =I84-I87 -> 3.0610599 | J90: =J84-J87 -> 13.697802
B91: % of revenue | F91: =+F90/F$61 -> -0.10214261 | G91: =+G90/G$61 -> -0.061549933 | H91: =+H90/H$61 -> -0.032801954 | I91: =+I90/I$61 -> 0.020917805 | J91: =+J90/J$61 -> 0.076536103
B94: Supporting schedules | E94: 0 | F94: 1 | G94: =F94+1 -> 2 | H94: =G94+1 -> 3 | I94: =H94+1 -> 4 | J94: =I94+1 -> 5
B95: Net working capital, beginning | F95: =E97 -> 100 | G95: =F97 -> 105 | H95: =G97 -> 110 | I95: =H97 -> 115 | J95: =I97 -> 120
B96: (+) Increase / (decrease) | F96: 5 | G96: 5 | H96: 5 | I96: 5 | J96: 5
B97: Net working capital, ending | E97: =E45 -> 100 | F97: =SUM(F95:F96) -> 105 | G97: =SUM(G95:G96) -> 110 | H97: =SUM(H95:H96) -> 115 | I97: =SUM(I95:I96) -> 120 | J97: =SUM(J95:J96) -> 125
B99: PP&E, beginning | F99: =E102 -> 20 | G99: =F102 -> 21.426504 | H99: =G102 -> 23.292171 | I99: =H102 -> 25.663058 | J99: =I102 -> 28.589809
B100: (+) Capex | F100: =F103*F61 -> 5.706016 | G100: =G103*G61 -> 7.4626682 | H100: =H103*H61 -> 9.483549 | I100: =I103*I61 -> 11.707002 | J100: =J103*J61 -> 14.317741
B101: (-) D&A | F101: =F76 -> 4.279512 | G101: =G76 -> 5.5970011 | H101: =H76 -> 7.1126617 | I101: =I76 -> 8.7802516 | J101: =J76 -> 10.738306
B102: PP&E, ending | E102: =E49 -> 20 | F102: =F99+F100-F101 -> 21.426504 | G102: =G99+G100-G101 -> 23.292171 | H102: =H99+H100-H101 -> 25.663058 | I102: =I99+I100-I101 -> 28.589809 | J102: =J99+J100-J101 -> 32.169244
B103: Capex - % of revenue | F103: 0.08 | G103: 0.08 | H103: 0.08 | I103: 0.08 | J103: 0.08
B104: D&A - % of revenue | F104: =F77 -> 0.06 | G104: =G77 -> 0.06 | H104: =H77 -> 0.06 | I104: =I77 -> 0.06 | J104: =J77 -> 0.06
B106: Capitalized financing fees, beginning | D106: Amort. years? | E106: Yearly exp. | F106: =E108 -> 0 | G106: =F108 -> 0 | H106: =G108 -> 0 | I106: =H108 -> 0 | J106: =I108 -> 0
B107: (-) Fee amortization expense | D107: 5 | E107: =E108/D107 -> 0 | F107: =$E$107 -> 0 | G107: =$E$107 -> 0 | H107: =$E$107 -> 0 | I107: =$E$107 -> 0 | J107: =$E$107 -> 0
B108: Capitalized financing fees, ending | E108: =E46 -> 0 | F108: =F106-F107 -> 0 | G108: =G106-G107 -> 0 | H108: =H106-H107 -> 0 | I108: =I106-I107 -> 0 | J108: =J106-J107 -> 0
B110: Existing debt, beginning | F110: =E112 -> 0 | G110: =F112 -> 0 | H110: =G112 -> 0 | I110: =H112 -> 0 | J110: =I112 -> 0
B111: (-) Net issuance / (paydown) | F111: 0 | G111: 0 | H111: 0 | I111: 0 | J111: 0
B112: Existing debt, ending | E112: =E52 -> 0 | F112: =F111+F110 -> 0 | G112: =G111+G110 -> 0 | H112: =H111+H110 -> 0 | I112: =I111+I110 -> 0 | J112: =J111+J110 -> 0
B113: % Interest rate | F113: 0.05 | G113: 0.05 | H113: 0.05 | I113: 0.05 | J113: 0.05
B114: Interest expense | F114: =AVERAGE(E112:F112)*F113 -> 0 | G114: =AVERAGE(F112:G112)*G113 -> 0 | H114: =AVERAGE(G112:H112)*H113 -> 0 | I114: =AVERAGE(H112:I112)*I113 -> 0 | J114: =AVERAGE(I112:J112)*J113 -> 0
B116: New debt, beginning | F116: =E118 -> 0 | G116: =F118 -> 0 | H116: =G118 -> 0 | I116: =H118 -> 0 | J116: =I118 -> 0
B117: (-) Net issuance / (paydown) | F117: =-MIN(F116, F147+E44-F122) -> 0 | G117: =-MIN(G116, G147+F44-G122) -> 0 | H117: =-MIN(H116, H147+G44-H122) -> 0 | I117: =-MIN(I116, I147+H44-I122) -> 0 | J117: =-MIN(J116, J147+I44-J122) -> 0
B118: New debt, ending | E118: =E53 -> 0 | F118: =SUM(F116:F117) -> 0 | G118: =SUM(G116:G117) -> 0 | H118: =SUM(H116:H117) -> 0 | I118: =SUM(I116:I117) -> 0 | J118: =SUM(J116:J117) -> 0
B119: % Interest rate | F119: 0.08 | G119: 0.08 | H119: 0.08 | I119: 0.08 | J119: 0.08
B120: Interest expense | F120: =AVERAGE(E118:F118)*F119 -> 0 | G120: =AVERAGE(F118:G118)*G119 -> 0 | H120: =AVERAGE(G118:H118)*H119 -> 0 | I120: =AVERAGE(H118:I118)*I119 -> 0 | J120: =AVERAGE(I118:J118)*J119 -> 0
B122: Minimum cash balance | F122: 5 | G122: 5 | H122: 5 | I122: 5 | J122: 5
B125: Earnings before taxes | F125: =+F84 -> -9.221952 | G125: =+G84 -> -7.2678279 | H125: =+H84 -> -4.922135 | I125: =+I84 -> 3.8747593 | J125: =+J84 -> 17.338989
B126: (-) NOLs used | F126: =+F132 -> 0 | G126: =+G132 -> 0 | H126: =+H132 -> 0 | I126: =+I132 -> -3.0998075 | J126: =+J132 -> -13.871192
B127: Adjusted taxable income | F127: =SUM(F125:F126) -> -9.221952 | G127: =SUM(G125:G126) -> -7.2678279 | H127: =SUM(H125:H126) -> -4.922135 | I127: =SUM(I125:I126) -> 0.77495187 | J127: =SUM(J125:J126) -> 3.4677979
B128: Memo: Maximum allowable NOL used | F128: =+F125*80% -> -7.3775616 | G128: =+G125*80% -> -5.8142623 | H128: =+H125*80% -> -3.937708 | I128: =+I125*80% -> 3.0998075 | J128: =+J125*80% -> 13.871192
B130: Net operating losses, beginning | F130: =+E133 -> 50 | G130: =+F133 -> 59.221952 | H130: =+G133 -> 66.48978 | I130: =+H133 -> 71.411915 | J130: =+I133 -> 68.312107
B131: (+) Net operating losses, created | F131: =IF(F125>0, 0, -F125) -> 9.221952 | G131: =IF(G125>0, 0, -G125) -> 7.2678279 | H131: =IF(H125>0, 0, -H125) -> 4.922135 | I131: =IF(I125>0, 0, -I125) -> 0 | J131: =IF(J125>0, 0, -J125) -> 0
B132: (-) Net operating losses, used | F132: =IF(F125<0, 0, -MIN(F128, SUM(F130:F131))) -> 0 | G132: =IF(G125<0, 0, -MIN(G128, SUM(G130:G131))) -> 0 | H132: =IF(H125<0, 0, -MIN(H128, SUM(H130:H131))) -> 0 | I132: =IF(I125<0, 0, -MIN(I128, SUM(I130:I131))) -> -3.0998075 | J132: =IF(J125<0, 0, -MIN(J128, SUM(J130:J131))) -> -13.871192
B133: Net operating losses, ending | E133: 50 | F133: =SUM(F130:F132) -> 59.221952 | G133: =SUM(G130:G132) -> 66.48978 | H133: =SUM(H130:H132) -> 71.411915 | I133: =SUM(I130:I132) -> 68.312107 | J133: =SUM(J130:J132) -> 54.440916
B135: Tax provision | F135: =+F125*F137 -> -1.9366099 | G135: =+G125*G137 -> -1.5262439 | H135: =+H125*H137 -> -1.0336484 | I135: =+I125*I137 -> 0.81369946 | J135: =+J125*J137 -> 3.6411878
...

Sheet Cohorts (End)
B2: ARR Waterfall Summary | M2: $ millions
B3: Annual recurring revenue | F3: -2 | G3: -1 | H3: 0 | I3: 1 | J3: =I3+1 -> 2 | K3: =J3+1 -> 3 | L3: =K3+1 -> 4 | M3: =L3+1 -> 5
B4: ARR, beginning | F4: 12 | G4: =+F8 -> 22.6 | H4: =+G8 -> 38.8 | I4: =+H8 -> 59.8 | J4: =+I8 -> 83.912 | K4: =+J8 -> 109.74512 | L4: =+K8 -> 139.46396 | M4: =+L8 -> 172.1618
B5: (+) New bookings | F5: =+F112 -> 12 | G5: =+G112 -> 18 | H5: =+H112 -> 24 | I5: =+I112 -> 30 | J5: =+J112 -> 33.6 | K5: =+K112 -> 39.2 | L5: =+L112 -> 44.2 | M5: =+M112 -> 52
B6: (-) Logo churn | F6: =-F85 -> -1.4 | G6: =-G85 -> -1.8 | H6: =-H85 -> -3 | I6: =-I85 -> -5.888 | J6: =-J85 -> -7.76688 | K6: =-K85 -> -9.4811648 | L6: =-L85 -> -11.502158 | M6: =-M85 -> -13.606776
B7: (+) Net upsell/(downsell) | F7: =+F98 -> 0 | G7: =+G98 -> 0 | H7: =+H98 -> 0 | I7: =+I98 -> 0 | J7: =+J98 -> 0 | K7: =+K98 -> 0 | L7: =+L98 -> 0 | M7: =+M98 -> 0
B8: ARR, ending | F8: =SUM(F4:F7) -> 22.6 | G8: =SUM(G4:G7) -> 38.8 | H8: =SUM(H4:H7) -> 59.8 | I8: =SUM(I4:I7) -> 83.912 | J8: =SUM(J4:J7) -> 109.74512 | K8: =SUM(K4:K7) -> 139.46396 | L8: =SUM(L4:L7) -> 172.1618 | M8: =SUM(M4:M7) -> 210.55502
B10: % GAAP recognition | F10: 0.85 | G10: 0.85 | H10: 0.85 | I10: 0.85 | J10: 0.85 | K10: 0.85 | L10: 0.85 | M10: 0.85
B11: Recognized revenue | F11: =+F10*F8 -> 19.21 | G11: =+G10*G8 -> 32.98 | H11: =+H10*H8 -> 50.83 | I11: =+I10*I8 -> 71.3252 | J11: =+J10*J8 -> 93.283352 | K11: =+K10*K8 -> 118.54436 | L11: =+L10*L8 -> 146.33753 | M11: =+M10*M8 -> 178.97177
B12: % growth | G12: =+IFERROR(G11/F11-1, "n/a") -> 0.71681416 | H12: =+IFERROR(H11/G11-1, "n/a") -> 0.54123711 | I12: =+IFERROR(I11/H11-1, "n/a") -> 0.4032107 | J12: =+IFERROR(J11/I11-1, "n/a") -> 0.30785966 | K12: =+IFERROR(K11/J11-1, "n/a") -> 0.27079869 | L12: =+IFERROR(L11/K11-1, "n/a") -> 0.23445371 | M12: =+IFERROR(M11/L11-1, "n/a") -> 0.22300664
B15: ARR Build | M15: $ millions
B16: Customers by cohort | F16: =+F$3 -> -2 | G16: =+G$3 -> -1 | H16: =+H$3 -> 0 | I16: =+I$3 -> 1 | J16: =+J$3 -> 2 | K16: =+K$3 -> 3 | L16: =+L$3 -> 4 | M16: =+M$3 -> 5
C17: New logos
B18: Before Year -2 | C18: n/a | F18: 53 | G18: 48 | H18: 45 | I18: =H18*I34 -> 43.2 | J18: =I18*J34 -> 41.472 | K18: =J18*K34 -> 39.81312 | L18: =K18*L34 -> 38.220595 | M18: =L18*M34 -> 36.691771
B19: -2 | C19: =+F120 -> 60 | F19: =+$C19 -> 60 | G19: 56 | H19: 54 | I19: =H19*I35 -> 50.76 | J19: =I19*J35 -> 48.7296 | K19: =J19*K35 -> 46.780416 | L19: =K19*L35 -> 44.909199 | M19: =L19*M35 -> 43.112831
B20: -1 | C20: =+G120 -> 90 | G20: =+$C20 -> 90 | H20: 80 | I20: =H20*I36 -> 73.6 | J20: =I20*J36 -> 69.184 | K20: =J20*K36 -> 66.41664 | L20: =K20*L36 -> 63.759974 | M20: =L20*M36 -> 61.209575
B21: 0 | C21: =+H120 -> 120 | H21: =+$C21 -> 120 | I21: =H21*I37 -> 102 | J21: =I21*J37 -> 93.84 | K21: =J21*K37 -> 88.2096 | L21: =K21*L37 -> 84.681216 | M21: =L21*M37 -> 81.293967
B22: 1 | C22: =+I120 -> 150 | I22: =+$C22 -> 150 | J22: =I22*J38 -> 127.5 | K22: =J22*K38 -> 117.3 | L22: =K22*L38 -> 110.262 | M22: =L22*M38 -> 105.85152
B23: 2 | C23: =+J120 -> 168 | J23: =+$C23 -> 168 | K23: =J23*K39 -> 142.8 | L23: =K23*L39 -> 131.376 | M23: =L23*M39 -> 123.49344
B24: 3 | C24: =+K120 -> 196 | K24: =+$C24 -> 196 | L24: =K24*L40 -> 166.6 | M24: =L24*M40 -> 153.272
B25: 4 | C25: =+L120 -> 221 | L25: =+$C25 -> 221 | M25: =L25*M41 -> 187.85
B26: 5 | C26: =+M120 -> 260 | M26: =+$C26 -> 260
B27: Total | F27: =SUM(F18:F26) -> 113 | G27: =SUM(G18:G26) -> 194 | H27: =SUM(H18:H26) -> 299 | I27: =SUM(I18:I26) -> 419.56 | J27: =SUM(J18:J26) -> 548.7256 | K27: =SUM(K18:K26) -> 697.31978 | L27: =SUM(L18:L26) -> 860.80898 | M27: =SUM(M18:M26) -> 1052.7751
B30: Use this retention curve unless given otherwise --> | E30: Year 0 | F30: +1 Year | G30: +2 Years | H30: +3 Years | I30: Beyond
B31: Customer retention % | E31: 0.85 | F31: 0.92 | G31: 0.94 | H31: 0.96 | I31: 0.96
B33: Retention % | F33: =+F$3 -> -2 | G33: =+G$3 -> -1 | H33: =+H$3 -> 0 | I33: =+I$3 -> 1 | J33: =+J$3 -> 2 | K33: =+K$3 -> 3 | L33: =+L$3 -> 4 | M33: =+M$3 -> 5
B34: =+B18 -> Before Year -2 | G34: =+G18/F18 -> 0.90566038 | H34: =+H18/G18 -> 0.9375 | I34: 0.96 | J34: 0.96 | K34: 0.96 | L34: 0.96 | M34: 0.96
B35: =+B19 -> -2 | G35: =+G19/F19 -> 0.93333333 | H35: =+H19/G19 -> 0.96428571 | I35: 0.94 | J35: 0.96 | K35: 0.96 | L35: 0.96 | M35: 0.96
B36: =+B20 -> -1 | H36: =+H20/G20 -> 0.88888889 | I36: 0.92 | J36: 0.94 | K36: 0.96 | L36: 0.96 | M36: 0.96
B37: =+B21 -> 0 | I37: 0.85 | J37: 0.92 | K37: 0.94 | L37: 0.96 | M37: 0.96
B38: =+B22 -> 1 | J38: 0.85 | K38: 0.92 | L38: 0.94 | M38: 0.96
B39: =+B23 -> 2 | K39: 0.85 | L39: 0.92 | M39: 0.94
B40: =+B24 -> 3 | L40: 0.85 | M40: 0.92
B41: =+B25 -> 4 | M41: 0.85
B42: =+B26 -> 5
B43: Total
B46: Churned customers | F46: =+F$3 -> -2 | G46: =+G$3 -> -1 | H46: =+H$3 -> 0 | I46: =+I$3 -> 1 | J46: =+J$3 -> 2 | K46: =+K$3 -> 3 | L46: =+L$3 -> 4 | M46: =+M$3 -> 5
B47: =+B34 -> Before Year -2 | F47: 7 | G47: =+F18-G18 -> 5 | H47: =+G18-H18 -> 3 | I47: =+H18-I18 -> 1.8 | J47: =+I18-J18 -> 1.728 | K47: =+J18-K18 -> 1.65888 | L47: =+K18-L18 -> 1.5925248 | M47: =+L18-M18 -> 1.5288238
B48: =+B35 -> -2 | G48: =+F19-G19 -> 4 | H48: =+G19-H19 -> 2 | I48: =+H19-I19 -> 3.24 | J48: =+I19-J19 -> 2.0304 | K48: =+J19-K19 -> 1.949184 | L48: =+K19-L19 -> 1.8712166 | M48: =+L19-M19 -> 1.796368
B49: =+B36 -> -1 | H49: =+G20-H20 -> 10 | I49: =+H20-I20 -> 6.4 | J49: =+I20-J20 -> 4.416 | K49: =+J20-K20 -> 2.76736 | L49: =+K20-L20 -> 2.6566656 | M49: =+L20-M20 -> 2.550399
B50: =+B37 -> 0 | I50: =+H21-I21 -> 18 | J50: =+I21-J21 -> 8.16 | K50: =+J21-K21 -> 5.6304 | L50: =+K21-L21 -> 3.528384 | M50: =+L21-M21 -> 3.3872486
B51: =+B38 -> 1 | J51: =+I22-J22 -> 22.5 | K51: =+J22-K22 -> 10.2 | L51: =+K22-L22 -> 7.038 | M51: =+L22-M22 -> 4.41048
B52: =+B39 -> 2 | K52: =+J23-K23 -> 25.2 | L52: =+K23-L23 -> 11.424 | M52: =+L23-M23 -> 7.88256
B53: =+B40 -> 3 | L53: =+K24-L24 -> 29.4 | M53: =+L24-M24 -> 13.328
B54: =+B41 -> 4 | M54: =+L25-M25 -> 33.15
B55: =+B42 -> 5
B56: Total | F56: =SUM(F47:F55) -> 7 | G56: =SUM(G47:G55) -> 9 | H56: =SUM(H47:H55) -> 15 | I56: =SUM(I47:I55) -> 29.44 | J56: =SUM(J47:J55) -> 38.8344 | K56: =SUM(K47:K55) -> 47.405824 | L56: =SUM(L47:L55) -> 57.510791 | M56: =SUM(M47:M55) -> 68.033879
B59: Use this pricing curve unless given otherwise --> | E59: Year 0 | F59: +1 Year | G59: +2 Years | H59: +3 Years | I59: Beyond
B60: Pricing | E60: 0.2 | F60: 0.2 | G60: 0.2 | H60: 0.2 | I60: 0.2
B62: Average revenue per customer ("ARPU") | E62: -3 | F62: =+F$3 -> -2 | G62: =+G$3 -> -1 | H62: =+H$3 -> 0 | I62: =+I$3 -> 1 | J62: =+J$3 -> 2 | K62: =+K$3 -> 3 | L62: =+L$3 -> 4 | M62: =+M$3 -> 5
B63: =+B47 -> Before Year -2 | E63: 0.2 | F63: 0.2 | G63: 0.2 | H63: 0.2 | I63: 0.2 | J63: 0.2 | K63: 0.2 | L63: 0.2 | M63: 0.2
B64: =+B48 -> -2 | F64: 0.2 | G64: 0.2 | H64: 0.2 | I64: 0.2 | J64: 0.2 | K64: 0.2 | L64: 0.2 | M64: 0.2
B65: =+B49 -> -1 | G65: 0.2 | H65: 0.2 | I65: 0.2 | J65: 0.2 | K65: 0.2 | L65: 0.2 | M65: 0.2
B66: =+B50 -> 0 | H66: 0.2 | I66: 0.2 | J66: 0.2 | K66: 0.2 | L66: 0.2 | M66: 0.2
B67: =+B51 -> 1 | I67: 0.2 | J67: 0.2 | K67: 0.2 | L67: 0.2 | M67: 0.2
B68: =+B52 -> 2 | J68: 0.2 | K68: 0.2 | L68: 0.2 | M68: 0.2
B69: =+B53 -> 3 | K69: 0.2 | L69: 0.2 | M69: 0.2
B70: =+B54 -> 4 | L70: 0.2 | M70: 0.2
B71: =+B55 -> 5 | M71: 0.2
B72: Average total | F72: =+IFERROR(F111/F27, "n/a") -> 0.2 | G72: =+IFERROR(G111/G27, "n/a") -> 0.2 | H72: =+IFERROR(H111/H27, "n/a") -> 0.2 | I72: =+IFERROR(I111/I27, "n/a") -> 0.2 | J72: =+IFERROR(J111/J27, "n/a") -> 0.2 | K72: =+IFERROR(K111/K27, "n/a") -> 0.2 | L72: =+IFERROR(L111/L27, "n/a") -> 0.2 | M72: =+IFERROR(M111/M27, "n/a") -> 0.2
B75: Churn by cohort - $ | F75: =+F$3 -> -2 | G75: =+G$3 -> -1 | H75: =+H$3 -> 0 | I75: =+I$3 -> 1 | J75: =+J$3 -> 2 | K75: =+K$3 -> 3 | L75: =+L$3 -> 4 | M75: =+M$3 -> 5
B76: =+B47 -> Before Year -2 | F76: =+F47*E63 -> 1.4 | G76: =+G47*F63 -> 1 | H76: =+H47*G63 -> 0.6 | I76: =+I47*H63 -> 0.36 | J76: =+J47*I63 -> 0.3456 | K76: =+K47*J63 -> 0.331776 | L76: =+L47*K63 -> 0.31850496 | M76: =+M47*L63 -> 0.30576476
B77: =+B48 -> -2 | G77: =+G48*F64 -> 0.8 | H77: =+H48*G64 -> 0.4 | I77: =+I48*H64 -> 0.648 | J77: =+J48*I64 -> 0.40608 | K77: =+K48*J64 -> 0.3898368 | L77: =+L48*K64 -> 0.37424333 | M77: =+M48*L64 -> 0.35927359
B78: =+B49 -> -1 | H78: =+H49*G65 -> 2 | I78: =+I49*H65 -> 1.28 | J78: =+J49*I65 -> 0.8832 | K78: =+K49*J65 -> 0.553472 | L78: =+L49*K65 -> 0.53133312 | M78: =+M49*L65 -> 0.5100798
B79: =+B50 -> 0 | I79: =+I50*H66 -> 3.6 | J79: =+J50*I66 -> 1.632 | K79: =+K50*J66 -> 1.12608 | L79: =+L50*K66 -> 0.7056768 | M79: =+M50*L66 -> 0.67744973
B80: =+B51 -> 1 | J80: =+J51*I67 -> 4.5 | K80: =+K51*J67 -> 2.04 | L80: =+L51*K67 -> 1.4076 | M80: =+M51*L67 -> 0.882096
B81: =+B52 -> 2 | K81: =+K52*J68 -> 5.04 | L81: =+L52*K68 -> 2.2848 | M81: =+M52*L68 -> 1.576512
B82: =+B53 -> 3 | L82: =+L53*K69 -> 5.88 | M82: =+M53*L69 -> 2.6656
B83: =+B54 -> 4 | M83: =+M54*L70 -> 6.63
B84: =+B55 -> 5
B85: Total | F85: =SUM(F76:F84) -> 1.4 | G85: =SUM(G76:G84) -> 1.8 | H85: =SUM(H76:H84) -> 3 | I85: =SUM(I76:I84) -> 5.888 | J85: =SUM(J76:J84) -> 7.76688 | K85: =SUM(K76:K84) -> 9.4811648 | L85: =SUM(L76:L84) -> 11.502158 | M85: =SUM(M76:M84) -> 13.606776
B88: Net upsell/(downsell) - $ | F88: =+F$3 -> -2 | G88: =+G$3 -> -1 | H88: =+H$3 -> 0 | I88: =+I$3 -> 1 | J88: =+J$3 -> 2 | K88: =+K$3 -> 3 | L88: =+L$3 -> 4 | M88: =+M$3 -> 5
B89: =+B34 -> Before Year -2 | F89: =+F18*(F63-E63) -> 0 | G89: =+G18*(G63-F63) -> 0 | H89: =+H18*(H63-G63) -> 0 | I89: =+I18*(I63-H63) -> 0 | J89: =+J18*(J63-I63) -> 0 | K89: =+K18*(K63-J63) -> 0 | L89: =+L18*(L63-K63) -> 0 | M89: =+M18*(M63-L63) -> 0
B90: =+B35 -> -2 | G90: =+G19*(G64-F64) -> 0 | H90: =+H19*(H64-G64) -> 0 | I90: =+I19*(I64-H64) -> 0 | J90: =+J19*(J64-I64) -> 0 | K90: =+K19*(K64-J64) -> 0 | L90: =+L19*(L64-K64) -> 0 | M90: =+M19*(M64-L64) -> 0
B91: =+B36 -> -1 | H91: =+H20*(H65-G65) -> 0 | I91: =+I20*(I65-H65) -> 0 | J91: =+J20*(J65-I65) -> 0 | K91: =+K20*(K65-J65) -> 0 | L91: =+L20*(L65-K65) -> 0 | M91: =+M20*(M65-L65) -> 0
B92: =+B37 -> 0 | I92: =+I21*(I66-H66) -> 0 | J92: =+J21*(J66-I66) -> 0 | K92: =+K21*(K66-J66) -> 0 | L92: =+L21*(L66-K66) -> 0 | M92: =+M21*(M66-L66) -> 0
B93: =+B38 -> 1 | J93: =+J22*(J67-I67) -> 0 | K93: =+K22*(K67-J67) -> 0 | L93: =+L22*(L67-K67) -> 0 | M93: =+M22*(M67-L67) -> 0
B94: =+B39 -> 2 | K94: =+K23*(K68-J68) -> 0 | L94: =+L23*(L68-K68) -> 0 | M94: =+M23*(M68-L68) -> 0
B95: =+B40 -> 3 | L95: =+L24*(L69-K69) -> 0 | M95: =+M24*(M69-L69) -> 0
B96: =+B41 -> 4 | M96: =+M25*(M70-L70) -> 0
B97: =+B42 -> 5
B98: Total | F98: =SUM(F89:F97) -> 0 | G98: =SUM(G89:G97) -> 0 | H98: =SUM(H89:H97) -> 0 | I98: =SUM(I89:I97) -> 0 | J98: =SUM(J89:J97) -> 0 | K98: =SUM(K89:K97) -> 0 | L98: =SUM(L89:L97) -> 0 | M98: =SUM(M89:M97) -> 0
B101: Total ARR by cohort | F101: =+F$3 -> -2 | G101: =+G$3 -> -1 | H101: =+H$3 -> 0 | I101: =+I$3 -> 1 | J101: =+J$3 -> 2 | K101: =+K$3 -> 3 | L101: =+L$3 -> 4 | M101: =+M$3 -> 5
B102: =+B63 -> Before Year -2 | F102: =+F63*F18 -> 10.6 | G102: =+G63*G18 -> 9.6 | H102: =+H63*H18 -> 9 | I102: =+I63*I18 -> 8.64 | J102: =+J63*J18 -> 8.2944 | K102: =+K63*K18 -> 7.962624 | L102: =+L63*L18 -> 7.644119 | M102: =+M63*M18 -> 7.3383543
B103: =+B64 -> -2 | F103: =+F64*F19 -> 12 | G103: =+G64*G19 -> 11.2 | H103: =+H64*H19 -> 10.8 | I103: =+I64*I19 -> 10.152 | J103: =+J64*J19 -> 9.74592 | K103: =+K64*K19 -> 9.3560832 | L103: =+L64*L19 -> 8.9818399 | M103: =+M64*M19 -> 8.6225663
B104: =+B65 -> -1 | G104: =+G65*G20 -> 18 | H104: =+H65*H20 -> 16 | I104: =+I65*I20 -> 14.72 | J104: =+J65*J20 -> 13.8368 | K104: =+K65*K20 -> 13.283328 | L104: =+L65*L20 -> 12.751995 | M104: =+M65*M20 -> 12.241915
B105: =+B66 -> 0 | H105: =+H66*H21 -> 24 | I105: =+I66*I21 -> 20.4 | J105: =+J66*J21 -> 18.768 | K105: =+K66*K21 -> 17.64192 | L105: =+L66*L21 -> 16.936243 | M105: =+M66*M21 -> 16.258793
B106: =+B67 -> 1 | I106: =+I67*I22 -> 30 | J106: =+J67*J22 -> 25.5 | K106: =+K67*K22 -> 23.46 | L106: =+L67*L22 -> 22.0524 | M106: =+M67*M22 -> 21.170304
B107: =+B68 -> 2 | J107: =+J68*J23 -> 33.6 | K107: =+K68*K23 -> 28.56 | L107: =+L68*L23 -> 26.2752 | M107: =+M68*M23 -> 24.698688
B108: =+B69 -> 3 | K108: =+K69*K24 -> 39.2 | L108: =+L69*L24 -> 33.32 | M108: =+M69*M24 -> 30.6544
B109: =+B70 -> 4 | L109: =+L70*L25 -> 44.2 | M109: =+M70*M25 -> 37.57
B110: =+B71 -> 5 | M110: =+M71*M26 -> 52
B111: Total ARR | F111: =SUM(F102:F110) -> 22.6 | G111: =SUM(G102:G110) -> 38.8 | H111: =SUM(H102:H110) -> 59.8 | I111: =SUM(I102:I110) -> 83.912 | J111: =SUM(J102:J110) -> 109.74512 | K111: =SUM(K102:K110) -> 139.46396 | L111: =SUM(L102:L110) -> 172.1618 | M111: =SUM(M102:M110) -> 210.55502
B112: ARR from new customers | F112: =+F103 -> 12 | G112: =+G104 -> 18 | H112: =+H105 -> 24 | I112: =+I106 -> 30 | J112: =+J107 -> 33.6 | K112: =+K108 -> 39.2 | L112: =+L109 -> 44.2 | M112: =+M110 -> 52
B115: Drivers & assumptions | M115: $ millions
B116: Sales employees | F116: 16 | G116: 24 | H116: 32 | I116: 40 | J116: 48 | K116: 56 | L116: 68 | M116: 80
B117: Marketing employees | F117: 4 | G117: 5 | H117: 5 | I117: 6 | J117: 8 | K117: 10 | L117: 12 | M117: 14
B118: Implementation employees | F118: 8 | G118: 20 | H118: 30 | I118: 40 | J118: 60 | K118: 65 | L118: 70 | M118: 75
B119: New sales wins per sales employee | F119: 3.75 | G119: 3.75 | H119: 3.75 | I119: 3.75 | J119: 3.5 | K119: 3.5 | L119: 3.25 | M119: 3.25
B120: New customer wins | F120: =+F119*F116 -> 60 | G120: =+G119*G116 -> 90 | H120: =+H119*H116 -> 120 | I120: =+I119*I116 -> 150 | J120: =+J119*J116 -> 168 | K120: =+K119*K116 -> 196 | L120: =+L119*L116 -> 221 | M120: =+M119*M116 -> 260
...

Sheet Sensitivities (End)
B2: Sensitivities | J2: $ millions
E3: 0 | F3: 1 | G3: =F3+1 -> 2 | H3: =G3+1 -> 3 | I3: =H3+1 -> 4 | J3: =I3+1 -> 5
B4: Revenue | E4: ='Model (End)'!E61 -> 50.83 | F4: =+OFFSET(F4, 'Model (End)'!$J$8, 0) -> 71.3252 | G4: =+OFFSET(G4, 'Model (End)'!$J$8, 0) -> 93.283352 | H4: =+OFFSET(H4, 'Model (End)'!$J$8, 0) -> 118.54436 | I4: =+OFFSET(I4, 'Model (End)'!$J$8, 0) -> 146.33753 | J4: =+OFFSET(J4, 'Model (End)'!$J$8, 0) -> 178.97177
B5: =+'Model (End)'!$G$9 -> Management case | E5: =+E4 -> 50.83 | F5: 71.162 | G5: 99.6268 | H5: 139.47752 | I5: 195.26853 | J5: 273.37594
B6: =+'Model (End)'!$G$10 -> Base case | E6: =+E5 -> 50.83 | F6: =+'Cohorts (End)'!I11 -> 71.3252 | G6: =+'Cohorts (End)'!J11 -> 93.283352 | H6: =+'Cohorts (End)'!K11 -> 118.54436 | I6: =+'Cohorts (End)'!L11 -> 146.33753 | J6: =+'Cohorts (End)'!M11 -> 178.97177
B8: YoY growth | D8: CAGR
B9: =+'Model (End)'!$G$9 -> Management case | D9: =((J5/E5)^(1/5)-1) -> 0.4 | F9: =+F5/E5-1 -> 0.4 | G9: =+G5/F5-1 -> 0.4 | H9: =+H5/G5-1 -> 0.4 | I9: =+I5/H5-1 -> 0.4 | J9: =+J5/I5-1 -> 0.4
B10: =+'Model (End)'!$G$10 -> Base case | D10: =((J6/E6)^(1/5)-1) -> 0.2862722 | F10: =+F6/E6-1 -> 0.4032107 | G10: =+G6/F6-1 -> 0.30785966 | H10: =+H6/G6-1 -> 0.27079869 | I10: =+I6/H6-1 -> 0.23445371 | J10: =+J6/I6-1 -> 0.22300664
B13: Selling & marketing expenses | E13: =+'Model (End)'!E67 -> 20.75 | F13: =+OFFSET(F13, 'Model (End)'!$J$8, 0) -> 26.34 | G13: =+OFFSET(G13, 'Model (End)'!$J$8, 0) -> 34.32 | H13: =+OFFSET(H13, 'Model (End)'!$J$8, 0) -> 39.3 | I13: =+OFFSET(I13, 'Model (End)'!$J$8, 0) -> 45.88 | J13: =+OFFSET(J13, 'Model (End)'!$J$8, 0) -> 52.46
B14: =+'Model (End)'!$G$9 -> Management case | E14: =+E13 -> 20.75 | F14: 28.4648 | G14: 37.858184 | H14: 50.211907 | I14: 66.3913 | J14: 87.480301
B15: =+'Model (End)'!$G$10 -> Base case | E15: =+E14 -> 20.75 | F15: ='Cohorts (End)'!I132 -> 26.34 | G15: ='Cohorts (End)'!J132 -> 34.32 | H15: ='Cohorts (End)'!K132 -> 39.3 | I15: ='Cohorts (End)'!L132 -> 45.88 | J15: ='Cohorts (End)'!M132 -> 52.46
B17: % of revenue | D17: CAGR
B18: =+'Model (End)'!$G$9 -> Management case | D18: =((J14/E14)^(1/5)-1) -> 0.33345521 | F18: =+F14/F5 -> 0.4 | G18: =+G14/G5 -> 0.38 | H18: =+H14/H5 -> 0.36 | I18: =+I14/I5 -> 0.34 | J18: =+J14/J5 -> 0.32
B19: =+'Model (End)'!$G$10 -> Base case | D19: =((J15/E15)^(1/5)-1) -> 0.20382134 | F19: =+F15/F6 -> 0.36929444 | G19: =+G15/G6 -> 0.36791131 | H19: =+H15/H6 -> 0.33152146 | I19: =+I15/I6 -> 0.31352177 | J19: =+J15/J6 -> 0.29311886

Sheet Valuation (End)
B2: Public trading comparables | AC2: $ millions
E3: Valuation metrics | M3: Operating metrics
C4: Enterprise | E4: EV/Revenue | I4: EV/EBITDA | M4: Revenue | Q4: Revenue Growth | V4: EBITDA | Z4: EBITDA margin
C5: Value | E5: LTM | F5: NTM | G5: NTM+1 | I5: LTM | J5: NTM | K5: NTM+1 | M5: LTM | N5: NTM | O5: NTM+1 | Q5: LTM | R5: NTM | S5: NTM+1 | T5: CAGR | V5: LTM | W5: NTM | X5: NTM+1 | Z5: LTM | AA5: NTM | AB5: NTM+1 | AC5: Average
B7: Company 1 | C7: 9536 | E7: =+$C7/M7 -> 18.16381 | F7: =+$C7/N7 -> 10.684594 | G7: =+$C7/O7 -> 6.6778711 | I7: =+$C7/V7 -> -181.6381 | J7: =+$C7/W7 -> -213.69188 | K7: =+$C7/X7 -> 333.89356 | M7: 525 | N7: =+M7*(1+R7) -> 892.5 | O7: =+N7*(1+S7) -> 1428 | Q7: 0.87 | R7: 0.7 | S7: 0.6 | T7: =(O7/M7)^(1/2)-1 -> 0.64924225 | V7: =+Z7*M7 -> -52.5 | W7: =+AA7*N7 -> -44.625 | X7: =+AB7*O7 -> 28.56 | Z7: -0.1 | AA7: -0.05 | AB7: 0.02 | AC7: =AVERAGE(Z7:AB7) -> -0.043333333
B8: Company 2 | C8: 5551 | E8: =+$C8/M8 -> 4.6258333 | F8: =+$C8/N8 -> 4.1302083 | G8: =+$C8/O8 -> 3.789182 | I8: =+$C8/V8 -> 14.017677 | J8: =+$C8/W8 -> 11.800595 | K8: =+$C8/X8 -> 10.826234 | M8: 1200 | N8: =+M8*(1+R8) -> 1344 | O8: =+N8*(1+S8) -> 1464.96 | Q8: 0.08 | R8: 0.12 | S8: 0.09 | T8: =(O8/M8)^(1/2)-1 -> 0.10489819 | V8: =+Z8*M8 -> 396 | W8: =+AA8*N8 -> 470.4 | X8: =+AB8*O8 -> 512.736 | Z8: 0.33 | AA8: 0.35 | AB8: 0.35 | AC8: =AVERAGE(Z8:AB8) -> 0.34333333
B9: Company 3 | C9: 5078 | E9: =+$C9/M9 -> 15.295181 | F9: =+$C9/N9 -> 8.4973226 | G9: =+$C9/O9 -> 4.9984251 | I9: =+$C9/V9 -> -38.237952 | J9: =+$C9/W9 -> -28.324409 | K9: =+$C9/X9 -> -24.992125 | M9: 332 | N9: =+M9*(1+R9) -> 597.6 | O9: =+N9*(1+S9) -> 1015.92 | Q9: 0.92 | R9: 0.8 | S9: 0.7 | T9: =(O9/M9)^(1/2)-1 -> 0.74928557 | V9: =+Z9*M9 -> -132.8 | W9: =+AA9*N9 -> -179.28 | X9: =+AB9*O9 -> -203.184 | Z9: -0.4 | AA9: -0.3 | AB9: -0.2 | AC9: =AVERAGE(Z9:AB9) -> -0.3
B10: Company 4 | C10: 896 | E10: =+$C10/M10 -> 11.487179 | F10: =+$C10/N10 -> 7.6074036 | G10: =+$C10/O10 -> 5.3953217 | I10: =+$C10/V10 -> -45.948718 | J10: =+$C10/W10 -> -36.225732 | K10: =+$C10/X10 -> -28.39643 | M10: 78 | N10: =+M10*(1+R10) -> 117.78 | O10: =+N10*(1+S10) -> 166.0698 | Q10: 0.66 | R10: 0.51 | S10: 0.41 | T10: =(O10/M10)^(1/2)-1 -> 0.45914358 | V10: =+Z10*M10 -> -19.5 | W10: =+AA10*N10 -> -24.7338 | X10: =+AB10*O10 -> -31.553262 | Z10: -0.25 | AA10: -0.21 | AB10: -0.19 | AC10: =AVERAGE(Z10:AB10) -> -0.21666667
B11: Company 5 | C11: 7412 | E11: =+$C11/M11 -> 12.332779 | F11: =+$C11/N11 -> 10.108835 | G11: =+$C11/O11 -> 8.087068 | I11: =+$C11/V11 -> -246.65557 | J11: =+$C11/W11 -> 336.96117 | K11: =+$C11/X11 -> 80.87068 | M11: 601 | N11: =+M11*(1+R11) -> 733.22 | O11: =+N11*(1+S11) -> 916.525 | Q11: 0.27 | R11: 0.22 | S11: 0.25 | T11: =(O11/M11)^(1/2)-1 -> 0.2349089 | V11: =+Z11*M11 -> -30.05 | W11: =+AA11*N11 -> 21.9966 | X11: =+AB11*O11 -> 91.6525 | Z11: -0.05 | AA11: 0.03 | AB11: 0.1 | AC11: =AVERAGE(Z11:AB11) -> 0.026666667
B12: Company 6 | C12: 4301 | E12: =+$C12/M12 -> 14.336667 | F12: =+$C12/N12 -> 10.779449 | G12: =+$C12/O12 -> 8.6235589 | I12: =+$C12/V12 -> 119.47222 | J12: =+$C12/W12 -> 71.862991 | K12: =+$C12/X12 -> 53.897243 | M12: 300 | N12: =+M12*(1+R12) -> 399 | O12: =+N12*(1+S12) -> 498.75 | Q12: 0.35 | R12: 0.33 | S12: 0.25 | T12: =(O12/M12)^(1/2)-1 -> 0.2893797 | V12: =+Z12*M12 -> 36 | W12: =+AA12*N12 -> 59.85 | X12: =+AB12*O12 -> 79.8 | Z12: 0.12 | AA12: 0.15 | AB12: 0.16 | AC12: =AVERAGE(Z12:AB12) -> 0.14333333
B13: Company 7 | C13: 5523 | E13: =+$C13/M13 -> 24.99095 | F13: =+$C13/N13 -> 12.190707 | G13: =+$C13/O13 -> 6.5895716 | I13: =+$C13/V13 -> -131.53132 | J13: =+$C13/W13 -> -67.726152 | K13: =+$C13/X13 -> -38.762186 | M13: 221 | N13: =+M13*(1+R13) -> 453.05 | O13: =+N13*(1+S13) -> 838.1425 | Q13: 1.08 | R13: 1.05 | S13: 0.85 | T13: =(O13/M13)^(1/2)-1 -> 0.94743421 | V13: =+Z13*M13 -> -41.99 | W13: =+AA13*N13 -> -81.549 | X13: =+AB13*O13 -> -142.48423 | Z13: -0.19 | AA13: -0.18 | AB13: -0.17 | AC13: =AVERAGE(Z13:AB13) -> -0.18
B14: Company 8 | C14: 2217 | E14: =+$C14/M14 -> 5.5012407 | F14: =+$C14/N14 -> 5.0470098 | G14: =+$C14/O14 -> 4.7168316 | I14: =+$C14/V14 -> 15.717831 | J14: =+$C14/W14 -> 14.844147 | K14: =+$C14/X14 -> 13.873034 | M14: 403 | N14: =+M14*(1+R14) -> 439.27 | O14: =+N14*(1+S14) -> 470.0189 | Q14: 0.1 | R14: 0.09 | S14: 0.07 | T14: =(O14/M14)^(1/2)-1 -> 0.079953703 | V14: =+Z14*M14 -> 141.05 | W14: =+AA14*N14 -> 149.3518 | X14: =+AB14*O14 -> 159.80643 | Z14: 0.35 | AA14: 0.34 | AB14: 0.34 | AC14: =AVERAGE(Z14:AB14) -> 0.34333333
B16: Entire comp set
B17: Average | E17: =AVERAGE(E7:E14) -> 13.341705 | F17: =AVERAGE(F7:F14) -> 8.6306912 | G17: =AVERAGE(G7:G14) -> 6.1097287 | I17: =AVERAGE(I7:I14) -> -61.850491 | J17: =AVERAGE(J7:J14) -> 11.187591 | K17: =AVERAGE(K7:K14) -> 50.151251
B18: Median | E18: =MEDIAN(E7:E14) -> 13.334723 | F18: =MEDIAN(F7:F14) -> 9.3030788 | G18: =MEDIAN(G7:G14) -> 5.9924467 | I18: =MEDIAN(I7:I14) -> -42.093335 | J18: =MEDIAN(J7:J14) -> -8.2619068 | K18: =MEDIAN(K7:K14) -> 12.349634
B20: Selected comps
B21: Average | E21: =AVERAGE(E11:E12) -> 13.334723 | F21: =AVERAGE(F11:F12) -> 10.444142 | G21: =AVERAGE(G11:G12) -> 8.3553134 | I21: =AVERAGE(I11:I12) -> -63.591676 | J21: =AVERAGE(J11:J12) -> 204.41208 | K21: =AVERAGE(K11:K12) -> 67.383962
B24: Precedent transaction comparables | AC24: $ millions
C25: Acquisition | E25: Valuation metrics | M25: Operating metrics
C26: Enterprise | E26: EV/Revenue | I26: EV/EBITDA | M26: Revenue | Q26: Revenue Growth | V26: EBITDA | Z26: EBITDA margin
C27: Value | E27: LTM | F27: NTM | G27: NTM+1 | I27: LTM | J27: NTM | K27: NTM+1 | M27: LTM | N27: NTM | O27: NTM+1 | Q27: LTM | R27: NTM | S27: NTM+1 | T27: CAGR | V27: LTM | W27: NTM | X27: NTM+1 | Z27: LTM | AA27: NTM | AB27: NTM+1 | AC27: Average
B29: Company A | C29: 3000 | E29: =+$C29/M29 -> 24 | F29: =+$C29/N29 -> 13.333333 | G29: =+$C29/O29 -> 8.2304527 | I29: =+$C29/V29 -> -240 | J29: =+$C29/W29 -> -266.66667 | K29: =+$C29/X29 -> 411.52263 | M29: 125 | N29: =+M29*(1+R29) -> 225 | O29: =+N29*(1+S29) -> 364.5 | Q29: 0.78 | R29: 0.8 | S29: 0.62 | T29: =(O29/M29)^(1/2)-1 -> 0.70762994 | V29: =+Z29*M29 -> -12.5 | W29: =+AA29*N29 -> -11.25 | X29: =+AB29*O29 -> 7.29 | Z29: -0.1 | AA29: -0.05 | AB29: 0.02 | AC29: =AVERAGE(Z29:AB29) -> -0.043333333
B30: Company B | C30: 8800 | E30: =+$C30/M30 -> 9.8104794 | F30: =+$C30/N30 -> 8.0413765 | G30: =+$C30/O30 -> 6.8147259 | I30: =+$C30/V30 -> 54.502663 | J30: =+$C30/W30 -> 47.302215 | K30: =+$C30/X30 -> 37.859588 | M30: 897 | N30: =+M30*(1+R30) -> 1094.34 | O30: =+N30*(1+S30) -> 1291.3212 | Q30: 0.32 | R30: 0.22 | S30: 0.18 | T30: =(O30/M30)^(1/2)-1 -> 0.19983332 | V30: =+Z30*M30 -> 161.46 | W30: =+AA30*N30 -> 186.0378 | X30: =+AB30*O30 -> 232.43782 | Z30: 0.18 | AA30: 0.17 | AB30: 0.18 | AC30: =AVERAGE(Z30:AB30) -> 0.17666667
B31: Company C | C31: 2500 | E31: =+$C31/M31 -> 11.261261 | F31: =+$C31/N31 -> 10.23751 | G31: =+$C31/O31 -> 9.4791761 | I31: =+$C31/V31 -> 28.153153 | J31: =+$C31/W31 -> 24.375024 | K31: =+$C31/X31 -> 22.569467 | M31: 222 | N31: =+M31*(1+R31) -> 244.2 | O31: =+N31*(1+S31) -> 263.736 | Q31: 0.12 | R31: 0.1 | S31: 0.08 | T31: =(O31/M31)^(1/2)-1 -> 0.089954127 | V31: =+Z31*M31 -> 88.8 | W31: =+AA31*N31 -> 102.564 | X31: =+AB31*O31 -> 110.76912 | Z31: 0.4 | AA31: 0.42 | AB31: 0.42 | AC31: =AVERAGE(Z31:AB31) -> 0.41333333
B32: Company D | C32: 1250 | E32: =+$C32/M32 -> 23.584906 | F32: =+$C32/N32 -> 11.792453 | G32: =+$C32/O32 -> 6.0474117 | I32: =+$C32/V32 -> -63.742988 | J32: =+$C32/W32 -> -39.308176 | K32: =+$C32/X32 -> -30.237059 | M32: 53 | N32: =+M32*(1+R32) -> 106 | O32: =+N32*(1+S32) -> 206.7 | Q32: 1.22 | R32: 1 | S32: 0.95 | T32: =(O32/M32)^(1/2)-1 -> 0.97484177 | V32: =+Z32*M32 -> -19.61 | W32: =+AA32*N32 -> -31.8 | X32: =+AB32*O32 -> -41.34 | Z32: -0.37 | AA32: -0.3 | AB32: -0.2 | AC32: =AVERAGE(Z32:AB32) -> -0.29
B33: Company E | C33: 500 | E33: =+$C33/M33 -> 11.904762 | F33: =+$C33/N33 -> 9.1575092 | G33: =+$C33/O33 -> 7.2106371 | I33: =+$C33/V33 -> -99.206349 | J33: =+$C33/W33 -> -183.15018 | K33: =+$C33/X33 -> 144.21274 | M33: 42 | N33: =+M33*(1+R33) -> 54.6 | O33: =+N33*(1+S33) -> 69.342 | Q33: 0.38 | R33: 0.3 | S33: 0.27 | T33: =(O33/M33)^(1/2)-1 -> 0.28491245 | V33: =+Z33*M33 -> -5.04 | W33: =+AA33*N33 -> -2.73 | X33: =+AB33*O33 -> 3.4671 | Z33: -0.12 | AA33: -0.05 | AB33: 0.05 | AC33: =AVERAGE(Z33:AB33) -> -0.04
B35: Entire comp set
B36: Average | E36: =AVERAGE(E29:E33) -> 16.112282 | F36: =AVERAGE(F29:F33) -> 10.512436 | G36: =AVERAGE(G29:G33) -> 7.5564807 | I36: =AVERAGE(I29:I33) -> -64.058704 | J36: =AVERAGE(J29:J33) -> -83.489557 | K36: =AVERAGE(K29:K33) -> 117.18547
B37: Median | E37: =MEDIAN(E29:E33) -> 11.904762 | F37: =MEDIAN(F29:F33) -> 10.23751 | G37: =MEDIAN(G29:G33) -> 7.2106371 | I37: =MEDIAN(I29:I33) -> -63.742988 | J37: =MEDIAN(J29:J33) -> -39.308176 | K37: =MEDIAN(K29:K33) -> 37.859588
B39: Selected comps
B40: Average | E40: =AVERAGE(E33,E30) -> 10.857621 | F40: =AVERAGE(F33,F30) -> 8.5994428 | G40: =AVERAGE(G33,G30) -> 7.0126815 | I40: =AVERAGE(I33,I30) -> -22.351843 | J40: =AVERAGE(J33,J30) -> -67.923984 | K40: =AVERAGE(K33,K30) -> 91.036165
B43: Historical trading comparables - Software index
C45: Median
C46: EV/LTM Rev
B47: 20 quarters ago | C47: 5.2
B48: 19 quarters ago | C48: 5.9
B49: 18 quarters ago | C49: 6.2
B50: 17 quarters ago | C50: 6.5
B51: 16 quarters ago | C51: 7.2
B52: 15 quarters ago | C52: 6.9
B53: 14 quarters ago | C53: 6.7
B54: 13 quarters ago | C54: 6.4
B55: 12 quarters ago | C55: 7.4
B56: 11 quarters ago | C56: 7.7
B57: 10 quarters ago | C57: 8.4
B58: 9 quarters ago | C58: 8.6
... B67: Current quarter | C67: 13.3
B70: Average | C70: =AVERAGE(C47:C67) -> 9.147619
B71: Ratio | C71: =+C70/C67 -> 0.68779091
B74: Proposed valuation | C74: 12
B75: Adjusted valuation | C75: =+C74*70% -> 8.4
