Workbook
Name different: #REF!
Name mike: 'ARR Waterfall'!$A$8
Name unit: 'ARR Waterfall'!$A$1
Name unit: 'Billing Waterfall'!#REF!
Name unit: Capitalizations!#REF!
Name unit: Cohorts!$A$1
Name unit: Model!#REF!
Name unit: 'Model (Start)'!#REF!
Name unit: 'SaaS Metrics'!#REF!
Name unit: Transaction!#REF!
Name unit: #REF!

Sheet Resources
B4: GO, GO, GO!
B5: Practice really does make perfect!
B6: You got this! :-)
B10: This template is part of a comprehensive course for SaaS investing roles & interviews.
B11: For more video courses and tutorials:
B13: =HYPERLINK("https://GrowthEquityInterviewGuide.com", "GrowthEquityInterviewGuide.com") -> GrowthEquityInterviewGuide.com
B25: All rights reserved. Growth Equity Interview Guide.

Sheet Start ->

Sheet Model (Start)
B2: Income Statement | AH2: $ in millions, except noted
C3: =YEAR(C4) -> 2020 | D3: =YEAR(D4) -> 2020 | E3: =YEAR(E4) -> 2020 | F3: =YEAR(F4) -> 2020 | G3: =YEAR(G4) -> 2021 | H3: =YEAR(H4) -> 2021 | I3: =YEAR(I4) -> 2021 | J3: =YEAR(J4) -> 2021 | ... AH3: =YEAR(AH4) -> 2027
C4: 43921 | D4: =EOMONTH(C4, 3) -> 44012 | E4: =EOMONTH(D4, 3) -> 44104 | F4: =EOMONTH(E4, 3) -> 44196 | G4: =EOMONTH(F4, 3) -> 44286 | H4: =EOMONTH(G4, 3) -> 44377 | I4: =EOMONTH(H4, 3) -> 44469 | J4: =EOMONTH(I4, 3) -> 44561 | K4: =EOMONTH(J4, 3) -> 44651 | ... AH4: =EOMONTH(AG4, 3) -> 46752
B5: GAAP Revenue | C5: 73.455054 | D5: 73.869141 | E5: 77.137926 | F5: 78.14858 | G5: 76.99011 | H5: 76.949729 | I5: 77.996212 | J5: 78.018904 | K5: 79.197922 | L5: 80.146255 | M5: 81.768686 | N5: 82.397303
B6: % YoY Growth | G6: =G5/C5-1 -> 0.04812543 | H6: =H5/D5-1 -> 0.041703321 | I6: =I5/E5-1 -> 0.011126641 | J6: =J5/F5-1 -> -0.0016593573 | K6: =K5/G5-1 -> 0.028676573 | L6: =L5/H5-1 -> 0.041540435 | M6: =M5/I5-1 -> 0.0483674 | N6: =N5/J5-1 -> 0.056119714
B8: Gross Profit
B9: COGS | C9: 16.814184 | D9: 16.439784 | E9: 17.243159 | F9: 17.381202 | G9: 17.181649 | H9: 17.041217 | I9: 17.760996 | J9: 17.260387 | K9: 18.194632 | L9: 18.159883 | M9: 18.430077 | N9: 18.925571
B10: Gross Profit | C10: =C5-C9 -> 56.64087 | D10: =D5-D9 -> 57.429357 | E10: =E5-E9 -> 59.894767 | F10: =F5-F9 -> 60.767378 | G10: =G5-G9 -> 59.808461 | H10: =H5-H9 -> 59.908513 | I10: =I5-I9 -> 60.235216 | J10: =J5-J9 -> 60.758517 | ... N10: =N5-N9 -> 63.471732
B11: Gross Margin % | C11: =C10/C5 -> 0.77109561 | D11: =D10/D5 -> 0.77744721 | E11: =E10/E5 -> 0.77646328 | F11: =F10/F5 -> 0.77758774 | G11: =G10/G5 -> 0.77683304 | H11: =H10/H5 -> 0.77854092 | I11: =I10/I5 -> 0.77228386 | J11: =J10/J5 -> 0.77876661 | ... N11: =N10/N5 -> 0.77031322
B13: Operating Expenses
B14: S&M | C14: 14.00397 | D14: 14.083162 | E14: 14.056085 | F14: 14.845196 | G14: 13.968859 | H14: 14.048706 | I14: 14.759204 | J14: 14.257532 | K14: 14.673868 | L14: 15.107327 | M14: 15.409772 | N14: 15.384978
B15: R&D | C15: 9.2062254 | D15: 9.6841711 | E15: 9.7135544 | F15: 10.07255 | G15: 9.3605583 | H15: 9.9635406 | I15: 9.5611794 | J15: 9.4684992 | K15: 10.008531 | L15: 9.9327403 | M15: 10.530412 | N15: 10.727017
B16: G&A | C16: 7.8364503 | D16: 7.7408835 | E16: 8.5227341 | F16: 8.297927 | G16: 7.7674467 | H16: 8.4813746 | I16: 8.1831799 | J16: 8.5208101 | K16: 8.1719339 | L16: 8.6967456 | M16: 8.4261176 | N16: 9.0984912
B17: Operating Expenses | C17: =SUM(C14:C16) -> 31.046645 | D17: =SUM(D14:D16) -> 31.508217 | E17: =SUM(E14:E16) -> 32.292374 | F17: =SUM(F14:F16) -> 33.215673 | G17: =SUM(G14:G16) -> 31.096864 | H17: =SUM(H14:H16) -> 32.493621 | I17: =SUM(I14:I16) -> 32.503563 | J17: =SUM(J14:J16) -> 32.246841 | ... N17: =SUM(N14:N16) -> 35.210486
B18: =B14&" as % of Revenue" -> S&M as % of Revenue | C18: =+C14/C$5 -> 0.19064678 | D18: =+D14/D$5 -> 0.19065014 | E18: =+E14/E$5 -> 0.18222016 | F18: =+F14/F$5 -> 0.18996118 | G18: =+G14/G$5 -> 0.18143705 | H18: =+H14/H$5 -> 0.18256992 | I18: =+I14/I$5 -> 0.18922975 | J18: =+J14/J$5 -> 0.18274458 | ... N18: =+N14/N$5 -> 0.18671701
B19: =B15&" as % of Revenue" -> R&D as % of Revenue | C19: =+C15/C$5 -> 0.12533141 | D19: =+D15/D$5 -> 0.13109901 | E19: =+E15/E$5 -> 0.1259245 | F19: =+F15/F$5 -> 0.12888973 | G19: =+G15/G$5 -> 0.12158131 | H19: =+H15/H$5 -> 0.12948117 | I19: =+I15/I$5 -> 0.12258518 | J19: =+J15/J$5 -> 0.1213616 | ... N19: =+N15/N$5 -> 0.1301865
B20: =B16&" as % of Revenue" -> G&A as % of Revenue | C20: =+C16/C$5 -> 0.10668361 | D20: =+D16/D$5 -> 0.10479184 | E20: =+E16/E$5 -> 0.11048695 | F20: =+F16/F$5 -> 0.10618142 | G20: =+G16/G$5 -> 0.10088889 | H20: =+H16/H$5 -> 0.11021968 | I20: =+I16/I$5 -> 0.10491766 | J20: =+J16/J$5 -> 0.10921469 | ... N20: =+N16/N$5 -> 0.1104222
B21: =B17&" as % of Revenue" -> Operating Expenses as % of Revenue | C21: =+C17/C$5 -> 0.4226618 | D21: =+D17/D$5 -> 0.426541 | E21: =+E17/E$5 -> 0.4186316 | F21: =+F17/F$5 -> 0.42503233 | G21: =+G17/G$5 -> 0.40390725 | H21: =+H17/H$5 -> 0.42227077 | I21: =+I17/I$5 -> 0.41673259 | J21: =+J17/J$5 -> 0.41332086 | ... N21: =+N17/N$5 -> 0.42732571
B23: Operating Income | C23: =+C10-C17 -> 25.594225 | D23: =+D10-D17 -> 25.92114 | E23: =+E10-E17 -> 27.602394 | F23: =+F10-F17 -> 27.551705 | G23: =+G10-G17 -> 28.711597 | H23: =+H10-H17 -> 27.414892 | I23: =+I10-I17 -> 27.731653 | J23: =+J10-J17 -> 28.511676 | ... N23: =+N10-N17 -> 28.261246
B24: % Margin | C24: =+C23/C5 -> 0.34843381 | D24: =+D23/D5 -> 0.35090621 | E24: =+E23/E5 -> 0.35783168 | F24: =+F23/F5 -> 0.35255542 | G24: =+G23/G5 -> 0.37292579 | H24: =+H23/H5 -> 0.35627015 | I24: =+I23/I5 -> 0.35555128 | J24: =+J23/J5 -> 0.36544574 | ... N24: =+N23/N5 -> 0.34298752
B26: D&A | F26: 7.6474565 | G26: 7.8761646 | H26: 7.8292759 | I26: 7.9909183 | J26: 7.7891753 | K26: 7.881978 | L26: 8.1080011 | M26: 8.090979 | N26: 8.3755639
B27: EBITDA | F27: =+F23+F26 -> 35.199162 | G27: =+G23+G26 -> 36.587762 | H27: =+H23+H26 -> 35.244167 | I27: =+I23+I26 -> 35.722571 | J27: =+J23+J26 -> 36.300852 | K27: =+K23+K26 -> 36.030935 | L27: =+L23+L26 -> 36.357559 | M27: =+M23+M26 -> 37.063287 | N27: =+N23+N26 -> 36.63681
B28: % Margin | F28: =+F27/F5 -> 0.45041332 | G28: =+G27/G5 -> 0.47522678 | H28: =+H27/H5 -> 0.45801548 | I28: =+I27/I5 -> 0.45800392 | J28: =+J27/J5 -> 0.46528277 | K28: =+K27/K5 -> 0.45494799 | L28: =+L27/L5 -> 0.45364015 | M28: =+M27/M5 -> 0.45326994 | N28: =+N27/N5 -> 0.44463604
B30: LTM EBITDA | I30: =SUM(F27:I27) -> 142.75366 | J30: =SUM(G27:J27) -> 143.85535 | K30: =SUM(H27:K27) -> 143.29853 | L30: =SUM(I27:L27) -> 144.41192 | M30: =SUM(J27:M27) -> 145.75263 | N30: =SUM(K27:N27) -> 146.08859
B32: Note:
B33: Prior Year Renewal ARR for Billing | K33: 72.741228 | L33: 73.966444 | M33: 74.663909 | N33: 75.736755
B36: Balance Sheet | AH36: $ in millions, except noted
N37: =N4 -> 44926
B38: Cash | N38: =(55601.141636816-990)/1000 -> 54.611142
B39: Accounts Receivable | N39: 12.312163
B40: Net PP&E | N40: 35.699125
B41: Prepaid Expenses | N41: 13.122155
B42: Deferred Commissions | N42: 14.2204
B43: Capitalized Software Costs | N43: 5.9109174
B44: Goodwill | N44: 0
B45: Total Assets | N45: =SUM(N38:N44) -> 135.8759
B47: Accounts Payable | N47: 14.671147
B48: Deferred Revenue | N48: 17.993601
B49: Existing Debt | N49: 12.201
B50: New Debt | N50: 0
B51: Equity | N51: 91.010153
B52: Total Liabilities & Equity | N52: =SUM(N47:N51) -> 135.8759

Sheet Raw Customer ARR (Start)
A1: Customer | B1: =EOMONTH(C1, -3) -> 43830 | C1: 43921 | D1: =EOMONTH(C1,3) -> 44012 | E1: =EOMONTH(D1,3) -> 44104 | F1: =EOMONTH(E1,3) -> 44196 | G1: =EOMONTH(F1,3) -> 44286 | H1: =EOMONTH(G1,3) -> 44377 | I1: =EOMONTH(H1,3) -> 44469 | J1: =EOMONTH(I1,3) -> 44561 | K1: =EOMONTH(J1,3) -> 44651 | ... N1: =EOMONTH(M1,3) -> 44926
A2: 1 | B2: 0 | C2: 0 | D2: 0 | E2: 0 | F2: 0 | G2: 0 | H2: 0 | I2: 1152000 | J2: 1152000 | K2: 1152000 | L2: 1152000 | M2: 975056 | N2: 975056
A3: =+A2+1 -> 2 | B3: 0 | C3: 0 | D3: 0 | E3: 0 | F3: 0 | G3: 0 | H3: 0 | I3: 2304000 | J3: 1950104 | K3: 1950104 | L3: 1950104 | M3: 1950104 | N3: 1950104
A4: =+A3+1 -> 3 | B4: 0 | C4: 0 | D4: 0 | E4: 0 | F4: 0 | G4: 0 | H4: 0 | I4: 2304000 | J4: 2304000 | K4: 2119680 | L4: 2119680 | M4: 2119680 | N4: 2119680
A5: =+A4+1 -> 4 | B5: 0 | C5: 0 | D5: 0 | E5: 0 | F5: 0 | G5: 0 | H5: 0 | I5: 2304000 | J5: 2304000 | K5: 2304000 | L5: 2304000 | M5: 2304000 | N5: 2304000
A6: =+A5+1 -> 5 | B6: 0 | C6: 0 | D6: 0 | E6: 0 | F6: 0 | G6: 0 | H6: 0 | I6: 3456000 | J6: 3456000 | K6: 3456000 | L6: 3456000 | M6: 3456000 | N6: 3456000
A7: =+A6+1 -> 6 | B7: 1445072 | C7: 0 | D7: 0 | E7: 0 | F7: 0 | G7: 0 | H7: 0 | I7: 0 | J7: 0 | K7: 0 | L7: 0 | M7: 0 | N7: 0
A8: =+A7+1 -> 7 | B8: 2119680 | C8: 0 | D8: 0 | E8: 0 | F8: 0 | G8: 0 | H8: 0 | I8: 0 | J8: 0 | K8: 0 | L8: 0 | M8: 0 | N8: 0
A9: =+A8+1 -> 8 | B9: 975056 | C9: 0 | D9: 0 | E9: 0 | F9: 0 | G9: 0 | H9: 0 | I9: 0 | J9: 0 | K9: 0 | L9: 0 | M9: 0 | N9: 0
A10: =+A9+1 -> 9 | B10: 2739760 | C10: 0 | D10: 0 | E10: 0 | F10: 0 | G10: 0 | H10: 0 | I10: 0 | J10: 0 | K10: 0 | L10: 0 | M10: 0 | N10: 0
A11: =+A10+1 -> 10 | B11: 0 | C11: 0 | D11: 0 | E11: 0 | F11: 0 | G11: 0 | H11: 0 | I11: 0 | J11: 0 | K11: 0 | L11: 0 | M11: 0 | N11: 3456000
A12: =+A11+1 -> 11 | B12: 0 | C12: 0 | D12: 0 | E12: 0 | F12: 0 | G12: 0 | H12: 0 | I12: 0 | J12: 0 | K12: 0 | L12: 0 | M12: 0 | N12: 2304000
A13: =+A12+1 -> 12 | B13: 0 | C13: 0 | D13: 0 | E13: 0 | F13: 0 | G13: 0 | H13: 0 | I13: 0 | J13: 0 | K13: 0 | L13: 0 | M13: 0 | N13: 2580480
A14: =+A13+1 -> 13 | B14: 0 | C14: 0 | D14: 0 | E14: 0 | F14: 0 | G14: 0 | H14: 0 | I14: 0 | J14: 0 | K14: 0 | L14: 0 | M14: 0 | N14: 2304000
... A197: =+A196+1 -> 196 | B197: 1489000 | C197: 1489000 | D197: 1489000 | E197: 1489000 | F197: 1489000 | G197: 1489000 | H197: 0 | I197: 0 | J197: 0 | K197: 0 | L197: 0 | M197: 0 | N197: 0

Sheet End ->

Sheet Transaction
B2: Entry | G2: $ in millions, except noted
B3: Entry Assumptions | E3: Sources
B4: Entry LTM EBITDA | C4: =Model!N36 -> 146.08859 | E4: Sponsor Equity | G4: =G13-G5 -> 770.05182
B5: Entry Multiple | C5: 10 | E5: New Debt | G5: =+D21 -> 730.44296
B6: Purchase Enterprise Value | C6: =C5*C4 -> 1460.8859 | E6: Total Sources | G6: =SUM(G4:G5) -> 1500.4948
B7: (-) Debt | C7: =Model!L61 -> 12.201
B8: (+) Cash | C8: =Model!L50 -> 54.611142 | E8: Uses
B9: Purchase Equity Value | C9: =+C6-C7+C8 -> 1503.2961 | E9: Purchase Enterprise Value | G9: =+C6 -> 1460.8859
E10: Ending Cash to B/S | G10: 25
B11: Pre-Money Shares Outstanding | C11: 1230000 | E11: Transaction Fees | G11: =1%*C6 -> 14.608859
B12: Pre-Money Stock Price | C12: =+C9/C11*1000 -> 1.2221919
B13: Post-Money Shares Outstanding | C13: =+C11 -> 1230000 | E13: Total Uses | G13: =SUM(G9:G12) -> 1500.4948
B16: Debt Assumptions
C17: xEBITDA | D17: $ Amount | E17: % Interest
B18: Revolver | C18: 0 | D18: =C18*C$4 -> 0 | E18: 0.02
B19: Term Loan B | C19: 3 | D19: =C19*C$4 -> 438.26578 | E19: 0.02
B20: Senior Notes | C20: 2 | D20: =C20*C$4 -> 292.17718 | E20: 0.05
B21: Total Debt | C21: =SUM(C18:C20) -> 5 | D21: =SUM(D18:D20) -> 730.44296
B24: Exit & Returns
B25: Exit Value | E25: Exit Ownership
B26: Exit LTM EBITDA | C26: =Model!AH36 -> 176.07296 | E26: Initial Ownership | G26: 1
B27: Exit Multiple | C27: 10 | E27: Dilution from SBC | G27: =+Model!AH182 -> 0.057442591
B28: Exit Enterprise Value | C28: =C27*C26 -> 1760.7296 | E28: Exit Ownership | G28: =+G26*(1-G27) -> 0.94255741
B29: (-) Debt | C29: =+Model!AH62+Model!AH61 -> 546.27792
B30: (+) Cash | C30: =+Model!AH50 -> 25
B31: Exit Equity value | C31: =+C28+C30-C29 -> 1239.4517
B32: (x) Exit Ownership | C32: =+G28 -> 0.94255741
B33: Exit Sponsor Value | C33: =+C31*C32 -> 1168.2543
B35: IRR | C35: =XIRR(C39:C40, C41:C42) -> 0.086885175
B36: M-o-M | C36: =+C40/(-C39) -> 1.5171113
B39: Entry Investment | C39: =+-G4 -> -770.05182
B40: Exit Proceeds | C40: =+C33 -> 1168.2543
B41: Entry Date | C41: =+Model!N4 -> 44926
B42: Exit Date | C42: =+Model!AH4 -> 46752

Sheet Model
B2: Income Statement | AH2: $ in millions, except noted
C3: =YEAR(C4) -> 2020 | D3: =YEAR(D4) -> 2020 | E3: =YEAR(E4) -> 2020 | F3: =YEAR(F4) -> 2020 | G3: =YEAR(G4) -> 2021 | H3: =YEAR(H4) -> 2021 | I3: =YEAR(I4) -> 2021 | J3: =YEAR(J4) -> 2021 | ... AH3: =YEAR(AH4) -> 2027
C4: 43921 | D4: =EOMONTH(C4, 3) -> 44012 | E4: =EOMONTH(D4, 3) -> 44104 | F4: =EOMONTH(E4, 3) -> 44196 | G4: =EOMONTH(F4, 3) -> 44286 | H4: =EOMONTH(G4, 3) -> 44377 | I4: =EOMONTH(H4, 3) -> 44469 | J4: =EOMONTH(I4, 3) -> 44561 | K4: =EOMONTH(J4, 3) -> 44651 | ... AH4: =EOMONTH(AG4, 3) -> 46752
B5: Ending ARR | C5: =+'ARR Waterfall'!C11 -> 301.18761 | D5: =+'ARR Waterfall'!D11 -> 304.4751 | E5: =+'ARR Waterfall'!E11 -> 308.34238 | F5: =+'ARR Waterfall'!F11 -> 313.78571 | G5: =+'ARR Waterfall'!G11 -> 310.36867 | H5: =+'ARR Waterfall'!H11 -> 309.6027 | I5: =+'ARR Waterfall'!I11 -> 312.48882 | J5: =+'ARR Waterfall'!J11 -> 315.91418 | ... AH5: =+'ARR Waterfall'!AH11 -> 373.35968
B6: % YoY Growth | G6: =G5/C5-1 -> 0.030482874 | H6: =H5/D5-1 -> 0.016840759 | I6: =I5/E5-1 -> 0.013447545 | J6: =J5/F5-1 -> 0.0067832024 | K6: =K5/G5-1 -> 0.026340777 | L6: =L5/H5-1 -> 0.039668698 | M6: =M5/I5-1 -> 0.049247534 | N6: =N5/J5-1 -> 0.069638583 | ... AH6: =AH5/AD5-1 -> 0.020150501
B8: GAAP Revenue | C8: 73.455054 | D8: 73.869141 | E8: 77.137926 | F8: 78.14858 | G8: 76.99011 | H8: 76.949729 | I8: 77.996212 | J8: 78.018904 | K8: 79.197922 | L8: 80.146255 | M8: 81.768686 | N8: 82.397303 | O8: =O9*O5 -> 81.504857 | P8: =P9*P5 -> 81.912381 | Q8: =Q9*Q5 -> 82.321943 | R8: =R9*R5 -> 82.733553 | S8: =S9*S5 -> 83.14722 | T8: =T9*T5 -> 83.562957 | U8: =U9*U5 -> 83.980771 | V8: =V9*V5 -> 84.400675 | ... AH8: =AH9*AH5 -> 89.606324
B9: % of ARR | C9: =+C8/C5 -> 0.24388471 | D9: =+D8/D5 -> 0.24261143 | E9: =+E8/E5 -> 0.25016972 | F9: =+F8/F5 -> 0.24905079 | G9: =+G8/G5 -> 0.24806018 | H9: =+H8/H5 -> 0.24854347 | I9: =+I8/I5 -> 0.24959681 | J9: =+J8/J5 -> 0.24696233 | ... N9: =+N8/N5 -> 0.24384104 | O9: 0.24 | P9: 0.24 | Q9: 0.24 | R9: 0.24 | S9: 0.24 | T9: 0.24 | U9: 0.24 | V9: 0.24 | W9: 0.24 | X9: 0.24 | Y9: 0.24 | Z9: 0.24 | AA9: 0.24 | AB9: 0.24 | AC9: 0.24 | AD9: 0.24 | AE9: 0.24 | AF9: 0.24 | AG9: 0.24 | AH9: 0.24
B10: % YoY Growth | G10: =G8/C8-1 -> 0.04812543 | H10: =H8/D8-1 -> 0.041703321 | I10: =I8/E8-1 -> 0.011126641 | J10: =J8/F8-1 -> -0.0016593573 | K10: =K8/G8-1 -> 0.028676573 | L10: =L8/H8-1 -> 0.041540435 | M10: =M8/I8-1 -> 0.0483674 | N10: =N8/J8-1 -> 0.056119714 | ... AH10: =AH8/AD8-1 -> 0.020150501
B12: LTM GAAP Revenue | F12: =SUM(C8:F8) -> 302.6107 | G12: =SUM(D8:G8) -> 306.14576 | H12: =SUM(E8:H8) -> 309.22635 | I12: =SUM(F8:I8) -> 310.08463 | J12: =SUM(G8:J8) -> 309.95496 | K12: =SUM(H8:K8) -> 312.16277 | L12: =SUM(I8:L8) -> 315.35929 | M12: =SUM(J8:M8) -> 319.13177 | ... AH12: =SUM(AE8:AH8) -> 355.75934
B14: Gross Profit
B15: COGS | C15: 16.814184 | D15: 16.439784 | E15: 17.243159 | F15: 17.381202 | G15: 17.181649 | H15: 17.041217 | I15: 17.760996 | J15: 17.260387 | K15: 18.194632 | L15: 18.159883 | M15: 18.430077 | N15: 18.925571 | O15: =(1-O17)*O8 -> 18.746117 | P15: =(1-P17)*P8 -> 18.839848 | Q15: =(1-Q17)*Q8 -> 18.934047 | R15: =(1-R17)*R8 -> 19.028717 | S15: =(1-S17)*S8 -> 19.123861 | T15: =(1-T17)*T8 -> 19.21948 | U15: =(1-U17)*U8 -> 19.315577 | V15: =(1-V17)*V8 -> 19.412155 | ... AH15: =(1-AH17)*AH8 -> 20.609455
B16: Gross Profit | C16: =C8-C15 -> 56.64087 | D16: =D8-D15 -> 57.429357 | E16: =E8-E15 -> 59.894767 | F16: =F8-F15 -> 60.767378 | G16: =G8-G15 -> 59.808461 | H16: =H8-H15 -> 59.908513 | I16: =I8-I15 -> 60.235216 | J16: =J8-J15 -> 60.758517 | ... AH16: =AH8-AH15 -> 68.99687
B17: Gross Margin % | C17: =C16/C8 -> 0.77109561 | D17: =D16/D8 -> 0.77744721 | E17: =E16/E8 -> 0.77646328 | F17: =F16/F8 -> 0.77758774 | G17: =G16/G8 -> 0.77683304 | H17: =H16/H8 -> 0.77854092 | I17: =I16/I8 -> 0.77228386 | J17: =J16/J8 -> 0.77876661 | ... N17: =N16/N8 -> 0.77031322 | O17: 0.77 | P17: 0.77 | Q17: 0.77 | R17: 0.77 | S17: 0.77 | T17: 0.77 | U17: 0.77 | V17: 0.77 | W17: 0.77 | X17: 0.77 | Y17: 0.77 | Z17: 0.77 | AA17: 0.77 | AB17: 0.77 | AC17: 0.77 | AD17: 0.77 | AE17: 0.77 | AF17: 0.77 | AG17: 0.77 | AH17: 0.77
B19: Operating Expenses
B20: S&M | C20: 14.00397 | D20: 14.083162 | E20: 14.056085 | F20: 14.845196 | G20: 13.968859 | H20: 14.048706 | I20: 14.759204 | J20: 14.257532 | K20: 14.673868 | L20: 15.107327 | M20: 15.409772 | N20: 15.384978 | O20: =O$8*O24 -> 14.670874 | P20: =P$8*P24 -> 14.744229 | Q20: =Q$8*Q24 -> 14.81795 | R20: =R$8*R24 -> 14.892039 | S20: =S$8*S24 -> 14.9665 | T20: =T$8*T24 -> 15.041332 | U20: =U$8*U24 -> 15.116539 | V20: =V$8*V24 -> 15.192122 | ... AH20: =AH$8*AH24 -> 16.129138
B21: R&D | C21: 9.2062254 | D21: 9.6841711 | E21: 9.7135544 | F21: 10.07255 | G21: 9.3605583 | H21: 9.9635406 | I21: 9.5611794 | J21: 9.4684992 | K21: 10.008531 | L21: 9.9327403 | M21: 10.530412 | N21: 10.727017 | O21: =O$8*O25 -> 9.7805828 | P21: =P$8*P25 -> 9.8294857 | Q21: =Q$8*Q25 -> 9.8786332 | R21: =R$8*R25 -> 9.9280263 | S21: =S$8*S25 -> 9.9776665 | T21: =T$8*T25 -> 10.027555 | U21: =U$8*U25 -> 10.077693 | V21: =V$8*V25 -> 10.128081 | ... AH21: =AH$8*AH25 -> 10.752759
B22: G&A | C22: 7.8364503 | D22: 7.7408835 | E22: 8.5227341 | F22: 8.297927 | G22: 7.7674467 | H22: 8.4813746 | I22: 8.1831799 | J22: 8.5208101 | K22: 8.1719339 | L22: 8.6967456 | M22: 8.4261176 | N22: 9.0984912 | O22: =O$8*O26 -> 8.9655342 | P22: =P$8*P26 -> 9.0103619 | Q22: =Q$8*Q26 -> 9.0554137 | R22: =R$8*R26 -> 9.1006908 | S22: =S$8*S26 -> 9.1461943 | T22: =T$8*T26 -> 9.1919252 | U22: =U$8*U26 -> 9.2378848 | V22: =V$8*V26 -> 9.2840743 | ... AH22: =AH$8*AH26 -> 9.8566957
B23: Operating Expenses | C23: =SUM(C20:C22) -> 31.046645 | D23: =SUM(D20:D22) -> 31.508217 | E23: =SUM(E20:E22) -> 32.292374 | F23: =SUM(F20:F22) -> 33.215673 | G23: =SUM(G20:G22) -> 31.096864 | H23: =SUM(H20:H22) -> 32.493621 | I23: =SUM(I20:I22) -> 32.503563 | J23: =SUM(J20:J22) -> 32.246841 | ... AH23: =SUM(AH20:AH22) -> 36.738593
B24: =B20&" as % of Revenue" -> S&M as % of Revenue | C24: =+C20/C$8 -> 0.19064678 | D24: =+D20/D$8 -> 0.19065014 | E24: =+E20/E$8 -> 0.18222016 | F24: =+F20/F$8 -> 0.18996118 | G24: =+G20/G$8 -> 0.18143705 | H24: =+H20/H$8 -> 0.18256992 | I24: =+I20/I$8 -> 0.18922975 | J24: =+J20/J$8 -> 0.18274458 | ... N24: =+N20/N$8 -> 0.18671701 | O24: 0.18 | P24: 0.18 | Q24: 0.18 | R24: 0.18 | S24: 0.18 | T24: 0.18 | U24: 0.18 | V24: 0.18 | W24: 0.18 | X24: 0.18 | Y24: 0.18 | Z24: 0.18 | AA24: 0.18 | AB24: 0.18 | AC24: 0.18 | AD24: 0.18 | AE24: 0.18 | AF24: 0.18 | AG24: 0.18 | AH24: 0.18
B25: =B21&" as % of Revenue" -> R&D as % of Revenue | C25: =+C21/C$8 -> 0.12533141 | D25: =+D21/D$8 -> 0.13109901 | E25: =+E21/E$8 -> 0.1259245 | F25: =+F21/F$8 -> 0.12888973 | G25: =+G21/G$8 -> 0.12158131 | H25: =+H21/H$8 -> 0.12948117 | I25: =+I21/I$8 -> 0.12258518 | J25: =+J21/J$8 -> 0.1213616 | ... N25: =+N21/N$8 -> 0.1301865 | O25: 0.12 | P25: 0.12 | Q25: 0.12 | R25: 0.12 | S25: 0.12 | T25: 0.12 | U25: 0.12 | V25: 0.12 | W25: 0.12 | X25: 0.12 | Y25: 0.12 | Z25: 0.12 | AA25: 0.12 | AB25: 0.12 | AC25: 0.12 | AD25: 0.12 | AE25: 0.12 | AF25: 0.12 | AG25: 0.12 | AH25: 0.12
B26: =B22&" as % of Revenue" -> G&A as % of Revenue | C26: =+C22/C$8 -> 0.10668361 | D26: =+D22/D$8 -> 0.10479184 | E26: =+E22/E$8 -> 0.11048695 | F26: =+F22/F$8 -> 0.10618142 | G26: =+G22/G$8 -> 0.10088889 | H26: =+H22/H$8 -> 0.11021968 | I26: =+I22/I$8 -> 0.10491766 | J26: =+J22/J$8 -> 0.10921469 | ... N26: =+N22/N$8 -> 0.1104222 | O26: 0.11 | P26: 0.11 | Q26: 0.11 | R26: 0.11 | S26: 0.11 | T26: 0.11 | U26: 0.11 | V26: 0.11 | W26: 0.11 | X26: 0.11 | Y26: 0.11 | Z26: 0.11 | AA26: 0.11 | AB26: 0.11 | AC26: 0.11 | AD26: 0.11 | AE26: 0.11 | AF26: 0.11 | AG26: 0.11 | AH26: 0.11
B27: =B23&" as % of Revenue" -> Operating Expenses as % of Revenue | C27: =+C23/C$8 -> 0.4226618 | D27: =+D23/D$8 -> 0.426541 | E27: =+E23/E$8 -> 0.4186316 | F27: =+F23/F$8 -> 0.42503233 | G27: =+G23/G$8 -> 0.40390725 | H27: =+H23/H$8 -> 0.42227077 | I27: =+I23/I$8 -> 0.41673259 | J27: =+J23/J$8 -> 0.41332086 | ... AH27: =+AH23/AH$8 -> 0.41
B29: Operating Income | C29: =+C16-C23 -> 25.594225 | D29: =+D16-D23 -> 25.92114 | E29: =+E16-E23 -> 27.602394 | F29: =+F16-F23 -> 27.551705 | G29: =+G16-G23 -> 28.711597 | H29: =+H16-H23 -> 27.414892 | I29: =+I16-I23 -> 27.731653 | J29: =+J16-J23 -> 28.511676 | ... AH29: =+AH16-AH23 -> 32.258277
B30: % Margin | C30: =+C29/C8 -> 0.34843381 | D30: =+D29/D8 -> 0.35090621 | E30: =+E29/E8 -> 0.35783168 | F30: =+F29/F8 -> 0.35255542 | G30: =+G29/G8 -> 0.37292579 | H30: =+H29/H8 -> 0.35627015 | I30: =+I29/I8 -> 0.35555128 | J30: =+J29/J8 -> 0.36544574 | ... AH30: =+AH29/AH8 -> 0.36
B32: D&A | F32: 7.6474565 | G32: 7.8761646 | H32: 7.8292759 | I32: 7.9909183 | J32: 7.7891753 | K32: 7.881978 | L32: 8.1080011 | M32: 8.090979 | N32: 8.3755639 | O32: =+O149+O150 -> 9.2804907 | P32: =+P149+P150 -> 9.5141427 | Q32: =+Q149+Q150 -> 9.7184204 | R32: =+R149+R150 -> 9.9182252 | S32: =+S149+S150 -> 10.15164 | T32: =+T149+T150 -> 10.386221 | U32: =+U149+U150 -> 10.621976 | V32: =+V149+V150 -> 10.858909 | ... AH32: =+AH149+AH150 -> 12.089822
B33: EBITDA | F33: =+F29+F32 -> 35.199162 | G33: =+G29+G32 -> 36.587762 | H33: =+H29+H32 -> 35.244167 | I33: =+I29+I32 -> 35.722571 | J33: =+J29+J32 -> 36.300852 | K33: =+K29+K32 -> 36.030935 | L33: =+L29+L32 -> 36.357559 | M33: =+M29+M32 -> 37.063287 | ... AH33: =+AH29+AH32 -> 44.348099
B34: % Margin | F34: =+F33/F8 -> 0.45041332 | G34: =+G33/G8 -> 0.47522678 | H34: =+H33/H8 -> 0.45801548 | I34: =+I33/I8 -> 0.45800392 | J34: =+J33/J8 -> 0.46528277 | K34: =+K33/K8 -> 0.45494799 | L34: =+L33/L8 -> 0.45364015 | M34: =+M33/M8 -> 0.45326994 | ... AH34: =+AH33/AH8 -> 0.49492153
B36: LTM EBITDA | I36: =SUM(F33:I33) -> 142.75366 | J36: =SUM(G33:J33) -> 143.85535 | K36: =SUM(H33:K33) -> 143.29853 | L36: =SUM(I33:L33) -> 144.41192 | M36: =SUM(J33:M33) -> 145.75263 | N36: =SUM(K33:N33) -> 146.08859 | O36: =SUM(L33:O33) -> 148.6799 | P36: =SUM(M33:P33) -> 151.32494 | ... AH36: =SUM(AE33:AH33) -> 176.07296
B38: Interest Expense | O38: =O140 -> 23.337718 | P38: =P140 -> 23.261522 | Q38: =Q140 -> 23.159876 | R38: =R140 -> 23.002742 | S38: =S140 -> 22.854347 | T38: =T140 -> 22.744444 | U38: =U140 -> 22.609001 | V38: =V140 -> 22.418071 | ... AH38: =AH140 -> 19.84632
B39: Taxable Income | O39: =+O29-O38 -> 6.0040305 | P39: =+P29-P38 -> 6.2269347 | Q39: =+Q29-Q38 -> 6.4760233 | R39: =+R29-R38 -> 6.7813374 | S39: =+S29-S38 -> 7.0786526 | T39: =+T29-T38 -> 7.3382207 | U39: =+U29-U38 -> 7.6240766 | V39: =+V29-V38 -> 7.9661724 | ... AH39: =+AH29-AH38 -> 12.411956
B41: Taxes | O41: =IF(O39<0, 0, O39*O42) -> 1.5010076 | P41: =IF(P39<0, 0, P39*P42) -> 1.5567337 | Q41: =IF(Q39<0, 0, Q39*Q42) -> 1.6190058 | R41: =IF(R39<0, 0, R39*R42) -> 1.6953343 | S41: =IF(S39<0, 0, S39*S42) -> 1.7696631 | T41: =IF(T39<0, 0, T39*T42) -> 1.8345552 | U41: =IF(U39<0, 0, U39*U42) -> 1.9060192 | V41: =IF(V39<0, 0, V39*V42) -> 1.9915431 | ... AH41: =IF(AH39<0, 0, AH39*AH42) -> 3.1029891
B42: Tax Rate | O42: 0.25 | P42: 0.25 | Q42: 0.25 | R42: 0.25 | S42: 0.25 | T42: 0.25 | U42: 0.25 | V42: 0.25 | W42: 0.25 | X42: 0.25 | Y42: 0.25 | Z42: 0.25 | AA42: 0.25 | AB42: 0.25 | AC42: 0.25 | AD42: 0.25 | AE42: 0.25 | AF42: 0.25 | AG42: 0.25 | AH42: 0.25
B44: Net Income | O44: =+O39-O41 -> 4.5030229 | P44: =+P39-P41 -> 4.6702011 | Q44: =+Q39-Q41 -> 4.8570175 | R44: =+R39-R41 -> 5.086003 | S44: =+S39-S41 -> 5.3089894 | T44: =+T39-T41 -> 5.5036655 | U44: =+U39-U41 -> 5.7180575 | V44: =+V39-V41 -> 5.9746293 | ... AH44: =+AH39-AH41 -> 9.3089672
B45: % Margin | O45: =+O44/O8 -> 0.055248522 | P45: =+P44/P8 -> 0.057014593 | Q45: =+Q44/Q8 -> 0.059000278 | R45: =+R44/R8 -> 0.061474491 | S45: =+S44/S8 -> 0.063850474 | T45: =+T44/T8 -> 0.065862504 | U45: =+U44/U8 -> 0.068087699 | V45: =+V44/V8 -> 0.070788881 | ... AH45: =+AH44/AH8 -> 0.10388739
B48: Balance Sheet | L48: Actual | N48: PF | AH48: $ in millions, except noted
L49: =N4 -> 44926 | M49: Adj. | N49: =+L49 -> 44926 | O49: =O4 -> 45016 | P49: =P4 -> 45107 | Q49: =Q4 -> 45199 | R49: =R4 -> 45291 | S49: =S4 -> 45382 | T49: =T4 -> 45473 | U49: =U4 -> 45565 | V49: =V4 -> 45657 | ... AH49: =AH4 -> 46752
B50: Cash | L50: =(55601.141636816-990)/1000 -> 54.611142 | M50: =+-L50+Transaction!G10 -> -29.611142 | N50: =+M50+L50 -> 25 | O50: =+O165 -> 25 | P50: =+P165 -> 25 | Q50: =+Q165 -> 25 | R50: =+R165 -> 25 | S50: =+S165 -> 25 | T50: =+T165 -> 25 | U50: =+U165 -> 25 | V50: =+V165 -> 25 | ... AH50: =+AH165 -> 25
B51: Accounts Receivable | L51: 12.312163 | N51: =+M51+L51 -> 12.312163 | O51: =O96 -> 11.484919 | P51: =P96 -> 11.696749 | Q51: =Q96 -> 12.046712 | R51: =R96 -> 12.568749 | S51: =S96 -> 11.742789 | T51: =T96 -> 11.955908 | U51: =U96 -> 12.307167 | V51: =V96 -> 12.830506 | ... AH51: =AH96 -> 13.64785
B52: Net PP&E | L52: 35.699125 | N52: =+M52+L52 -> 35.699125 | O52: =+O86 -> 36.513668 | P52: =+P86 -> 37.332626 | Q52: =+Q86 -> 38.152967 | R52: =+R86 -> 38.974149 | S52: =+S86 -> 39.799437 | T52: =+T86 -> 40.628851 | U52: =+U86 -> 41.462412 | V52: =+V86 -> 42.300141 | ... AH52: =+AH86 -> 52.68567
B53: Prepaid Expenses | L53: 13.122155 | N53: =+M53+L53 -> 13.122155 | O53: =O77*O68 -> 13.032684 | P53: =P77*P68 -> 13.103329 | Q53: =Q77*Q68 -> 13.125459 | R53: =R77*R68 -> 13.138909 | S53: =S77*S68 -> 13.204604 | T53: =T77*T68 -> 13.270627 | U53: =U77*U68 -> 13.33698 | V53: =V77*V68 -> 13.403665 | ... AH53: =AH77*AH68 -> 14.230374
B54: Deferred Commissions | L54: 14.2204 | N54: =+M54+L54 -> 14.2204 | O54: =Capitalizations!H9 -> 15.972382 | P54: =Capitalizations!I9 -> 17.572521 | Q54: =Capitalizations!J9 -> 19.020057 | R54: =Capitalizations!K9 -> 20.314227 | S54: =Capitalizations!L9 -> 21.454265 | T54: =Capitalizations!M9 -> 22.4394 | U54: =Capitalizations!N9 -> 23.268856 | V54: =Capitalizations!O9 -> 23.941857 | ... AH54: =Capitalizations!AA9 -> 24.074264
B55: Capitalized Software Costs | L55: 5.9109174 | N55: =+M55+L55 -> 5.9109174 | O55: =Capitalizations!H49 -> 6.2514641 | P55: =Capitalizations!I49 -> 6.5704936 | Q55: =Capitalizations!J49 -> 6.8678982 | R55: =Capitalizations!K49 -> 7.1435698 | S55: =Capitalizations!L49 -> 7.3973997 | T55: =Capitalizations!M49 -> 7.6292788 | U55: =Capitalizations!N49 -> 7.8390972 | V55: =Capitalizations!O49 -> 8.0267448 | ... AH55: =Capitalizations!AA49 -> 9.6406229
B56: Goodwill | L56: 0 | M56: =Transaction!C9-Model!L63 -> 1412.2859 | N56: =+M56+L56 -> 1412.2859 | O56: =N56 -> 1412.2859 | P56: =O56 -> 1412.2859 | Q56: =P56 -> 1412.2859 | R56: =Q56 -> 1412.2859 | S56: =R56 -> 1412.2859 | T56: =S56 -> 1412.2859 | U56: =T56 -> 1412.2859 | V56: =U56 -> 1412.2859 | ... AH56: =AG56 -> 1412.2859
B57: Total Assets | L57: =SUM(L50:L56) -> 135.8759 | N57: =SUM(N50:N56) -> 1518.5507 | O57: =SUM(O50:O56) -> 1520.541 | P57: =SUM(P50:P56) -> 1523.5616 | Q57: =SUM(Q50:Q56) -> 1526.499 | R57: =SUM(R50:R56) -> 1529.4255 | S57: =SUM(S50:S56) -> 1530.8844 | T57: =SUM(T50:T56) -> 1533.21 | U57: =SUM(U50:U56) -> 1535.5004 | ... AH57: =SUM(AH50:AH56) -> 1551.5647
B59: Accounts Payable | L59: 14.671147 | N59: =+M59+L59 -> 14.671147 | O59: =O76*O15/90 -> 14.580313 | P59: =P76*P15/90 -> 14.653215 | Q59: =Q76*Q15/90 -> 14.726481 | R59: =R76*R15/90 -> 14.800113 | S59: =S76*S15/90 -> 14.874114 | T59: =T76*T15/90 -> 14.948484 | U59: =U76*U15/90 -> 15.023227 | V59: =V76*V15/90 -> 15.098343 | ... AH59: =AH76*AH15/90 -> 16.029576
B60: Deferred Revenue | L60: 17.993601 | N60: =+M60+L60 -> 17.993601 | O60: =O102 -> 14.64796 | P60: =P102 -> 12.306991 | Q60: =Q102 -> 11.889548 | R60: =R102 -> 14.540741 | S60: =S102 -> 11.271865 | T60: =T102 -> 9.0080446 | U60: =U102 -> 8.668136 | V60: =V102 -> 11.397252 | ... AH60: =AH102 -> 3.8859757
B61: Existing Debt | L61: 12.201 | M61: =-L61 -> -12.201 | N61: =+M61+L61 -> 0 | O61: =N61 -> 0 | P61: =O61 -> 0 | Q61: =P61 -> 0 | R61: =Q61 -> 0 | S61: =R61 -> 0 | T61: =S61 -> 0 | U61: =T61 -> 0 | V61: =U61 -> 0 | ... AH61: =AG61 -> 0
B62: New Debt | L62: 0 | M62: =+Transaction!G5 -> 730.44296 | N62: =+M62+L62 -> 730.44296 | O62: =+O138 -> 726.79728 | P62: =+P138 -> 722.82341 | Q62: =+Q138 -> 716.63265 | R62: =+R138 -> 707.10996 | S62: =+S138 -> 701.79317 | T62: =+T138 -> 696.11965 | U62: =+U138 -> 688.24891 | V62: =+V138 -> 677.02661 | ... AH62: =+AH138 -> 546.27792
B63: Equity | L63: 91.010153 | M63: =+-L63+Transaction!G4-Transaction!G11 -> 664.43281 | N63: =+M63+L63 -> 755.44296 | O63: =N63+O44+O152 -> 764.51547 | P63: =O63+P44+P152 -> 773.77801 | Q63: =P63+Q44+Q152 -> 783.25032 | R63: =Q63+R44+R152 -> 792.9747 | S63: =R63+S44+S152 -> 802.94525 | T63: =S63+T44+T152 -> 813.13379 | U63: =T63+U44+U152 -> 823.56015 | V63: =U63+V44+V152 -> 834.26662 | ... AH63: =AG63+AH44+AH152 -> 985.37122
B64: Total Liabilities & Equity | L64: =SUM(L59:L63) -> 135.8759 | N64: =SUM(N59:N63) -> 1518.5507 | O64: =SUM(O59:O63) -> 1520.541 | P64: =SUM(P59:P63) -> 1523.5616 | Q64: =SUM(Q59:Q63) -> 1526.499 | R64: =SUM(R59:R63) -> 1529.4255 | S64: =SUM(S59:S63) -> 1530.8844 | T64: =SUM(T59:T63) -> 1533.21 | U64: =SUM(U59:U63) -> 1535.5004 | ... AH64: =SUM(AH59:AH63) -> 1551.5647
B65: Check? | L65: =+L57-L64 -> 0 | N65: =+N57-N64 -> 0 | O65: =+O57-O64 -> 0 | P65: =+P57-P64 -> 0 | Q65: =+Q57-Q64 -> 0 | R65: =+R57-R64 -> 0 | S65: =+S57-S64 -> 0 | T65: =+T57-T64 -> 0 | U65: =+U57-U64 -> 0 | ... AH65: =+AH57-AH64 -> -2.5788722e-09
B67: Memo
B68: LTM GAAP Revenue | L68: =+N68 -> 323.51017 | N68: =SUM(K8:N8) -> 323.51017 | O68: =SUM(L8:O8) -> 325.8171 | P68: =SUM(M8:P8) -> 327.58323 | Q68: =SUM(N8:Q8) -> 328.13648 | R68: =SUM(O8:R8) -> 328.47273 | S68: =SUM(P8:S8) -> 330.1151 | T68: =SUM(Q8:T8) -> 331.76567 | U68: =SUM(R8:U8) -> 333.4245 | ... AH68: =SUM(AE8:AH8) -> 355.75934
B69: LTM COGS | L69: =+N69 -> 73.710163 | N69: =N15+M15+L15+K15 -> 73.710163 | O69: =O15+N15+M15+L15 -> 74.261648 | P69: =P15+O15+N15+M15 -> 74.941612 | Q69: =Q15+P15+O15+N15 -> 75.445582 | R69: =R15+Q15+P15+O15 -> 75.548729 | S69: =S15+R15+Q15+P15 -> 75.926472 | T69: =T15+S15+R15+Q15 -> 76.306105 | U69: =U15+T15+S15+R15 -> 76.687635 | ... AH69: =AH15+AG15+AF15+AE15 -> 81.824649
B70: LTM S&M Expense | L70: =+N70 -> 60.575945 | N70: =SUM(K20:N20) -> 60.575945 | O70: =SUM(L20:O20) -> 60.572951 | P70: =SUM(M20:P20) -> 60.209852 | Q70: =SUM(N20:Q20) -> 59.61803 | R70: =SUM(O20:R20) -> 59.125092 | S70: =SUM(P20:S20) -> 59.420718 | T70: =SUM(Q20:T20) -> 59.717821 | U70: =SUM(R20:U20) -> 60.01641 | ... AH70: =SUM(AE20:AH20) -> 64.036682
B71: LTM R&D Expense | L71: =+N71 -> 41.1987 | N71: =SUM(K21:N21) -> 41.1987 | O71: =SUM(L21:O21) -> 40.970752 | P71: =SUM(M21:P21) -> 40.867497 | Q71: =SUM(N21:Q21) -> 40.215719 | R71: =SUM(O21:R21) -> 39.416728 | S71: =SUM(P21:S21) -> 39.613812 | T71: =SUM(Q21:T21) -> 39.811881 | U71: =SUM(R21:U21) -> 40.01094 | ... AH71: =SUM(AE21:AH21) -> 42.691121
B72: Net Working Capital | L72: =+L51+L53-L59-L60 -> -7.2304309 | N72: =+N51+N53-N59-N60 -> -7.2304309 | O72: =+O51+O53-O59-O60 -> -4.7106695 | P72: =+P51+P53-P59-P60 -> -2.1601276 | Q72: =+Q51+Q53-Q59-Q60 -> -1.4438571 | R72: =+R51+R53-R59-R60 -> -3.6331961 | S72: =+S51+S53-S59-S60 -> -1.1985859 | T72: =+T51+T53-T59-T60 -> 1.2700055 | U72: =+U51+U53-U59-U60 -> 1.9527838 | ... AH72: =+AH51+AH53-AH59-AH60 -> 7.9626725
B74: Metrics & Drivers
B75: Receivable Days Outstanding | N75: =N51/N8*90 -> 13.448191 | O75: =O51/O8*90 -> 12.681977 | P75: =P51/P8*90 -> 12.851627 | Q75: =Q51/Q8*90 -> 13.170293 | R75: =R51/R8*90 -> 13.672656 | S75: =S51/S8*90 -> 12.710599 | T75: =T51/T8*90 -> 12.876898 | U75: =U51/U8*90 -> 13.189269 | ... AH75: =AH51/AH8*90 -> 13.707811
B76: Payable Days Outstanding | N76: =N59/N15*90 -> 69.768213 | O76: 70 | P76: =O76 -> 70 | Q76: =P76 -> 70 | R76: =Q76 -> 70 | S76: =R76 -> 70 | T76: =S76 -> 70 | U76: =T76 -> 70 | V76: =U76 -> 70 | W76: =V76 -> 70 | ... AH76: =AG76 -> 70
B77: Prepaid Expenses, % of LTM Rev | N77: =N53/N68 -> 0.0405618 | O77: 0.04 | P77: =O77 -> 0.04 | Q77: =P77 -> 0.04 | R77: =Q77 -> 0.04 | S77: =R77 -> 0.04 | T77: =S77 -> 0.04 | U77: =T77 -> 0.04 | V77: =U77 -> 0.04 | W77: =V77 -> 0.04 | ... AH77: =AG77 -> 0.04
B78: Deferred Commissions, % of LTM S&M Expense | N78: =+N54/N70 -> 0.23475325 | O78: =+O54/O70 -> 0.26368836 | P78: =+P54/P70 -> 0.29185458 | Q78: =+Q54/Q70 -> 0.31903196 | R78: =+R54/R70 -> 0.34358048 | S78: =+S54/S70 -> 0.36105699 | T78: =+T54/T70 -> 0.37575717 | U78: =+U54/U70 -> 0.38770823 | ... AH78: =+AH54/AH70 -> 0.3759449
B79: Capitalized Software Costs, % of LTM R&D Expense | N79: =N55/N71 -> 0.14347339 | O79: =O55/O71 -> 0.15258358 | P79: =P55/P71 -> 0.16077553 | Q79: =Q55/Q71 -> 0.17077646 | R79: =R55/R71 -> 0.18123193 | S79: =S55/S71 -> 0.18673789 | T79: =T55/T71 -> 0.19163322 | U79: =U55/U71 -> 0.19592385 | ... AH79: =AH55/AH71 -> 0.22582267
B80: Deferred Revenue, % of ARR | N80: =N60/N5 -> 0.053249055 | O80: =O60/O5 -> 0.043132526 | P80: =P60/P5 -> 0.036058991 | Q80: =Q60/Q5 -> 0.034662586 | R80: =R60/R5 -> 0.042180926 | S80: =S60/S5 -> 0.032535634 | T80: =T60/T5 -> 0.025871879 | U80: =U60/U5 -> 0.024771773 | ... AH80: =AH60/AH5 -> 0.010408129
B82: Net PP&E
B83: Beginning Net PP&E | O83: =+N86 -> 35.699125 | P83: =+O86 -> 36.513668 | Q83: =+P86 -> 37.332626 | R83: =+Q86 -> 38.152967 | S83: =+R86 -> 38.974149 | T83: =+S86 -> 39.799437 | U83: =+T86 -> 40.628851 | V83: =+U86 -> 41.462412 | ... AH83: =+AG86 -> 51.796271
B84: Capex | O84: =O90*O68 -> 8.9599703 | P84: =P90*P68 -> 9.0085387 | Q84: =Q90*Q68 -> 9.0237533 | R84: =R90*R68 -> 9.0330002 | S84: =S90*S68 -> 9.0781652 | T84: =T90*T68 -> 9.123556 | U84: =U90*U68 -> 9.1691738 | V84: =V90*V68 -> 9.2150196 | ... AH84: =AH90*AH68 -> 9.7833819
B85: Depreciation | O85: =-O89*O68 -> -8.1454275 | P85: =-P89*P68 -> -8.1895807 | Q85: =-Q89*Q68 -> -8.2034121 | R85: =-R89*R68 -> -8.2118183 | S85: =-S89*S68 -> -8.2528774 | T85: =-T89*T68 -> -8.2941418 | U85: =-U89*U68 -> -8.3356125 | V85: =-V89*V68 -> -8.3772906 | ... AH85: =-AH89*AH68 -> -8.8939835
B86: Ending Net PP&E | N86: =+N52 -> 35.699125 | O86: =SUM(O83:O85) -> 36.513668 | P86: =SUM(P83:P85) -> 37.332626 | Q86: =SUM(Q83:Q85) -> 38.152967 | R86: =SUM(R83:R85) -> 38.974149 | S86: =SUM(S83:S85) -> 39.799437 | T86: =SUM(T83:T85) -> 40.628851 | U86: =SUM(U83:U85) -> 41.462412 | V86: =SUM(V83:V85) -> 42.300141 | ... AH86: =SUM(AH83:AH85) -> 52.68567
B88: Drivers:
B89: Depreciation as % of LTM Rev | O89: 0.025 | P89: 0.025 | Q89: 0.025 | R89: 0.025 | S89: 0.025 | T89: 0.025 | U89: 0.025 | V89: 0.025 | W89: 0.025 | X89: 0.025 | Y89: 0.025 | Z89: 0.025 | AA89: 0.025 | AB89: 0.025 | AC89: 0.025 | AD89: 0.025 | AE89: 0.025 | AF89: 0.025 | AG89: 0.025 | AH89: 0.025
B90: Capex as % of LTM Rev | O90: 0.0275 | P90: 0.0275 | Q90: 0.0275 | R90: 0.0275 | S90: 0.0275 | T90: 0.0275 | U90: 0.0275 | V90: 0.0275 | W90: 0.0275 | X90: 0.0275 | Y90: 0.0275 | Z90: 0.0275 | AA90: 0.0275 | AB90: 0.0275 | AC90: 0.0275 | AD90: 0.0275 | AE90: 0.0275 | AF90: 0.0275 | AG90: 0.0275 | AH90: 0.0275
B92: Accounts Receivable
B93: Beginning Accounts Receivable | O93: =+N96 -> 12.312163 | P93: =+O96 -> 11.484919 | Q93: =+P96 -> 11.696749 | R93: =+Q96 -> 12.046712 | S93: =+R96 -> 12.568749 | T93: =+S96 -> 11.742789 | U93: =+T96 -> 11.955908 | V93: =+U96 -> 12.307167 | ... AH93: =+AG96 -> 13.120445
B94: New Billings | O94: =+'Billing Waterfall'!I69 -> 78.159215 | P94: =+'Billing Waterfall'!J69 -> 79.571412 | Q94: =+'Billing Waterfall'!K69 -> 81.9045 | R94: =+'Billing Waterfall'!L69 -> 85.384746 | S94: =+'Billing Waterfall'!M69 -> 79.878344 | T94: =+'Billing Waterfall'!N69 -> 81.299136 | U94: =+'Billing Waterfall'!O69 -> 83.640863 | V94: =+'Billing Waterfall'!P69 -> 87.129791 | ... AH94: =+'Billing Waterfall'!AB69 -> 92.578755
B95: Cash Collected | O95: =+-'Billing Waterfall'!I126 -> -78.986459 | P95: =+-'Billing Waterfall'!J126 -> -79.359583 | Q95: =+-'Billing Waterfall'!K126 -> -81.554537 | R95: =+-'Billing Waterfall'!L126 -> -84.862709 | S95: =+-'Billing Waterfall'!M126 -> -80.704304 | T95: =+-'Billing Waterfall'!N126 -> -81.086018 | U95: =+-'Billing Waterfall'!O126 -> -83.289604 | V95: =+-'Billing Waterfall'!P126 -> -86.606452 | ... AH95: =+-'Billing Waterfall'!AB126 -> -92.051349
B96: Ending Accounts Receivable | N96: =N51 -> 12.312163 | O96: =SUM(O93:O95) -> 11.484919 | P96: =SUM(P93:P95) -> 11.696749 | Q96: =SUM(Q93:Q95) -> 12.046712 | R96: =SUM(R93:R95) -> 12.568749 | S96: =SUM(S93:S95) -> 11.742789 | T96: =SUM(T93:T95) -> 11.955908 | U96: =SUM(U93:U95) -> 12.307167 | V96: =SUM(V93:V95) -> 12.830506 | ... AH96: =SUM(AH93:AH95) -> 13.64785
B98: Deferred Revenue
B99: Beginning Deferred Revenue | O99: =+N102 -> 17.993601 | P99: =+O102 -> 14.64796 | Q99: =+P102 -> 12.306991 | R99: =+Q102 -> 11.889548 | S99: =+R102 -> 14.540741 | T99: =+S102 -> 11.271865 | U99: =+T102 -> 9.0080446 | V99: =+U102 -> 8.668136 | ... AH99: =+AG102 -> 0.91354531
B100: New Billings | O100: =O94 -> 78.159215 | P100: =P94 -> 79.571412 | Q100: =Q94 -> 81.9045 | R100: =R94 -> 85.384746 | S100: =S94 -> 79.878344 | T100: =T94 -> 81.299136 | U100: =U94 -> 83.640863 | V100: =V94 -> 87.129791 | ... AH100: =AH94 -> 92.578755
B101: Recognized Revenue | O101: =-O8 -> -81.504857 | P101: =-P8 -> -81.912381 | Q101: =-Q8 -> -82.321943 | R101: =-R8 -> -82.733553 | S101: =-S8 -> -83.14722 | T101: =-T8 -> -83.562957 | U101: =-U8 -> -83.980771 | V101: =-V8 -> -84.400675 | ... AH101: =-AH8 -> -89.606324
B102: Ending Deferred Revenue | N102: =N60 -> 17.993601 | O102: =SUM(O99:O101) -> 14.64796 | P102: =SUM(P99:P101) -> 12.306991 | Q102: =SUM(Q99:Q101) -> 11.889548 | R102: =SUM(R99:R101) -> 14.540741 | S102: =SUM(S99:S101) -> 11.271865 | T102: =SUM(T99:T101) -> 9.0080446 | U102: =SUM(U99:U101) -> 8.668136 | V102: =SUM(V99:V101) -> 11.397252 | ... AH102: =SUM(AH99:AH101) -> 3.8859757
B104: Debt Schedule | AH104: $ in millions, except noted
O105: =+O4 -> 45016 | P105: =+P4 -> 45107 | Q105: =+Q4 -> 45199 | R105: =+R4 -> 45291 | S105: =+S4 -> 45382 | T105: =+T4 -> 45473 | U105: =+U4 -> 45565 | V105: =+V4 -> 45657 | ... AH105: =+AH4 -> 46752
B106: Cash Available Before Revolver
B107: Beginning Cash Balance | O107: =+O163 -> 25 | P107: =+P163 -> 25 | Q107: =+Q163 -> 25 | R107: =+R163 -> 25 | S107: =+S163 -> 25 | T107: =+T163 -> 25 | U107: =+U163 -> 25 | V107: =+V163 -> 25 | ... AH107: =+AH163 -> 25
B108: Free Cash Flow | O108: =+O156 -> 3.6456779 | P108: =+P156 -> 3.9738686 | Q108: =+Q156 -> 6.1907626 | R108: =+R156 -> 9.5226922 | S108: =+S156 -> 5.3167897 | T108: =+T156 -> 5.6735201 | U108: =+U156 -> 7.8707409 | V108: =+V156 -> 11.222299 | ... AH108: =+AH156 -> 15.544662
B109: Required Minimum Cash Balance | O109: 25 | P109: 25 | Q109: 25 | R109: 25 | S109: 25 | T109: 25 | U109: 25 | V109: 25 | W109: 25 | X109: 25 | Y109: 25 | Z109: 25 | AA109: 25 | AB109: 25 | AC109: 25 | AD109: 25 | AE109: 25 | AF109: 25 | AG109: 25 | AH109: 25
B110: Cash Available Before Revolver | O110: =+O107-O109+O108 -> 3.6456779 | P110: =+P107-P109+P108 -> 3.9738686 | Q110: =+Q107-Q109+Q108 -> 6.1907626 | R110: =+R107-R109+R108 -> 9.5226922 | S110: =+S107-S109+S108 -> 5.3167897 | T110: =+T107-T109+T108 -> 5.6735201 | U110: =+U107-U109+U108 -> 7.8707409 | V110: =+V107-V109+V108 -> 11.222299 | ... AH110: =+AH107-AH109+AH108 -> 15.544662
B112: Revolver
B113: Beginning Balance | O113: =+N115 -> 0 | P113: =+O115 -> 0 | Q113: =+P115 -> 0 | R113: =+Q115 -> 0 | S113: =+R115 -> 0 | T113: =+S115 -> 0 | U113: =+T115 -> 0 | V113: =+U115 -> 0 | ... AH113: =+AG115 -> 0
B114: Net Issuance / (Paydown) | O114: =-MIN(O113,O110) -> 0 | P114: =-MIN(P113,P110) -> 0 | Q114: =-MIN(Q113,Q110) -> 0 | R114: =-MIN(R113,R110) -> 0 | S114: =-MIN(S113,S110) -> 0 | T114: =-MIN(T113,T110) -> 0 | U114: =-MIN(U113,U110) -> 0 | V114: =-MIN(V113,V110) -> 0 | ... AH114: =-MIN(AH113,AH110) -> 0
B115: Ending Balance | N115: =+Transaction!D18 -> 0 | O115: =SUM(O113:O114) -> 0 | P115: =SUM(P113:P114) -> 0 | Q115: =SUM(Q113:Q114) -> 0 | R115: =SUM(R113:R114) -> 0 | S115: =SUM(S113:S114) -> 0 | T115: =SUM(T113:T114) -> 0 | U115: =SUM(U113:U114) -> 0 | V115: =SUM(V113:V114) -> 0 | ... AH115: =SUM(AH113:AH114) -> 0
B116: % Interest Rate | O116: =Transaction!$E$18 -> 0.02 | P116: =Transaction!$E$18 -> 0.02 | Q116: =Transaction!$E$18 -> 0.02 | R116: =Transaction!$E$18 -> 0.02 | S116: =Transaction!$E$18 -> 0.02 | T116: =Transaction!$E$18 -> 0.02 | U116: =Transaction!$E$18 -> 0.02 | V116: =Transaction!$E$18 -> 0.02 | ... AH116: =Transaction!$E$18 -> 0.02
B117: Interest Expense | O117: =+O116*AVERAGE(N115:O115) -> 0 | P117: =+P116*AVERAGE(O115:P115) -> 0 | Q117: =+Q116*AVERAGE(P115:Q115) -> 0 | R117: =+R116*AVERAGE(Q115:R115) -> 0 | S117: =+S116*AVERAGE(R115:S115) -> 0 | T117: =+T116*AVERAGE(S115:T115) -> 0 | U117: =+U116*AVERAGE(T115:U115) -> 0 | V117: =+V116*AVERAGE(U115:V115) -> 0 | ... AH117: =+AH116*AVERAGE(AG115:AH115) -> 0
B119: Cash Available Before Term Loan B | O119: =+O114+O110 -> 3.6456779 | P119: =+P114+P110 -> 3.9738686 | Q119: =+Q114+Q110 -> 6.1907626 | R119: =+R114+R110 -> 9.5226922 | S119: =+S114+S110 -> 5.3167897 | T119: =+T114+T110 -> 5.6735201 | U119: =+U114+U110 -> 7.8707409 | V119: =+V114+V110 -> 11.222299 | ... AH119: =+AH114+AH110 -> 15.544662
B121: Term Loan B
B122: Beginning Balance | O122: =+N124 -> 438.26578 | P122: =+O124 -> 434.6201 | Q122: =+P124 -> 430.64623 | R122: =+Q124 -> 424.45547 | S122: =+R124 -> 414.93277 | T122: =+S124 -> 409.61598 | U122: =+T124 -> 403.94246 | V122: =+U124 -> 396.07172 | ... AH122: =+AG124 -> 269.6454
B123: Optional (Paydown) | O123: =-MIN(O122,O119) -> -3.6456779 | P123: =-MIN(P122,P119) -> -3.9738686 | Q123: =-MIN(Q122,Q119) -> -6.1907626 | R123: =-MIN(R122,R119) -> -9.5226922 | S123: =-MIN(S122,S119) -> -5.3167897 | T123: =-MIN(T122,T119) -> -5.6735201 | U123: =-MIN(U122,U119) -> -7.8707409 | V123: =-MIN(V122,V119) -> -11.222299 | ... AH123: =-MIN(AH122,AH119) -> -15.544662
B124: Ending Balance | N124: =+Transaction!D19 -> 438.26578 | O124: =SUM(O122:O123) -> 434.6201 | P124: =SUM(P122:P123) -> 430.64623 | Q124: =SUM(Q122:Q123) -> 424.45547 | R124: =SUM(R122:R123) -> 414.93277 | S124: =SUM(S122:S123) -> 409.61598 | T124: =SUM(T122:T123) -> 403.94246 | U124: =SUM(U122:U123) -> 396.07172 | V124: =SUM(V122:V123) -> 384.84942 | ... AH124: =SUM(AH122:AH123) -> 254.10073
...

Sheet Billing Waterfall
AB2: $ in millions, except noted
I3: =EOMONTH(#REF!, 3) -> #REF! | J3: =EOMONTH(I3, 3) -> #REF! | K3: =EOMONTH(J3, 3) -> #REF! | L3: =EOMONTH(K3, 3) -> #REF! | M3: =EOMONTH(L3, 3) -> #REF! | N3: =EOMONTH(M3, 3) -> #REF! | O3: =EOMONTH(N3, 3) -> #REF! | P3: =EOMONTH(O3, 3) -> #REF! | Q3: =EOMONTH(P3, 3) -> #REF! | ... AB3: =EOMONTH(AA3, 3) -> #REF!
I4: =EOMONTH(#REF!, 2)+1 -> #REF! | J4: =EOMONTH(I4, 2)+1 -> #REF! | K4: =EOMONTH(J4, 2)+1 -> #REF! | L4: =EOMONTH(K4, 2)+1 -> #REF! | M4: =EOMONTH(L4, 2)+1 -> #REF! | N4: =EOMONTH(M4, 2)+1 -> #REF! | O4: =EOMONTH(N4, 2)+1 -> #REF! | P4: =EOMONTH(O4, 2)+1 -> #REF! | Q4: =EOMONTH(P4, 2)+1 -> #REF! | ... AB4: =EOMONTH(AA4, 2)+1 -> #REF!
E5: =EOMONTH(F5, -3) -> 44651 | F5: =EOMONTH(G5, -3) -> 44742 | G5: =EOMONTH(H5, -3) -> 44834 | H5: =EOMONTH(I5, -3) -> 44926 | I5: =Model!O4 -> 45016 | J5: =EOMONTH(I5, 3) -> 45107 | K5: =EOMONTH(J5, 3) -> 45199 | L5: =EOMONTH(K5, 3) -> 45291 | M5: =EOMONTH(L5, 3) -> 45382 | N5: =EOMONTH(M5, 3) -> 45473 | O5: =EOMONTH(N5, 3) -> 45565 | P5: =EOMONTH(O5, 3) -> 45657 | Q5: =EOMONTH(P5, 3) -> 45747 | ... AB5: =EOMONTH(AA5, 3) -> 46752
B6: ARR Eligible for Billings | H6: `
B7: Prior Year Renewal ARR | E7: 72.741228 | F7: 73.966444 | G7: 74.663909 | H7: 75.736755 | I7: =+E12 -> 75.371068 | J7: =+F12 -> 77.306652 | K7: =+G12 -> 80.657805 | L7: =+H12 -> 85.772627 | M7: =+I12 -> 77.060638 | N7: =+J12 -> 79.004669 | O7: =+K12 -> 82.364313 | P7: =+L12 -> 87.487667 | ... AB7: =+X12 -> 92.842942
B8: New Logo ARR | E8: ='ARR Waterfall'!K7 -> 15.34464 | F8: ='ARR Waterfall'!L7 -> 12.672 | G8: ='ARR Waterfall'!M7 -> 18.432 | H8: ='ARR Waterfall'!N7 -> 18.98496 | I8: ='ARR Waterfall'!O7 -> 13.51656 | J8: ='ARR Waterfall'!P7 -> 13.584143 | K8: ='ARR Waterfall'!Q7 -> 13.652064 | L8: ='ARR Waterfall'!R7 -> 13.720324 | ... AB8: ='ARR Waterfall'!AH7 -> 14.860087
B9: Upsell ARR | E9: ='ARR Waterfall'!K8 -> 4.374232 | F9: ='ARR Waterfall'!L8 -> 4.794456 | G9: ='ARR Waterfall'!M8 -> 3.091184 | H9: ='ARR Waterfall'!N8 -> 4.551768 | I9: ='ARR Waterfall'!O8 -> 5.06871 | J9: ='ARR Waterfall'!P8 -> 5.0940536 | K9: ='ARR Waterfall'!Q8 -> 5.1195238 | L9: ='ARR Waterfall'!R8 -> 5.1451214 | ... AB9: ='ARR Waterfall'!AH8 -> 5.5725326
B10: Downsell ARR | E10: ='ARR Waterfall'!K9 -> -3.469624 | F10: ='ARR Waterfall'!L9 -> -1.843504 | G10: ='ARR Waterfall'!M9 -> -4.098736 | H10: ='ARR Waterfall'!N9 -> -1.989072 | I10: ='ARR Waterfall'!O9 -> -3.37914 | J10: ='ARR Waterfall'!P9 -> -3.3960357 | K10: ='ARR Waterfall'!Q9 -> -3.4130159 | L10: ='ARR Waterfall'!R9 -> -3.430081 | ... AB10: ='ARR Waterfall'!AH9 -> -3.7150217
B11: Churn ARR | E11: ='ARR Waterfall'!K10 -> -13.619408 | F11: ='ARR Waterfall'!L10 -> -12.282744 | G11: ='ARR Waterfall'!M10 -> -11.430552 | H11: ='ARR Waterfall'!N10 -> -11.511784 | I11: ='ARR Waterfall'!O10 -> -13.51656 | J11: ='ARR Waterfall'!P10 -> -13.584143 | K11: ='ARR Waterfall'!Q10 -> -13.652064 | L11: ='ARR Waterfall'!R10 -> -13.720324 | ... AB11: ='ARR Waterfall'!AH10 -> -14.860087
B12: ARR Eligible for Billing | E12: =SUM(E7:E11) -> 75.371068 | F12: =SUM(F7:F11) -> 77.306652 | G12: =SUM(G7:G11) -> 80.657805 | H12: =SUM(H7:H11) -> 85.772627 | I12: =SUM(I7:I11) -> 77.060638 | J12: =SUM(J7:J11) -> 79.004669 | K12: =SUM(K7:K11) -> 82.364313 | L12: =SUM(L7:L11) -> 87.487667 | ... AB12: =SUM(AB7:AB11) -> 94.700452
B14: Upfront (Annual) Billing
B15: Cohort | C15: $ Eligible | D15: Cohort %
B16: {=TRANSPOSE(E5:AB5)} -> 44651 | C16: {=TRANSPOSE(E12:AB12)} -> 75.371068 | D16: 0.65 | E16: =$C16*$D16 -> 48.991194
B17: 44742 | C17: 77.306652 | D17: =+D16 -> 0.65 | F17: =$C17*$D17 -> 50.249323
B18: 44834 | C18: 80.657805 | D18: =+D17 -> 0.65 | G18: =$C18*$D18 -> 52.427573
B19: 44926 | C19: 85.772627 | D19: =+D18 -> 0.65 | H19: =$C19*$D19 -> 55.752207
B20: 45016 | C20: 77.060638 | D20: =+D19 -> 0.65 | I20: =$C20*$D20 -> 50.089415
B21: 45107 | C21: 79.004669 | D21: =+D20 -> 0.65 | J21: =$C21*$D21 -> 51.353035
B22: 45199 | C22: 82.364313 | D22: =+D21 -> 0.65 | K22: =$C22*$D22 -> 53.536803
B23: 45291 | C23: 87.487667 | D23: =+D22 -> 0.65 | L23: =$C23*$D23 -> 56.866984
B24: 45382 | C24: 78.784254 | D24: =+D23 -> 0.65 | M24: =$C24*$D24 -> 51.209765
B25: 45473 | C25: 80.736903 | D25: =+D24 -> 0.65 | N25: =$C25*$D25 -> 52.478987
B26: 45565 | C26: 84.105208 | D26: =+D25 -> 0.65 | O26: =$C26*$D26 -> 54.668385
B27: 45657 | C27: 89.237266 | D27: =+D26 -> 0.65 | P27: =$C27*$D27 -> 58.004223
B28: 45747 | C28: 80.542601 | D28: =+D27 -> 0.65 | Q28: =$C28*$D28 -> 52.352691
B29: 45838 | C29: 82.504042 | D29: =+D28 -> 0.65 | R29: =$C29*$D29 -> 53.627627
B30: 45930 | C30: 85.881183 | D30: =+D29 -> 0.65 | S30: =$C30*$D30 -> 55.822769
B31: 46022 | C31: 91.022121 | D31: =+D30 -> 0.65 | T31: =$C31*$D31 -> 59.164379
B32: 46112 | C32: 82.33638 | D32: =+D31 -> 0.65 | U32: =$C32*$D32 -> 53.518647
B33: 46203 | C33: 84.30679 | D33: =+D32 -> 0.65 | V33: =$C33*$D33 -> 54.799414
B34: 46295 | C34: 87.692944 | D34: =+D33 -> 0.65 | W34: =$C34*$D34 -> 57.000414
B35: 46387 | C35: 92.842942 | D35: =+D34 -> 0.65 | X35: =$C35*$D35 -> 60.347912
B36: 46477 | C36: 84.166305 | D36: =+D35 -> 0.65 | Y36: =$C36*$D36 -> 54.708098
B37: 46568 | C37: 86.145864 | D37: =+D36 -> 0.65 | Z37: =$C37*$D37 -> 55.994812
B38: 46660 | C38: 89.541214 | D38: =+D37 -> 0.65 | AA38: =$C38*$D38 -> 58.201789
B39: 46752 | C39: 94.700452 | D39: =+D38 -> 0.65 | AB39: =$C39*$D39 -> 61.555294
B42: Quarterly Billing
B43: Cohort | C43: $ Eligible | D43: Cohort %
B44: =+B16 -> 44651 | C44: =+C16 -> 75.371068 | D44: =1-D16 -> 0.35 | E44: =$C44*$D44/4 -> 6.5949685 | F44: =$C44*$D44/4 -> 6.5949685 | G44: =$C44*$D44/4 -> 6.5949685 | H44: =$C44*$D44/4 -> 6.5949685
B45: =+B17 -> 44742 | C45: =+C17 -> 77.306652 | D45: =1-D17 -> 0.35 | F45: =$C45*$D45/4 -> 6.764332 | G45: =$C45*$D45/4 -> 6.764332 | H45: =$C45*$D45/4 -> 6.764332 | I45: =$C45*$D45/4 -> 6.764332
B46: =+B18 -> 44834 | C46: =+C18 -> 80.657805 | D46: =1-D18 -> 0.35 | G46: =$C46*$D46/4 -> 7.0575579 | H46: =$C46*$D46/4 -> 7.0575579 | I46: =$C46*$D46/4 -> 7.0575579 | J46: =$C46*$D46/4 -> 7.0575579
B47: =+B19 -> 44926 | C47: =+C19 -> 85.772627 | D47: =1-D19 -> 0.35 | H47: =$C47*$D47/4 -> 7.5051048 | I47: =$C47*$D47/4 -> 7.5051048 | J47: =$C47*$D47/4 -> 7.5051048 | K47: =$C47*$D47/4 -> 7.5051048
B48: =+B20 -> 45016 | C48: =+C20 -> 77.060638 | D48: =1-D20 -> 0.35 | I48: =$C48*$D48/4 -> 6.7428058 | J48: =$C48*$D48/4 -> 6.7428058 | K48: =$C48*$D48/4 -> 6.7428058 | L48: =$C48*$D48/4 -> 6.7428058
B49: =+B21 -> 45107 | C49: =+C21 -> 79.004669 | D49: =1-D21 -> 0.35 | J49: =$C49*$D49/4 -> 6.9129086 | K49: =$C49*$D49/4 -> 6.9129086 | L49: =$C49*$D49/4 -> 6.9129086 | M49: =$C49*$D49/4 -> 6.9129086
B50: =+B22 -> 45199 | C50: =+C22 -> 82.364313 | D50: =1-D22 -> 0.35 | K50: =$C50*$D50/4 -> 7.2068774 | L50: =$C50*$D50/4 -> 7.2068774 | M50: =$C50*$D50/4 -> 7.2068774 | N50: =$C50*$D50/4 -> 7.2068774
B51: =+B23 -> 45291 | C51: =+C23 -> 87.487667 | D51: =1-D23 -> 0.35 | L51: =$C51*$D51/4 -> 7.6551709 | M51: =$C51*$D51/4 -> 7.6551709 | N51: =$C51*$D51/4 -> 7.6551709 | O51: =$C51*$D51/4 -> 7.6551709
B52: =+B24 -> 45382 | C52: =+C24 -> 78.784254 | D52: =1-D24 -> 0.35 | M52: =$C52*$D52/4 -> 6.8936222 | N52: =$C52*$D52/4 -> 6.8936222 | O52: =$C52*$D52/4 -> 6.8936222 | P52: =$C52*$D52/4 -> 6.8936222
B53: =+B25 -> 45473 | C53: =+C25 -> 80.736903 | D53: =1-D25 -> 0.35 | N53: =$C53*$D53/4 -> 7.064479 | O53: =$C53*$D53/4 -> 7.064479 | P53: =$C53*$D53/4 -> 7.064479 | Q53: =$C53*$D53/4 -> 7.064479
B54: =+B26 -> 45565 | C54: =+C26 -> 84.105208 | D54: =1-D26 -> 0.35 | O54: =$C54*$D54/4 -> 7.3592057 | P54: =$C54*$D54/4 -> 7.3592057 | Q54: =$C54*$D54/4 -> 7.3592057 | R54: =$C54*$D54/4 -> 7.3592057
B55: =+B27 -> 45657 | C55: =+C27 -> 89.237266 | D55: =1-D27 -> 0.35 | P55: =$C55*$D55/4 -> 7.8082608 | Q55: =$C55*$D55/4 -> 7.8082608 | R55: =$C55*$D55/4 -> 7.8082608 | S55: =$C55*$D55/4 -> 7.8082608
B56: =+B28 -> 45747 | C56: =+C28 -> 80.542601 | D56: =1-D28 -> 0.35 | Q56: =$C56*$D56/4 -> 7.0474776 | R56: =$C56*$D56/4 -> 7.0474776 | S56: =$C56*$D56/4 -> 7.0474776 | T56: =$C56*$D56/4 -> 7.0474776
B57: =+B29 -> 45838 | C57: =+C29 -> 82.504042 | D57: =1-D29 -> 0.35 | R57: =$C57*$D57/4 -> 7.2191037 | S57: =$C57*$D57/4 -> 7.2191037 | T57: =$C57*$D57/4 -> 7.2191037 | U57: =$C57*$D57/4 -> 7.2191037
B58: =+B30 -> 45930 | C58: =+C30 -> 85.881183 | D58: =1-D30 -> 0.35 | S58: =$C58*$D58/4 -> 7.5146035 | T58: =$C58*$D58/4 -> 7.5146035 | U58: =$C58*$D58/4 -> 7.5146035 | V58: =$C58*$D58/4 -> 7.5146035
B59: =+B31 -> 46022 | C59: =+C31 -> 91.022121 | D59: =1-D31 -> 0.35 | T59: =$C59*$D59/4 -> 7.9644356 | U59: =$C59*$D59/4 -> 7.9644356 | V59: =$C59*$D59/4 -> 7.9644356 | W59: =$C59*$D59/4 -> 7.9644356
B60: =+B32 -> 46112 | C60: =+C32 -> 82.33638 | D60: =1-D32 -> 0.35 | U60: =$C60*$D60/4 -> 7.2044333 | V60: =$C60*$D60/4 -> 7.2044333 | W60: =$C60*$D60/4 -> 7.2044333 | X60: =$C60*$D60/4 -> 7.2044333
B61: =+B33 -> 46203 | C61: =+C33 -> 84.30679 | D61: =1-D33 -> 0.35 | V61: =$C61*$D61/4 -> 7.3768441 | W61: =$C61*$D61/4 -> 7.3768441 | X61: =$C61*$D61/4 -> 7.3768441 | Y61: =$C61*$D61/4 -> 7.3768441
B62: =+B34 -> 46295 | C62: =+C34 -> 87.692944 | D62: =1-D34 -> 0.35 | W62: =$C62*$D62/4 -> 7.6731326 | X62: =$C62*$D62/4 -> 7.6731326 | Y62: =$C62*$D62/4 -> 7.6731326 | Z62: =$C62*$D62/4 -> 7.6731326
B63: =+B35 -> 46387 | C63: =+C35 -> 92.842942 | D63: =1-D35 -> 0.35 | X63: =$C63*$D63/4 -> 8.1237574 | Y63: =$C63*$D63/4 -> 8.1237574 | Z63: =$C63*$D63/4 -> 8.1237574 | AA63: =$C63*$D63/4 -> 8.1237574
B64: =+B36 -> 46477 | C64: =+C36 -> 84.166305 | D64: =1-D36 -> 0.35 | Y64: =$C64*$D64/4 -> 7.3645517 | Z64: =$C64*$D64/4 -> 7.3645517 | AA64: =$C64*$D64/4 -> 7.3645517 | AB64: =$C64*$D64/4 -> 7.3645517
B65: =+B37 -> 46568 | C65: =+C37 -> 86.145864 | D65: =1-D37 -> 0.35 | Z65: =$C65*$D65/4 -> 7.5377631 | AA65: =$C65*$D65/4 -> 7.5377631 | AB65: =$C65*$D65/4 -> 7.5377631
B66: =+B38 -> 46660 | C66: =+C38 -> 89.541214 | D66: =1-D38 -> 0.35 | AA66: =$C66*$D66/4 -> 7.8348562 | AB66: =$C66*$D66/4 -> 7.8348562
B67: =+B39 -> 46752 | C67: =+C39 -> 94.700452 | D67: =1-D39 -> 0.35 | AB67: =$C67*$D67/4 -> 8.2862896
B69: Total Billed Amount | E69: =SUM(E16:E68) -> 55.586163 | F69: =SUM(F16:F68) -> 63.608624 | G69: =SUM(G16:G68) -> 72.844432 | H69: =SUM(H16:H68) -> 83.67417 | I69: =SUM(I16:I68) -> 78.159215 | J69: =SUM(J16:J68) -> 79.571412 | K69: =SUM(K16:K68) -> 81.9045 | L69: =SUM(L16:L68) -> 85.384746 | ... AB69: =SUM(AB16:AB68) -> 92.578755
B72: Cash Collections in Same Quarter
B73: Cohort | C73: $ Billed | D73: Cohort %
B74: =+B44 -> 44651 | C74: {=TRANSPOSE(E69:AB69)} -> 55.586163 | D74: 0.85 | E74: =+$C74*$D74 -> 47.248238
B75: =+B45 -> 44742 | C75: 63.608624 | D75: =+D74 -> 0.85 | F75: =+$C75*$D75 -> 54.06733
B76: =+B46 -> 44834 | C76: 72.844432 | D76: =+D75 -> 0.85 | G76: =+$C76*$D76 -> 61.917767
B77: =+B47 -> 44926 | C77: 83.67417 | D77: =+D76 -> 0.85 | H77: =+$C77*$D77 -> 71.123045
B78: =+B48 -> 45016 | C78: 78.159215 | D78: =+D77 -> 0.85 | I78: =+$C78*$D78 -> 66.435333
B79: =+B49 -> 45107 | C79: 79.571412 | D79: =+D78 -> 0.85 | J79: =+$C79*$D79 -> 67.6357
B80: =+B50 -> 45199 | C80: 81.9045 | D80: =+D79 -> 0.85 | K80: =+$C80*$D80 -> 69.618825
B81: =+B51 -> 45291 | C81: 85.384746 | D81: =+D80 -> 0.85 | L81: =+$C81*$D81 -> 72.577034
B82: =+B52 -> 45382 | C82: 79.878344 | D82: =+D81 -> 0.85 | M82: =+$C82*$D82 -> 67.896592
B83: =+B53 -> 45473 | C83: 81.299136 | D83: =+D82 -> 0.85 | N83: =+$C83*$D83 -> 69.104266
B84: =+B54 -> 45565 | C84: 83.640863 | D84: =+D83 -> 0.85 | O84: =+$C84*$D84 -> 71.094733
B85: =+B55 -> 45657 | C85: 87.129791 | D85: =+D84 -> 0.85 | P85: =+$C85*$D85 -> 74.060322
B86: =+B56 -> 45747 | C86: 81.632114 | D86: =+D85 -> 0.85 | Q86: =+$C86*$D86 -> 69.387297
B87: =+B57 -> 45838 | C87: 83.061675 | D87: =+D86 -> 0.85 | R87: =+$C87*$D87 -> 70.602424
B88: =+B58 -> 45930 | C88: 85.412214 | D88: =+D87 -> 0.85 | S88: =+$C88*$D88 -> 72.600382
B89: =+B59 -> 46022 | C89: 88.909999 | D89: =+D88 -> 0.85 | T89: =+$C89*$D89 -> 75.573499
B90: =+B60 -> 46112 | C90: 83.421223 | D90: =+D89 -> 0.85 | U90: =+$C90*$D90 -> 70.90804
B91: =+B61 -> 46203 | C91: 84.85973 | D91: =+D90 -> 0.85 | V91: =+$C91*$D91 -> 72.130771
B92: =+B62 -> 46295 | C92: 87.219259 | D92: =+D91 -> 0.85 | W92: =+$C92*$D92 -> 74.13637
B93: =+B63 -> 46387 | C93: 90.726079 | D93: =+D92 -> 0.85 | X93: =+$C93*$D93 -> 77.117167
B94: =+B64 -> 46477 | C94: 85.246384 | D94: =+D93 -> 0.85 | Y94: =+$C94*$D94 -> 72.459426
B95: =+B65 -> 46568 | C95: 86.694017 | D95: =+D94 -> 0.85 | Z95: =+$C95*$D95 -> 73.689914
B96: =+B66 -> 46660 | C96: 89.062717 | D96: =+D95 -> 0.85 | AA96: =+$C96*$D96 -> 75.70331
B97: =+B67 -> 46752 | C97: 92.578755 | D97: =+D96 -> 0.85 | AB97: =+$C97*$D97 -> 78.691941
B99: Cash Collections in Next Quarter
B100: Cohort | C100: $ Billed | D100: Cohort %
B101: =B74 -> 44651 | C101: =+C74 -> 55.586163 | D101: =1-D74 -> 0.15 | F101: =+$C101*$D101 -> 8.3379244
B102: =B75 -> 44742 | C102: =+C75 -> 63.608624 | D102: =1-D75 -> 0.15 | G102: =+$C102*$D102 -> 9.5412936
B103: =B76 -> 44834 | C103: =+C76 -> 72.844432 | D103: =1-D76 -> 0.15 | H103: =+$C103*$D103 -> 10.926665
B104: =B77 -> 44926 | C104: =+C77 -> 83.67417 | D104: =1-D77 -> 0.15 | I104: =+$C104*$D104 -> 12.551126
B105: =B78 -> 45016 | C105: =+C78 -> 78.159215 | D105: =1-D78 -> 0.15 | J105: =+$C105*$D105 -> 11.723882
B106: =B79 -> 45107 | C106: =+C79 -> 79.571412 | D106: =1-D79 -> 0.15 | K106: =+$C106*$D106 -> 11.935712
B107: =B80 -> 45199 | C107: =+C80 -> 81.9045 | D107: =1-D80 -> 0.15 | L107: =+$C107*$D107 -> 12.285675
B108: =B81 -> 45291 | C108: =+C81 -> 85.384746 | D108: =1-D81 -> 0.15 | M108: =+$C108*$D108 -> 12.807712
...

Sheet Capitalizations
AA2: $ in millions, except noted
G3: 44926 | H3: =EOMONTH(G3, 3) -> 45016 | I3: =EOMONTH(H3, 3) -> 45107 | J3: =EOMONTH(I3, 3) -> 45199 | K3: =EOMONTH(J3, 3) -> 45291 | L3: =EOMONTH(K3, 3) -> 45382 | M3: =EOMONTH(L3, 3) -> 45473 | N3: =EOMONTH(M3, 3) -> 45565 | O3: =EOMONTH(N3, 3) -> 45657 | ... AA3: =EOMONTH(Z3, 3) -> 46752
B4: Deferred Commissions
B5: Balance Sheet
B6: Beginning Deferred Commissions | H6: =+G9 -> 14.2204 | I6: =+H9 -> 15.972382 | J6: =+I9 -> 17.572521 | K6: =+J9 -> 19.020057 | L6: =+K9 -> 20.314227 | M6: =+L9 -> 21.454265 | N6: =+M9 -> 22.4394 | O6: =+N9 -> 23.268856 | ... AA6: =+Z9 -> 23.954491
B7: New Deferred Commissions | H7: =+H12*H13 -> 2.6407574 | I7: =+I12*I13 -> 2.6539611 | J7: =+J12*J13 -> 2.667231 | K7: =+K12*K13 -> 2.6805671 | L7: =+L12*L13 -> 2.6939699 | M7: =+M12*M13 -> 2.7074398 | N7: =+N12*N13 -> 2.720977 | O7: =+O12*O13 -> 2.7345819 | ... AA7: =+AA12*AA13 -> 2.9032449
B8: Amortization of Deferred Commissions | H8: =+-H39 -> -0.888775 | I8: =+-I39 -> -1.0538223 | J8: =+-J39 -> -1.2196949 | K8: =+-K39 -> -1.3863968 | L8: =+-L39 -> -1.5539323 | M8: =+-M39 -> -1.7223054 | N8: =+-N39 -> -1.8915204 | O8: =+-O39 -> -2.0615815 | ... AA8: =+-AA39 -> -2.7834724
B9: Ending Deferred Commissions | G9: =Model!N54 -> 14.2204 | H9: =SUM(H6:H8) -> 15.972382 | I9: =SUM(I6:I8) -> 17.572521 | J9: =SUM(J6:J8) -> 19.020057 | K9: =SUM(K6:K8) -> 20.314227 | L9: =SUM(L6:L8) -> 21.454265 | M9: =SUM(M6:M8) -> 22.4394 | N9: =SUM(N6:N8) -> 23.268856 | O9: =SUM(O6:O8) -> 23.941857 | ... AA9: =SUM(AA6:AA8) -> 24.074264
B11: Memo/Drivers:
B12: Total S&M Expense | H12: =Model!O20 -> 14.670874 | I12: =Model!P20 -> 14.744229 | J12: =Model!Q20 -> 14.81795 | K12: =Model!R20 -> 14.892039 | L12: =Model!S20 -> 14.9665 | M12: =Model!T20 -> 15.041332 | N12: =Model!U20 -> 15.116539 | O12: =Model!V20 -> 15.192122 | ... AA12: =Model!AH20 -> 16.129138
B13: Deferred Comp as % of Total S&M Expense | H13: 0.18 | I13: 0.18 | J13: 0.18 | K13: 0.18 | L13: 0.18 | M13: 0.18 | N13: 0.18 | O13: 0.18 | P13: 0.18 | Q13: 0.18 | R13: 0.18 | S13: 0.18 | T13: 0.18 | U13: 0.18 | V13: 0.18 | W13: 0.18 | X13: 0.18 | Y13: 0.18 | Z13: 0.18 | AA13: 0.18
B15: Amortization Schedule
B16: Cohort | C16: $ Deferrals | D16: Years | E16: Quarters | F16: End
B17: {=TRANSPOSE(G3:AA3)} -> 44926 | C17: =G9 -> 14.2204 | D17: 4 | E17: =+D17*4 -> 16 | F17: =EOMONTH(B17, D17*12) -> 46387 | H17: =$C17/$E17 -> 0.888775 | I17: =$C17/$E17 -> 0.888775 | J17: =$C17/$E17 -> 0.888775 | K17: =$C17/$E17 -> 0.888775 | L17: =$C17/$E17 -> 0.888775 | M17: =$C17/$E17 -> 0.888775 | N17: =$C17/$E17 -> 0.888775 | O17: =$C17/$E17 -> 0.888775 | ... W17: =$C17/$E17 -> 0.888775
B18: 45016 | C18: {=TRANSPOSE(H7:AA7)} -> 2.6407574 | D18: 4 | E18: =+D18*4 -> 16 | F18: =EOMONTH(B18, D18*12) -> 46477 | I18: =$C18/$E18 -> 0.16504734 | J18: =$C18/$E18 -> 0.16504734 | K18: =$C18/$E18 -> 0.16504734 | L18: =$C18/$E18 -> 0.16504734 | M18: =$C18/$E18 -> 0.16504734 | N18: =$C18/$E18 -> 0.16504734 | O18: =$C18/$E18 -> 0.16504734 | P18: =$C18/$E18 -> 0.16504734 | ... X18: =$C18/$E18 -> 0.16504734
B19: 45107 | C19: 2.6539611 | D19: 4 | E19: =+D19*4 -> 16 | F19: =EOMONTH(B19, D19*12) -> 46568 | J19: =$C19/$E19 -> 0.16587257 | K19: =$C19/$E19 -> 0.16587257 | L19: =$C19/$E19 -> 0.16587257 | M19: =$C19/$E19 -> 0.16587257 | N19: =$C19/$E19 -> 0.16587257 | O19: =$C19/$E19 -> 0.16587257 | P19: =$C19/$E19 -> 0.16587257 | Q19: =$C19/$E19 -> 0.16587257 | ... Y19: =$C19/$E19 -> 0.16587257
B20: 45199 | C20: 2.667231 | D20: 4 | E20: =+D20*4 -> 16 | F20: =EOMONTH(B20, D20*12) -> 46660 | K20: =$C20/$E20 -> 0.16670193 | L20: =$C20/$E20 -> 0.16670193 | M20: =$C20/$E20 -> 0.16670193 | N20: =$C20/$E20 -> 0.16670193 | O20: =$C20/$E20 -> 0.16670193 | P20: =$C20/$E20 -> 0.16670193 | Q20: =$C20/$E20 -> 0.16670193 | R20: =$C20/$E20 -> 0.16670193 | ... Z20: =$C20/$E20 -> 0.16670193
B21: 45291 | C21: 2.6805671 | D21: 4 | E21: =+D21*4 -> 16 | F21: =EOMONTH(B21, D21*12) -> 46752 | L21: =$C21/$E21 -> 0.16753544 | M21: =$C21/$E21 -> 0.16753544 | N21: =$C21/$E21 -> 0.16753544 | O21: =$C21/$E21 -> 0.16753544 | P21: =$C21/$E21 -> 0.16753544 | Q21: =$C21/$E21 -> 0.16753544 | R21: =$C21/$E21 -> 0.16753544 | S21: =$C21/$E21 -> 0.16753544 | ... AA21: =$C21/$E21 -> 0.16753544
B22: 45382 | C22: 2.6939699 | D22: 4 | E22: =+D22*4 -> 16 | F22: =EOMONTH(B22, D22*12) -> 46843 | M22: =$C22/$E22 -> 0.16837312 | N22: =$C22/$E22 -> 0.16837312 | O22: =$C22/$E22 -> 0.16837312 | P22: =$C22/$E22 -> 0.16837312 | Q22: =$C22/$E22 -> 0.16837312 | R22: =$C22/$E22 -> 0.16837312 | S22: =$C22/$E22 -> 0.16837312 | T22: =$C22/$E22 -> 0.16837312 | ... AA22: =$C22/$E22 -> 0.16837312
B23: 45473 | C23: 2.7074398 | D23: 4 | E23: =+D23*4 -> 16 | F23: =EOMONTH(B23, D23*12) -> 46934 | N23: =$C23/$E23 -> 0.16921499 | O23: =$C23/$E23 -> 0.16921499 | P23: =$C23/$E23 -> 0.16921499 | Q23: =$C23/$E23 -> 0.16921499 | R23: =$C23/$E23 -> 0.16921499 | S23: =$C23/$E23 -> 0.16921499 | T23: =$C23/$E23 -> 0.16921499 | U23: =$C23/$E23 -> 0.16921499 | ... AA23: =$C23/$E23 -> 0.16921499
B24: 45565 | C24: 2.720977 | D24: 4 | E24: =+D24*4 -> 16 | F24: =EOMONTH(B24, D24*12) -> 47026 | O24: =$C24/$E24 -> 0.17006106 | P24: =$C24/$E24 -> 0.17006106 | Q24: =$C24/$E24 -> 0.17006106 | R24: =$C24/$E24 -> 0.17006106 | S24: =$C24/$E24 -> 0.17006106 | T24: =$C24/$E24 -> 0.17006106 | U24: =$C24/$E24 -> 0.17006106 | V24: =$C24/$E24 -> 0.17006106 | ... AA24: =$C24/$E24 -> 0.17006106
B25: 45657 | C25: 2.7345819 | D25: 4 | E25: =+D25*4 -> 16 | F25: =EOMONTH(B25, D25*12) -> 47118 | P25: =$C25/$E25 -> 0.17091137 | Q25: =$C25/$E25 -> 0.17091137 | R25: =$C25/$E25 -> 0.17091137 | S25: =$C25/$E25 -> 0.17091137 | T25: =$C25/$E25 -> 0.17091137 | U25: =$C25/$E25 -> 0.17091137 | V25: =$C25/$E25 -> 0.17091137 | W25: =$C25/$E25 -> 0.17091137 | ... AA25: =$C25/$E25 -> 0.17091137
B26: 45747 | C26: 2.7482548 | D26: 4 | E26: =+D26*4 -> 16 | F26: =EOMONTH(B26, D26*12) -> 47208 | Q26: =$C26/$E26 -> 0.17176592 | R26: =$C26/$E26 -> 0.17176592 | S26: =$C26/$E26 -> 0.17176592 | T26: =$C26/$E26 -> 0.17176592 | U26: =$C26/$E26 -> 0.17176592 | V26: =$C26/$E26 -> 0.17176592 | W26: =$C26/$E26 -> 0.17176592 | X26: =$C26/$E26 -> 0.17176592 | ... AA26: =$C26/$E26 -> 0.17176592
B27: 45838 | C27: 2.7619961 | D27: 4 | E27: =+D27*4 -> 16 | F27: =EOMONTH(B27, D27*12) -> 47299 | R27: =$C27/$E27 -> 0.17262475 | S27: =$C27/$E27 -> 0.17262475 | T27: =$C27/$E27 -> 0.17262475 | U27: =$C27/$E27 -> 0.17262475 | V27: =$C27/$E27 -> 0.17262475 | W27: =$C27/$E27 -> 0.17262475 | X27: =$C27/$E27 -> 0.17262475 | Y27: =$C27/$E27 -> 0.17262475 | ... AA27: =$C27/$E27 -> 0.17262475
B28: 45930 | C28: 2.775806 | D28: 4 | E28: =+D28*4 -> 16 | F28: =EOMONTH(B28, D28*12) -> 47391 | S28: =$C28/$E28 -> 0.17348788 | T28: =$C28/$E28 -> 0.17348788 | U28: =$C28/$E28 -> 0.17348788 | V28: =$C28/$E28 -> 0.17348788 | W28: =$C28/$E28 -> 0.17348788 | X28: =$C28/$E28 -> 0.17348788 | Y28: =$C28/$E28 -> 0.17348788 | Z28: =$C28/$E28 -> 0.17348788 | AA28: =$C28/$E28 -> 0.17348788
B29: 46022 | C29: 2.7896851 | D29: 4 | E29: =+D29*4 -> 16 | F29: =EOMONTH(B29, D29*12) -> 47483 | T29: =$C29/$E29 -> 0.17435532 | U29: =$C29/$E29 -> 0.17435532 | V29: =$C29/$E29 -> 0.17435532 | W29: =$C29/$E29 -> 0.17435532 | X29: =$C29/$E29 -> 0.17435532 | Y29: =$C29/$E29 -> 0.17435532 | Z29: =$C29/$E29 -> 0.17435532 | AA29: =$C29/$E29 -> 0.17435532
B30: 46112 | C30: 2.8036335 | D30: 4 | E30: =+D30*4 -> 16 | F30: =EOMONTH(B30, D30*12) -> 47573 | U30: =$C30/$E30 -> 0.17522709 | V30: =$C30/$E30 -> 0.17522709 | W30: =$C30/$E30 -> 0.17522709 | X30: =$C30/$E30 -> 0.17522709 | Y30: =$C30/$E30 -> 0.17522709 | Z30: =$C30/$E30 -> 0.17522709 | AA30: =$C30/$E30 -> 0.17522709
B31: 46203 | C31: 2.8176517 | D31: 4 | E31: =+D31*4 -> 16 | F31: =EOMONTH(B31, D31*12) -> 47664 | V31: =$C31/$E31 -> 0.17610323 | W31: =$C31/$E31 -> 0.17610323 | X31: =$C31/$E31 -> 0.17610323 | Y31: =$C31/$E31 -> 0.17610323 | Z31: =$C31/$E31 -> 0.17610323 | AA31: =$C31/$E31 -> 0.17610323
B32: 46295 | C32: 2.8317399 | D32: 4 | E32: =+D32*4 -> 16 | F32: =EOMONTH(B32, D32*12) -> 47756 | W32: =$C32/$E32 -> 0.17698375 | X32: =$C32/$E32 -> 0.17698375 | Y32: =$C32/$E32 -> 0.17698375 | Z32: =$C32/$E32 -> 0.17698375 | AA32: =$C32/$E32 -> 0.17698375
B33: 46387 | C33: 2.8458986 | D33: 4 | E33: =+D33*4 -> 16 | F33: =EOMONTH(B33, D33*12) -> 47848 | X33: =$C33/$E33 -> 0.17786866 | Y33: =$C33/$E33 -> 0.17786866 | Z33: =$C33/$E33 -> 0.17786866 | AA33: =$C33/$E33 -> 0.17786866
B34: 46477 | C34: 2.8601281 | D34: 4 | E34: =+D34*4 -> 16 | F34: =EOMONTH(B34, D34*12) -> 47938 | Y34: =$C34/$E34 -> 0.17875801 | Z34: =$C34/$E34 -> 0.17875801 | AA34: =$C34/$E34 -> 0.17875801
B35: 46568 | C35: 2.8744288 | D35: 4 | E35: =+D35*4 -> 16 | F35: =EOMONTH(B35, D35*12) -> 48029 | Z35: =$C35/$E35 -> 0.1796518 | AA35: =$C35/$E35 -> 0.1796518
B36: 46660 | C36: 2.8888009 | D36: 4 | E36: =+D36*4 -> 16 | F36: =EOMONTH(B36, D36*12) -> 48121 | AA36: =$C36/$E36 -> 0.18055006
B37: 46752 | C37: 2.9032449 | D37: 4 | E37: =+D37*4 -> 16 | F37: =EOMONTH(B37, D37*12) -> 48213
B39: Amortization of Deferred Compensation | H39: =SUM(H17:H38) -> 0.888775 | I39: =SUM(I17:I38) -> 1.0538223 | J39: =SUM(J17:J38) -> 1.2196949 | K39: =SUM(K17:K38) -> 1.3863968 | L39: =SUM(L17:L38) -> 1.5539323 | M39: =SUM(M17:M38) -> 1.7223054 | N39: =SUM(N17:N38) -> 1.8915204 | O39: =SUM(O17:O38) -> 2.0615815 | ... AA39: =SUM(AA17:AA38) -> 2.7834724
B44: Capitalized Software Costs
B45: Balance Sheet
B46: Beginning Capitalized Software Costs | H46: =+G49 -> 5.9109174 | I46: =+H49 -> 6.2514641 | J46: =+I49 -> 6.5704936 | K46: =+J49 -> 6.8678982 | L46: =+K49 -> 7.1435698 | M46: =+L49 -> 7.3973997 | N46: =+M49 -> 7.6292788 | O46: =+N49 -> 7.8390972 | ... AA46: =+Z49 -> 9.4078237
B47: New Capitalized Software Costs | H47: =H52*H53 -> 0.58683497 | I47: =I52*I53 -> 0.58976914 | J47: =J52*J53 -> 0.59271799 | K47: =K52*K53 -> 0.59568158 | L47: =L52*L53 -> 0.59865999 | M47: =M52*M53 -> 0.60165329 | N47: =N52*N53 -> 0.60466155 | O47: =O52*O53 -> 0.60768486 | ... AA47: =AA52*AA53 -> 0.64516553
B48: Amortization of Capitalized Software Costs | H48: =-H78 -> -0.24628822 | I48: =-I78 -> -0.27073968 | J48: =-J78 -> -0.29531339 | K48: =-K78 -> -0.32000998 | L48: =-L78 -> -0.34483004 | M48: =-M78 -> -0.36977421 | N48: =-N78 -> -0.3948431 | O48: =-O78 -> -0.42003733 | ... AA48: =-AA78 -> -0.41236629
B49: Ending Capitalized Software Costs | G49: =Model!N55 -> 5.9109174 | H49: =SUM(H46:H48) -> 6.2514641 | I49: =SUM(I46:I48) -> 6.5704936 | J49: =SUM(J46:J48) -> 6.8678982 | K49: =SUM(K46:K48) -> 7.1435698 | L49: =SUM(L46:L48) -> 7.3973997 | M49: =SUM(M46:M48) -> 7.6292788 | N49: =SUM(N46:N48) -> 7.8390972 | O49: =SUM(O46:O48) -> 8.0267448 | ... AA49: =SUM(AA46:AA48) -> 9.6406229
B51: Memo/Drivers
B52: Total R&D Expense | H52: =Model!O21 -> 9.7805828 | I52: =Model!P21 -> 9.8294857 | J52: =Model!Q21 -> 9.8786332 | K52: =Model!R21 -> 9.9280263 | L52: =Model!S21 -> 9.9776665 | M52: =Model!T21 -> 10.027555 | N52: =Model!U21 -> 10.077693 | O52: =Model!V21 -> 10.128081 | ... AA52: =Model!AH21 -> 10.752759
B53: Capitalized Software Costs as % of R&D Expense | H53: 0.06 | I53: 0.06 | J53: 0.06 | K53: 0.06 | L53: 0.06 | M53: 0.06 | N53: 0.06 | O53: 0.06 | P53: 0.06 | Q53: 0.06 | R53: 0.06 | S53: 0.06 | T53: 0.06 | U53: 0.06 | V53: 0.06 | W53: 0.06 | X53: 0.06 | Y53: 0.06 | Z53: 0.06 | AA53: 0.06
B55: Amortization Schedule
B56: Cohort | C56: $ Costs | D56: Years | E56: Quarters | F56: End
B57: {=TRANSPOSE(G3:AA3)} -> 44926 | C57: =G49 -> 5.9109174 | D57: 6 | E57: =+D57*4 -> 24 | F57: =EOMONTH(B57, 12*D57) -> 47118 | H57: =$C57/$E57 -> 0.24628822 | I57: =$C57/$E57 -> 0.24628822 | J57: =$C57/$E57 -> 0.24628822 | K57: =$C57/$E57 -> 0.24628822 | L57: =$C57/$E57 -> 0.24628822 | M57: =$C57/$E57 -> 0.24628822 | N57: =$C57/$E57 -> 0.24628822 | O57: =$C57/$E57 -> 0.24628822 | ... W57: =$C57/$E57 -> 0.24628822
B58: 45016 | C58: {=TRANSPOSE(H47:AA47)} -> 0.58683497 | D58: 6 | E58: =+D58*4 -> 24 | F58: =EOMONTH(B58, 12*D58) -> 47208 | I58: =$C58/$E58 -> 0.024451457 | J58: =$C58/$E58 -> 0.024451457 | K58: =$C58/$E58 -> 0.024451457 | L58: =$C58/$E58 -> 0.024451457 | M58: =$C58/$E58 -> 0.024451457 | N58: =$C58/$E58 -> 0.024451457 | O58: =$C58/$E58 -> 0.024451457 | P58: =$C58/$E58 -> 0.024451457 | ... X58: =$C58/$E58 -> 0.024451457
B59: 45107 | C59: 0.58976914 | D59: 6 | E59: =+D59*4 -> 24 | F59: =EOMONTH(B59, 12*D59) -> 47299 | J59: =$C59/$E59 -> 0.024573714 | K59: =$C59/$E59 -> 0.024573714 | L59: =$C59/$E59 -> 0.024573714 | M59: =$C59/$E59 -> 0.024573714 | N59: =$C59/$E59 -> 0.024573714 | O59: =$C59/$E59 -> 0.024573714 | P59: =$C59/$E59 -> 0.024573714 | Q59: =$C59/$E59 -> 0.024573714 | ... Y59: =$C59/$E59 -> 0.024573714
B60: 45199 | C60: 0.59271799 | D60: 6 | E60: =+D60*4 -> 24 | F60: =EOMONTH(B60, 12*D60) -> 47391 | K60: =$C60/$E60 -> 0.024696583 | L60: =$C60/$E60 -> 0.024696583 | M60: =$C60/$E60 -> 0.024696583 | N60: =$C60/$E60 -> 0.024696583 | O60: =$C60/$E60 -> 0.024696583 | P60: =$C60/$E60 -> 0.024696583 | Q60: =$C60/$E60 -> 0.024696583 | R60: =$C60/$E60 -> 0.024696583 | ... Z60: =$C60/$E60 -> 0.024696583
B61: 45291 | C61: 0.59568158 | D61: 6 | E61: =+D61*4 -> 24 | F61: =EOMONTH(B61, 12*D61) -> 47483 | L61: =$C61/$E61 -> 0.024820066 | M61: =$C61/$E61 -> 0.024820066 | N61: =$C61/$E61 -> 0.024820066 | O61: =$C61/$E61 -> 0.024820066 | P61: =$C61/$E61 -> 0.024820066 | Q61: =$C61/$E61 -> 0.024820066 | R61: =$C61/$E61 -> 0.024820066 | S61: =$C61/$E61 -> 0.024820066 | ... AA61: =$C61/$E61 -> 0.024820066
B62: 45382 | C62: 0.59865999 | D62: 6 | E62: =+D62*4 -> 24 | F62: =EOMONTH(B62, 12*D62) -> 47573 | M62: =$C62/$E62 -> 0.024944166 | N62: =$C62/$E62 -> 0.024944166 | O62: =$C62/$E62 -> 0.024944166 | P62: =$C62/$E62 -> 0.024944166 | Q62: =$C62/$E62 -> 0.024944166 | R62: =$C62/$E62 -> 0.024944166 | S62: =$C62/$E62 -> 0.024944166 | T62: =$C62/$E62 -> 0.024944166 | ... AA62: =$C62/$E62 -> 0.024944166
B63: 45473 | C63: 0.60165329 | D63: 6 | E63: =+D63*4 -> 24 | F63: =EOMONTH(B63, 12*D63) -> 47664 | N63: =$C63/$E63 -> 0.025068887 | O63: =$C63/$E63 -> 0.025068887 | P63: =$C63/$E63 -> 0.025068887 | Q63: =$C63/$E63 -> 0.025068887 | R63: =$C63/$E63 -> 0.025068887 | S63: =$C63/$E63 -> 0.025068887 | T63: =$C63/$E63 -> 0.025068887 | U63: =$C63/$E63 -> 0.025068887 | ... AA63: =$C63/$E63 -> 0.025068887
B64: 45565 | C64: 0.60466155 | D64: 6 | E64: =+D64*4 -> 24 | F64: =EOMONTH(B64, 12*D64) -> 47756 | O64: =$C64/$E64 -> 0.025194231 | P64: =$C64/$E64 -> 0.025194231 | Q64: =$C64/$E64 -> 0.025194231 | R64: =$C64/$E64 -> 0.025194231 | S64: =$C64/$E64 -> 0.025194231 | T64: =$C64/$E64 -> 0.025194231 | U64: =$C64/$E64 -> 0.025194231 | V64: =$C64/$E64 -> 0.025194231 | ... AA64: =$C64/$E64 -> 0.025194231
B65: 45657 | C65: 0.60768486 | D65: 6 | E65: =+D65*4 -> 24 | F65: =EOMONTH(B65, 12*D65) -> 47848 | P65: =$C65/$E65 -> 0.025320203 | Q65: =$C65/$E65 -> 0.025320203 | R65: =$C65/$E65 -> 0.025320203 | S65: =$C65/$E65 -> 0.025320203 | T65: =$C65/$E65 -> 0.025320203 | U65: =$C65/$E65 -> 0.025320203 | V65: =$C65/$E65 -> 0.025320203 | W65: =$C65/$E65 -> 0.025320203 | ... AA65: =$C65/$E65 -> 0.025320203
B66: 45747 | C66: 0.61072329 | D66: 6 | E66: =+D66*4 -> 24 | F66: =EOMONTH(B66, 12*D66) -> 47938 | Q66: =$C66/$E66 -> 0.025446804 | R66: =$C66/$E66 -> 0.025446804 | S66: =$C66/$E66 -> 0.025446804 | T66: =$C66/$E66 -> 0.025446804 | U66: =$C66/$E66 -> 0.025446804 | V66: =$C66/$E66 -> 0.025446804 | W66: =$C66/$E66 -> 0.025446804 | X66: =$C66/$E66 -> 0.025446804 | ... AA66: =$C66/$E66 -> 0.025446804
B67: 45838 | C67: 0.6137769 | D67: 6 | E67: =+D67*4 -> 24 | F67: =EOMONTH(B67, 12*D67) -> 48029 | R67: =$C67/$E67 -> 0.025574038 | S67: =$C67/$E67 -> 0.025574038 | T67: =$C67/$E67 -> 0.025574038 | U67: =$C67/$E67 -> 0.025574038 | V67: =$C67/$E67 -> 0.025574038 | W67: =$C67/$E67 -> 0.025574038 | X67: =$C67/$E67 -> 0.025574038 | Y67: =$C67/$E67 -> 0.025574038 | ... AA67: =$C67/$E67 -> 0.025574038
B68: 45930 | C68: 0.61684579 | D68: 6 | E68: =+D68*4 -> 24 | F68: =EOMONTH(B68, 12*D68) -> 48121 | S68: =$C68/$E68 -> 0.025701908 | T68: =$C68/$E68 -> 0.025701908 | U68: =$C68/$E68 -> 0.025701908 | V68: =$C68/$E68 -> 0.025701908 | W68: =$C68/$E68 -> 0.025701908 | X68: =$C68/$E68 -> 0.025701908 | Y68: =$C68/$E68 -> 0.025701908 | Z68: =$C68/$E68 -> 0.025701908 | AA68: =$C68/$E68 -> 0.025701908
B69: 46022 | C69: 0.61993002 | D69: 6 | E69: =+D69*4 -> 24 | F69: =EOMONTH(B69, 12*D69) -> 48213 | T69: =$C69/$E69 -> 0.025830417 | U69: =$C69/$E69 -> 0.025830417 | V69: =$C69/$E69 -> 0.025830417 | W69: =$C69/$E69 -> 0.025830417 | X69: =$C69/$E69 -> 0.025830417 | Y69: =$C69/$E69 -> 0.025830417 | Z69: =$C69/$E69 -> 0.025830417 | AA69: =$C69/$E69 -> 0.025830417
B70: 46112 | C70: 0.62302967 | D70: 6 | E70: =+D70*4 -> 24 | F70: =EOMONTH(B70, 12*D70) -> 48304 | U70: =$C70/$E70 -> 0.025959569 | V70: =$C70/$E70 -> 0.025959569 | W70: =$C70/$E70 -> 0.025959569 | X70: =$C70/$E70 -> 0.025959569 | Y70: =$C70/$E70 -> 0.025959569 | Z70: =$C70/$E70 -> 0.025959569 | AA70: =$C70/$E70 -> 0.025959569
B71: 46203 | C71: 0.62614481 | D71: 6 | E71: =+D71*4 -> 24 | F71: =EOMONTH(B71, 12*D71) -> 48395 | V71: =$C71/$E71 -> 0.026089367 | W71: =$C71/$E71 -> 0.026089367 | X71: =$C71/$E71 -> 0.026089367 | Y71: =$C71/$E71 -> 0.026089367 | Z71: =$C71/$E71 -> 0.026089367 | AA71: =$C71/$E71 -> 0.026089367
B72: 46295 | C72: 0.62927554 | D72: 6 | E72: =+D72*4 -> 24 | F72: =EOMONTH(B72, 12*D72) -> 48487 | W72: =$C72/$E72 -> 0.026219814 | X72: =$C72/$E72 -> 0.026219814 | Y72: =$C72/$E72 -> 0.026219814 | Z72: =$C72/$E72 -> 0.026219814 | AA72: =$C72/$E72 -> 0.026219814
B73: 46387 | C73: 0.63242192 | D73: 6 | E73: =+D73*4 -> 24 | F73: =EOMONTH(B73, 12*D73) -> 48579 | X73: =$C73/$E73 -> 0.026350913 | Y73: =$C73/$E73 -> 0.026350913 | Z73: =$C73/$E73 -> 0.026350913 | AA73: =$C73/$E73 -> 0.026350913
B74: 46477 | C74: 0.63558403 | D74: 6 | E74: =+D74*4 -> 24 | F74: =EOMONTH(B74, 12*D74) -> 48669 | Y74: =$C74/$E74 -> 0.026482668 | Z74: =$C74/$E74 -> 0.026482668 | AA74: =$C74/$E74 -> 0.026482668
B75: 46568 | C75: 0.63876195 | D75: 6 | E75: =+D75*4 -> 24 | F75: =EOMONTH(B75, 12*D75) -> 48760 | Z75: =$C75/$E75 -> 0.026615081 | AA75: =$C75/$E75 -> 0.026615081
B76: 46660 | C76: 0.64195576 | D76: 6 | E76: =+D76*4 -> 24 | F76: =EOMONTH(B76, 12*D76) -> 48852 | AA76: =$C76/$E76 -> 0.026748156
B77: 46752 | C77: 0.64516553 | D77: 6 | E77: =+D77*4 -> 24 | F77: =EOMONTH(B77, 12*D77) -> 48944
B78: Amortization of Capitalized Software Costs | H78: =SUM(H57:H77) -> 0.24628822 | I78: =SUM(I57:I77) -> 0.27073968 | J78: =SUM(J57:J77) -> 0.29531339 | K78: =SUM(K57:K77) -> 0.32000998 | L78: =SUM(L57:L77) -> 0.34483004 | M78: =SUM(M57:M77) -> 0.36977421 | N78: =SUM(N57:N77) -> 0.3948431 | O78: =SUM(O57:O77) -> 0.42003733 | ... AA78: =SUM(AA57:AA77) -> 0.41236629

Sheet SaaS Metrics
B2: Key Metrics | AH2: $ in millions, except noted
C3: =YEAR(C4) -> 2020 | D3: =YEAR(D4) -> 2020 | E3: =YEAR(E4) -> 2020 | F3: =YEAR(F4) -> 2020 | G3: =YEAR(G4) -> 2021 | H3: =YEAR(H4) -> 2021 | I3: =YEAR(I4) -> 2021 | J3: =YEAR(J4) -> 2021 | ... AH3: =YEAR(AH4) -> 2027
C4: ='ARR Waterfall'!C4 -> 43921 | D4: =EOMONTH(C4, 3) -> 44012 | E4: =EOMONTH(D4, 3) -> 44104 | F4: =EOMONTH(E4, 3) -> 44196 | G4: =EOMONTH(F4, 3) -> 44286 | H4: =EOMONTH(G4, 3) -> 44377 | I4: =EOMONTH(H4, 3) -> 44469 | J4: =EOMONTH(I4, 3) -> 44561 | K4: =EOMONTH(J4, 3) -> 44651 | ... AH4: =EOMONTH(AG4, 3) -> 46752
B5: =+'ARR Waterfall'!B5 -> ARR Build
B6: =+'ARR Waterfall'!B6 -> Beginning ARR | C6: =+'ARR Waterfall'!C6 -> 289.19772 | D6: =+'ARR Waterfall'!D6 -> 301.18761 | E6: =+'ARR Waterfall'!E6 -> 304.4751 | F6: =+'ARR Waterfall'!F6 -> 308.34238 | G6: =+'ARR Waterfall'!G6 -> 313.78571 | H6: =+'ARR Waterfall'!H6 -> 310.36867 | I6: =+'ARR Waterfall'!I6 -> 309.6027 | ... AH6: =+'ARR Waterfall'!AH6 -> 371.50217
B7: =+'ARR Waterfall'!B7 -> New Logo ARR | C7: =+'ARR Waterfall'!C7 -> 16.54272 | D7: =+'ARR Waterfall'!D7 -> 12.672 | E7: =+'ARR Waterfall'!E7 -> 10.78272 | F7: =+'ARR Waterfall'!F7 -> 12.034256 | G7: =+'ARR Waterfall'!G7 -> 6.912 | H7: =+'ARR Waterfall'!H7 -> 7.87968 | I7: =+'ARR Waterfall'!I7 -> 11.52 | ... AH7: =+'ARR Waterfall'!AH7 -> 14.860087
B8: =+'ARR Waterfall'!B8 -> Upsell ARR | C8: =+'ARR Waterfall'!C8 -> 6.277032 | D8: =+'ARR Waterfall'!D8 -> 4.857832 | E8: =+'ARR Waterfall'!E8 -> 3.987528 | F8: =+'ARR Waterfall'!F8 -> 5.73084 | G8: =+'ARR Waterfall'!G8 -> 5.394216 | H8: =+'ARR Waterfall'!H8 -> 6.486064 | I8: =+'ARR Waterfall'!I8 -> 5.75956 | ... AH8: =+'ARR Waterfall'!AH8 -> 5.5725326
B9: =+'ARR Waterfall'!B9 -> Downsell ARR | C9: =+'ARR Waterfall'!C9 -> -3.550296 | D9: =+'ARR Waterfall'!D9 -> -4.078288 | E9: =+'ARR Waterfall'!E9 -> -3.61396 | F9: =+'ARR Waterfall'!F9 -> -4.169752 | G9: =+'ARR Waterfall'!G9 -> -3.52144 | H9: =+'ARR Waterfall'!H9 -> -4.33488 | I9: =+'ARR Waterfall'!I9 -> -4.362616 | ... AH9: =+'ARR Waterfall'!AH9 -> -3.7150217
B10: =+'ARR Waterfall'!B10 -> Churn ARR | C10: =+'ARR Waterfall'!C10 -> -7.279568 | D10: =+'ARR Waterfall'!D10 -> -10.164048 | E10: =+'ARR Waterfall'!E10 -> -7.289016 | F10: =+'ARR Waterfall'!F10 -> -8.152008 | G10: =+'ARR Waterfall'!G10 -> -12.201816 | H10: =+'ARR Waterfall'!H10 -> -10.79684 | I10: =+'ARR Waterfall'!I10 -> -10.030816 | ... AH10: =+'ARR Waterfall'!AH10 -> -14.860087
B11: =+'ARR Waterfall'!B11 -> Ending ARR | C11: =+'ARR Waterfall'!C11 -> 301.18761 | D11: =+'ARR Waterfall'!D11 -> 304.4751 | E11: =+'ARR Waterfall'!E11 -> 308.34238 | F11: =+'ARR Waterfall'!F11 -> 313.78571 | G11: =+'ARR Waterfall'!G11 -> 310.36867 | H11: =+'ARR Waterfall'!H11 -> 309.6027 | I11: =+'ARR Waterfall'!I11 -> 312.48882 | ... AH11: =+'ARR Waterfall'!AH11 -> 373.35968
B13: =+'ARR Waterfall'!B20 -> Customer Bridge
B14: =+'ARR Waterfall'!B21 -> Beginning Customers | C14: =+'ARR Waterfall'!C21 -> 124 | D14: =+'ARR Waterfall'!D21 -> 126 | E14: =+'ARR Waterfall'!E21 -> 127 | F14: =+'ARR Waterfall'!F21 -> 130 | G14: =+'ARR Waterfall'!G21 -> 132 | H14: =+'ARR Waterfall'!H21 -> 131 | I14: =+'ARR Waterfall'!I21 -> 131 | ... AH14: =+'ARR Waterfall'!AH21 -> 170.50433
B15: =+'ARR Waterfall'!B22 -> New Customers | C15: =+'ARR Waterfall'!C22 -> 6 | D15: =+'ARR Waterfall'!D22 -> 6 | E15: =+'ARR Waterfall'!E22 -> 6 | F15: =+'ARR Waterfall'!F22 -> 5 | G15: =+'ARR Waterfall'!G22 -> 4 | H15: =+'ARR Waterfall'!H22 -> 4 | I15: =+'ARR Waterfall'!I22 -> 5 | ... AH15: =+'ARR Waterfall'!AH22 -> 7.0762319
B16: =+'ARR Waterfall'!B23 -> Churn Customers | C16: =+'ARR Waterfall'!C23 -> -4 | D16: =+'ARR Waterfall'!D23 -> -5 | E16: =+'ARR Waterfall'!E23 -> -3 | F16: =+'ARR Waterfall'!F23 -> -3 | G16: =+'ARR Waterfall'!G23 -> -5 | H16: =+'ARR Waterfall'!H23 -> -4 | I16: =+'ARR Waterfall'!I23 -> -3 | ... AH16: =+'ARR Waterfall'!AH23 -> -5.5551727
B17: =+'ARR Waterfall'!B24 -> Ending Customers | C17: =+'ARR Waterfall'!C24 -> 126 | D17: =+'ARR Waterfall'!D24 -> 127 | E17: =+'ARR Waterfall'!E24 -> 130 | F17: =+'ARR Waterfall'!F24 -> 132 | G17: =+'ARR Waterfall'!G24 -> 131 | H17: =+'ARR Waterfall'!H24 -> 131 | I17: =+'ARR Waterfall'!I24 -> 133 | ... AH17: =+'ARR Waterfall'!AH24 -> 172.02539
B20: Revenue & Retention
B21: YoY ARR Growth
B22: Ending ARR | C22: =+'ARR Waterfall'!C11 -> 301.18761 | D22: =+'ARR Waterfall'!D11 -> 304.4751 | E22: =+'ARR Waterfall'!E11 -> 308.34238 | F22: =+'ARR Waterfall'!F11 -> 313.78571 | G22: =+'ARR Waterfall'!G11 -> 310.36867 | H22: =+'ARR Waterfall'!H11 -> 309.6027 | I22: =+'ARR Waterfall'!I11 -> 312.48882 | J22: =+'ARR Waterfall'!J11 -> 315.91418 | ... AH22: =+'ARR Waterfall'!AH11 -> 373.35968
B23: YoY ARR Growth | G23: =+G22/C22-1 -> 0.030482874 | H23: =+H22/D22-1 -> 0.016840759 | I23: =+I22/E22-1 -> 0.013447545 | J23: =+J22/F22-1 -> 0.0067832024 | K23: =+K22/G22-1 -> 0.026340777 | L23: =+L22/H22-1 -> 0.039668698 | M23: =+M22/I22-1 -> 0.049247534 | N23: =+N22/J22-1 -> 0.069638583 | ... AH23: =+AH22/AD22-1 -> 0.020150501
B25: Retention
B26: Annualized Net Dollar Retention | C26: {=1+((SUM(C8:C10/C6)*4))} -> 0.93702811 | D26: {=1+((SUM(D8:D10/D6)*4))} -> 0.87536667 | E26: {=1+((SUM(E8:E10/E6)*4))} -> 0.90914925 | F26: {=1+((SUM(F8:F10/F6)*4))} -> 0.91449868 | G26: {=1+((SUM(G8:G10/G6)*4))} -> 0.86833001 | H26: {=1+((SUM(H8:H10/H6)*4))} -> 0.88857566 | I26: {=1+((SUM(I8:I10/I6)*4))} -> 0.88845224 | J26: {=1+((SUM(J8:J10/J6)*4))} -> 0.88399816 | ... AH26: {=1+((SUM(AH8:AH10/AH6)*4))} -> 0.86
B27: Annualized Gross Dollar Retention | C27: =1+((SUM(C9:C10)/C6)*4) -> 0.85020817 | D27: =1+((SUM(D9:D10)/D6)*4) -> 0.81085097 | E27: =1+((SUM(E9:E10)/E6)*4) -> 0.85676365 | F27: =1+((SUM(F9:F10)/F6)*4) -> 0.84015483 | G27: =1+((SUM(G9:G10)/G6)*4) -> 0.79956696 | H27: =1+((SUM(H9:H10)/H6)*4) -> 0.80498393 | I27: =1+((SUM(I9:I10)/I6)*4) -> 0.81403997 | J27: =1+((SUM(J9:J10)/J6)*4) -> 0.8001103 | ... AH27: =1+((SUM(AH9:AH10)/AH6)*4) -> 0.8
B28: Annualized Logo Retention | C28: =1+((C16/C14)*4) -> 0.87096774 | D28: =1+((D16/D14)*4) -> 0.84126984 | E28: =1+((E16/E14)*4) -> 0.90551181 | F28: =1+((F16/F14)*4) -> 0.90769231 | G28: =1+((G16/G14)*4) -> 0.84848485 | H28: =1+((H16/H14)*4) -> 0.8778626 | I28: =1+((I16/I14)*4) -> 0.90839695 | J28: =1+((J16/J14)*4) -> 0.81954887 | ... AH28: =1+((AH16/AH14)*4) -> 0.86967668
B30: Quick Ratio
B31: New Logo ARR | C31: =+C7 -> 16.54272 | D31: =+D7 -> 12.672 | E31: =+E7 -> 10.78272 | F31: =+F7 -> 12.034256 | G31: =+G7 -> 6.912 | H31: =+H7 -> 7.87968 | I31: =+I7 -> 11.52 | J31: =+J7 -> 12.48768 | ... AH31: =+AH7 -> 14.860087
B32: Upsell ARR | C32: =+C8 -> 6.277032 | D32: =+D8 -> 4.857832 | E32: =+E8 -> 3.987528 | F32: =+F8 -> 5.73084 | G32: =+G8 -> 5.394216 | H32: =+H8 -> 6.486064 | I32: =+I8 -> 5.75956 | J32: =+J8 -> 6.553504 | ... AH32: =+AH8 -> 5.5725326
B33: Downsell ARR | C33: =+C9 -> -3.550296 | D33: =+D9 -> -4.078288 | E33: =+E9 -> -3.61396 | F33: =+F9 -> -4.169752 | G33: =+G9 -> -3.52144 | H33: =+H9 -> -4.33488 | I33: =+I9 -> -4.362616 | J33: =+J9 -> -3.73416 | ... AH33: =+AH9 -> -3.7150217
B34: Churn ARR | C34: =+C10 -> -7.279568 | D34: =+D10 -> -10.164048 | E34: =+E10 -> -7.289016 | F34: =+F10 -> -8.152008 | G34: =+G10 -> -12.201816 | H34: =+H10 -> -10.79684 | I34: =+I10 -> -10.030816 | J34: =+J10 -> -11.881664 | ... AH34: =+AH10 -> -14.860087
B35: Quick Ratio | C35: =-SUM(C31:C32)/SUM(C33:C34) -> 2.1071134 | D35: =-SUM(D31:D32)/SUM(D33:D34) -> 1.2308256 | E35: =-SUM(E31:E32)/SUM(E33:E34) -> 1.3546988 | F35: =-SUM(F31:F32)/SUM(F33:F34) -> 1.4417661 | G35: =-SUM(G31:G32)/SUM(G33:G34) -> 0.78267606 | H35: =-SUM(H31:H32)/SUM(H33:H34) -> 0.94937945 | I35: =-SUM(I31:I32)/SUM(I33:I34) -> 1.200517 | J35: =-SUM(J31:J32)/SUM(J33:J34) -> 1.2193519 | ... AH35: =-SUM(AH31:AH32)/SUM(AH33:AH34) -> 1.1
B37: Efficiency
B38: Rule of 40
B39: LTM GAAP Revenue | C39: =SUM(Model!C8:C8) -> 73.455054 | D39: =SUM(Model!C8:D8) -> 147.32419 | E39: =SUM(Model!C8:E8) -> 224.46212 | F39: =SUM(Model!C8:F8) -> 302.6107 | G39: =SUM(Model!D8:G8) -> 306.14576 | H39: =SUM(Model!E8:H8) -> 309.22635 | I39: =SUM(Model!F8:I8) -> 310.08463 | J39: =SUM(Model!G8:J8) -> 309.95496 | K39: =SUM(Model!H8:K8) -> 312.16277 | L39: =SUM(Model!I8:L8) -> 315.35929 | M39: =SUM(Model!J8:M8) -> 319.13177 | ... AH39: =SUM(Model!AE8:AH8) -> 355.75934
B40: LTM EBITDA | C40: =SUM(Model!C33:C33) -> 0 | D40: =SUM(Model!C33:D33) -> 0 | E40: =SUM(Model!C33:E33) -> 0 | F40: =SUM(Model!C33:F33) -> 35.199162 | G40: =SUM(Model!D33:G33) -> 71.786924 | H40: =SUM(Model!E33:H33) -> 107.03109 | I40: =SUM(Model!F33:I33) -> 142.75366 | J40: =SUM(Model!G33:J33) -> 143.85535 | K40: =SUM(Model!H33:K33) -> 143.29853 | L40: =SUM(Model!I33:L33) -> 144.41192 | M40: =SUM(Model!J33:M33) -> 145.75263 | ... AH40: =SUM(Model!AE33:AH33) -> 176.07296
B41: YoY Growth | G41: =G39/C39-1 -> 3.1677971 | H41: =H39/D39-1 -> 1.0989515 | I41: =I39/E39-1 -> 0.38145639 | J41: =J39/F39-1 -> 0.024269644 | K41: =K39/G39-1 -> 0.019654072 | L41: =L39/H39-1 -> 0.019833198 | M41: =M39/I39-1 -> 0.029176342 | N41: =N39/J39-1 -> 0.04373284 | ... AH41: =AH39/AD39-1 -> 0.020150501
B42: EBITDA Margin | G42: =G40/G39 -> 0.2344861 | H42: =H40/H39 -> 0.3461254 | I42: =I40/I39 -> 0.46037 | J42: =J40/J39 -> 0.46411696 | K42: =K40/K39 -> 0.45905066 | L42: =L40/L39 -> 0.45792821 | M42: =M40/M39 -> 0.45671615 | N42: =N40/N39 -> 0.45157342 | ... AH42: =AH40/AH39 -> 0.49492153
B43: Rule of 40 | G43: =G41+G42 -> 3.4022832 | H43: =H41+H42 -> 1.4450769 | I43: =I41+I42 -> 0.84182639 | J43: =J41+J42 -> 0.48838661 | K43: =K41+K42 -> 0.47870473 | L43: =L41+L42 -> 0.47776141 | M43: =M41+M42 -> 0.4858925 | N43: =N41+N42 -> 0.49530626 | ... AH43: =AH41+AH42 -> 0.51507203
B45: Magic Number
B46: New Logo ARR | D46: =+D7 -> 12.672 | E46: =+E7 -> 10.78272 | F46: =+F7 -> 12.034256 | G46: =+G7 -> 6.912 | H46: =+H7 -> 7.87968 | I46: =+I7 -> 11.52 | J46: =+J7 -> 12.48768 | K46: =+K7 -> 15.34464 | ... AH46: =+AH7 -> 14.860087
B47: Upsell ARR | D47: =+D8 -> 4.857832 | E47: =+E8 -> 3.987528 | F47: =+F8 -> 5.73084 | G47: =+G8 -> 5.394216 | H47: =+H8 -> 6.486064 | I47: =+I8 -> 5.75956 | J47: =+J8 -> 6.553504 | K47: =+K8 -> 4.374232 | ... AH47: =+AH8 -> 5.5725326
B48: Prior Period S&M | D48: =+Model!C20 -> 14.00397 | E48: =+Model!D20 -> 14.083162 | F48: =+Model!E20 -> 14.056085 | G48: =+Model!F20 -> 14.845196 | H48: =+Model!G20 -> 13.968859 | I48: =+Model!H20 -> 14.048706 | J48: =+Model!I20 -> 14.759204 | K48: =+Model!J20 -> 14.257532 | ... AH48: =+Model!AG20 -> 16.048894
B49: Magic Number | D49: =+D46/D48 -> 0.90488629 | E49: =+E46/E48 -> 0.76564622 | F49: =+F46/F48 -> 0.85615987 | G49: =+G46/G48 -> 0.46560516 | H49: =+H46/H48 -> 0.56408903 | I49: =+I46/I48 -> 0.82000434 | J49: =+J46/J48 -> 0.84609442 | K49: =+K46/K48 -> 1.076248 | ... AH49: =+AH46/AH48 -> 0.92592593
B51: Burn Multiple
B52: Net Cash Burned | P52: =-Model!O156 -> -3.6456779 | Q52: =-Model!P156 -> -3.9738686 | R52: =-Model!Q156 -> -6.1907626 | S52: =-Model!R156 -> -9.5226922 | T52: =-Model!S156 -> -5.3167897 | U52: =-Model!T156 -> -5.6735201 | V52: =-Model!U156 -> -7.8707409 | W52: =-Model!V156 -> -11.222299 | ... AH52: =-Model!AG156 -> -12.298479
B53: Net New ARR | P53: =P11-O11 -> 1.6980178 | Q53: =Q11-P11 -> 1.7065079 | R53: =R11-Q11 -> 1.7150405 | S53: =S11-R11 -> 1.7236157 | T53: =T11-S11 -> 1.7322338 | U53: =U11-T11 -> 1.7408949 | V53: =V11-U11 -> 1.7495994 | W53: =W11-V11 -> 1.7583474 | ... AH53: =AH11-AG11 -> 1.8575109
B54: Burn Multiple | P54: =+P52/P53 -> -2.1470198 | Q54: =+Q52/Q53 -> -2.3286552 | R54: =+R52/R53 -> -3.6096889 | S54: =+S52/S53 -> -5.524835 | T54: =+T52/T53 -> -3.0693258 | U54: =+U52/U53 -> -3.2589675 | V54: =+V52/V53 -> -4.498596 | W54: =+W52/W53 -> -6.3822993 | ... AH54: =+AH52/AH53 -> -6.6209457
B57: Unit Economics
B58: Gross Margin
B59: Gross Profit - Total | C59: =Model!C16 -> 56.64087 | D59: =Model!D16 -> 57.429357 | E59: =Model!E16 -> 59.894767 | F59: =Model!F16 -> 60.767378 | G59: =Model!G16 -> 59.808461 | H59: =Model!H16 -> 59.908513 | I59: =Model!I16 -> 60.235216 | J59: =Model!J16 -> 60.758517 | ... AH59: =Model!AH16 -> 68.99687
B60: GAAP Revenue - Total | C60: =+Model!C8 -> 73.455054 | D60: =+Model!D8 -> 73.869141 | E60: =+Model!E8 -> 77.137926 | F60: =+Model!F8 -> 78.14858 | G60: =+Model!G8 -> 76.99011 | H60: =+Model!H8 -> 76.949729 | I60: =+Model!I8 -> 77.996212 | J60: =+Model!J8 -> 78.018904 | ... AH60: =+Model!AH8 -> 89.606324
B61: LTM Gross Margin % | C61: =SUM(C59:C59)/SUM(C60:C60) -> 0.77109561 | D61: =SUM(C59:D59)/SUM(C60:D60) -> 0.77428034 | E61: =SUM(C59:E59)/SUM(C60:E60) -> 0.77503052 | F61: =SUM(C59:F59)/SUM(C60:F60) -> 0.77569092 | G61: =SUM(D59:G59)/SUM(D60:G60) -> 0.77708071 | H61: =SUM(E59:H59)/SUM(E60:H60) -> 0.77735653 | I61: =SUM(F59:I59)/SUM(F60:I60) -> 0.7763028 | J61: =SUM(G59:J59)/SUM(G60:J60) -> 0.776599 | K61: =SUM(H59:K59)/SUM(H60:K60) -> 0.77493398 | L61: =SUM(I59:L59)/SUM(I60:L60) -> 0.773668 | M61: =SUM(J59:M59)/SUM(J60:M60) -> 0.77424692 | ... AH61: =SUM(AE59:AH59)/SUM(AE60:AH60) -> 0.77
B63: CAC
B64: New Customers | D64: =D15 -> 6 | E64: =E15 -> 6 | F64: =F15 -> 5 | G64: =G15 -> 4 | H64: =H15 -> 4 | I64: =I15 -> 5 | J64: =J15 -> 5 | K64: =K15 -> 7 | ... AH64: =AH15 -> 7.0762319
B65: S&M Prior Period | D65: =+Model!C20 -> 14.00397 | E65: =+Model!D20 -> 14.083162 | F65: =+Model!E20 -> 14.056085 | G65: =+Model!F20 -> 14.845196 | H65: =+Model!G20 -> 13.968859 | I65: =+Model!H20 -> 14.048706 | J65: =+Model!I20 -> 14.759204 | K65: =+Model!J20 -> 14.257532 | ... AH65: =+Model!AG20 -> 16.048894
B66: Acquisition Cost Per Customer | D66: =+D65/D64 -> 2.3339949 | E66: =+E65/E64 -> 2.3471937 | F66: =+F65/F64 -> 2.811217 | G66: =+G65/G64 -> 3.7112991 | H66: =+H65/H64 -> 3.4922147 | I66: =+I65/I64 -> 2.8097412 | J66: =+J65/J64 -> 2.9518408 | K66: =+K65/K64 -> 2.0367902 | ... AH66: =+AH65/AH64 -> 2.268
B68: CAC Payback
B69: New Logo ARR | C69: =+C7 -> 16.54272 | D69: =+D7 -> 12.672 | E69: =+E7 -> 10.78272 | F69: =+F7 -> 12.034256 | G69: =+G7 -> 6.912 | H69: =+H7 -> 7.87968 | I69: =+I7 -> 11.52 | J69: =+J7 -> 12.48768 | ... AH69: =+AH7 -> 14.860087
B70: Gross Margin Subscriptions | C70: =+Model!C17 -> 0.77109561 | D70: =+Model!D17 -> 0.77744721 | E70: =+Model!E17 -> 0.77646328 | F70: =+Model!F17 -> 0.77758774 | G70: =+Model!G17 -> 0.77683304 | H70: =+Model!H17 -> 0.77854092 | I70: =+Model!I17 -> 0.77228386 | J70: =+Model!J17 -> 0.77876661 | ... AH70: =+Model!AH17 -> 0.77
B71: New Logo Gross Profit | C71: =+C70*C69 -> 12.756019 | D71: =+D70*D69 -> 9.851811 | E71: =+E70*E69 -> 8.3723862 | F71: =+F70*F69 -> 9.3576899 | G71: =+G70*G69 -> 5.36947 | H71: =+H70*H69 -> 6.1346533 | I71: =+I70*I69 -> 8.8967101 | J71: =+J70*J69 -> 9.7249882 | ... AH71: =+AH70*AH69 -> 11.442267
B72: S&M Prior Period | C72: =+C65 -> 0 | D72: =+D65 -> 14.00397 | E72: =+E65 -> 14.083162 | F72: =+F65 -> 14.056085 | G72: =+G65 -> 14.845196 | H72: =+H65 -> 13.968859 | I72: =+I65 -> 14.048706 | J72: =+J65 -> 14.759204 | ... AH72: =+AH65 -> 16.048894
B73: GP Payback [Months] | C73: =(C72/C71)*12 -> 0 | D73: =(D72/D71)*12 -> 17.057537 | E73: =(E72/E71)*12 -> 20.185159 | F73: =(F72/F71)*12 -> 18.025071 | G73: =(G72/G71)*12 -> 33.176898 | H73: =(H72/H71)*12 -> 27.324495 | I73: =(I72/I71)*12 -> 18.94908 | J73: =(J72/J71)*12 -> 18.211893 | ... AH73: =(AH72/AH71)*12 -> 16.831169
B74: GP Payback w/ Upsell [Months] | C74: =(C72/(SUM(C7:C8)*C70))*12 -> 0 | D74: =(D72/(SUM(D7:D8)*D70))*12 -> 12.330587 | E74: =(E72/(SUM(E7:E8)*E70))*12 -> 14.735766 | F74: =(F72/(SUM(F7:F8)*F70))*12 -> 12.210365 | G74: =(G72/(SUM(G7:G8)*G70))*12 -> 18.634381 | H74: =(H72/(SUM(H7:H8)*H70))*12 -> 14.987618 | I74: =(I72/(SUM(I7:I8)*I70))*12 -> 12.633042 | J74: =(J72/(SUM(J7:J8)*J70))*12 -> 11.943811 | ... AH74: =(AH72/(SUM(AH7:AH8)*AH70))*12 -> 12.24085
B76: LTV / CAC
B77: Customer Lifetime (Years) | D77: =IFERROR(1/(1-D28),0) -> 6.3 | E77: =IFERROR(1/(1-E28),0) -> 10.583333 | F77: =IFERROR(1/(1-F28),0) -> 10.833333 | G77: =IFERROR(1/(1-G28),0) -> 6.6 | H77: =IFERROR(1/(1-H28),0) -> 8.1875 | I77: =IFERROR(1/(1-I28),0) -> 10.916667 | J77: =IFERROR(1/(1-J28),0) -> 5.5416667 | K77: =IFERROR(1/(1-K28),0) -> 6.6 | ... AH77: =IFERROR(1/(1-AH28),0) -> 7.6732238
B78: New Logo Gross Profit - Year 1 | D78: =D7*D70 -> 9.851811 | E78: =E7*E70 -> 8.3723862 | F78: =F7*F70 -> 9.3576899 | G78: =G7*G70 -> 5.36947 | H78: =H7*H70 -> 6.1346533 | I78: =I7*I70 -> 8.8967101 | J78: =J7*J70 -> 9.7249882 | K78: =K7*K70 -> 11.81942 | ... AH78: =AH7*AH70 -> 11.442267
B79: New Logo Gross Profit - Year 2 | D79: =+D78*D$26 -> 8.6239469 | E79: =+E78*E$26 -> 7.6117486 | F79: =+F78*F$26 -> 8.5575951 | G79: =+G78*G$26 -> 4.6624719 | H79: =+H78*H$26 -> 5.4511036 | I79: =+I78*I$26 -> 7.904302 | J79: =+J78*J$26 -> 8.5968716 | K79: =+K78*K$26 -> 9.9166052 | ... AH79: =+AH78*AH$26 -> 9.8403496
B80: New Logo Gross Profit - Year 3 | D80: =+D79*D$26 -> 7.5491157 | E80: =+E79*E$26 -> 6.9202155 | F80: =+F79*F$26 -> 7.8259094 | G80: =+G79*G$26 -> 4.0485643 | H80: =+H79*H$26 -> 4.843718 | I80: =+I79*I$26 -> 7.0225948 | J80: =+J79*J$26 -> 7.5996186 | K80: =+K79*K$26 -> 8.3201255 | ... AH80: =+AH79*AH$26 -> 8.4627006
B81: New Logo Gross Profit - Year 4 | D81: =+D80*D$26 -> 6.6082442 | E81: =+E80*E$26 -> 6.2915087 | F81: =+F80*F$26 -> 7.1567839 | G81: =+G80*G$26 -> 3.5154899 | H81: =+H80*H$26 -> 4.3040099 | I81: =+I80*I$26 -> 6.2392401 | J81: =+J80*J$26 -> 6.7180489 | K81: =+K80*K$26 -> 6.9806638 | ... AH81: =+AH80*AH$26 -> 7.2779225
B82: New Logo Gross Profit - Year 5 | D82: =+D81*D$26 -> 5.7846367 | E82: =+E81*E$26 -> 5.7199204 | F82: =+F81*F$26 -> 6.5448694 | G82: =+G81*G$26 -> 3.0526054 | H82: =+H81*H$26 -> 3.8244385 | I82: =+I81*I$26 -> 5.5432668 | J82: =+J81*J$26 -> 5.9387428 | K82: =+K81*K$26 -> 5.8568429 | ... AH82: =+AH81*AH$26 -> 6.2590134
B83: Overall LTV | D83: =+D77*D78 -> 62.066409 | E83: =+E77*E78 -> 88.607753 | F83: =+F77*F78 -> 101.37497 | G83: =+G77*G78 -> 35.438502 | H83: =+H77*H78 -> 50.227474 | I83: =+I77*I78 -> 97.122419 | J83: =+J77*J78 -> 53.892643 | K83: =+K77*K78 -> 78.008174 | ... AH83: =+AH77*AH78 -> 87.799076
B84: 3 Year LTV | D84: =SUM(D78:D80) -> 26.024874 | E84: =SUM(E78:E80) -> 22.90435 | F84: =SUM(F78:F80) -> 25.741194 | G84: =SUM(G78:G80) -> 14.080506 | H84: =SUM(H78:H80) -> 16.429475 | I84: =SUM(I78:I80) -> 23.823607 | J84: =SUM(J78:J80) -> 25.921478 | K84: =SUM(K78:K80) -> 30.056151 | ... AH84: =SUM(AH78:AH80) -> 29.745317
B85: 5 Year LTV | D85: =SUM(D78:D82) -> 38.417754 | E85: =SUM(E78:E82) -> 34.915779 | F85: =SUM(F78:F82) -> 39.442848 | G85: =SUM(G78:G82) -> 20.648602 | H85: =SUM(H78:H82) -> 24.557923 | I85: =SUM(I78:I82) -> 35.606114 | J85: =SUM(J78:J82) -> 38.57827 | K85: =SUM(K78:K82) -> 42.893658 | ... AH85: =SUM(AH78:AH82) -> 43.282253
B86: S&M Prior Period | D86: =D72 -> 14.00397 | E86: =E72 -> 14.083162 | F86: =F72 -> 14.056085 | G86: =G72 -> 14.845196 | H86: =H72 -> 13.968859 | I86: =I72 -> 14.048706 | J86: =J72 -> 14.759204 | K86: =K72 -> 14.257532 | ... AH86: =AH72 -> 16.048894
B87: Overall LTV / CAC | D87: =D83/D86 -> 4.4320583 | E87: =E83/E86 -> 6.2917512 | F87: =F83/F86 -> 7.2121771 | G87: =G83/G86 -> 2.3872033 | H87: =H83/H86 -> 3.5956748 | I87: =I83/I86 -> 6.9132643 | J87: =J83/J86 -> 3.65146 | K87: =K83/K86 -> 5.471366 | ... AH87: =AH83/AH86 -> 5.4707244
B88: 3 Year LTV / CAC | D88: =+D84/D86 -> 1.8583926 | E88: =+E84/E86 -> 1.6263641 | F88: =+F84/F86 -> 1.8313203 | G88: =+G84/G86 -> 0.94848905 | H88: =+H84/H86 -> 1.1761501 | I88: =+I84/I86 -> 1.6957866 | J88: =+J84/J86 -> 1.7562925 | K88: =+K84/K86 -> 2.1080894 | ... AH88: =+AH84/AH86 -> 1.8534185
B89: 5 Year LTV / CAC | D89: =+D85/D86 -> 2.7433475 | E89: =+E85/E86 -> 2.479257 | F89: =+F85/F86 -> 2.8061048 | G89: =+G85/G86 -> 1.3909282 | H89: =+H85/H86 -> 1.7580479 | I89: =+I85/I86 -> 2.5344764 | J89: =+J85/J86 -> 2.6138449 | K89: =+K85/K86 -> 3.0084912 | ... AH89: =+AH85/AH86 -> 2.6968994
B91: Other Margin Profile
B92: GAAP Revenue | C92: =Model!C8 -> 73.455054 | D92: =Model!D8 -> 73.869141 | E92: =Model!E8 -> 77.137926 | F92: =Model!F8 -> 78.14858 | G92: =Model!G8 -> 76.99011 | H92: =Model!H8 -> 76.949729 | I92: =Model!I8 -> 77.996212 | J92: =Model!J8 -> 78.018904 | ... AH92: =Model!AH8 -> 89.606324
B93: S&M | C93: =Model!C20 -> 14.00397 | D93: =Model!D20 -> 14.083162 | E93: =Model!E20 -> 14.056085 | F93: =Model!F20 -> 14.845196 | G93: =Model!G20 -> 13.968859 | H93: =Model!H20 -> 14.048706 | I93: =Model!I20 -> 14.759204 | J93: =Model!J20 -> 14.257532 | ... AH93: =Model!AH20 -> 16.129138
B94: R&D | C94: =Model!C21 -> 9.2062254 | D94: =Model!D21 -> 9.6841711 | E94: =Model!E21 -> 9.7135544 | F94: =Model!F21 -> 10.07255 | G94: =Model!G21 -> 9.3605583 | H94: =Model!H21 -> 9.9635406 | I94: =Model!I21 -> 9.5611794 | J94: =Model!J21 -> 9.4684992 | ... AH94: =Model!AH21 -> 10.752759
B95: G&A | C95: =Model!C22 -> 7.8364503 | D95: =Model!D22 -> 7.7408835 | E95: =Model!E22 -> 8.5227341 | F95: =Model!F22 -> 8.297927 | G95: =Model!G22 -> 7.7674467 | H95: =Model!H22 -> 8.4813746 | I95: =Model!I22 -> 8.1831799 | J95: =Model!J22 -> 8.5208101 | ... AH95: =Model!AH22 -> 9.8566957
B96: Free Cash Flow - (Negative) / Positive | O96: =Model!O156 -> 3.6456779 | P96: =Model!P156 -> 3.9738686 | Q96: =Model!Q156 -> 6.1907626 | R96: =Model!R156 -> 9.5226922 | S96: =Model!S156 -> 5.3167897 | T96: =Model!T156 -> 5.6735201 | U96: =Model!U156 -> 7.8707409 | V96: =Model!V156 -> 11.222299 | ... AH96: =Model!AH156 -> 15.544662
B97: LTM S&M, % of Revenue | C97: =+SUM(C93:C93)/SUM(C$92:C$92) -> 0.19064678 | D97: =+SUM(C93:D93)/SUM(C$92:D$92) -> 0.19064847 | E97: =+SUM(C93:E93)/SUM(C$92:E$92) -> 0.18775202 | F97: =+SUM(C93:F93)/SUM(C$92:F$92) -> 0.18832253 | G97: =+SUM(D93:G93)/SUM(D$92:G$92) -> 0.18603329 | H97: =+SUM(E93:H93)/SUM(E$92:H$92) -> 0.18406855 | I97: =+SUM(F93:I93)/SUM(F$92:I$92) -> 0.18582657 | J97: =+SUM(G93:J93)/SUM(G$92:J$92) -> 0.18400835 | K97: =+SUM(H93:K93)/SUM(H$92:K$92) -> 0.18496539 | L97: =+SUM(I93:L93)/SUM(I$92:L$92) -> 0.18644743 | M97: =+SUM(J93:M93)/SUM(J$92:M$92) -> 0.18628198 | ... AH97: =+SUM(AE93:AH93)/SUM(AE$92:AH$92) -> 0.18
B98: LTM R&D, % of Revenue | C98: =+SUM(C94:C94)/SUM(C$92:C$92) -> 0.12533141 | D98: =+SUM(C94:D94)/SUM(C$92:D$92) -> 0.12822331 | E98: =+SUM(C94:E94)/SUM(C$92:E$92) -> 0.12743331 | F98: =+SUM(C94:F94)/SUM(C$92:F$92) -> 0.12780943 | G98: =+SUM(D94:G94)/SUM(D$92:G$92) -> 0.12683773 | H98: =+SUM(E94:H94)/SUM(E$92:H$92) -> 0.12647759 | I98: =+SUM(F94:I94)/SUM(F$92:I$92) -> 0.12563611 | J98: =+SUM(G94:J94)/SUM(G$92:J$92) -> 0.12373984 | K98: =+SUM(H94:K94)/SUM(H$92:K$92) -> 0.12494043 | L98: =+SUM(I94:L94)/SUM(I$92:L$92) -> 0.12357635 | M98: =+SUM(J94:M94)/SUM(J$92:M$92) -> 0.12515264 | ... AH98: =+SUM(AE94:AH94)/SUM(AE$92:AH$92) -> 0.12
B99: LTM G&A, % of Revenue | C99: =+SUM(C95:C95)/SUM(C$92:C$92) -> 0.10668361 | D99: =+SUM(C95:D95)/SUM(C$92:D$92) -> 0.10573507 | E99: =+SUM(C95:E95)/SUM(C$92:E$92) -> 0.10736808 | F99: =+SUM(C95:F95)/SUM(C$92:F$92) -> 0.10706163 | G99: =+SUM(D95:G95)/SUM(D$92:G$92) -> 0.1056 | H99: =+SUM(E95:H95)/SUM(E$92:H$92) -> 0.10694264 | I99: =+SUM(F95:I95)/SUM(F$92:I$92) -> 0.1055516 | J99: =+SUM(G95:J95)/SUM(G$92:J$92) -> 0.10631484 | K99: =+SUM(H95:K95)/SUM(H$92:K$92) -> 0.10685867 | L99: =+SUM(I95:L95)/SUM(I$92:L$92) -> 0.10645848 | M99: =+SUM(J95:M95)/SUM(J$92:M$92) -> 0.10596127 | ... AH99: =+SUM(AE95:AH95)/SUM(AE$92:AH$92) -> 0.11
B100: LTM FCF, % Margin | R100: =+SUM(O96:R96)/SUM(O$92:R$92) -> 0.071034819 | S100: =+SUM(P96:S96)/SUM(P$92:S$92) -> 0.075743622 | T100: =+SUM(Q96:T96)/SUM(Q$92:T$92) -> 0.080489836 | U100: =+SUM(R96:U96)/SUM(R$92:U$92) -> 0.085127946 | V100: =+SUM(S96:V96)/SUM(S$92:V$92) -> 0.089776491 | W100: =+SUM(T96:W96)/SUM(T$92:W$92) -> 0.094627921 | X100: =+SUM(U96:X96)/SUM(U$92:X$92) -> 0.099528171 | Y100: =+SUM(V96:Y96)/SUM(V$92:Y$92) -> 0.10447773 | ... AH100: =+SUM(AE96:AH96)/SUM(AE$92:AH$92) -> 0.13490985

Sheet Cohorts
A1: 1000000
B2: Cohorts | O2: $ in millions, except noted
D3: =EOMONTH(#REF!, 3) -> #REF! | E3: =EOMONTH(D3, 3) -> #REF! | F3: =EOMONTH(E3, 3) -> #REF! | G3: =EOMONTH(F3, 3) -> #REF! | H3: =EOMONTH(G3, 3) -> #REF! | I3: =EOMONTH(H3, 3) -> #REF! | J3: =EOMONTH(I3, 3) -> #REF! | K3: =EOMONTH(J3, 3) -> #REF! | L3: =EOMONTH(K3, 3) -> #REF! | ... O3: =EOMONTH(N3, 3) -> #REF!
D4: =EOMONTH(#REF!, 2)+1 -> #REF! | E4: =EOMONTH(D4, 2)+1 -> #REF! | F4: =EOMONTH(E4, 2)+1 -> #REF! | G4: =EOMONTH(F4, 2)+1 -> #REF! | H4: =EOMONTH(G4, 2)+1 -> #REF! | I4: =EOMONTH(H4, 2)+1 -> #REF! | J4: =EOMONTH(I4, 2)+1 -> #REF! | K4: =EOMONTH(J4, 2)+1 -> #REF! | L4: =EOMONTH(K4, 2)+1 -> #REF! | ... O4: =EOMONTH(N4, 2)+1 -> #REF!
D5: ='Raw Customer ARR'!D1 -> 43921 | E5: =EOMONTH(D5, 3) -> 44012 | F5: =EOMONTH(E5, 3) -> 44104 | G5: =EOMONTH(F5, 3) -> 44196 | H5: =EOMONTH(G5, 3) -> 44286 | I5: =EOMONTH(H5, 3) -> 44377 | J5: =EOMONTH(I5, 3) -> 44469 | K5: =EOMONTH(J5, 3) -> 44561 | L5: =EOMONTH(K5, 3) -> 44651 | ... O5: =EOMONTH(N5, 3) -> 44926
B6: ARR by Cohort
B7: =EOMONTH(B8, -3) -> 43830 | D7: =SUMIFS('Raw Customer ARR'!D$2:D$197, 'Raw Customer ARR'!$B$2:$B$197, Cohorts!$B7)/unit -> 284.64489 | E7: =SUMIFS('Raw Customer ARR'!E$2:E$197, 'Raw Customer ARR'!$B$2:$B$197, Cohorts!$B7)/unit -> 275.26038 | F7: =SUMIFS('Raw Customer ARR'!F$2:F$197, 'Raw Customer ARR'!$B$2:$B$197, Cohorts!$B7)/unit -> 268.06846 | G7: =SUMIFS('Raw Customer ARR'!G$2:G$197, 'Raw Customer ARR'!$B$2:$B$197, Cohorts!$B7)/unit -> 261.81396 | H7: =SUMIFS('Raw Customer ARR'!H$2:H$197, 'Raw Customer ARR'!$B$2:$B$197, Cohorts!$B7)/unit -> 251.87383 | I7: =SUMIFS('Raw Customer ARR'!I$2:I$197, 'Raw Customer ARR'!$B$2:$B$197, Cohorts!$B7)/unit -> 243.39045 | J7: =SUMIFS('Raw Customer ARR'!J$2:J$197, 'Raw Customer ARR'!$B$2:$B$197, Cohorts!$B7)/unit -> 234.13417 | K7: =SUMIFS('Raw Customer ARR'!K$2:K$197, 'Raw Customer ARR'!$B$2:$B$197, Cohorts!$B7)/unit -> 224.92661 | ... O7: =SUMIFS('Raw Customer ARR'!O$2:O$197, 'Raw Customer ARR'!$B$2:$B$197, Cohorts!$B7)/unit -> 186.91562
B8: {=TRANSPOSE(D5:O5)} -> 43921 | D8: =SUMIFS('Raw Customer ARR'!D$2:D$197, 'Raw Customer ARR'!$B$2:$B$197, Cohorts!$B8)/unit -> 16.54272 | E8: =SUMIFS('Raw Customer ARR'!E$2:E$197, 'Raw Customer ARR'!$B$2:$B$197, Cohorts!$B8)/unit -> 16.54272 | F8: =SUMIFS('Raw Customer ARR'!F$2:F$197, 'Raw Customer ARR'!$B$2:$B$197, Cohorts!$B8)/unit -> 16.95744 | G8: =SUMIFS('Raw Customer ARR'!G$2:G$197, 'Raw Customer ARR'!$B$2:$B$197, Cohorts!$B8)/unit -> 16.77312 | H8: =SUMIFS('Raw Customer ARR'!H$2:H$197, 'Raw Customer ARR'!$B$2:$B$197, Cohorts!$B8)/unit -> 16.5888 | I8: =SUMIFS('Raw Customer ARR'!I$2:I$197, 'Raw Customer ARR'!$B$2:$B$197, Cohorts!$B8)/unit -> 16.9132 | J8: =SUMIFS('Raw Customer ARR'!J$2:J$197, 'Raw Customer ARR'!$B$2:$B$197, Cohorts!$B8)/unit -> 17.198088 | K8: =SUMIFS('Raw Customer ARR'!K$2:K$197, 'Raw Customer ARR'!$B$2:$B$197, Cohorts!$B8)/unit -> 16.718856 | ... O8: =SUMIFS('Raw Customer ARR'!O$2:O$197, 'Raw Customer ARR'!$B$2:$B$197, Cohorts!$B8)/unit -> 16.882752
B9: 44012 | D9: =SUMIFS('Raw Customer ARR'!D$2:D$197, 'Raw Customer ARR'!$B$2:$B$197, Cohorts!$B9)/unit -> 0 | E9: =SUMIFS('Raw Customer ARR'!E$2:E$197, 'Raw Customer ARR'!$B$2:$B$197, Cohorts!$B9)/unit -> 12.672 | F9: =SUMIFS('Raw Customer ARR'!F$2:F$197, 'Raw Customer ARR'!$B$2:$B$197, Cohorts!$B9)/unit -> 12.53376 | G9: =SUMIFS('Raw Customer ARR'!G$2:G$197, 'Raw Customer ARR'!$B$2:$B$197, Cohorts!$B9)/unit -> 12.243416 | H9: =SUMIFS('Raw Customer ARR'!H$2:H$197, 'Raw Customer ARR'!$B$2:$B$197, Cohorts!$B9)/unit -> 12.18628 | I9: =SUMIFS('Raw Customer ARR'!I$2:I$197, 'Raw Customer ARR'!$B$2:$B$197, Cohorts!$B9)/unit -> 11.574272 | J9: =SUMIFS('Raw Customer ARR'!J$2:J$197, 'Raw Customer ARR'!$B$2:$B$197, Cohorts!$B9)/unit -> 11.119808 | K9: =SUMIFS('Raw Customer ARR'!K$2:K$197, 'Raw Customer ARR'!$B$2:$B$197, Cohorts!$B9)/unit -> 10.885792 | ... O9: =SUMIFS('Raw Customer ARR'!O$2:O$197, 'Raw Customer ARR'!$B$2:$B$197, Cohorts!$B9)/unit -> 8.548288
B10: 44104 | D10: =SUMIFS('Raw Customer ARR'!D$2:D$197, 'Raw Customer ARR'!$B$2:$B$197, Cohorts!$B10)/unit -> 0 | E10: =SUMIFS('Raw Customer ARR'!E$2:E$197, 'Raw Customer ARR'!$B$2:$B$197, Cohorts!$B10)/unit -> 0 | F10: =SUMIFS('Raw Customer ARR'!F$2:F$197, 'Raw Customer ARR'!$B$2:$B$197, Cohorts!$B10)/unit -> 10.78272 | G10: =SUMIFS('Raw Customer ARR'!G$2:G$197, 'Raw Customer ARR'!$B$2:$B$197, Cohorts!$B10)/unit -> 10.92096 | H10: =SUMIFS('Raw Customer ARR'!H$2:H$197, 'Raw Customer ARR'!$B$2:$B$197, Cohorts!$B10)/unit -> 10.92096 | I10: =SUMIFS('Raw Customer ARR'!I$2:I$197, 'Raw Customer ARR'!$B$2:$B$197, Cohorts!$B10)/unit -> 10.73664 | J10: =SUMIFS('Raw Customer ARR'!J$2:J$197, 'Raw Customer ARR'!$B$2:$B$197, Cohorts!$B10)/unit -> 10.891472 | K10: =SUMIFS('Raw Customer ARR'!K$2:K$197, 'Raw Customer ARR'!$B$2:$B$197, Cohorts!$B10)/unit -> 10.343008 | ... O10: =SUMIFS('Raw Customer ARR'!O$2:O$197, 'Raw Customer ARR'!$B$2:$B$197, Cohorts!$B10)/unit -> 8.252008
B11: 44196 | D11: =SUMIFS('Raw Customer ARR'!D$2:D$197, 'Raw Customer ARR'!$B$2:$B$197, Cohorts!$B11)/unit -> 0 | E11: =SUMIFS('Raw Customer ARR'!E$2:E$197, 'Raw Customer ARR'!$B$2:$B$197, Cohorts!$B11)/unit -> 0 | F11: =SUMIFS('Raw Customer ARR'!F$2:F$197, 'Raw Customer ARR'!$B$2:$B$197, Cohorts!$B11)/unit -> 0 | G11: =SUMIFS('Raw Customer ARR'!G$2:G$197, 'Raw Customer ARR'!$B$2:$B$197, Cohorts!$B11)/unit -> 12.034256 | H11: =SUMIFS('Raw Customer ARR'!H$2:H$197, 'Raw Customer ARR'!$B$2:$B$197, Cohorts!$B11)/unit -> 11.8868 | I11: =SUMIFS('Raw Customer ARR'!I$2:I$197, 'Raw Customer ARR'!$B$2:$B$197, Cohorts!$B11)/unit -> 12.196456 | J11: =SUMIFS('Raw Customer ARR'!J$2:J$197, 'Raw Customer ARR'!$B$2:$B$197, Cohorts!$B11)/unit -> 12.533168 | K11: =SUMIFS('Raw Customer ARR'!K$2:K$197, 'Raw Customer ARR'!$B$2:$B$197, Cohorts!$B11)/unit -> 12.723976 | ... O11: =SUMIFS('Raw Customer ARR'!O$2:O$197, 'Raw Customer ARR'!$B$2:$B$197, Cohorts!$B11)/unit -> 12.244904
B12: 44286 | D12: =SUMIFS('Raw Customer ARR'!D$2:D$197, 'Raw Customer ARR'!$B$2:$B$197, Cohorts!$B12)/unit -> 0 | E12: =SUMIFS('Raw Customer ARR'!E$2:E$197, 'Raw Customer ARR'!$B$2:$B$197, Cohorts!$B12)/unit -> 0 | F12: =SUMIFS('Raw Customer ARR'!F$2:F$197, 'Raw Customer ARR'!$B$2:$B$197, Cohorts!$B12)/unit -> 0 | G12: =SUMIFS('Raw Customer ARR'!G$2:G$197, 'Raw Customer ARR'!$B$2:$B$197, Cohorts!$B12)/unit -> 0 | H12: =SUMIFS('Raw Customer ARR'!H$2:H$197, 'Raw Customer ARR'!$B$2:$B$197, Cohorts!$B12)/unit -> 6.912 | I12: =SUMIFS('Raw Customer ARR'!I$2:I$197, 'Raw Customer ARR'!$B$2:$B$197, Cohorts!$B12)/unit -> 6.912 | J12: =SUMIFS('Raw Customer ARR'!J$2:J$197, 'Raw Customer ARR'!$B$2:$B$197, Cohorts!$B12)/unit -> 7.32672 | K12: =SUMIFS('Raw Customer ARR'!K$2:K$197, 'Raw Customer ARR'!$B$2:$B$197, Cohorts!$B12)/unit -> 8.219272 | ... O12: =SUMIFS('Raw Customer ARR'!O$2:O$197, 'Raw Customer ARR'!$B$2:$B$197, Cohorts!$B12)/unit -> 8.650912
B13: 44377 | D13: =SUMIFS('Raw Customer ARR'!D$2:D$197, 'Raw Customer ARR'!$B$2:$B$197, Cohorts!$B13)/unit -> 0 | E13: =SUMIFS('Raw Customer ARR'!E$2:E$197, 'Raw Customer ARR'!$B$2:$B$197, Cohorts!$B13)/unit -> 0 | F13: =SUMIFS('Raw Customer ARR'!F$2:F$197, 'Raw Customer ARR'!$B$2:$B$197, Cohorts!$B13)/unit -> 0 | G13: =SUMIFS('Raw Customer ARR'!G$2:G$197, 'Raw Customer ARR'!$B$2:$B$197, Cohorts!$B13)/unit -> 0 | H13: =SUMIFS('Raw Customer ARR'!H$2:H$197, 'Raw Customer ARR'!$B$2:$B$197, Cohorts!$B13)/unit -> 0 | I13: =SUMIFS('Raw Customer ARR'!I$2:I$197, 'Raw Customer ARR'!$B$2:$B$197, Cohorts!$B13)/unit -> 7.87968 | J13: =SUMIFS('Raw Customer ARR'!J$2:J$197, 'Raw Customer ARR'!$B$2:$B$197, Cohorts!$B13)/unit -> 7.7654 | K13: =SUMIFS('Raw Customer ARR'!K$2:K$197, 'Raw Customer ARR'!$B$2:$B$197, Cohorts!$B13)/unit -> 8.442888 | ... O13: =SUMIFS('Raw Customer ARR'!O$2:O$197, 'Raw Customer ARR'!$B$2:$B$197, Cohorts!$B13)/unit -> 8.164224
B14: 44469 | D14: =SUMIFS('Raw Customer ARR'!D$2:D$197, 'Raw Customer ARR'!$B$2:$B$197, Cohorts!$B14)/unit -> 0 | E14: =SUMIFS('Raw Customer ARR'!E$2:E$197, 'Raw Customer ARR'!$B$2:$B$197, Cohorts!$B14)/unit -> 0 | F14: =SUMIFS('Raw Customer ARR'!F$2:F$197, 'Raw Customer ARR'!$B$2:$B$197, Cohorts!$B14)/unit -> 0 | G14: =SUMIFS('Raw Customer ARR'!G$2:G$197, 'Raw Customer ARR'!$B$2:$B$197, Cohorts!$B14)/unit -> 0 | H14: =SUMIFS('Raw Customer ARR'!H$2:H$197, 'Raw Customer ARR'!$B$2:$B$197, Cohorts!$B14)/unit -> 0 | I14: =SUMIFS('Raw Customer ARR'!I$2:I$197, 'Raw Customer ARR'!$B$2:$B$197, Cohorts!$B14)/unit -> 0 | J14: =SUMIFS('Raw Customer ARR'!J$2:J$197, 'Raw Customer ARR'!$B$2:$B$197, Cohorts!$B14)/unit -> 11.52 | K14: =SUMIFS('Raw Customer ARR'!K$2:K$197, 'Raw Customer ARR'!$B$2:$B$197, Cohorts!$B14)/unit -> 11.166104 | ... O14: =SUMIFS('Raw Customer ARR'!O$2:O$197, 'Raw Customer ARR'!$B$2:$B$197, Cohorts!$B14)/unit -> 10.80484
B15: 44561 | D15: =SUMIFS('Raw Customer ARR'!D$2:D$197, 'Raw Customer ARR'!$B$2:$B$197, Cohorts!$B15)/unit -> 0 | E15: =SUMIFS('Raw Customer ARR'!E$2:E$197, 'Raw Customer ARR'!$B$2:$B$197, Cohorts!$B15)/unit -> 0 | F15: =SUMIFS('Raw Customer ARR'!F$2:F$197, 'Raw Customer ARR'!$B$2:$B$197, Cohorts!$B15)/unit -> 0 | G15: =SUMIFS('Raw Customer ARR'!G$2:G$197, 'Raw Customer ARR'!$B$2:$B$197, Cohorts!$B15)/unit -> 0 | H15: =SUMIFS('Raw Customer ARR'!H$2:H$197, 'Raw Customer ARR'!$B$2:$B$197, Cohorts!$B15)/unit -> 0 | I15: =SUMIFS('Raw Customer ARR'!I$2:I$197, 'Raw Customer ARR'!$B$2:$B$197, Cohorts!$B15)/unit -> 0 | J15: =SUMIFS('Raw Customer ARR'!J$2:J$197, 'Raw Customer ARR'!$B$2:$B$197, Cohorts!$B15)/unit -> 0 | K15: =SUMIFS('Raw Customer ARR'!K$2:K$197, 'Raw Customer ARR'!$B$2:$B$197, Cohorts!$B15)/unit -> 12.48768 | ... O15: =SUMIFS('Raw Customer ARR'!O$2:O$197, 'Raw Customer ARR'!$B$2:$B$197, Cohorts!$B15)/unit -> 12.8342
B16: 44651 | D16: =SUMIFS('Raw Customer ARR'!D$2:D$197, 'Raw Customer ARR'!$B$2:$B$197, Cohorts!$B16)/unit -> 0 | E16: =SUMIFS('Raw Customer ARR'!E$2:E$197, 'Raw Customer ARR'!$B$2:$B$197, Cohorts!$B16)/unit -> 0 | F16: =SUMIFS('Raw Customer ARR'!F$2:F$197, 'Raw Customer ARR'!$B$2:$B$197, Cohorts!$B16)/unit -> 0 | G16: =SUMIFS('Raw Customer ARR'!G$2:G$197, 'Raw Customer ARR'!$B$2:$B$197, Cohorts!$B16)/unit -> 0 | H16: =SUMIFS('Raw Customer ARR'!H$2:H$197, 'Raw Customer ARR'!$B$2:$B$197, Cohorts!$B16)/unit -> 0 | I16: =SUMIFS('Raw Customer ARR'!I$2:I$197, 'Raw Customer ARR'!$B$2:$B$197, Cohorts!$B16)/unit -> 0 | J16: =SUMIFS('Raw Customer ARR'!J$2:J$197, 'Raw Customer ARR'!$B$2:$B$197, Cohorts!$B16)/unit -> 0 | K16: =SUMIFS('Raw Customer ARR'!K$2:K$197, 'Raw Customer ARR'!$B$2:$B$197, Cohorts!$B16)/unit -> 0 | ... O16: =SUMIFS('Raw Customer ARR'!O$2:O$197, 'Raw Customer ARR'!$B$2:$B$197, Cohorts!$B16)/unit -> 15.194528
B17: 44742 | D17: =SUMIFS('Raw Customer ARR'!D$2:D$197, 'Raw Customer ARR'!$B$2:$B$197, Cohorts!$B17)/unit -> 0 | E17: =SUMIFS('Raw Customer ARR'!E$2:E$197, 'Raw Customer ARR'!$B$2:$B$197, Cohorts!$B17)/unit -> 0 | F17: =SUMIFS('Raw Customer ARR'!F$2:F$197, 'Raw Customer ARR'!$B$2:$B$197, Cohorts!$B17)/unit -> 0 | G17: =SUMIFS('Raw Customer ARR'!G$2:G$197, 'Raw Customer ARR'!$B$2:$B$197, Cohorts!$B17)/unit -> 0 | H17: =SUMIFS('Raw Customer ARR'!H$2:H$197, 'Raw Customer ARR'!$B$2:$B$197, Cohorts!$B17)/unit -> 0 | I17: =SUMIFS('Raw Customer ARR'!I$2:I$197, 'Raw Customer ARR'!$B$2:$B$197, Cohorts!$B17)/unit -> 0 | J17: =SUMIFS('Raw Customer ARR'!J$2:J$197, 'Raw Customer ARR'!$B$2:$B$197, Cohorts!$B17)/unit -> 0 | K17: =SUMIFS('Raw Customer ARR'!K$2:K$197, 'Raw Customer ARR'!$B$2:$B$197, Cohorts!$B17)/unit -> 0 | ... O17: =SUMIFS('Raw Customer ARR'!O$2:O$197, 'Raw Customer ARR'!$B$2:$B$197, Cohorts!$B17)/unit -> 12.672
B18: 44834 | D18: =SUMIFS('Raw Customer ARR'!D$2:D$197, 'Raw Customer ARR'!$B$2:$B$197, Cohorts!$B18)/unit -> 0 | E18: =SUMIFS('Raw Customer ARR'!E$2:E$197, 'Raw Customer ARR'!$B$2:$B$197, Cohorts!$B18)/unit -> 0 | F18: =SUMIFS('Raw Customer ARR'!F$2:F$197, 'Raw Customer ARR'!$B$2:$B$197, Cohorts!$B18)/unit -> 0 | G18: =SUMIFS('Raw Customer ARR'!G$2:G$197, 'Raw Customer ARR'!$B$2:$B$197, Cohorts!$B18)/unit -> 0 | H18: =SUMIFS('Raw Customer ARR'!H$2:H$197, 'Raw Customer ARR'!$B$2:$B$197, Cohorts!$B18)/unit -> 0 | I18: =SUMIFS('Raw Customer ARR'!I$2:I$197, 'Raw Customer ARR'!$B$2:$B$197, Cohorts!$B18)/unit -> 0 | J18: =SUMIFS('Raw Customer ARR'!J$2:J$197, 'Raw Customer ARR'!$B$2:$B$197, Cohorts!$B18)/unit -> 0 | K18: =SUMIFS('Raw Customer ARR'!K$2:K$197, 'Raw Customer ARR'!$B$2:$B$197, Cohorts!$B18)/unit -> 0 | ... O18: =SUMIFS('Raw Customer ARR'!O$2:O$197, 'Raw Customer ARR'!$B$2:$B$197, Cohorts!$B18)/unit -> 17.76476
B19: 44926 | D19: =SUMIFS('Raw Customer ARR'!D$2:D$197, 'Raw Customer ARR'!$B$2:$B$197, Cohorts!$B19)/unit -> 0 | E19: =SUMIFS('Raw Customer ARR'!E$2:E$197, 'Raw Customer ARR'!$B$2:$B$197, Cohorts!$B19)/unit -> 0 | F19: =SUMIFS('Raw Customer ARR'!F$2:F$197, 'Raw Customer ARR'!$B$2:$B$197, Cohorts!$B19)/unit -> 0 | G19: =SUMIFS('Raw Customer ARR'!G$2:G$197, 'Raw Customer ARR'!$B$2:$B$197, Cohorts!$B19)/unit -> 0 | H19: =SUMIFS('Raw Customer ARR'!H$2:H$197, 'Raw Customer ARR'!$B$2:$B$197, Cohorts!$B19)/unit -> 0 | I19: =SUMIFS('Raw Customer ARR'!I$2:I$197, 'Raw Customer ARR'!$B$2:$B$197, Cohorts!$B19)/unit -> 0 | J19: =SUMIFS('Raw Customer ARR'!J$2:J$197, 'Raw Customer ARR'!$B$2:$B$197, Cohorts!$B19)/unit -> 0 | K19: =SUMIFS('Raw Customer ARR'!K$2:K$197, 'Raw Customer ARR'!$B$2:$B$197, Cohorts!$B19)/unit -> 0 | ... O19: =SUMIFS('Raw Customer ARR'!O$2:O$197, 'Raw Customer ARR'!$B$2:$B$197, Cohorts!$B19)/unit -> 18.98496
B20: Ending ARR | D20: =SUM(D7:D19) -> 301.18761 | E20: =SUM(E7:E19) -> 304.4751 | F20: =SUM(F7:F19) -> 308.34238 | G20: =SUM(G7:G19) -> 313.78571 | H20: =SUM(H7:H19) -> 310.36867 | I20: =SUM(I7:I19) -> 309.6027 | J20: =SUM(J7:J19) -> 312.48882 | K20: =SUM(K7:K19) -> 315.91418 | ... O20: =SUM(O7:O19) -> 337.914
B21: Check? | D21: ='ARR Waterfall'!C11-D20 -> 0 | E21: ='ARR Waterfall'!D11-E20 -> 0 | F21: ='ARR Waterfall'!E11-F20 -> 0 | G21: ='ARR Waterfall'!F11-G20 -> 0 | H21: ='ARR Waterfall'!G11-H20 -> 0 | I21: ='ARR Waterfall'!H11-I20 -> 0 | J21: ='ARR Waterfall'!I11-J20 -> 0 | K21: ='ARR Waterfall'!J11-K20 -> 0 | ... O21: ='ARR Waterfall'!N11-O20 -> 0
D24: 1 | E24: =+D24+1 -> 2 | F24: =+E24+1 -> 3 | G24: =+F24+1 -> 4 | H24: =+G24+1 -> 5 | I24: =+H24+1 -> 6 | J24: =+I24+1 -> 7 | K24: =+J24+1 -> 8 | L24: =+K24+1 -> 9 | ... O24: =+N24+1 -> 12
B25: ARR by Cohort (Reordered)
B26: =+B7 -> 43830 | D26: =D7 -> 284.64489 | E26: =E7 -> 275.26038 | F26: =F7 -> 268.06846 | G26: =G7 -> 261.81396 | H26: =H7 -> 251.87383 | I26: =I7 -> 243.39045 | J26: =J7 -> 234.13417 | K26: =K7 -> 224.92661 | ... O26: =O7 -> 186.91562
B27: =+B8 -> 43921 | D27: =D8 -> 16.54272 | E27: =E8 -> 16.54272 | F27: =F8 -> 16.95744 | G27: =G8 -> 16.77312 | H27: =H8 -> 16.5888 | I27: =I8 -> 16.9132 | J27: =J8 -> 17.198088 | K27: =K8 -> 16.718856 | ... O27: =O8 -> 16.882752
B28: =+B9 -> 44012 | D28: =+E9 -> 12.672 | E28: =+F9 -> 12.53376 | F28: =+G9 -> 12.243416 | G28: =+H9 -> 12.18628 | H28: =+I9 -> 11.574272 | I28: =+J9 -> 11.119808 | J28: =+K9 -> 10.885792 | K28: =+L9 -> 10.742264 | ... O28: =+P9 -> 0
B29: =+B10 -> 44104 | D29: =+F10 -> 10.78272 | E29: =+G10 -> 10.92096 | F29: =+H10 -> 10.92096 | G29: =+I10 -> 10.73664 | H29: =+J10 -> 10.891472 | I29: =+K10 -> 10.343008 | J29: =+L10 -> 10.343008 | K29: =+M10 -> 10.378032 | ... O29: =+Q10 -> 0
B30: =+B11 -> 44196 | D30: =+G11 -> 12.034256 | E30: =+H11 -> 11.8868 | F30: =+I11 -> 12.196456 | G30: =+J11 -> 12.533168 | H30: =+K11 -> 12.723976 | I30: =+L11 -> 12.180304 | J30: =+M11 -> 12.108544 | K30: =+N11 -> 12.163088 | ... O30: =+R11 -> 0
B31: =+B12 -> 44286 | D31: =+H12 -> 6.912 | E31: =+I12 -> 6.912 | F31: =+J12 -> 7.32672 | G31: =+K12 -> 8.219272 | H31: =+L12 -> 8.494064 | I31: =+M12 -> 9.671864 | J31: =+N12 -> 9.710752 | K31: =+O12 -> 8.650912 | ... O31: =+S12 -> 0
B32: =+B13 -> 44377 | D32: =+I13 -> 7.87968 | E32: =+J13 -> 7.7654 | F32: =+K13 -> 8.442888 | G32: =+L13 -> 8.442888 | H32: =+M13 -> 8.273312 | I32: =+N13 -> 7.87068 | J32: =+O13 -> 8.164224 | K32: =+P13 -> 0 | ... O32: =+T13 -> 0
B33: =+B14 -> 44469 | D33: =+J14 -> 11.52 | E33: =+K14 -> 11.166104 | F33: =+L14 -> 10.981784 | G33: =+M14 -> 10.981784 | H33: =+N14 -> 10.80484 | I33: =+O14 -> 10.80484 | J33: =+P14 -> 0 | K33: =+Q14 -> 0 | ... O33: =+U14 -> 0
B34: =+B15 -> 44561 | D34: =+K15 -> 12.48768 | E34: =+L15 -> 12.48768 | F34: =+M15 -> 12.48768 | G34: =+N15 -> 12.57984 | H34: =+O15 -> 12.8342 | I34: =+P15 -> 0 | J34: =+Q15 -> 0 | K34: =+R15 -> 0 | ... O34: =+V15 -> 0
B35: =+B16 -> 44651 | D35: =+L16 -> 15.34464 | E35: =+M16 -> 15.04604 | F35: =+N16 -> 15.378848 | G35: =+O16 -> 15.194528 | H35: =+P16 -> 0 | I35: =+Q16 -> 0 | J35: =+R16 -> 0 | K35: =+S16 -> 0 | ... O35: =+W16 -> 0
B36: =+B17 -> 44742 | D36: =+M17 -> 12.672 | E36: =+N17 -> 12.672 | F36: =+O17 -> 12.672 | G36: =+P17 -> 0 | H36: =+Q17 -> 0 | I36: =+R17 -> 0 | J36: =+S17 -> 0 | K36: =+T17 -> 0 | ... O36: =+X17 -> 0
B37: =+B18 -> 44834 | D37: =+N18 -> 18.432 | E37: =+O18 -> 17.76476 | F37: =+P18 -> 0 | G37: =+Q18 -> 0 | H37: =+R18 -> 0 | I37: =+S18 -> 0 | J37: =+T18 -> 0 | K37: =+U18 -> 0 | ... O37: =+Y18 -> 0
B38: =+B19 -> 44926 | D38: =+O19 -> 18.98496 | E38: =+P19 -> 0 | F38: =+Q19 -> 0 | G38: =+R19 -> 0 | H38: =+S19 -> 0 | I38: =+T19 -> 0 | J38: =+U19 -> 0 | K38: =+V19 -> 0 | ... O38: =+Z19 -> 0
D41: =+D$24 -> 1 | E41: =+E$24 -> 2 | F41: =+F$24 -> 3 | G41: =+G$24 -> 4 | H41: =+H$24 -> 5 | I41: =+I$24 -> 6 | J41: =+J$24 -> 7 | K41: =+K$24 -> 8 | ... O41: =+O$24 -> 12
B42: Net Revenue Retention by Cohort
B43: =+B26 -> 43830 | D43: =D26/$D26 -> 1 | E43: =E26/$D26 -> 0.96703084 | F43: =F26/$D26 -> 0.94176452 | G43: =G26/$D26 -> 0.91979154 | H43: =H26/$D26 -> 0.88487039 | I43: =I26/$D26 -> 0.85506699 | J43: =J26/$D26 -> 0.8225483 | K43: =K26/$D26 -> 0.79020076 | ... O43: =O26/$D26 -> 0.6566625
B44: =+B27 -> 43921 | D44: =D27/$D27 -> 1 | E44: =E27/$D27 -> 1 | F44: =F27/$D27 -> 1.0250696 | G44: =G27/$D27 -> 1.0139276 | H44: =H27/$D27 -> 1.0027855 | I44: =I27/$D27 -> 1.0223953 | J44: =J27/$D27 -> 1.0396167 | K44: =K27/$D27 -> 1.0106473 | ... O44: =O27/$D27 -> 1.0205548
B45: =+B28 -> 44012 | D45: =D28/$D28 -> 1 | E45: =E28/$D28 -> 0.98909091 | F45: =F28/$D28 -> 0.96617866 | G45: =G28/$D28 -> 0.96166982 | H45: =H28/$D28 -> 0.91337374 | I45: =I28/$D28 -> 0.8775101 | J45: =J28/$D28 -> 0.85904293 | K45: =K28/$D28 -> 0.84771654 | ... O45: =O28/$D28 -> 0
B46: =+B29 -> 44104 | D46: =D29/$D29 -> 1 | E46: =E29/$D29 -> 1.0128205 | F46: =F29/$D29 -> 1.0128205 | G46: =G29/$D29 -> 0.9957265 | H46: =H29/$D29 -> 1.0100858 | I46: =I29/$D29 -> 0.95922068 | J46: =J29/$D29 -> 0.95922068 | K46: =K29/$D29 -> 0.96246884 | ... O46: =O29/$D29 -> 0
B47: =+B30 -> 44196 | D47: =D30/$D30 -> 1 | E47: =E30/$D30 -> 0.98774698 | F47: =F30/$D30 -> 1.0134782 | G47: =G30/$D30 -> 1.0414577 | H47: =H30/$D30 -> 1.0573131 | I47: =I30/$D30 -> 1.012136 | J47: =J30/$D30 -> 1.006173 | K47: =K30/$D30 -> 1.0107054 | ... O47: =O30/$D30 -> 0
B48: =+B31 -> 44286 | D48: =D31/$D31 -> 1 | E48: =E31/$D31 -> 1 | F48: =F31/$D31 -> 1.06 | G48: =G31/$D31 -> 1.1891308 | H48: =H31/$D31 -> 1.2288866 | I48: =I31/$D31 -> 1.3992859 | J48: =J31/$D31 -> 1.404912 | K48: =K31/$D31 -> 1.2515787 | ... O48: =O31/$D31 -> 0
B49: =+B32 -> 44377 | D49: =D32/$D32 -> 1 | E49: =E32/$D32 -> 0.98549687 | F49: =F32/$D32 -> 1.071476 | G49: =G32/$D32 -> 1.071476 | H49: =H32/$D32 -> 1.0499553 | I49: =I32/$D32 -> 0.99885782 | J49: =J32/$D32 -> 1.0361111 | K49: =K32/$D32 -> 0 | ... O49: =O32/$D32 -> 0
B50: =+B33 -> 44469 | D50: =D33/$D33 -> 1 | E50: =E33/$D33 -> 0.96927986 | F50: =F33/$D33 -> 0.95327986 | G50: =G33/$D33 -> 0.95327986 | H50: =H33/$D33 -> 0.93792014 | I50: =I33/$D33 -> 0.93792014 | J50: =J33/$D33 -> 0 | K50: =K33/$D33 -> 0 | ... O50: =O33/$D33 -> 0
B51: =+B34 -> 44561 | D51: =D34/$D34 -> 1 | E51: =E34/$D34 -> 1 | F51: =F34/$D34 -> 1 | G51: =G34/$D34 -> 1.0073801 | H51: =H34/$D34 -> 1.0277489 | I51: =I34/$D34 -> 0 | J51: =J34/$D34 -> 0 | K51: =K34/$D34 -> 0 | ... O51: =O34/$D34 -> 0
B52: =+B35 -> 44651 | D52: =D35/$D35 -> 1 | E52: =E35/$D35 -> 0.98054044 | F52: =F35/$D35 -> 1.0022293 | G52: =G35/$D35 -> 0.9902173 | H52: =H35/$D35 -> 0 | I52: =I35/$D35 -> 0 | J52: =J35/$D35 -> 0 | K52: =K35/$D35 -> 0 | ... O52: =O35/$D35 -> 0
B53: =+B36 -> 44742 | D53: =D36/$D36 -> 1 | E53: =E36/$D36 -> 1 | F53: =F36/$D36 -> 1 | G53: =G36/$D36 -> 0 | H53: =H36/$D36 -> 0 | I53: =I36/$D36 -> 0 | J53: =J36/$D36 -> 0 | K53: =K36/$D36 -> 0 | ... O53: =O36/$D36 -> 0
B54: =+B37 -> 44834 | D54: =D37/$D37 -> 1 | E54: =E37/$D37 -> 0.96379991 | F54: =F37/$D37 -> 0 | G54: =G37/$D37 -> 0 | H54: =H37/$D37 -> 0 | I54: =I37/$D37 -> 0 | J54: =J37/$D37 -> 0 | K54: =K37/$D37 -> 0 | ... O54: =O37/$D37 -> 0
B55: =+B38 -> 44926 | D55: =D38/$D38 -> 1 | E55: =E38/$D38 -> 0 | F55: =F38/$D38 -> 0 | G55: =G38/$D38 -> 0 | H55: =H38/$D38 -> 0 | I55: =I38/$D38 -> 0 | J55: =J38/$D38 -> 0 | K55: =K38/$D38 -> 0 | ... O55: =O38/$D38 -> 0
C58: S&M | D58: =+D$24 -> 1 | E58: =+E$24 -> 2 | F58: =+F$24 -> 3 | G58: =+G$24 -> 4 | H58: =+H$24 -> 5 | I58: =+I$24 -> 6 | J58: =+J$24 -> 7 | K58: =+K$24 -> 8 | ... O58: =+O$24 -> 12 | P58: GM%
B59: CAC Payback by Cohort
B60: =+B44 -> 43921 | C60: {=-TRANSPOSE(Model!C20:N20)} -> -14.00397 | D60: =C60+(D27*$P60/4) -> -10.814965 | E60: =D60+(E27*$P60/4) -> -7.6259601 | F60: =E60+(F27*$P60/4) -> -4.3570082 | G60: =F60+(G27*$P60/4) -> -1.1235884 | H60: =G60+(H27*$P60/4) -> 2.0742993 | I60: =H60+(I27*$P60/4) -> 5.3347229 | J60: =I60+(J27*$P60/4) -> 8.6500655 | K60: =J60+(K27*$P60/4) -> 11.873025 | ... O60: =N60+(O27*$P60/4) -> 25.291038 | P60: {=+TRANSPOSE(Model!C17:N17)} -> 0.77109561
B61: =+B45 -> 44012 | C61: -14.083162 | D61: =C61+(D28*$P61/4) -> -11.62021 | E61: =D61+(E28*$P61/4) -> -9.1841254 | F61: =E61+(F28*$P61/4) -> -6.804473 | G61: =F61+(G28*$P61/4) -> -4.4359257 | H61: =G61+(H28*$P61/4) -> -2.1863293 | I61: =H61+(I28*$P61/4) -> -0.025063393 | J61: =I61+(J28*$P61/4) -> 2.0907187 | K61: =J61+(K28*$P61/4) -> 4.1786045 | ... N61: =M61+(N28*$P61/4) -> 9.2953857 | P61: 0.77744721
B62: =+B46 -> 44104 | C62: -14.056085 | D62: =C62+(D29*$P62/4) -> -11.962989 | E62: =D62+(E29*$P62/4) -> -9.8430574 | F62: =E62+(F29*$P62/4) -> -7.7231263 | G62: =F62+(G29*$P62/4) -> -5.6389747 | H62: =G62+(H29*$P62/4) -> -3.5247676 | I62: =H62+(I29*$P62/4) -> -1.5170262 | J62: =I62+(J29*$P62/4) -> 0.49071533 | K62: =J62+(K29*$P62/4) -> 2.5052555 | ... M62: =L62+(M29*$P62/4) -> 6.1361236 | P62: 0.77646328
B63: =+B47 -> 44196 | C63: -14.845196 | D63: =C63+(D30*$P63/4) -> -12.505774 | E63: =D63+(E30*$P63/4) -> -10.195016 | F63: =E63+(F30*$P63/4) -> -7.8240627 | G63: =F63+(G30*$P63/4) -> -5.3876532 | H63: =G63+(H30*$P63/4) -> -2.9141513 | I63: =H63+(I30*$P63/4) -> -0.54633751 | J63: =I63+(J30*$P63/4) -> 1.8075263 | K63: =J63+(K30*$P63/4) -> 4.1719934 | L63: =K63+(L30*$P63/4) -> 6.5523652 | P63: 0.77758774
B64: =+B48 -> 44286 | C64: -13.968859 | D64: =C64+(D31*$P64/4) -> -12.626491 | E64: =D64+(E31*$P64/4) -> -11.284124 | F64: =E64+(F31*$P64/4) -> -9.8612142 | G64: =F64+(G31*$P64/4) -> -8.2649637 | H64: =G64+(H31*$P64/4) -> -6.6153463 | I64: =H64+(I31*$P64/4) -> -4.7369905 | J64: =I64+(J31*$P64/4) -> -2.8510822 | K64: =J64+(K31*$P64/4) -> -1.1710036 | P64: 0.77683304
B65: =+B49 -> 44377 | C65: -14.048706 | D65: =C65+(D32*$P65/4) -> -12.515043 | E65: =D65+(E32*$P65/4) -> -11.003622 | F65: =E65+(F32*$P65/4) -> -9.3603389 | G65: =F65+(G32*$P65/4) -> -7.7170555 | H65: =G65+(H32*$P65/4) -> -6.1067775 | I65: =H65+(I32*$P65/4) -> -4.5748659 | J65: =I65+(J32*$P65/4) -> -2.9858203 | P65: 0.77854092
B66: =+B50 -> 44469 | C66: -14.759204 | D66: =C66+(D33*$P66/4) -> -12.535026 | E66: =D66+(E33*$P66/4) -> -10.379176 | F66: =E66+(F33*$P66/4) -> -8.2589122 | G66: =F66+(G33*$P66/4) -> -6.1386485 | H66: =G66+(H33*$P66/4) -> -4.0525476 | I66: =H66+(I33*$P66/4) -> -1.9664468 | P66: 0.77228386
B67: =+B51 -> 44561 | C67: -14.257532 | D67: =C67+(D34*$P67/4) -> -11.826285 | E67: =D67+(E34*$P67/4) -> -9.3950375 | F67: =E67+(F34*$P67/4) -> -6.9637905 | G67: =F67+(G34*$P67/4) -> -4.5146007 | H67: =G67+(H34*$P67/4) -> -2.0158891 | P67: 0.77876661
B68: =+B52 -> 44651 | C68: -14.673868 | D68: =C68+(D35*$P68/4) -> -11.719013 | E68: =D68+(E35*$P68/4) -> -8.8216578 | F68: =E68+(F35*$P68/4) -> -5.8602154 | G68: =F68+(G35*$P68/4) -> -2.9342668 | P68: 0.77026377
B69: =+B53 -> 44742 | C69: -15.107327 | D69: =C69+(D36*$P69/4) -> -12.657146 | E69: =D69+(E36*$P69/4) -> -10.206966 | F69: =E69+(F36*$P69/4) -> -7.7567846 | P69: 0.7734157
B70: =+B54 -> 44834 | C70: -15.409772 | D70: =C70+(D37*$P70/4) -> -11.840382 | E70: =D70+(E37*$P70/4) -> -8.4002046 | P70: 0.77460716
B71: =+B55 -> 44926 | C71: -15.384978 | D71: =C71+(D38*$P71/4) -> -11.728886 | P71: 0.77031322
D74: =+D$24 -> 1 | E74: =+E$24 -> 2 | F74: =+F$24 -> 3 | G74: =+G$24 -> 4 | H74: =+H$24 -> 5 | I74: =+I$24 -> 6 | J74: =+J$24 -> 7 | K74: =+K$24 -> 8 | ... O74: =+O$24 -> 12 | P74: GM%
B75: Cumulative Realized LTV
B76: =+B60 -> 43921 | D76: =(SUM($D27:D27)/4)*$P76 -> 3.1890047 | E76: =(SUM($D27:E27)/4)*$P76 -> 6.3780094 | F76: =(SUM($D27:F27)/4)*$P76 -> 9.6469613 | G76: =(SUM($D27:G27)/4)*$P76 -> 12.880381 | H76: =(SUM($D27:H27)/4)*$P76 -> 16.078269 | I76: =(SUM($D27:I27)/4)*$P76 -> 19.338692 | J76: =(SUM($D27:J27)/4)*$P76 -> 22.654035 | K76: =(SUM($D27:K27)/4)*$P76 -> 25.876994 | ... O76: =(SUM($D27:O27)/4)*$P76 -> 39.295008 | P76: =P60 -> 0.77109561
B77: =+B61 -> 44012 | D77: =(SUM($D28:D28)/4)*$P77 -> 2.4629527 | E77: =(SUM($D28:E28)/4)*$P77 -> 4.8990369 | F77: =(SUM($D28:F28)/4)*$P77 -> 7.2786893 | G77: =(SUM($D28:G28)/4)*$P77 -> 9.6472366 | H77: =(SUM($D28:H28)/4)*$P77 -> 11.896833 | I77: =(SUM($D28:I28)/4)*$P77 -> 14.058099 | J77: =(SUM($D28:J28)/4)*$P77 -> 16.173881 | K77: =(SUM($D28:K28)/4)*$P77 -> 18.261767 | ... N77: =(SUM($D28:N28)/4)*$P77 -> 23.378548 | P77: =P61 -> 0.77744721
B78: =+B62 -> 44104 | D78: =(SUM($D29:D29)/4)*$P78 -> 2.0930965 | E78: =(SUM($D29:E29)/4)*$P78 -> 4.2130276 | F78: =(SUM($D29:F29)/4)*$P78 -> 6.3329588 | G78: =(SUM($D29:G29)/4)*$P78 -> 8.4171104 | H78: =(SUM($D29:H29)/4)*$P78 -> 10.531317 | I78: =(SUM($D29:I29)/4)*$P78 -> 12.539059 | J78: =(SUM($D29:J29)/4)*$P78 -> 14.5468 | K78: =(SUM($D29:K29)/4)*$P78 -> 16.561341 | ... M78: =(SUM($D29:M29)/4)*$P78 -> 20.192209 | P78: =P62 -> 0.77646328
B79: =+B63 -> 44196 | D79: =(SUM($D30:D30)/4)*$P79 -> 2.3394225 | E79: =(SUM($D30:E30)/4)*$P79 -> 4.65018 | F79: =(SUM($D30:F30)/4)*$P79 -> 7.0211336 | G79: =(SUM($D30:G30)/4)*$P79 -> 9.4575431 | H79: =(SUM($D30:H30)/4)*$P79 -> 11.931045 | I79: =(SUM($D30:I30)/4)*$P79 -> 14.298859 | J79: =(SUM($D30:J30)/4)*$P79 -> 16.652723 | K79: =(SUM($D30:K30)/4)*$P79 -> 19.01719 | L79: =(SUM($D30:L30)/4)*$P79 -> 21.397562 | P79: =P63 -> 0.77758774
B80: =+B64 -> 44286 | D80: =(SUM($D31:D31)/4)*$P80 -> 1.3423675 | E80: =(SUM($D31:E31)/4)*$P80 -> 2.684735 | F80: =(SUM($D31:F31)/4)*$P80 -> 4.1076445 | G80: =(SUM($D31:G31)/4)*$P80 -> 5.703895 | H80: =(SUM($D31:H31)/4)*$P80 -> 7.3535124 | I80: =(SUM($D31:I31)/4)*$P80 -> 9.2318683 | J80: =(SUM($D31:J31)/4)*$P80 -> 11.117777 | K80: =(SUM($D31:K31)/4)*$P80 -> 12.797855 | P80: =P64 -> 0.77683304
B81: =+B65 -> 44377 | D81: =(SUM($D32:D32)/4)*$P81 -> 1.5336633 | E81: =(SUM($D32:E32)/4)*$P81 -> 3.0450837 | F81: =(SUM($D32:F32)/4)*$P81 -> 4.6883672 | G81: =(SUM($D32:G32)/4)*$P81 -> 6.3316506 | H81: =(SUM($D32:H32)/4)*$P81 -> 7.9419286 | I81: =(SUM($D32:I32)/4)*$P81 -> 9.4738402 | J81: =(SUM($D32:J32)/4)*$P81 -> 11.062886 | P81: =P65 -> 0.77854092
B82: =+B66 -> 44469 | D82: =(SUM($D33:D33)/4)*$P82 -> 2.2241775 | E82: =(SUM($D33:E33)/4)*$P82 -> 4.380028 | F82: =(SUM($D33:F33)/4)*$P82 -> 6.5002916 | G82: =(SUM($D33:G33)/4)*$P82 -> 8.6205553 | H82: =(SUM($D33:H33)/4)*$P82 -> 10.706656 | I82: =(SUM($D33:I33)/4)*$P82 -> 12.792757 | P82: =P66 -> 0.77228386
B83: =+B67 -> 44561 | D83: =(SUM($D34:D34)/4)*$P83 -> 2.431247 | E83: =(SUM($D34:E34)/4)*$P83 -> 4.8624941 | F83: =(SUM($D34:F34)/4)*$P83 -> 7.2937411 | G83: =(SUM($D34:G34)/4)*$P83 -> 9.742931 | H83: =(SUM($D34:H34)/4)*$P83 -> 12.241643 | P83: =P67 -> 0.77876661
B84: =+B68 -> 44651 | D84: =(SUM($D35:D35)/4)*$P84 -> 2.9548551 | E84: =(SUM($D35:E35)/4)*$P84 -> 5.85221 | F84: =(SUM($D35:F35)/4)*$P84 -> 8.8136523 | G84: =(SUM($D35:G35)/4)*$P84 -> 11.739601 | P84: =P68 -> 0.77026377
B85: =+B69 -> 44742 | D85: =(SUM($D36:D36)/4)*$P85 -> 2.4501809 | E85: =(SUM($D36:E36)/4)*$P85 -> 4.9003618 | F85: =(SUM($D36:F36)/4)*$P85 -> 7.3505428 | P85: =P69 -> 0.7734157
B86: =+B70 -> 44834 | D86: =(SUM($D37:D37)/4)*$P86 -> 3.5693898 | E86: =(SUM($D37:E37)/4)*$P86 -> 7.0095673 | P86: =P70 -> 0.77460716
B87: =+B71 -> 44926 | D87: =(SUM($D38:D38)/4)*$P87 -> 3.6560914 | P87: =P71 -> 0.77031322
C90: S&M | D90: =+D$24 -> 1 | E90: =+E$24 -> 2 | F90: =+F$24 -> 3 | G90: =+G$24 -> 4 | H90: =+H$24 -> 5 | I90: =+I$24 -> 6 | J90: =+J$24 -> 7 | K90: =+K$24 -> 8 | ... O90: =+O$24 -> 12 | P90: Max
B91: LTV / CAC
B92: =+B76 -> 43921 | C92: =+C60 -> -14.00397 | D92: =D76/-$C92 -> 0.22772148 | E92: =E76/-$C92 -> 0.45544297 | F92: =F76/-$C92 -> 0.68887334 | G92: =G76/-$C92 -> 0.91976644 | H92: =H76/-$C92 -> 1.1481222 | I92: =I76/-$C92 -> 1.3809436 | J92: =J76/-$C92 -> 1.6176867 | K92: =K76/-$C92 -> 1.8478328 | ... O92: =O76/-$C92 -> 2.8059907 | P92: =MAX(D92:O92) -> 2.8059907
B93: =+B77 -> 44012 | C93: =+C61 -> -14.083162 | D93: =D77/-$C93 -> 0.17488634 | E93: =E77/-$C93 -> 0.34786483 | F93: =F77/-$C93 -> 0.51683629 | G93: =G77/-$C93 -> 0.6850192 | H93: =H77/-$C93 -> 0.8447558 | I93: =I77/-$C93 -> 0.99822033 | J93: =J77/-$C93 -> 1.1484552 | K93: =K77/-$C93 -> 1.2967093 | ... O93: =O77/-$C93 -> 0 | P93: =MAX(D93:O93) -> 1.6600354
B94: =+B78 -> 44104 | C94: =+C62 -> -14.056085 | D94: =D78/-$C94 -> 0.14891035 | E94: =E78/-$C94 -> 0.29972981 | F94: =F78/-$C94 -> 0.45054926 | G94: =G78/-$C94 -> 0.59882324 | H94: =H78/-$C94 -> 0.74923547 | I94: =I78/-$C94 -> 0.89207335 | J94: =J78/-$C94 -> 1.0349112 | K94: =K78/-$C94 -> 1.1782328 | ... O94: =O78/-$C94 -> 0 | P94: =MAX(D94:O94) -> 1.4365457
B95: =+B79 -> 44196 | C95: =+C63 -> -14.845196 | D95: =D79/-$C95 -> 0.15758784 | E95: =E79/-$C95 -> 0.31324476 | F95: =F79/-$C95 -> 0.4729566 | G95: =G79/-$C95 -> 0.63707767 | H95: =H79/-$C95 -> 0.80369736 | I95: =I79/-$C95 -> 0.96319769 | J95: =J79/-$C95 -> 1.1217583 | K95: =K79/-$C95 -> 1.2810332 | ... O95: =O79/-$C95 -> 0 | P95: =MAX(D95:O95) -> 1.4413795
B96: =+B80 -> 44286 | C96: =+C64 -> -13.968859 | D96: =D80/-$C96 -> 0.096097148 | E96: =E80/-$C96 -> 0.1921943 | F96: =F80/-$C96 -> 0.29405727 | G96: =G80/-$C96 -> 0.40832935 | H96: =H80/-$C96 -> 0.52642185 | I96: =I80/-$C96 -> 0.66088923 | J96: =J80/-$C96 -> 0.79589727 | K96: =K80/-$C96 -> 0.91617041 | ... O96: =O80/-$C96 -> 0 | P96: =MAX(D96:O96) -> 0.91617041
B97: =+B81 -> 44377 | C97: =+C65 -> -14.048706 | D97: =D81/-$C97 -> 0.10916759 | E97: =E81/-$C97 -> 0.2167519 | F97: =F81/-$C97 -> 0.33372235 | G97: =G81/-$C97 -> 0.4506928 | H97: =H81/-$C97 -> 0.56531388 | I97: =I81/-$C97 -> 0.67435678 | J97: =J81/-$C97 -> 0.78746653 | K97: =K81/-$C97 -> 0 | ... O97: =O81/-$C97 -> 0 | P97: =MAX(D97:O97) -> 0.78746653
B98: =+B82 -> 44469 | C98: =+C66 -> -14.759204 | D98: =D82/-$C98 -> 0.15069766 | E98: =E82/-$C98 -> 0.29676587 | F98: =F82/-$C98 -> 0.44042292 | G98: =G82/-$C98 -> 0.58407997 | H98: =H82/-$C98 -> 0.72542234 | I98: =I82/-$C98 -> 0.86676471 | J98: =J82/-$C98 -> 0 | K98: =K82/-$C98 -> 0 | ... O98: =O82/-$C98 -> 0 | P98: =MAX(D98:O98) -> 0.86676471
B99: =+B83 -> 44561 | C99: =+C67 -> -14.257532 | D99: =D83/-$C99 -> 0.1705237 | E99: =E83/-$C99 -> 0.3410474 | F99: =F83/-$C99 -> 0.5115711 | G99: =G83/-$C99 -> 0.68335328 | H99: =H83/-$C99 -> 0.85860883 | I99: =I83/-$C99 -> 0 | J99: =J83/-$C99 -> 0 | K99: =K83/-$C99 -> 0 | ... O99: =O83/-$C99 -> 0 | P99: =MAX(D99:O99) -> 0.85860883
B100: =+B84 -> 44651 | C100: =+C68 -> -14.673868 | D100: =D84/-$C100 -> 0.20136852 | E100: =E84/-$C100 -> 0.3988185 | F100: =F84/-$C100 -> 0.60063594 | G100: =G84/-$C100 -> 0.80003453 | H100: =H84/-$C100 -> 0 | I100: =I84/-$C100 -> 0 | J100: =J84/-$C100 -> 0 | K100: =K84/-$C100 -> 0 | ... O100: =O84/-$C100 -> 0 | P100: =MAX(D100:O100) -> 0.80003453
B101: =+B85 -> 44742 | C101: =+C69 -> -15.107327 | D101: =D85/-$C101 -> 0.16218494 | E101: =E85/-$C101 -> 0.32436987 | F101: =F85/-$C101 -> 0.48655481 | G101: =G85/-$C101 -> 0 | H101: =H85/-$C101 -> 0 | I101: =I85/-$C101 -> 0 | J101: =J85/-$C101 -> 0 | K101: =K85/-$C101 -> 0 | ... O101: =O85/-$C101 -> 0 | P101: =MAX(D101:O101) -> 0.48655481
B102: =+B86 -> 44834 | C102: =+C70 -> -15.409772 | D102: =D86/-$C102 -> 0.23163158 | E102: =E86/-$C102 -> 0.45487807 | F102: =F86/-$C102 -> 0 | G102: =G86/-$C102 -> 0 | H102: =H86/-$C102 -> 0 | I102: =I86/-$C102 -> 0 | J102: =J86/-$C102 -> 0 | K102: =K86/-$C102 -> 0 | ... O102: =O86/-$C102 -> 0 | P102: =MAX(D102:O102) -> 0.45487807
B103: =+B87 -> 44926 | C103: =+C71 -> -15.384978 | D103: =D87/-$C103 -> 0.23764035 | E103: =E87/-$C103 -> 0 | F103: =F87/-$C103 -> 0 | G103: =G87/-$C103 -> 0 | H103: =H87/-$C103 -> 0 | I103: =I87/-$C103 -> 0 | J103: =J87/-$C103 -> 0 | K103: =K87/-$C103 -> 0 | ... O103: =O87/-$C103 -> 0 | P103: =MAX(D103:O103) -> 0.23764035
B104: Average | D104: =AVERAGEIFS(D92:D103, D92:D103, "<>"&0) -> 0.17236812 | E104: =AVERAGEIFS(E92:E103, E92:E103, "<>"&0) -> 0.33100984 | F104: =AVERAGEIFS(F92:F103, F92:F103, "<>"&0) -> 0.47961799 | G104: =AVERAGEIFS(G92:G103, G92:G103, "<>"&0) -> 0.64079739 | H104: =AVERAGEIFS(H92:H103, H92:H103, "<>"&0) -> 0.77769722 | I104: =AVERAGEIFS(I92:I103, I92:I103, "<>"&0) -> 0.91949225 | J104: =AVERAGEIFS(J92:J103, J92:J103, "<>"&0) -> 1.0843625 | K104: =AVERAGEIFS(K92:K103, K92:K103, "<>"&0) -> 1.3039957 | ... O104: =AVERAGEIFS(O92:O103, O92:O103, "<>"&0) -> 2.8059907

Sheet ARR Waterfall
A1: 1000000
B2: ARR Waterfall | AH2: $ in millions, except noted
O3: =YEAR(O4) -> 2023 | P3: =YEAR(P4) -> 2023 | Q3: =YEAR(Q4) -> 2023 | R3: =YEAR(R4) -> 2023 | S3: =YEAR(S4) -> 2024 | T3: =YEAR(T4) -> 2024 | U3: =YEAR(U4) -> 2024 | V3: =YEAR(V4) -> 2024 | ... AH3: =YEAR(AH4) -> 2027
C4: 43921 | D4: =EOMONTH(C4, 3) -> 44012 | E4: =EOMONTH(D4, 3) -> 44104 | F4: =EOMONTH(E4, 3) -> 44196 | G4: =EOMONTH(F4, 3) -> 44286 | H4: =EOMONTH(G4, 3) -> 44377 | I4: =EOMONTH(H4, 3) -> 44469 | J4: =EOMONTH(I4, 3) -> 44561 | K4: =EOMONTH(J4, 3) -> 44651 | ... AH4: =EOMONTH(AG4, 3) -> 46752
B5: ARR Build
B6: Beginning ARR | C6: =SUM('Raw Customer ARR'!C2:C197)/1000000 -> 289.19772 | D6: =+C11 -> 301.18761 | E6: =+D11 -> 304.4751 | F6: =+E11 -> 308.34238 | G6: =+F11 -> 313.78571 | H6: =+G11 -> 310.36867 | I6: =+H11 -> 309.6027 | J6: =+I11 -> 312.48882 | K6: =+J11 -> 315.91418 | ... AH6: =+AG11 -> 371.50217
B7: New Logo ARR | C7: {=SUMPRODUCT('Raw Customer ARR'!D$2:D$197 - 'Raw Customer ARR'!C$2:C$197, --('Raw Customer ARR'!C$2:C$197 = 0), --('Raw Customer ARR'!D$2:D$197 > 0))/unit} -> 16.54272 | D7: {=SUMPRODUCT('Raw Customer ARR'!E$2:E$197 - 'Raw Customer ARR'!D$2:D$197, --('Raw Customer ARR'!D$2:D$197 = 0), --('Raw Customer ARR'!E$2:E$197 > 0))/unit} -> 12.672 | E7: {=SUMPRODUCT('Raw Customer ARR'!F$2:F$197 - 'Raw Customer ARR'!E$2:E$197, --('Raw Customer ARR'!E$2:E$197 = 0), --('Raw Customer ARR'!F$2:F$197 > 0))/unit} -> 10.78272 | F7: {=SUMPRODUCT('Raw Customer ARR'!G$2:G$197 - 'Raw Customer ARR'!F$2:F$197, --('Raw Customer ARR'!F$2:F$197 = 0), --('Raw Customer ARR'!G$2:G$197 > 0))/unit} -> 12.034256 | G7: {=SUMPRODUCT('Raw Customer ARR'!H$2:H$197 - 'Raw Customer ARR'!G$2:G$197, --('Raw Customer ARR'!G$2:G$197 = 0), --('Raw Customer ARR'!H$2:H$197 > 0))/unit} -> 6.912 | H7: {=SUMPRODUCT('Raw Customer ARR'!I$2:I$197 - 'Raw Customer ARR'!H$2:H$197, --('Raw Customer ARR'!H$2:H$197 = 0), --('Raw Customer ARR'!I$2:I$197 > 0))/unit} -> 7.87968 | I7: {=SUMPRODUCT('Raw Customer ARR'!J$2:J$197 - 'Raw Customer ARR'!I$2:I$197, --('Raw Customer ARR'!I$2:I$197 = 0), --('Raw Customer ARR'!J$2:J$197 > 0))/unit} -> 11.52 | J7: {=SUMPRODUCT('Raw Customer ARR'!K$2:K$197 - 'Raw Customer ARR'!J$2:J$197, --('Raw Customer ARR'!J$2:J$197 = 0), --('Raw Customer ARR'!K$2:K$197 > 0))/unit} -> 12.48768 | ... N7: {=SUMPRODUCT('Raw Customer ARR'!O$2:O$197 - 'Raw Customer ARR'!N$2:N$197, --('Raw Customer ARR'!N$2:N$197 = 0), --('Raw Customer ARR'!O$2:O$197 > 0))/unit} -> 18.98496 | O7: =O15*O$6 -> 13.51656 | P7: =P15*P$6 -> 13.584143 | Q7: =Q15*Q$6 -> 13.652064 | R7: =R15*R$6 -> 13.720324 | S7: =S15*S$6 -> 13.788925 | T7: =T15*T$6 -> 13.85787 | U7: =U15*U$6 -> 13.927159 | V7: =V15*V$6 -> 13.996795 | ... AH7: =AH15*AH$6 -> 14.860087
B8: Upsell ARR | C8: {=SUMPRODUCT('Raw Customer ARR'!D$2:D$197 - 'Raw Customer ARR'!C$2:C$197, --('Raw Customer ARR'!C$2:C$197 > 0), --('Raw Customer ARR'!D$2:D$197 > 'Raw Customer ARR'!C$2:C$197))/unit} -> 6.277032 | D8: {=SUMPRODUCT('Raw Customer ARR'!E$2:E$197 - 'Raw Customer ARR'!D$2:D$197, --('Raw Customer ARR'!D$2:D$197 > 0), --('Raw Customer ARR'!E$2:E$197 > 'Raw Customer ARR'!D$2:D$197))/unit} -> 4.857832 | E8: {=SUMPRODUCT('Raw Customer ARR'!F$2:F$197 - 'Raw Customer ARR'!E$2:E$197, --('Raw Customer ARR'!E$2:E$197 > 0), --('Raw Customer ARR'!F$2:F$197 > 'Raw Customer ARR'!E$2:E$197))/unit} -> 3.987528 | F8: {=SUMPRODUCT('Raw Customer ARR'!G$2:G$197 - 'Raw Customer ARR'!F$2:F$197, --('Raw Customer ARR'!F$2:F$197 > 0), --('Raw Customer ARR'!G$2:G$197 > 'Raw Customer ARR'!F$2:F$197))/unit} -> 5.73084 | G8: {=SUMPRODUCT('Raw Customer ARR'!H$2:H$197 - 'Raw Customer ARR'!G$2:G$197, --('Raw Customer ARR'!G$2:G$197 > 0), --('Raw Customer ARR'!H$2:H$197 > 'Raw Customer ARR'!G$2:G$197))/unit} -> 5.394216 | H8: {=SUMPRODUCT('Raw Customer ARR'!I$2:I$197 - 'Raw Customer ARR'!H$2:H$197, --('Raw Customer ARR'!H$2:H$197 > 0), --('Raw Customer ARR'!I$2:I$197 > 'Raw Customer ARR'!H$2:H$197))/unit} -> 6.486064 | I8: {=SUMPRODUCT('Raw Customer ARR'!J$2:J$197 - 'Raw Customer ARR'!I$2:I$197, --('Raw Customer ARR'!I$2:I$197 > 0), --('Raw Customer ARR'!J$2:J$197 > 'Raw Customer ARR'!I$2:I$197))/unit} -> 5.75956 | J8: {=SUMPRODUCT('Raw Customer ARR'!K$2:K$197 - 'Raw Customer ARR'!J$2:J$197, --('Raw Customer ARR'!J$2:J$197 > 0), --('Raw Customer ARR'!K$2:K$197 > 'Raw Customer ARR'!J$2:J$197))/unit} -> 6.553504 | ... N8: {=SUMPRODUCT('Raw Customer ARR'!O$2:O$197 - 'Raw Customer ARR'!N$2:N$197, --('Raw Customer ARR'!N$2:N$197 > 0), --('Raw Customer ARR'!O$2:O$197 > 'Raw Customer ARR'!N$2:N$197))/unit} -> 4.551768 | O8: =O16*O$6 -> 5.06871 | P8: =P16*P$6 -> 5.0940536 | Q8: =Q16*Q$6 -> 5.1195238 | R8: =R16*R$6 -> 5.1451214 | S8: =S16*S$6 -> 5.170847 | T8: =T16*T$6 -> 5.1967013 | U8: =U16*U$6 -> 5.2226848 | V8: =V16*V$6 -> 5.2487982 | ... AH8: =AH16*AH$6 -> 5.5725326
B9: Downsell ARR | C9: {=SUMPRODUCT('Raw Customer ARR'!D$2:D$197 - 'Raw Customer ARR'!C$2:C$197, --('Raw Customer ARR'!C$2:C$197 > 0), --('Raw Customer ARR'!D$2:D$197 < 'Raw Customer ARR'!C$2:C$197), --('Raw Customer ARR'!D$2:D$197 > 0))/unit} -> -3.550296 | D9: {=SUMPRODUCT('Raw Customer ARR'!E$2:E$197 - 'Raw Customer ARR'!D$2:D$197, --('Raw Customer ARR'!D$2:D$197 > 0), --('Raw Customer ARR'!E$2:E$197 < 'Raw Customer ARR'!D$2:D$197), --('Raw Customer ARR'!E$2:E$197 > 0))/unit} -> -4.078288 | E9: {=SUMPRODUCT('Raw Customer ARR'!F$2:F$197 - 'Raw Customer ARR'!E$2:E$197, --('Raw Customer ARR'!E$2:E$197 > 0), --('Raw Customer ARR'!F$2:F$197 < 'Raw Customer ARR'!E$2:E$197), --('Raw Customer ARR'!F$2:F$197 > 0))/unit} -> -3.61396 | F9: {=SUMPRODUCT('Raw Customer ARR'!G$2:G$197 - 'Raw Customer ARR'!F$2:F$197, --('Raw Customer ARR'!F$2:F$197 > 0), --('Raw Customer ARR'!G$2:G$197 < 'Raw Customer ARR'!F$2:F$197), --('Raw Customer ARR'!G$2:G$197 > 0))/unit} -> -4.169752 | G9: {=SUMPRODUCT('Raw Customer ARR'!H$2:H$197 - 'Raw Customer ARR'!G$2:G$197, --('Raw Customer ARR'!G$2:G$197 > 0), --('Raw Customer ARR'!H$2:H$197 < 'Raw Customer ARR'!G$2:G$197), --('Raw Customer ARR'!H$2:H$197 > 0))/unit} -> -3.52144 | H9: {=SUMPRODUCT('Raw Customer ARR'!I$2:I$197 - 'Raw Customer ARR'!H$2:H$197, --('Raw Customer ARR'!H$2:H$197 > 0), --('Raw Customer ARR'!I$2:I$197 < 'Raw Customer ARR'!H$2:H$197), --('Raw Customer ARR'!I$2:I$197 > 0))/unit} -> -4.33488 | I9: {=SUMPRODUCT('Raw Customer ARR'!J$2:J$197 - 'Raw Customer ARR'!I$2:I$197, --('Raw Customer ARR'!I$2:I$197 > 0), --('Raw Customer ARR'!J$2:J$197 < 'Raw Customer ARR'!I$2:I$197), --('Raw Customer ARR'!J$2:J$197 > 0))/unit} -> -4.362616 | J9: {=SUMPRODUCT('Raw Customer ARR'!K$2:K$197 - 'Raw Customer ARR'!J$2:J$197, --('Raw Customer ARR'!J$2:J$197 > 0), --('Raw Customer ARR'!K$2:K$197 < 'Raw Customer ARR'!J$2:J$197), --('Raw Customer ARR'!K$2:K$197 > 0))/unit} -> -3.73416 | ... N9: {=SUMPRODUCT('Raw Customer ARR'!O$2:O$197 - 'Raw Customer ARR'!N$2:N$197, --('Raw Customer ARR'!N$2:N$197 > 0), --('Raw Customer ARR'!O$2:O$197 < 'Raw Customer ARR'!N$2:N$197), --('Raw Customer ARR'!O$2:O$197 > 0))/unit} -> -1.989072 | O9: =O17*O$6 -> -3.37914 | P9: =P17*P$6 -> -3.3960357 | Q9: =Q17*Q$6 -> -3.4130159 | R9: =R17*R$6 -> -3.430081 | S9: =S17*S$6 -> -3.4472314 | T9: =T17*T$6 -> -3.4644675 | U9: =U17*U$6 -> -3.4817899 | V9: =V17*V$6 -> -3.4991988 | ... AH9: =AH17*AH$6 -> -3.7150217
B10: Churn ARR | C10: {=SUMPRODUCT('Raw Customer ARR'!D$2:D$197 - 'Raw Customer ARR'!C$2:C$197, --('Raw Customer ARR'!C$2:C$197 > 0), --('Raw Customer ARR'!D$2:D$197 = 0))/unit} -> -7.279568 | D10: {=SUMPRODUCT('Raw Customer ARR'!E$2:E$197 - 'Raw Customer ARR'!D$2:D$197, --('Raw Customer ARR'!D$2:D$197 > 0), --('Raw Customer ARR'!E$2:E$197 = 0))/unit} -> -10.164048 | E10: {=SUMPRODUCT('Raw Customer ARR'!F$2:F$197 - 'Raw Customer ARR'!E$2:E$197, --('Raw Customer ARR'!E$2:E$197 > 0), --('Raw Customer ARR'!F$2:F$197 = 0))/unit} -> -7.289016 | F10: {=SUMPRODUCT('Raw Customer ARR'!G$2:G$197 - 'Raw Customer ARR'!F$2:F$197, --('Raw Customer ARR'!F$2:F$197 > 0), --('Raw Customer ARR'!G$2:G$197 = 0))/unit} -> -8.152008 | G10: {=SUMPRODUCT('Raw Customer ARR'!H$2:H$197 - 'Raw Customer ARR'!G$2:G$197, --('Raw Customer ARR'!G$2:G$197 > 0), --('Raw Customer ARR'!H$2:H$197 = 0))/unit} -> -12.201816 | H10: {=SUMPRODUCT('Raw Customer ARR'!I$2:I$197 - 'Raw Customer ARR'!H$2:H$197, --('Raw Customer ARR'!H$2:H$197 > 0), --('Raw Customer ARR'!I$2:I$197 = 0))/unit} -> -10.79684 | I10: {=SUMPRODUCT('Raw Customer ARR'!J$2:J$197 - 'Raw Customer ARR'!I$2:I$197, --('Raw Customer ARR'!I$2:I$197 > 0), --('Raw Customer ARR'!J$2:J$197 = 0))/unit} -> -10.030816 | J10: {=SUMPRODUCT('Raw Customer ARR'!K$2:K$197 - 'Raw Customer ARR'!J$2:J$197, --('Raw Customer ARR'!J$2:J$197 > 0), --('Raw Customer ARR'!K$2:K$197 = 0))/unit} -> -11.881664 | ... N10: {=SUMPRODUCT('Raw Customer ARR'!O$2:O$197 - 'Raw Customer ARR'!N$2:N$197, --('Raw Customer ARR'!N$2:N$197 > 0), --('Raw Customer ARR'!O$2:O$197 = 0))/unit} -> -11.511784 | O10: =O18*O$6 -> -13.51656 | P10: =P18*P$6 -> -13.584143 | Q10: =Q18*Q$6 -> -13.652064 | R10: =R18*R$6 -> -13.720324 | S10: =S18*S$6 -> -13.788925 | T10: =T18*T$6 -> -13.85787 | U10: =U18*U$6 -> -13.927159 | V10: =V18*V$6 -> -13.996795 | ... AH10: =AH18*AH$6 -> -14.860087
B11: Ending ARR | C11: =SUM(C6:C10) -> 301.18761 | D11: =SUM(D6:D10) -> 304.4751 | E11: =SUM(E6:E10) -> 308.34238 | F11: =SUM(F6:F10) -> 313.78571 | G11: =SUM(G6:G10) -> 310.36867 | H11: =SUM(H6:H10) -> 309.6027 | I11: =SUM(I6:I10) -> 312.48882 | J11: =SUM(J6:J10) -> 315.91418 | ... AH11: =SUM(AH6:AH10) -> 373.35968
B12: Check? | C12: =(SUM('Raw Customer ARR'!D2:D197)/unit)-C11 -> 0 | D12: =(SUM('Raw Customer ARR'!E2:E197)/unit)-D11 -> 0 | E12: =(SUM('Raw Customer ARR'!F2:F197)/unit)-E11 -> 0 | F12: =(SUM('Raw Customer ARR'!G2:G197)/unit)-F11 -> 0 | G12: =(SUM('Raw Customer ARR'!H2:H197)/unit)-G11 -> 0 | H12: =(SUM('Raw Customer ARR'!I2:I197)/unit)-H11 -> 0 | I12: =(SUM('Raw Customer ARR'!J2:J197)/unit)-I11 -> 0 | J12: =(SUM('Raw Customer ARR'!K2:K197)/unit)-J11 -> 0 | ... N12: =(SUM('Raw Customer ARR'!O2:O197)/unit)-N11 -> 0
B14: NRR | C14: =SUM(C6,C8,C9,C10)/C6 -> 0.98425703 | D14: =SUM(D6,D8,D9,D10)/D6 -> 0.96884167 | E14: =SUM(E6,E8,E9,E10)/E6 -> 0.97728731 | F14: =SUM(F6,F8,F9,F10)/F6 -> 0.97862467 | G14: =SUM(G6,G8,G9,G10)/G6 -> 0.9670825 | H14: =SUM(H6,H8,H9,H10)/H6 -> 0.97214392 | I14: =SUM(I6,I8,I9,I10)/I6 -> 0.97211306 | J14: =SUM(J6,J8,J9,J10)/J6 -> 0.97099954 | ... AH14: =SUM(AH6,AH8,AH9,AH10)/AH6 -> 0.965
B15: New Logo as % of Beginning | C15: =+C7/C$6 -> 0.057202111 | D15: =+D7/D$6 -> 0.042073444 | E15: =+E7/E$6 -> 0.035414127 | F15: =+F7/F$6 -> 0.039028875 | G15: =+G7/G$6 -> 0.022027772 | H15: =+H7/H$6 -> 0.025388129 | I15: =+I7/I$6 -> 0.037208978 | J15: =+J7/J$6 -> 0.039962005 | ... N15: =+N7/N$6 -> 0.05790249 | O15: 0.04 | P15: 0.04 | Q15: 0.04 | R15: 0.04 | S15: 0.04 | T15: 0.04 | U15: 0.04 | V15: 0.04 | W15: 0.04 | X15: 0.04 | Y15: 0.04 | Z15: 0.04 | AA15: 0.04 | AB15: 0.04 | AC15: 0.04 | AD15: 0.04 | AE15: 0.04 | AF15: 0.04 | AG15: 0.04 | AH15: 0.04
B16: Upsell as % of Beginning | C16: =+C8/C$6 -> 0.021704984 | D16: =+D8/D$6 -> 0.016128924 | E16: =+E8/E$6 -> 0.013096401 | F16: =+F8/F$6 -> 0.018585963 | G16: =+G8/G$6 -> 0.017190764 | H16: =+H8/H$6 -> 0.020897934 | I16: =+I8/I$6 -> 0.018603068 | J16: =+J8/J$6 -> 0.020971963 | ... N16: =+N8/N$6 -> 0.0138825 | O16: 0.015 | P16: 0.015 | Q16: 0.015 | R16: 0.015 | S16: 0.015 | T16: 0.015 | U16: 0.015 | V16: 0.015 | W16: 0.015 | X16: 0.015 | Y16: 0.015 | Z16: 0.015 | AA16: 0.015 | AB16: 0.015 | AC16: 0.015 | AD16: 0.015 | AE16: 0.015 | AF16: 0.015 | AG16: 0.015 | AH16: 0.015
B17: Downsell as % of Beginning | C17: =+C9/C$6 -> -0.012276362 | D17: =+D9/D$6 -> -0.01354069 | E17: =+E9/E$6 -> -0.011869476 | F17: =+F9/F$6 -> -0.013523123 | G17: =+G9/G$6 -> -0.011222436 | H17: =+H9/H$6 -> -0.013966874 | I17: =+I9/I$6 -> -0.014091014 | J17: =+J9/J$6 -> -0.011949739 | ... N17: =+N9/N$6 -> -0.006066498 | O17: -0.01 | P17: -0.01 | Q17: -0.01 | R17: -0.01 | S17: -0.01 | T17: -0.01 | U17: -0.01 | V17: -0.01 | W17: -0.01 | X17: -0.01 | Y17: -0.01 | Z17: -0.01 | AA17: -0.01 | AB17: -0.01 | AC17: -0.01 | AD17: -0.01 | AE17: -0.01 | AF17: -0.01 | AG17: -0.01 | AH17: -0.01
B18: Churn as % of Beginning | C18: =+C10/C$6 -> -0.025171595 | D18: =+D10/D$6 -> -0.033746568 | E18: =+E10/E$6 -> -0.023939612 | F18: =+F10/F$6 -> -0.026438169 | G18: =+G10/G$6 -> -0.038885824 | H18: =+H10/H$6 -> -0.034787145 | I18: =+I10/I$6 -> -0.032398994 | J18: =+J10/J$6 -> -0.038022685 | ... N18: =+N10/N$6 -> -0.035109948 | O18: -0.04 | P18: -0.04 | Q18: -0.04 | R18: -0.04 | S18: -0.04 | T18: -0.04 | U18: -0.04 | V18: -0.04 | W18: -0.04 | X18: -0.04 | Y18: -0.04 | Z18: -0.04 | AA18: -0.04 | AB18: -0.04 | AC18: -0.04 | AD18: -0.04 | AE18: -0.04 | AF18: -0.04 | AG18: -0.04 | AH18: -0.04
B20: Customer Bridge
B21: Beginning Customers | C21: =COUNTIFS('Raw Customer ARR'!C$2:C$197, ">"&0 ) -> 124 | D21: =C24 -> 126 | E21: =D24 -> 127 | F21: =E24 -> 130 | G21: =F24 -> 132 | H21: =G24 -> 131 | I21: =H24 -> 131 | J21: =I24 -> 133 | K21: =J24 -> 132 | ... AH21: =AG24 -> 170.50433
B22: New Customers | C22: =COUNTIFS('Raw Customer ARR'!C$2:C$197, "="&0, 'Raw Customer ARR'!D$2:D$197, ">"&0 ) -> 6 | D22: =COUNTIFS('Raw Customer ARR'!D$2:D$197, "="&0, 'Raw Customer ARR'!E$2:E$197, ">"&0 ) -> 6 | E22: =COUNTIFS('Raw Customer ARR'!E$2:E$197, "="&0, 'Raw Customer ARR'!F$2:F$197, ">"&0 ) -> 6 | F22: =COUNTIFS('Raw Customer ARR'!F$2:F$197, "="&0, 'Raw Customer ARR'!G$2:G$197, ">"&0 ) -> 5 | G22: =COUNTIFS('Raw Customer ARR'!G$2:G$197, "="&0, 'Raw Customer ARR'!H$2:H$197, ">"&0 ) -> 4 | H22: =COUNTIFS('Raw Customer ARR'!H$2:H$197, "="&0, 'Raw Customer ARR'!I$2:I$197, ">"&0 ) -> 4 | I22: =COUNTIFS('Raw Customer ARR'!I$2:I$197, "="&0, 'Raw Customer ARR'!J$2:J$197, ">"&0 ) -> 5 | J22: =COUNTIFS('Raw Customer ARR'!J$2:J$197, "="&0, 'Raw Customer ARR'!K$2:K$197, ">"&0 ) -> 5 | ... N22: =COUNTIFS('Raw Customer ARR'!N$2:N$197, "="&0, 'Raw Customer ARR'!O$2:O$197, ">"&0 ) -> 8 | O22: =+O7/O27 -> 6.4364571 | P22: =+P7/P27 -> 6.4686394 | Q22: =+Q7/Q27 -> 6.5009826 | R22: =+R7/R27 -> 6.5334875 | S22: =+S7/S27 -> 6.566155 | T22: =+T7/T27 -> 6.5989858 | U22: =+U7/U27 -> 6.6319807 | V22: =+V7/V27 -> 6.6651406 | ... AH22: =+AH7/AH27 -> 7.0762319
B23: Churn Customers | C23: =-COUNTIFS('Raw Customer ARR'!C$2:C$197, ">"&0, 'Raw Customer ARR'!D$2:D$197, "="&0 ) -> -4 | D23: =-COUNTIFS('Raw Customer ARR'!D$2:D$197, ">"&0, 'Raw Customer ARR'!E$2:E$197, "="&0 ) -> -5 | E23: =-COUNTIFS('Raw Customer ARR'!E$2:E$197, ">"&0, 'Raw Customer ARR'!F$2:F$197, "="&0 ) -> -3 | F23: =-COUNTIFS('Raw Customer ARR'!F$2:F$197, ">"&0, 'Raw Customer ARR'!G$2:G$197, "="&0 ) -> -3 | G23: =-COUNTIFS('Raw Customer ARR'!G$2:G$197, ">"&0, 'Raw Customer ARR'!H$2:H$197, "="&0 ) -> -5 | H23: =-COUNTIFS('Raw Customer ARR'!H$2:H$197, ">"&0, 'Raw Customer ARR'!I$2:I$197, "="&0 ) -> -4 | I23: =-COUNTIFS('Raw Customer ARR'!I$2:I$197, ">"&0, 'Raw Customer ARR'!J$2:J$197, "="&0 ) -> -3 | J23: =-COUNTIFS('Raw Customer ARR'!J$2:J$197, ">"&0, 'Raw Customer ARR'!K$2:K$197, "="&0 ) -> -6 | ... N23: =-COUNTIFS('Raw Customer ARR'!N$2:N$197, ">"&0, 'Raw Customer ARR'!O$2:O$197, "="&0 ) -> -5 | O23: =+O10/O28 -> -5.0529196 | P23: =+P10/P28 -> -5.0781842 | Q23: =+Q10/Q28 -> -5.1035751 | R23: =+R10/R28 -> -5.129093 | S23: =+S10/S28 -> -5.1547385 | T23: =+T10/T28 -> -5.1805122 | U23: =+U10/U28 -> -5.2064147 | V23: =+V10/V28 -> -5.2324468 | ... AH23: =+AH10/AH28 -> -5.5551727
B24: Ending Customers | C24: =SUM(C21:C23) -> 126 | D24: =SUM(D21:D23) -> 127 | E24: =SUM(E21:E23) -> 130 | F24: =SUM(F21:F23) -> 132 | G24: =SUM(G21:G23) -> 131 | H24: =SUM(H21:H23) -> 131 | I24: =SUM(I21:I23) -> 133 | J24: =SUM(J21:J23) -> 132 | ... AH24: =SUM(AH21:AH23) -> 172.02539
B25: Check? | C25: =COUNTIFS('Raw Customer ARR'!D$2:D$197, ">"&0)-C24 -> 0 | D25: =COUNTIFS('Raw Customer ARR'!E$2:E$197, ">"&0)-D24 -> 0 | E25: =COUNTIFS('Raw Customer ARR'!F$2:F$197, ">"&0)-E24 -> 0 | F25: =COUNTIFS('Raw Customer ARR'!G$2:G$197, ">"&0)-F24 -> 0 | G25: =COUNTIFS('Raw Customer ARR'!H$2:H$197, ">"&0)-G24 -> 0 | H25: =COUNTIFS('Raw Customer ARR'!I$2:I$197, ">"&0)-H24 -> 0 | I25: =COUNTIFS('Raw Customer ARR'!J$2:J$197, ">"&0)-I24 -> 0 | J25: =COUNTIFS('Raw Customer ARR'!K$2:K$197, ">"&0)-J24 -> 0 | ... N25: =COUNTIFS('Raw Customer ARR'!O$2:O$197, ">"&0)-N24 -> 0
B27: ARR per New Customer | C27: =IFERROR(C7/C22, 0) -> 2.75712 | D27: =IFERROR(D7/D22, 0) -> 2.112 | E27: =IFERROR(E7/E22, 0) -> 1.79712 | F27: =IFERROR(F7/F22, 0) -> 2.4068512 | G27: =IFERROR(G7/G22, 0) -> 1.728 | H27: =IFERROR(H7/H22, 0) -> 1.96992 | I27: =IFERROR(I7/I22, 0) -> 2.304 | J27: =IFERROR(J7/J22, 0) -> 2.497536 | ... N27: =IFERROR(N7/N22, 0) -> 2.37312 | O27: 2.1 | P27: =+O27 -> 2.1 | Q27: =+P27 -> 2.1 | R27: =+Q27 -> 2.1 | S27: =+R27 -> 2.1 | T27: =+S27 -> 2.1 | U27: =+T27 -> 2.1 | V27: =+U27 -> 2.1 | W27: =+V27 -> 2.1 | ... AH27: =+AG27 -> 2.1
B28: ARR per Churned Customer | C28: =IFERROR(C10/C23,0) -> 1.819892 | D28: =IFERROR(D10/D23,0) -> 2.0328096 | E28: =IFERROR(E10/E23,0) -> 2.429672 | F28: =IFERROR(F10/F23,0) -> 2.717336 | G28: =IFERROR(G10/G23,0) -> 2.4403632 | H28: =IFERROR(H10/H23,0) -> 2.69921 | I28: =IFERROR(I10/I23,0) -> 3.3436053 | J28: =IFERROR(J10/J23,0) -> 1.9802773 | ... N28: =IFERROR(N10/N23,0) -> 2.3023568 | O28: 2.675 | P28: =+O28 -> 2.675 | Q28: =+P28 -> 2.675 | R28: =+Q28 -> 2.675 | S28: =+R28 -> 2.675 | T28: =+S28 -> 2.675 | U28: =+T28 -> 2.675 | V28: =+U28 -> 2.675 | W28: =+V28 -> 2.675 | ... AH28: =+AG28 -> 2.675
B29: ARR per Ending Customer | C29: =IFERROR(C11/C24, 0) -> 2.3903778 | D29: =IFERROR(D11/D24, 0) -> 2.3974418 | E29: =IFERROR(E11/E24, 0) -> 2.3718644 | F29: =IFERROR(F11/F24, 0) -> 2.3771645 | G29: =IFERROR(G11/G24, 0) -> 2.3692265 | H29: =IFERROR(H11/H24, 0) -> 2.3633794 | I29: =IFERROR(I11/I24, 0) -> 2.34954 | J29: =IFERROR(J11/J24, 0) -> 2.3932893 | ... N29: =IFERROR(N11/N24, 0) -> 2.363035 | O29: =O11/O24 -> 2.3520934 | P29: =P11/P24 -> 2.3413064 | Q29: =Q11/Q24 -> 2.3306709 | R29: =R11/R24 -> 2.3201837 | S29: =S11/S24 -> 2.3098419 | T29: =T11/T24 -> 2.2996428 | U29: =U11/U24 -> 2.2895833 | V29: =V11/V24 -> 2.2796609 | ... AH29: =AH11/AH24 -> 2.1703754

Sheet Raw Customer ARR
A1: Customer | B1: Cohort | C1: =EOMONTH(D1, -3) -> 43830 | D1: 43921 | E1: =EOMONTH(D1,3) -> 44012 | F1: =EOMONTH(E1,3) -> 44104 | G1: =EOMONTH(F1,3) -> 44196 | H1: =EOMONTH(G1,3) -> 44286 | I1: =EOMONTH(H1,3) -> 44377 | J1: =EOMONTH(I1,3) -> 44469 | K1: =EOMONTH(J1,3) -> 44561 | L1: =EOMONTH(K1,3) -> 44651 | ... O1: =EOMONTH(N1,3) -> 44926
A2: 1 | B2: {=INDEX(C$1:O$1, MATCH(TRUE, INDEX(($C2:$O2 <> 0), 0),0))} -> 44469 | C2: 0 | D2: 0 | E2: 0 | F2: 0 | G2: 0 | H2: 0 | I2: 0 | J2: 1152000 | K2: 1152000 | L2: 1152000 | M2: 1152000 | N2: 975056 | O2: 975056
A3: =+A2+1 -> 2 | B3: {=INDEX(C$1:O$1, MATCH(TRUE, INDEX(($C3:$O3 <> 0), 0),0))} -> 44469 | C3: 0 | D3: 0 | E3: 0 | F3: 0 | G3: 0 | H3: 0 | I3: 0 | J3: 2304000 | K3: 1950104 | L3: 1950104 | M3: 1950104 | N3: 1950104 | O3: 1950104
A4: =+A3+1 -> 3 | B4: {=INDEX(C$1:O$1, MATCH(TRUE, INDEX(($C4:$O4 <> 0), 0),0))} -> 44469 | C4: 0 | D4: 0 | E4: 0 | F4: 0 | G4: 0 | H4: 0 | I4: 0 | J4: 2304000 | K4: 2304000 | L4: 2119680 | M4: 2119680 | N4: 2119680 | O4: 2119680
A5: =+A4+1 -> 4 | B5: {=INDEX(C$1:O$1, MATCH(TRUE, INDEX(($C5:$O5 <> 0), 0),0))} -> 44469 | C5: 0 | D5: 0 | E5: 0 | F5: 0 | G5: 0 | H5: 0 | I5: 0 | J5: 2304000 | K5: 2304000 | L5: 2304000 | M5: 2304000 | N5: 2304000 | O5: 2304000
A6: =+A5+1 -> 5 | B6: {=INDEX(C$1:O$1, MATCH(TRUE, INDEX(($C6:$O6 <> 0), 0),0))} -> 44469 | C6: 0 | D6: 0 | E6: 0 | F6: 0 | G6: 0 | H6: 0 | I6: 0 | J6: 3456000 | K6: 3456000 | L6: 3456000 | M6: 3456000 | N6: 3456000 | O6: 3456000
A7: =+A6+1 -> 6 | B7: {=INDEX(C$1:O$1, MATCH(TRUE, INDEX(($C7:$O7 <> 0), 0),0))} -> 43830 | C7: 1445072 | D7: 0 | E7: 0 | F7: 0 | G7: 0 | H7: 0 | I7: 0 | J7: 0 | K7: 0 | L7: 0 | M7: 0 | N7: 0 | O7: 0
A8: =+A7+1 -> 7 | B8: {=INDEX(C$1:O$1, MATCH(TRUE, INDEX(($C8:$O8 <> 0), 0),0))} -> 43830 | C8: 2119680 | D8: 0 | E8: 0 | F8: 0 | G8: 0 | H8: 0 | I8: 0 | J8: 0 | K8: 0 | L8: 0 | M8: 0 | N8: 0 | O8: 0
A9: =+A8+1 -> 8 | B9: {=INDEX(C$1:O$1, MATCH(TRUE, INDEX(($C9:$O9 <> 0), 0),0))} -> 43830 | C9: 975056 | D9: 0 | E9: 0 | F9: 0 | G9: 0 | H9: 0 | I9: 0 | J9: 0 | K9: 0 | L9: 0 | M9: 0 | N9: 0 | O9: 0
A10: =+A9+1 -> 9 | B10: {=INDEX(C$1:O$1, MATCH(TRUE, INDEX(($C10:$O10 <> 0), 0),0))} -> 43830 | C10: 2739760 | D10: 0 | E10: 0 | F10: 0 | G10: 0 | H10: 0 | I10: 0 | J10: 0 | K10: 0 | L10: 0 | M10: 0 | N10: 0 | O10: 0
A11: =+A10+1 -> 10 | B11: {=INDEX(C$1:O$1, MATCH(TRUE, INDEX(($C11:$O11 <> 0), 0),0))} -> 44926 | C11: 0 | D11: 0 | E11: 0 | F11: 0 | G11: 0 | H11: 0 | I11: 0 | J11: 0 | K11: 0 | L11: 0 | M11: 0 | N11: 0 | O11: 3456000
A12: =+A11+1 -> 11 | B12: {=INDEX(C$1:O$1, MATCH(TRUE, INDEX(($C12:$O12 <> 0), 0),0))} -> 44926 | C12: 0 | D12: 0 | E12: 0 | F12: 0 | G12: 0 | H12: 0 | I12: 0 | J12: 0 | K12: 0 | L12: 0 | M12: 0 | N12: 0 | O12: 2304000
A13: =+A12+1 -> 12 | B13: {=INDEX(C$1:O$1, MATCH(TRUE, INDEX(($C13:$O13 <> 0), 0),0))} -> 44926 | C13: 0 | D13: 0 | E13: 0 | F13: 0 | G13: 0 | H13: 0 | I13: 0 | J13: 0 | K13: 0 | L13: 0 | M13: 0 | N13: 0 | O13: 2580480
A14: =+A13+1 -> 13 | B14: {=INDEX(C$1:O$1, MATCH(TRUE, INDEX(($C14:$O14 <> 0), 0),0))} -> 44926 | C14: 0 | D14: 0 | E14: 0 | F14: 0 | G14: 0 | H14: 0 | I14: 0 | J14: 0 | K14: 0 | L14: 0 | M14: 0 | N14: 0 | O14: 2304000
... A197: =+A196+1 -> 196 | B197: {=INDEX(C$1:O$1, MATCH(TRUE, INDEX(($C197:$O197 <> 0), 0),0))} -> 43830 | C197: 1489000 | D197: 1489000 | E197: 1489000 | F197: 1489000 | G197: 1489000 | H197: 1489000 | I197: 0 | J197: 0 | K197: 0 | L197: 0 | M197: 0 | N197: 0 | O197: 0
