Workbook

Sheet Start ->

Sheet Model - Start
B2: Model | J2: $ millions
B3: Income statement | C3: =+D3-1 -> -2 | D3: =+E3-1 -> -1 | E3: 0 | F3: 1 | G3: =F3+1 -> 2 | H3: =G3+1 -> 3 | I3: =H3+1 -> 4 | J3: =I3+1 -> 5
B4: Gross revenue | C4: 73.836296 | D4: 92.488396 | E4: 119.83782
B5: % Growth | D5: =D4/C4-1 -> 0.25261424 | E5: =E4/D4-1 -> 0.29570657
B7: Cancellations | C7: 10.410918 | D7: 13.688283 | E7: 18.215349
B8: Net revenue | C8: =C4-C7 -> 63.425378 | D8: =D4-D7 -> 78.800113 | E8: =E4-E7 -> 101.62247
B10: COGS | C10: 11.315087 | D10: 14.10522 | E10: 18.292045
B11: Gross profit | C11: =C8-C10 -> 52.110291 | D11: =D8-D10 -> 64.694893 | E11: =E8-E10 -> 83.330428
B13: Operations & support | C13: 11.923971 | D13: 14.499221 | E13: 17.479065
B14: Product development | C14: 11.099441 | D14: 14.18402 | E14: 18.698535
B15: Ad spend | C15: =+'Revenue Build - Start'!C20+'Revenue Build - Start'!C38 -> 8.4 | D15: =+'Revenue Build - Start'!D20+'Revenue Build - Start'!D38 -> 11.4 | E15: =+'Revenue Build - Start'!E20+'Revenue Build - Start'!E38 -> 13.8
B16: General & administrative | C16: 8.3721499 | D16: 10.874416 | E16: 13.719034
B17: Operating expenses | C17: =SUM(C13:C16) -> 39.795562 | D17: =SUM(D13:D16) -> 50.957657 | E17: =SUM(E13:E16) -> 63.696634
B19: EBITDA | C19: =+C11-C17 -> 12.314729 | D19: =+D11-D17 -> 13.737236 | E19: =+E11-E17 -> 19.633794
B22: Balance sheet | E22: 0 | F22: 1 | G22: =F22+1 -> 2 | H22: =G22+1 -> 3 | I22: =H22+1 -> 4 | J22: =I22+1 -> 5
B23: Cash | E23: 110.9
B24: Receivables | E24: 55.1
B25: Capitalized financing fees | E25: 0
B26: Goodwill | E26: 0
B27: Net PP&E | E27: 3
B28: Other assets | E28: 15.8
B29: Total assets | E29: =SUM(E23:E28) -> 184.8
B31: Payables & accrued expenses | E31: 38.4
B32: Other liabilities | E32: 7.7
B33: Debt | E33: 0
B34: Shareholder equity | E34: 138.7
B35: Total liabilities & equity | E35: =SUM(E31:E34) -> 184.8
B37: Working capital
B38: Receivable turnover | E38: =+E8/E24 -> 1.844328
B39: Payable turnover | E39: =+E10/E31 -> 0.47635534
B40: Net working capital | E40: =+E24+E28-E31-E32 -> 24.8

Sheet Revenue Build - Start
B2: Revenue Build | J2: $ millions
B3: Supply & Demand | C3: =+D3-1 -> -2 | D3: =+E3-1 -> -1 | E3: 0 | F3: 1 | G3: =F3+1 -> 2 | H3: =G3+1 -> 3 | I3: =H3+1 -> 4 | J3: =I3+1 -> 5
B4: Total vehicle days rented | C4: =MIN(C17,C35) -> 3212127 | D4: =MIN(D17,D35) -> 4304628.9 | E4: =MIN(E17,E35) -> 5402115.2
B5: Average price per vehicle day rented | C5: =+C6*1000000/C4 -> 152.23 | D5: =+D6*1000000/D4 -> 144.2 | E5: =+E6*1000000/E4 -> 147.89
B6: Total booking value | C6: 488.98209 | D6: 620.72749 | E6: 798.91881
B8: Marketplace fee % | C8: =+C9/C6 -> 0.151 | D8: =+D9/D6 -> 0.149 | E8: =+E9/E6 -> 0.15
B9: Gross revenue | C9: 73.836296 | D9: 92.488396 | E9: 119.83782
B12: Supply | C12: =+D12-1 -> -2 | D12: =+E12-1 -> -1 | E12: 0 | F12: 1 | G12: =F12+1 -> 2 | H12: =G12+1 -> 3 | I12: =H12+1 -> 4 | J12: =I12+1 -> 5
B13: Vehicles days available
B14: Beginning | D14: =+C17 -> 3212127 | E14: =+D17 -> 4304628.9
B15: New added | D15: =+D25 -> 1628927.1 | E15: =+E25 -> 1911061.1
B16: Churned | D16: 536425.21 | E16: 813574.86
B17: Ending | C17: 3212127 | D17: =D14+D15-D16 -> 4304628.9 | E17: =E14+E15-E16 -> 5402115.2
B18: % Growth | D18: =+D17/C17-1 -> 0.34011791 | E18: =+E17/D17-1 -> 0.25495491
B20: Vehicle ad spend | C20: 3.2 | D20: 4.5 | E20: 5.8
B21: Acquisition cost per vehicle | C21: 543.26 | D21: 621.02 | E21: 732.23
B22: New vehicles added | C22: =+C20*1000000/C21 -> 5890.3656 | D22: =+D20*1000000/D21 -> 7246.1434 | E22: =+E20*1000000/E21 -> 7921.0084
B24: Vehicle days available per vehicle added | C24: 250 | D24: 248 | E24: 252
B25: Total vehicle days added | C25: =+C24*AVERAGE(C22) -> 1472591.4 | D25: =+D24*AVERAGE(C22:D22) -> 1628927.1 | E25: =+E24*AVERAGE(D22:E22) -> 1911061.1
B27: Churn as % of prior ending | D27: =+D16/D14 -> 0.167 | E27: =+E16/E14 -> 0.189
B30: Demand | C30: =+D30-1 -> -2 | D30: =+E30-1 -> -1 | E30: 0 | F30: 1 | G30: =F30+1 -> 2 | H30: =G30+1 -> 3 | I30: =H30+1 -> 4 | J30: =I30+1 -> 5
B31: Driver days demanded
B32: Beginning | D32: =+C35 -> 3505699 | E32: =+D35 -> 5665304.5
B33: New added | D33: =+D43 -> 2731034.5 | E33: =+E43 -> 2471860.1
B34: Churned | D34: 571428.94 | E34: 974432.38
B35: Ending | C35: 3505699 | D35: =D32+D33-D34 -> 5665304.5 | E35: =E32+E33-E34 -> 7162732.3
B36: % Growth | D36: =+D35/C35-1 -> 0.61602709 | E36: =+E35/D35-1 -> 0.26431548
B38: Driver ad spend | C38: 5.2 | D38: 6.9 | E38: 8
B39: Acquisition cost per driver | C39: 14.5 | D39: 17.25 | E39: 18.87
B40: New drivers added | C40: =+C38*1000000/C39 -> 358620.69 | D40: =+D38*1000000/D39 -> 400000 | E40: =+E38*1000000/E39 -> 423953.37
B42: Driver days demanded per driver added | C42: 8 | D42: 7.2 | E42: 6
B43: Total driver days added | C43: =+C42*AVERAGE(C40) -> 2868965.5 | D43: =+D42*AVERAGE(C40:D40) -> 2731034.5 | E43: =+E42*AVERAGE(D40:E40) -> 2471860.1
B45: Churn as % of prior ending | D45: =+D34/D32 -> 0.163 | E45: =+E34/E32 -> 0.172

Sheet End ->

Sheet Model - End
B2: Assumptions | J2: $ millions
B3: Entry assumptions | G3: Other assumptions
C4: Pre-Money | D4: Post-Money | E4: Assumptions | G4: New option pool | J4: 0.043
B5: LTM EBITDA | C5: =E78 -> 19.633794 | G5: Family - % shares sold | J5: 0
B6: Entry multiple | C6: 15 | G6: Seed investor - % shares sold | J6: 0.5
B7: Enterprise value | C7: =C5*C6 -> 294.5069 | D7: =C7 -> 294.5069 | G7: Existing employees - % shares sold | J7: 0
B8: (-) New debt | C8: =+C105 -> 0 | D8: 0
B9: (+) Cash | C9: =C95 -> 110.9 | D9: 110.9
B10: Equity value | C10: =C7+C9-C8 -> 405.4069 | D10: =D7+D9-D8 -> 405.4069
B11: (+) Transaction fees | D11: =+E11*D7 -> 1.4725345 | E11: 0.005
B12: (+) Financing fees | D12: =+E12*D8 -> 0 | E12: 0
B13: Equity value (incl. fees) | D13: =+D10+D11+D12 -> 406.87944
B16: Sources & uses | J16: $ millions
B17: Sources | G17: Uses
B18: New debt | D18: =+D8 -> 0 | G18: Proceeds to selling shareholders | J18: =+SUM(D35:D37)-SUM(H35:H37) -> 61.945108
B19: Rollover equity | D19: =+J19 -> 343.4618 | G19: Rollover equity | J19: =SUM(H35:H37) -> 343.4618
B20: Sponsor equity | D20: =+J24-D19-D18 -> 63.417642 | G20: Cash added to B/S | J20: =+D9-C9 -> 0
G21: Transaction fees | J21: =+D11 -> 1.4725345
G22: Financing fees | J22: =+D12 -> 0
B24: Total sources | D24: =SUM(D18:D23) -> 406.87944 | G24: Total uses | J24: =SUM(J18:J23) -> 406.87944
B25: Check 1? | D25: =+D24-J24 -> 0
B26: Check 2? | D26: =+D20-H34 -> 0
B28: Capitalization table
D29: Pre-Money | H29: Post-Money
D30: $ Amount | E30: FD Shares | F30: FD own % | H30: $ Amount | I30: FD Shares | J30: FD own %
B31: Primary | D31: =+E31*D$41/1000000 -> 0 | E31: 0 | F31: =+E31/E$39 -> 0 | H31: =J20 -> 0 | I31: =+H31*1000000/H$41 -> 0 | J31: =+I31/I$39 -> 0
B32: Secondary | D32: =+E32*D$41/1000000 -> 0 | E32: 0 | F32: =+E32/E$39 -> 0 | H32: =D35-H35+D36-H36+D37-H37 -> 61.945108 | I32: =+H32*1000000/H$41 -> 1300000 | J32: =+I32/I$39 -> 0.14622708
B33: Deal fees | D33: 0 | E33: 0 | F33: =+E33/E$39 -> 0 | H33: =J21+J22 -> 1.4725345 | I33: 0 | J33: =+I33/I$39 -> 0
B34: Total new sponsor | D34: =SUM(D31:D33) -> 0 | E34: =SUM(E31:E33) -> 0 | F34: =+E34/E$39 -> 0 | H34: =SUM(H31:H33) -> 63.417642 | I34: =SUM(I31:I33) -> 1300000 | J34: =+I34/I$39 -> 0.14622708
B35: Family | D35: =+E35*D$41/1000000 -> 257.31045 | E35: 5400000 | F35: =+E35/E$39 -> 0.63469676 | H35: =+I35*H$41/1000000 -> 257.31045 | I35: =+E35*(1-J5) -> 5400000 | J35: =+I35/I$39 -> 0.6074048
B36: Seed investor | D36: =+E36*D$41/1000000 -> 123.89022 | E36: 2600000 | F36: =+E36/E$39 -> 0.30559473 | H36: =+I36*H$41/1000000 -> 61.945108 | I36: =+E36*(1-J6) -> 1300000 | J36: =+I36/I$39 -> 0.14622708
B37: Existing employee options | D37: =+E37*D$41/1000000 -> 24.206242 | E37: 508000 | F37: =+E37/E$39 -> 0.05970851 | H37: =+I37*H$41/1000000 -> 24.206242 | I37: =+E37*(1-J7) -> 508000 | J37: =+I37/I$39 -> 0.057141044
B38: New option pool | D38: =+E38*D$41/1000000 -> 0 | E38: 0 | F38: =+E38/E$39 -> 0 | H38: 0 | I38: =SUM(I34:I37)/(1-J4)*J4 -> 382282.13 | J38: =+I38/I$39 -> 0.043
B39: Total company | D39: =SUM(D34:D38) -> 405.4069 | E39: =SUM(E34:E38) -> 8508000 | F39: =+E39/E$39 -> 1 | H39: =SUM(H34:H38) -> 406.87944 | I39: =SUM(I34:I38) -> 8890282.1 | J39: =+I39/I$39 -> 1
B41: Share price | D41: =+C10*1000000/E39 -> 47.650083 | H41: =+D41 -> 47.650083
B44: Model | J44: $ millions
B45: Income statement | C45: =+D45-1 -> -2 | D45: =+E45-1 -> -1 | E45: 0 | F45: 1 | G45: =F45+1 -> 2 | H45: =G45+1 -> 3 | I45: =H45+1 -> 4 | J45: =I45+1 -> 5
B46: Gross revenue | C46: =+'Revenue Build - End'!C21 -> 73.836296 | D46: =+'Revenue Build - End'!D21 -> 92.488396 | E46: =+'Revenue Build - End'!E21 -> 119.83782 | F46: =+'Revenue Build - End'!F21 -> 148.79459 | G46: =+'Revenue Build - End'!G21 -> 191.91399 | H46: =+'Revenue Build - End'!H21 -> 242.33648 | I46: =+'Revenue Build - End'!I21 -> 301.40048 | J46: =+'Revenue Build - End'!J21 -> 370.68247
B47: % Growth | D47: =D46/C46-1 -> 0.25261424 | E47: =E46/D46-1 -> 0.29570657 | F47: =F46/E46-1 -> 0.24163296 | G47: =G46/F46-1 -> 0.28979148 | H47: =H46/G46-1 -> 0.26273478 | I47: =I46/H46-1 -> 0.24372725 | J47: =J46/I46-1 -> 0.22986688
B49: Cancellations | C49: =C54*C$46 -> 10.410918 | D49: =D54*D$46 -> 13.688283 | E49: =E54*E$46 -> 18.215349 | F49: =F54*F$46 -> 22.319189 | G49: =G54*G$46 -> 28.787099 | H49: =H54*H$46 -> 36.350471 | I49: =I54*I$46 -> 45.210072 | J49: =J54*J$46 -> 55.60237
B50: Net revenue | C50: =C46-C49 -> 63.425378 | D50: =D46-D49 -> 78.800113 | E50: =E46-E49 -> 101.62247 | F50: =F46-F49 -> 126.4754 | G50: =G46-G49 -> 163.12689 | H50: =H46-H49 -> 205.986 | I50: =I46-I49 -> 256.19041 | J50: =J46-J49 -> 315.0801
B51: % Growth | D51: =D50/C50-1 -> 0.24240667 | E51: =E50/D50-1 -> 0.28962344 | F51: =F50/E50-1 -> 0.24456134 | G51: =G50/F50-1 -> 0.28979148 | H51: =H50/G50-1 -> 0.26273478 | I51: =I50/H50-1 -> 0.24372725 | J51: =J50/I50-1 -> 0.22986688
B53: % of gross revenue
B54: Cancellations | C54: 0.141 | D54: 0.148 | E54: 0.152 | F54: 0.15 | G54: 0.15 | H54: 0.15 | I54: 0.15 | J54: 0.15
B55: Net revenue | C55: =C50/C$46 -> 0.859 | D55: =D50/D$46 -> 0.852 | E55: =E50/E$46 -> 0.848 | F55: =F50/F$46 -> 0.85 | G55: =G50/G$46 -> 0.85 | H55: =H50/H$46 -> 0.85 | I55: =I50/I$46 -> 0.85 | J55: =J50/J$46 -> 0.85
B57: COGS | C57: =+C58*C50 -> 11.315087 | D57: =+D58*D50 -> 14.10522 | E57: =+E58*E50 -> 18.292045 | F57: =+F58*F50 -> 22.765572 | G57: =+G58*G50 -> 29.362841 | H57: =+H58*H50 -> 37.077481 | I57: =+I58*I50 -> 46.114273 | J57: =+J58*J50 -> 56.714417
B58: % of net revenue | C58: 0.1784 | D58: 0.179 | E58: 0.18 | F58: 0.18 | G58: 0.18 | H58: 0.18 | I58: 0.18 | J58: 0.18
B60: Gross profit | C60: =C50-C57 -> 52.110291 | D60: =D50-D57 -> 64.694893 | E60: =E50-E57 -> 83.330428 | F60: =F50-F57 -> 103.70983 | G60: =G50-G57 -> 133.76405 | H60: =H50-H57 -> 168.90852 | I60: =I50-I57 -> 210.07613 | J60: =J50-J57 -> 258.36568
B61: % of net revenue | C61: =+C60/C$50 -> 0.8216 | D61: =+D60/D$50 -> 0.821 | E61: =+E60/E$50 -> 0.82 | F61: =+F60/F$50 -> 0.82 | G61: =+G60/G$50 -> 0.82 | H61: =+H60/H$50 -> 0.82 | I61: =+I60/I$50 -> 0.82 | J61: =+J60/J$50 -> 0.82
B63: Operations & support | C63: =C71*C$50 -> 11.923971 | D63: =D71*D$50 -> 14.499221 | E63: =E71*E$50 -> 17.479065 | F63: =F71*F$50 -> 21.500818 | G63: =G71*G$50 -> 27.731572 | H63: =H71*H$50 -> 35.017621 | I63: =I71*I$50 -> 43.552369 | J63: =J71*J$50 -> 53.563616
B64: Product development | C64: =C72*C$50 -> 11.099441 | D64: =D72*D$50 -> 14.18402 | E64: =E72*E$50 -> 18.698535 | F64: =F72*F$50 -> 25.29508 | G64: =G72*G$50 -> 32.625379 | H64: =H72*H$50 -> 41.197201 | I64: =I72*I$50 -> 51.238081 | J64: =J72*J$50 -> 63.016019
B65: Ad spend - vehicle acquisition | C65: =+'Revenue Build - End'!C33 -> 3.2 | D65: =+'Revenue Build - End'!D33 -> 4.5 | E65: =+'Revenue Build - End'!E33 -> 5.8 | F65: =+'Revenue Build - End'!F33 -> 7.25 | G65: =+'Revenue Build - End'!G33 -> 9.0625 | H65: =+'Revenue Build - End'!H33 -> 11.328125 | I65: =+'Revenue Build - End'!I33 -> 14.160156 | J65: =+'Revenue Build - End'!J33 -> 17.700195
B66: Ad spend - driver acquisition | C66: =+'Revenue Build - End'!C56 -> 5.2 | D66: =+'Revenue Build - End'!D56 -> 6.9 | E66: =+'Revenue Build - End'!E56 -> 8 | F66: =+'Revenue Build - End'!F56 -> 8.8 | G66: =+'Revenue Build - End'!G56 -> 9.68 | H66: =+'Revenue Build - End'!H56 -> 10.648 | I66: =+'Revenue Build - End'!I56 -> 11.7128 | J66: =+'Revenue Build - End'!J56 -> 12.88408
B67: General & administrative | C67: =C75*C$50 -> 8.3721499 | D67: =D75*D$50 -> 10.874416 | E67: =E75*E$50 -> 13.719034 | F67: =F75*F$50 -> 17.074179 | G67: =G75*G$50 -> 22.022131 | H67: =H75*H$50 -> 27.808111 | I67: =I75*I$50 -> 34.585705 | J67: =J75*J$50 -> 42.535813
B68: Operating expenses | C68: =SUM(C63:C67) -> 39.795562 | D68: =SUM(D63:D67) -> 50.957657 | E68: =SUM(E63:E67) -> 63.696634 | F68: =SUM(F63:F67) -> 79.920078 | G68: =SUM(G63:G67) -> 101.12158 | H68: =SUM(H63:H67) -> 125.99906 | I68: =SUM(I63:I67) -> 155.24911 | J68: =SUM(J63:J67) -> 189.69972
B70: % of net revenue
B71: =+B63 -> Operations & support | C71: 0.188 | D71: 0.184 | E71: 0.172 | F71: 0.17 | G71: 0.17 | H71: 0.17 | I71: 0.17 | J71: 0.17
B72: =+B64 -> Product development | C72: 0.175 | D72: 0.18 | E72: 0.184 | F72: 0.2 | G72: 0.2 | H72: 0.2 | I72: 0.2 | J72: 0.2
B73: =+B65 -> Ad spend - vehicle acquisition | C73: =+C65/C$50 -> 0.05045299 | D73: =+D65/D$50 -> 0.057106517 | E73: =+E65/E$50 -> 0.05707399 | F73: =+F65/F$50 -> 0.0573234 | G73: =+G65/G$50 -> 0.05555491 | H73: =+H65/H$50 -> 0.054994634 | I73: =+I65/I$50 -> 0.055272 | J73: =+J65/J$50 -> 0.056176812
B74: =+B66 -> Ad spend - driver acquisition | C74: =+C66/C$50 -> 0.081986109 | D74: =+D66/D$50 -> 0.087563326 | E74: =+E66/E$50 -> 0.078722745 | F74: =+F66/F$50 -> 0.069578747 | G74: =+G66/G$50 -> 0.059340307 | H74: =+H66/H$50 -> 0.051692832 | I74: =+I66/I$50 -> 0.04571912 | J74: =+J66/J$50 -> 0.040891444
B75: =+B67 -> General & administrative | C75: 0.132 | D75: 0.138 | E75: 0.135 | F75: 0.135 | G75: 0.135 | H75: 0.135 | I75: 0.135 | J75: 0.135
B76: Operating expenses | C76: =C68/C50 -> 0.6274391 | D76: =D68/D50 -> 0.64666984 | E76: =E68/E50 -> 0.62679673 | F76: =F68/F50 -> 0.63190215 | G76: =G68/G50 -> 0.61989522 | H76: =H68/H50 -> 0.61168747 | I76: =I68/I50 -> 0.60599112 | J76: =J68/J50 -> 0.60206826
B78: EBITDA | C78: =+C60-C68 -> 12.314729 | D78: =+D60-D68 -> 13.737236 | E78: =+E60-E68 -> 19.633794 | F78: =+F60-F68 -> 23.789752 | G78: =+G60-G68 -> 32.642472 | H78: =+H60-H68 -> 42.909466 | I78: =+I60-I68 -> 54.827022 | J78: =+J60-J68 -> 68.665955
B79: % of net revenue | C79: =+C78/C$50 -> 0.1941609 | D79: =+D78/D$50 -> 0.17433016 | E79: =+E78/E$50 -> 0.19320327 | F79: =+F78/F$50 -> 0.18809785 | G79: =+G78/G$50 -> 0.20010478 | H79: =+H78/H$50 -> 0.20831253 | I79: =+I78/I$50 -> 0.21400888 | J79: =+J78/J$50 -> 0.21793174
B81: D&A | F81: =F126*F$50 -> 0.3794262 | G81: =G126*G$50 -> 0.48938068 | H81: =H126*H$50 -> 0.61795801 | I81: =I126*I$50 -> 0.76857122 | J81: =J126*J$50 -> 0.94524029
B82: Interest expense | F82: =+F136 -> 0 | G82: =+G136 -> 0 | H82: =+H136 -> 0 | I82: =+I136 -> 0 | J82: =+J136 -> 0
B83: Fee amortization expense | F83: =F129 -> 0 | G83: =G129 -> 0 | H83: =H129 -> 0 | I83: =I129 -> 0 | J83: =J129 -> 0
B84: Earnings before taxes | F84: =F78-F81-F82-F83 -> 23.410325 | G84: =G78-G81-G82-G83 -> 32.153091 | H84: =H78-H81-H82-H83 -> 42.291508 | I84: =I78-I81-I82-I83 -> 54.05845 | J84: =J78-J81-J82-J83 -> 67.720714
B85: % of net revenue | F85: =+F84/F$50 -> 0.18509785 | G85: =+G84/G$50 -> 0.19710478 | H85: =+H84/H$50 -> 0.20531253 | I85: =+I84/I$50 -> 0.21100888 | J85: =+J84/J$50 -> 0.21493174
B87: Tax provision | F87: =+IF(F84<0, 0, F84*F88) -> 5.8525813 | G87: =+IF(G84<0, 0, G84*G88) -> 8.0382728 | H87: =+IF(H84<0, 0, H84*H88) -> 10.572877 | I87: =+IF(I84<0, 0, I84*I88) -> 13.514613 | J87: =+IF(J84<0, 0, J84*J88) -> 16.930179
B88: % tax rate | F88: 0.25 | G88: 0.25 | H88: 0.25 | I88: 0.25 | J88: 0.25
B90: Net income | F90: =F84-F87 -> 17.557744 | G90: =G84-G87 -> 24.114818 | H90: =H84-H87 -> 31.718631 | I90: =I84-I87 -> 40.543838 | J90: =J84-J87 -> 50.790536
B91: % of net revenue | F91: =+F90/F$50 -> 0.13882339 | G91: =+G90/G$50 -> 0.14782859 | H91: =+H90/H$50 -> 0.1539844 | I91: =+I90/I$50 -> 0.15825666 | J91: =+J90/J$50 -> 0.16119881
B94: Balance sheet | C94: 0 | D94: Adjust. | E94: Pro forma | F94: 1 | G94: =F94+1 -> 2 | H94: =G94+1 -> 3 | I94: =H94+1 -> 4 | J94: =I94+1 -> 5
B95: Cash | C95: 110.9 | D95: =E95-C95 -> 0 | E95: =+D9 -> 110.9 | F95: =F153+E95 -> 120 | G95: =G153+F95 -> 120 | H95: =H153+G95 -> 120 | I95: =I153+H95 -> 120 | J95: =J153+I95 -> 120
B96: Receivables | C96: 55.1 | E96: =+D96+C96 -> 55.1 | F96: =+F50/F115 -> 70.264112 | G96: =+G50/G115 -> 90.626053 | H96: =+H50/H115 -> 114.43667 | I96: =+I50/I115 -> 142.328 | J96: =+J50/J115 -> 175.0445
B97: Capitalized financing fees | C97: 0 | D97: =+D12 -> 0 | E97: =D97+C97 -> 0 | F97: =F130 -> 0 | G97: =G130 -> 0 | H97: =H130 -> 0 | I97: =I130 -> 0 | J97: =J130 -> 0
B98: Goodwill | C98: 0 | E98: =D98+C98 -> 0 | F98: =E98 -> 0 | G98: =F98 -> 0 | H98: =G98 -> 0 | I98: =H98 -> 0 | J98: =I98 -> 0
B99: Net PP&E | C99: 3 | E99: =D99+C99 -> 3 | F99: =F124 -> 3.2529508 | G99: =G124 -> 3.5792046 | H99: =H124 -> 3.9911766 | I99: =I124 -> 4.5035574 | J99: =J124 -> 5.1337176
B100: Other assets | C100: 15.8 | E100: =+D100+C100 -> 15.8 | F100: =+E100 -> 15.8 | G100: =+F100 -> 15.8 | H100: =+G100 -> 15.8 | I100: =+H100 -> 15.8 | J100: =+I100 -> 15.8
B101: Total assets | C101: =SUM(C95:C100) -> 184.8 | E101: =SUM(E95:E100) -> 184.8 | F101: =SUM(F95:F100) -> 209.31706 | G101: =SUM(G95:G100) -> 230.00526 | H101: =SUM(H95:H100) -> 254.22785 | I101: =SUM(I95:I100) -> 282.63156 | J101: =SUM(J95:J100) -> 315.97822
B103: Payables & accrued expenses | C103: 38.4 | E103: =+D103+C103 -> 38.4 | F103: =+F57/F116 -> 45.531145 | G103: =+G57/G116 -> 58.725682 | H103: =+H57/H116 -> 74.154962 | I103: =+I57/I116 -> 92.228546 | J103: =+J57/J116 -> 113.42883
B104: Other liabilities | C104: 7.7 | E104: =+D104+C104 -> 7.7 | F104: 7.7 | G104: 7.7 | H104: 7.7 | I104: 7.7 | J104: 7.7
B105: Debt | C105: 0 | D105: =+D8 -> 0 | E105: =D105+C105 -> 0 | F105: =F134 -> 0 | G105: =G134 -> 0 | H105: =H134 -> 0 | I105: =I134 -> 0 | J105: =J134 -> 0
B106: Shareholder equity | C106: 138.7 | D106: =+H31 -> 0 | E106: =D106+C106 -> 138.7 | F106: =E106+F90-F150 -> 156.08592 | G106: =F106+G90-G150 -> 163.57958 | H106: =G106+H90-H150 -> 172.37288 | I106: =H106+I90-I150 -> 182.70301 | J106: =I106+J90-J150 -> 194.84938
B107: Total liabilities & equity | C107: =SUM(C103:C106) -> 184.8 | E107: =SUM(E103:E106) -> 184.8 | F107: =SUM(F103:F106) -> 209.31706 | G107: =SUM(G103:G106) -> 230.00526 | H107: =SUM(H103:H106) -> 254.22785 | I107: =SUM(I103:I106) -> 282.63156 | J107: =SUM(J103:J106) -> 315.97822
B108: Check | C108: =C101-C107 -> 0 | E108: =E101-E107 -> 0 | F108: =F101-F107 -> 0 | G108: =G101-G107 -> 0 | H108: =H101-H107 -> 0 | I108: =I101-I107 -> 0 | J108: =J101-J107 -> 0
B110: Leverage metrics
B111: Debt/EBITDA | E111: =+(E105)/E78 -> 0 | F111: =+(F105)/F78 -> 0 | G111: =+(G105)/G78 -> 0 | H111: =+(H105)/H78 -> 0 | I111: =+(I105)/I78 -> 0 | J111: =+(J105)/J78 -> 0
B112: EBITDA/Interest expense | E112: =IFERROR(E78/E136, "n/a") -> n/a | F112: =IFERROR(F78/F136, "n/a") -> n/a | G112: =IFERROR(G78/G136, "n/a") -> n/a | H112: =IFERROR(H78/H136, "n/a") -> n/a | I112: =IFERROR(I78/I136, "n/a") -> n/a | J112: =IFERROR(J78/J136, "n/a") -> n/a
B114: Working capital
B115: Receivable turnover | C115: =+E50/C96 -> 1.844328 | F115: 1.8 | G115: 1.8 | H115: 1.8 | I115: 1.8 | J115: 1.8
B116: Payable turnover | C116: =+E57/C103 -> 0.47635534 | F116: 0.5 | G116: 0.5 | H116: 0.5 | I116: 0.5 | J116: 0.5
B117: Net working capital | C117: =+C96+C100-C103-C104 -> 24.8 | E117: =+E96+E100-E103-E104 -> 24.8 | F117: =+F96+F100-F103-F104 -> 32.832967 | G117: =+G96+G100-G103-G104 -> 40.000371 | H117: =+H96+H100-H103-H104 -> 48.381708 | I117: =+I96+I100-I103-I104 -> 58.199457 | J117: =+J96+J100-J103-J104 -> 69.715663
B120: Supporting schedules | E120: 0 | F120: 1 | G120: =F120+1 -> 2 | H120: =G120+1 -> 3 | I120: =H120+1 -> 4 | J120: =I120+1 -> 5
B121: PP&E, beginning | F121: =E124 -> 3 | G121: =F124 -> 3.2529508 | H121: =G124 -> 3.5792046 | I121: =H124 -> 3.9911766 | J121: =I124 -> 4.5035574
B122: (+) Capex | F122: =F125*F50 -> 0.63237701 | G122: =G125*G50 -> 0.81563447 | H122: =H125*H50 -> 1.02993 | I122: =I125*I50 -> 1.280952 | J122: =J125*J50 -> 1.5754005
B123: (-) D&A | F123: =F81 -> 0.3794262 | G123: =G81 -> 0.48938068 | H123: =H81 -> 0.61795801 | I123: =I81 -> 0.76857122 | J123: =J81 -> 0.94524029
B124: PP&E, ending | E124: =E99 -> 3 | F124: =F121+F122-F123 -> 3.2529508 | G124: =G121+G122-G123 -> 3.5792046 | H124: =H121+H122-H123 -> 3.9911766 | I124: =I121+I122-I123 -> 4.5035574 | J124: =J121+J122-J123 -> 5.1337176
B125: Capex - % of revenue | F125: 0.005 | G125: 0.005 | H125: 0.005 | I125: 0.005 | J125: 0.005
...

Sheet Revenue Build - End
B2: Revenue Build | J2: $ millions
B3: Supply & Demand | C3: =+D3-1 -> -2 | D3: =+E3-1 -> -1 | E3: 0 | F3: 1 | G3: =F3+1 -> 2 | H3: =G3+1 -> 3 | I3: =H3+1 -> 4 | J3: =I3+1 -> 5
B4: Vehicle days available | C4: =+C30 -> 3212127 | D4: =+D30 -> 4304628.9 | E4: =+E30 -> 5402115.2 | F4: =+F30 -> 6388042.2 | G4: =+G30 -> 7356466.4 | H4: =+H30 -> 8326512.9 | I4: =+I30 -> 9314840.6 | J4: =+J30 -> 10336253
B5: Driver days demanded | C5: =+C53 -> 3505699 | D5: =+D53 -> 5665304.5 | E5: =+E53 -> 7162732.3 | F5: =+F53 -> 8727222.9 | G5: =+G53 -> 10120227 | H5: =+H53 -> 11366633 | I5: =+I53 -> 12487861 | J5: =+J53 -> 13502350
B6: Supply as % of demand | C6: =+C4/C5 -> 0.91625864 | D6: =+D4/D5 -> 0.75982304 | E6: =+E4/E5 -> 0.75419756 | F6: =+F4/F5 -> 0.73196734 | G6: =+G4/G5 -> 0.72690725 | H6: =+H4/H5 -> 0.73253997 | I6: =+I4/I5 -> 0.7459116 | J6: =+J4/J5 -> 0.76551511
B8: Vehicle days rented
B9: Supply or demand minimum | C9: =+MIN(C4,C5) -> 3212127 | D9: =+MIN(D4,D5) -> 4304628.9 | E9: =+MIN(E4,E5) -> 5402115.2 | F9: =+MIN(F4,F5) -> 6388042.2 | G9: =+MIN(G4,G5) -> 7356466.4 | H9: =+MIN(H4,H5) -> 8326512.9 | I9: =+MIN(I4,I5) -> 9314840.6 | J9: =+MIN(J4,J5) -> 10336253
B10: Marketplace matching efficiency factor | C10: 1 | D10: 1 | E10: 1 | F10: 1 | G10: 1 | H10: 1 | I10: 1 | J10: 1
B11: Total vehicle days rented | C11: =+C10*C9 -> 3212127 | D11: =+D10*D9 -> 4304628.9 | E11: =+E10*E9 -> 5402115.2 | F11: =+F10*F9 -> 6388042.2 | G11: =+G10*G9 -> 7356466.4 | H11: =+H10*H9 -> 8326512.9 | I11: =+I10*I9 -> 9314840.6 | J11: =+J10*J9 -> 10336253
B13: Average price per vehicle day rented | C13: 152.23 | D13: 144.2 | E13: 147.89 | F13: =+E13*(1+F14) -> 155.2845 | G13: =+F13*(1+G14) -> 163.04872 | H13: =+G13*(1+H14) -> 171.20116 | I13: =+H13*(1+I14) -> 179.76122 | J13: =+I13*(1+J14) -> 188.74928
B14: % Growth | D14: =+D13/C13-1 -> -0.05274913 | E14: =+E13/D13-1 -> 0.025589459 | F14: 0.05 | G14: 0.05 | H14: 0.05 | I14: 0.05 | J14: 0.05
B16: Total booking value | C16: =+C13*C11/1000000 -> 488.98209 | D16: =+D13*D11/1000000 -> 620.72749 | E16: =+E13*E11/1000000 -> 798.91881 | F16: =+F13*F11/1000000 -> 991.96393 | G16: =+G13*G11/1000000 -> 1199.4625 | H16: =+H13*H11/1000000 -> 1425.5087 | I16: =+I13*I11/1000000 -> 1674.4471 | J16: =+J13*J11/1000000 -> 1950.9603
B17: % Growth | D17: =+D16/C16-1 -> 0.26942785 | E17: =+E16/D16-1 -> 0.28706853 | F17: =+F16/E16-1 -> 0.24163296 | G17: =+G16/F16-1 -> 0.20917951 | H17: =+H16/G16-1 -> 0.18845627 | I17: =+I16/H16-1 -> 0.17463129 | J17: =+J16/I16-1 -> 0.16513704
B19: Marketplace fee % | C19: 0.151 | D19: 0.149 | E19: 0.15 | F19: 0.15 | G19: 0.16 | H19: 0.17 | I19: 0.18 | J19: 0.19
B21: Gross revenue | C21: =+C19*C16 -> 73.836296 | D21: =+D19*D16 -> 92.488396 | E21: =+E19*E16 -> 119.83782 | F21: =+F19*F16 -> 148.79459 | G21: =+G19*G16 -> 191.91399 | H21: =+H19*H16 -> 242.33648 | I21: =+I19*I16 -> 301.40048 | J21: =+J19*J16 -> 370.68247
B22: % Growth | D22: =+D21/C21-1 -> 0.25261424 | E22: =+E21/D21-1 -> 0.29570657 | F22: =+F21/E21-1 -> 0.24163296 | G22: =+G21/F21-1 -> 0.28979148 | H22: =+H21/G21-1 -> 0.26273478 | I22: =+I21/H21-1 -> 0.24372725 | J22: =+J21/I21-1 -> 0.22986688
B25: Supply | C25: =+D25-1 -> -2 | D25: =+E25-1 -> -1 | E25: 0 | F25: 1 | G25: =F25+1 -> 2 | H25: =G25+1 -> 3 | I25: =H25+1 -> 4 | J25: =I25+1 -> 5
B26: Vehicles days available
B27: Beginning | D27: =+C30 -> 3212127 | E27: =+D30 -> 4304628.9 | F27: =+E30 -> 5402115.2 | G27: =+F30 -> 6388042.2 | H27: =+G30 -> 7356466.4 | I27: =+H30 -> 8326512.9 | J27: =+I30 -> 9314840.6
B28: New added | D28: =+D43 -> 1628927.1 | E28: =+E43 -> 1911061.1 | F28: =+F43 -> 2066350 | G28: =+G43 -> 2246032.6 | H28: =+H43 -> 2441339.8 | I28: =+I43 -> 2653630.2 | J28: =+J43 -> 2884380.7
B29: Churned | D29: =D27*D45 -> 536425.21 | E29: =E27*E45 -> 813574.86 | F29: =F27*F45 -> 1080423 | G29: =G27*G45 -> 1277608.4 | H29: =H27*H45 -> 1471293.3 | I29: =I27*I45 -> 1665302.6 | J29: =J27*J45 -> 1862968.1
B30: Ending | C30: 3212127 | D30: =D27+D28-D29 -> 4304628.9 | E30: =E27+E28-E29 -> 5402115.2 | F30: =F27+F28-F29 -> 6388042.2 | G30: =G27+G28-G29 -> 7356466.4 | H30: =H27+H28-H29 -> 8326512.9 | I30: =I27+I28-I29 -> 9314840.6 | J30: =J27+J28-J29 -> 10336253
B31: % Growth | D31: =+D30/C30-1 -> 0.34011791 | E31: =+E30/D30-1 -> 0.25495491 | F31: =+F30/E30-1 -> 0.18250758 | G31: =+G30/F30-1 -> 0.15159953 | H31: =+H30/G30-1 -> 0.13186311 | I31: =+I30/H30-1 -> 0.11869647 | J31: =+J30/I30-1 -> 0.10965433
B33: Vehicle ad spend | C33: 3.2 | D33: 4.5 | E33: 5.8 | F33: =+E33*(1+F34) -> 7.25 | G33: =+F33*(1+G34) -> 9.0625 | H33: =+G33*(1+H34) -> 11.328125 | I33: =+H33*(1+I34) -> 14.160156 | J33: =+I33*(1+J34) -> 17.700195
B34: % Growth | D34: =+D33/C33-1 -> 0.40625 | E34: =+E33/D33-1 -> 0.28888889 | F34: 0.25 | G34: 0.25 | H34: 0.25 | I34: 0.25 | J34: 0.25
B36: Acquisition cost per vehicle | C36: 543.26 | D36: 621.02 | E36: 732.23 | F36: =+E36*(1+F37) -> 842.0645 | G36: =+F36*(1+G37) -> 968.37417 | H36: =+G36*(1+H37) -> 1113.6303 | I36: =+H36*(1+I37) -> 1280.6748 | J36: =+I36*(1+J37) -> 1472.7761
B37: % Growth | D37: =+D36/C36-1 -> 0.14313588 | E37: =+E36/D36-1 -> 0.17907636 | F37: 0.15 | G37: 0.15 | H37: 0.15 | I37: 0.15 | J37: 0.15
B39: New vehicles added | C39: =+C33*1000000/C36 -> 5890.3656 | D39: =+D33*1000000/D36 -> 7246.1434 | E39: =+E33*1000000/E36 -> 7921.0084 | F39: =+F33*1000000/F36 -> 8609.7918 | G39: =+G33*1000000/G36 -> 9358.4693 | H39: =+H33*1000000/H36 -> 10172.249 | I39: =+I33*1000000/I36 -> 11056.793 | J39: =+J33*1000000/J36 -> 12018.253
B41: Vehicle days available per vehicle added | C41: 250 | D41: 248 | E41: 252 | F41: 250 | G41: 250 | H41: 250 | I41: 250 | J41: 250
B43: Total vehicle days added | C43: =+C41*AVERAGE(C39) -> 1472591.4 | D43: =+D41*AVERAGE(C39:D39) -> 1628927.1 | E43: =+E41*AVERAGE(D39:E39) -> 1911061.1 | F43: =+F41*AVERAGE(E39:F39) -> 2066350 | G43: =+G41*AVERAGE(F39:G39) -> 2246032.6 | H43: =+H41*AVERAGE(G39:H39) -> 2441339.8 | I43: =+I41*AVERAGE(H39:I39) -> 2653630.2 | J43: =+J41*AVERAGE(I39:J39) -> 2884380.7
B45: Churn as % of prior ending | D45: 0.167 | E45: 0.189 | F45: 0.2 | G45: 0.2 | H45: 0.2 | I45: 0.2 | J45: 0.2
B48: Demand | C48: =+D48-1 -> -2 | D48: =+E48-1 -> -1 | E48: 0 | F48: 1 | G48: =F48+1 -> 2 | H48: =G48+1 -> 3 | I48: =H48+1 -> 4 | J48: =I48+1 -> 5
B49: Driver days demanded
B50: Beginning | D50: =+C53 -> 3505699 | E50: =+D53 -> 5665304.5 | F50: =+E53 -> 7162732.3 | G50: =+F53 -> 8727222.9 | H50: =+G53 -> 10120227 | I50: =+H53 -> 11366633 | J50: =+I53 -> 12487861
B51: New added | D51: =+D66 -> 2731034.5 | E51: =+E66 -> 2471860.1 | F51: =+F66 -> 2567273.2 | G51: =+G66 -> 2614815.3 | H51: =+H66 -> 2663237.8 | I51: =+I66 -> 2712557 | J51: =+J66 -> 2762789.5
B52: Churned | D52: =D50*D68 -> 571428.94 | E52: =E50*E68 -> 974432.38 | F52: =F50*F68 -> 1002782.5 | G52: =G50*G68 -> 1221811.2 | H52: =H50*H68 -> 1416831.8 | I52: =I50*I68 -> 1591328.6 | J52: =J50*J68 -> 1748300.6
B53: Ending | C53: 3505699 | D53: =D50+D51-D52 -> 5665304.5 | E53: =E50+E51-E52 -> 7162732.3 | F53: =F50+F51-F52 -> 8727222.9 | G53: =G50+G51-G52 -> 10120227 | H53: =H50+H51-H52 -> 11366633 | I53: =I50+I51-I52 -> 12487861 | J53: =J50+J51-J52 -> 13502350
B54: % Growth | D54: =+D53/C53-1 -> 0.61602709 | E54: =+E53/D53-1 -> 0.26431548 | F54: =+F53/E53-1 -> 0.21842093 | G54: =+G53/F53-1 -> 0.15961596 | H54: =+H53/G53-1 -> 0.12315988 | I54: =+I53/H53-1 -> 0.098642084 | J54: =+J53/I53-1 -> 0.081238004
B56: Driver ad spend | C56: 5.2 | D56: 6.9 | E56: 8 | F56: =+E56*(1+F57) -> 8.8 | G56: =+F56*(1+G57) -> 9.68 | H56: =+G56*(1+H57) -> 10.648 | I56: =+H56*(1+I57) -> 11.7128 | J56: =+I56*(1+J57) -> 12.88408
B57: % Growth | D57: =+D56/C56-1 -> 0.32692308 | E57: =+E56/D56-1 -> 0.15942029 | F57: 0.1 | G57: 0.1 | H57: 0.1 | I57: 0.1 | J57: 0.1
B59: Acquisition cost per driver | C59: 14.5 | D59: 17.25 | E59: 18.87 | F59: =+E59*(1+F60) -> 20.3796 | G59: =+F59*(1+G60) -> 22.009968 | H59: =+G59*(1+H60) -> 23.770765 | I59: =+H59*(1+I60) -> 25.672427 | J59: =+I59*(1+J60) -> 27.726221
B60: % Growth | D60: =+D59/C59-1 -> 0.18965517 | E60: =+E59/D59-1 -> 0.093913043 | F60: 0.08 | G60: 0.08 | H60: 0.08 | I60: 0.08 | J60: 0.08
B62: New drivers added | C62: =+C56*1000000/C59 -> 358620.69 | D62: =+D56*1000000/D59 -> 400000 | E62: =+E56*1000000/E59 -> 423953.37 | F62: =+F56*1000000/F59 -> 431804.35 | G62: =+G56*1000000/G59 -> 439800.73 | H62: =+H56*1000000/H59 -> 447945.19 | I62: =+I56*1000000/I59 -> 456240.47 | J62: =+J56*1000000/J59 -> 464689.37
B64: Driver days demanded per driver added | C64: 8 | D64: 7.2 | E64: 6 | F64: 6 | G64: 6 | H64: 6 | I64: 6 | J64: 6
B66: Total driver days added | C66: =+C64*AVERAGE(C62) -> 2868965.5 | D66: =+D64*AVERAGE(C62:D62) -> 2731034.5 | E66: =+E64*AVERAGE(D62:E62) -> 2471860.1 | F66: =+F64*AVERAGE(E62:F62) -> 2567273.2 | G66: =+G64*AVERAGE(F62:G62) -> 2614815.3 | H66: =+H64*AVERAGE(G62:H62) -> 2663237.8 | I66: =+I64*AVERAGE(H62:I62) -> 2712557 | J66: =+J64*AVERAGE(I62:J62) -> 2762789.5
B68: Churn as % of prior ending | D68: 0.163 | E68: 0.172 | F68: 0.14 | G68: 0.14 | H68: 0.14 | I68: 0.14 | J68: 0.14
